Workbook

Sheet About
A1: BDCSoCaESoPbIC BAU Domestic Content Share of Consumption and Export Share of Production by ISIC Code
A3: Source: | B3: Most Industries
B4: OECD
B5: 2018
B6: Input-Output Tables 2018 Edition (ISIC Rev. 4)
B7: https://stats.oecd.org/Index.aspx?DataSetCode=IOTSI4_2018
B8: Variables: TTL and ICESHR
B10: ISIC Code Splits
B11: see variable io-model/DLIM
B12: ISIC codes are assigned to each SCN code in io-model/DLIM.
B13: This variables uses both the 128x27 IBGE "Recursos " and "Usos" tables (from the source specified in DLIM)
B14: National Account System (SCN) version 2010
B15: https://ftp.ibge.gov.br/Contas_Nacionais/Matriz_de_Insumo_Produto/2015/Matriz_de_Insumo_Produto_2015_Nivel_67.xls
A17: Notes
A18: This variable is used to determine the share of a policy-driven increase in the domestic need
A19: for a type of economic output that is satisfied by increased domestic production rather
A20: than by increased imports.
A22: This variable contains the share of the domestic consumption of goods/services
A23: within each ISIC code that was produced domestically rather than imported.
A24: The calculations appear on the "Calculations" tab and are straightforward to follow
A25: by looking at the formulas in Excel.
A27: Note on ISIC 84 in variable ICESHR
A28: Many non-European countries in the OECD database, in variable ICESHR, omit a value for
A29: ISIC code 84 (Public administration and defence; compulsory social security).
A30: Though this value may be low, it is unlikely to be zero, due to imported content in
... A52: We convert 2015 USD to 2012 USD with the following conversion factor:
A53: 0.96868157 | B53: 2015 USD / 2012 USD

Sheet OECD TTL
A1: =DotStatQuery(B1) -> #NAME? | B1: Sorry, the query is too large to fit into the Excel cell. You will not be able to update your table with the .Stat Populator.
A2: Dataset: Input-Output Tables (IOTs) 2018 ed.
A3: Variable | C3: TTL: Total
A4: Country | C4: BRA: Brazil
A5: Time | C5: 2015
A6: Unit | C6: US Dollar, Millions
A7: To: (sector in column) | C7: D01T03: Agriculture, forestry and fishing | D7: D05T06: Mining and extraction of energy producing products | E7: D07T08: Mining and quarrying of non-energy producing products | F7: D09: Mining support service activities | G7: D10T12: Food products, beverages and tobacco | H7: D13T15: Textiles, wearing apparel, leather and related products | I7: D16: Wood and products of wood and cork | J7: D17T18: Paper products and printing | K7: D19: Coke and refined petroleum products | L7: D20T21: Chemicals and pharmaceutical products | M7: D22: Rubber and plastic products | N7: D23: Other non-metallic mineral products | O7: D24: Basic metals | P7: D25: Fabricated metal products | Q7: D26: Computer, electronic and optical products | R7: D27: Electrical equipment | S7: D28: Machinery and equipment, nec | T7: D29: Motor vehicles, trailers and semi-trailers | U7: D30: Other transport equipment | V7: D31T33: Other manufacturing; repair and installation of machinery and equipment | W7: D35T39: Electricity, gas, water supply, sewerage, waste and remediation services | X7: D41T43: Construction | Y7: D45T47: Wholesale and retail trade; repair of motor vehicles | Z7: D49T53: Transportation and storage | AA7: D55T56: Accomodation and food services | AB7: D58T60: Publishing, audiovisual and broadcasting activities | AC7: D61: Telecommunications | AD7: D62T63: IT and other information services | AE7: D64T66: Financial and insurance activities | AF7: D68: Real estate activities | AG7: D69T82: Other business sector services | AH7: D84: Public admin. and defence; compulsory social security | AI7: D85: Education | AJ7: D86T88: Human health and social work | AK7: D90T96: Arts, entertainment, recreation and other service activities | AL7: D97T98: Private households with employed persons | AM7: HFCE: Final consumption expenditure of households | AN7: NPISH: Final consumption expenditure of non-profit institutions serving households | AO7: GGFC: Final consumption expenditure of general government | AP7: GFCF: Gross Fixed Capital Formation | AQ7: INVNT: Changes in inventories | AR7: CONS_ABR: Direct purchases abroad by residents (imports) | AS7: CONS_NONRES: Direct purchases by non-residents (exports) | AT7: EXPO: Exports (cross border) | AU7: IMPO: Imports (cross border)
A8: From: (sector in row)
A9: TTL_01T03: Agriculture, forestry and fishing | C9: 6071.2 | D9: 22.9 | E9: 12.6 | F9: 5.4 | G9: 54628.4 | H9: 1070.9 | I9: 950.5 | J9: 1220.4 | K9: 3732.1 | L9: 116.1 | M9: 376.9 | N9: 55 | O9: 271.2 | P9: 7.4 | Q9: 1.9 | R9: 1.6 | S9: 2.6 | T9: 17 | U9: 4.9 | V9: 15.4 | W9: 16.5 | X9: 420 | Y9: 820.1 | Z9: 24.6 | AA9: 1503.9 | AB9: 3.6 | AC9: 19.5 | AD9: 5.6 | AE9: 25.7 | AF9: 52 | AG9: 88.9 | AH9: 360.6 | AI9: 254.5 | AJ9: 170.5 | AK9: 156 | AL9: 0 | AM9: 35490.9 | AN9: 0 | AO9: 2021.7 | AP9: 5117.2 | AQ9: -280.5 | AR9: 150.2 | AS9: 17.4 | AT9: 34291.8 | AU9: -3343.4
A10: TTL_05T06: Mining and extraction of energy producing products | C10: 35.2 | D10: 3165.2 | E10: 72.9 | F10: 283.8 | G10: 439.3 | H10: 57.8 | I10: 17.3 | J10: 268.7 | K10: 32198.4 | L10: 855.8 | M10: 35.9 | N10: 233.3 | O10: 1547.6 | P10: 152.2 | Q10: 1.2 | R10: 10.2 | S10: 11.8 | T10: 112.3 | U10: 13.9 | V10: 3.6 | W10: 4544.1 | X10: 241 | Y10: 260.3 | Z10: 138.4 | AA10: 6.9 | AB10: 2.1 | AC10: 20 | AD10: 4.4 | AE10: 45.9 | AF10: 82.2 | AG10: 80.7 | AH10: 75 | AI10: 12.5 | AJ10: 199.1 | AK10: 150.6 | AL10: 0 | AM10: 161.6 | AN10: 0 | AO10: 32.7 | AP10: 4254.8 | AQ10: -228.8 | AR10: 6.4 | AS10: 0.2 | AT10: 11513.1 | AU10: -13509.9
A11: TTL_07T08: Mining and quarrying of non-energy producing products | C11: 148.4 | D11: 134.8 | E11: 774.1 | F11: 24.4 | G11: 141.5 | H11: 4.1 | I11: 0.7 | J11: 18.5 | K11: 66.9 | L11: 1065.1 | M11: 12.7 | N11: 1577.5 | O11: 6004.1 | P11: 79.9 | Q11: 5.5 | R11: 196.1 | S11: 33.4 | T11: 118.3 | U11: 22 | V11: 84.1 | W11: 34.6 | X11: 1914.2 | Y11: 60.7 | Z11: 17.1 | AA11: 3 | AB11: 0.3 | AC11: 0.7 | AD11: 0.5 | AE11: 6.2 | AF11: 30.5 | AG11: 12.9 | AH11: 80.6 | AI11: 6 | AJ11: 7.9 | AK11: 23.6 | AL11: 0 | AM11: 86.6 | AN11: 0 | AO11: 3.6 | AP11: 68.9 | AQ11: -49.2 | AR11: 1.1 | AS11: 0 | AT11: 15903.2 | AU11: -2324.1
A12: TTL_09: Mining support service activities | C12: 390.2 | D12: 1981.2 | E12: 412.9 | F12: 281.3 | G12: 96.6 | H12: 0 | I12: 2.6 | J12: 22.8 | K12: 67.6 | L12: 28.6 | M12: 29.1 | N12: 15 | O12: 6.5 | P12: 0.7 | Q12: 0 | R12: 0.1 | S12: 13.2 | T12: 0.5 | U12: 0.1 | V12: 6.9 | W12: 166.7 | X12: 439.9 | Y12: 0.8 | Z12: 14.5 | AA12: 0.1 | AB12: 0 | AC12: 0 | AD12: 0.1 | AE12: 0.2 | AF12: 0 | AG12: 9.4 | AH12: 53.2 | AI12: 17.9 | AJ12: 0.5 | AK12: 0.5 | AL12: 0 | AM12: 0.4 | AN12: 0 | AO12: 781.8 | AP12: 0.7 | AQ12: 0.5 | AR12: 0.2 | AS12: 0 | AT12: 62.1 | AU12: -73.5
A13: TTL_10T12: Food products, beverages and tobacco | C13: 4743.3 | D13: 149.8 | E13: 51.6 | F13: 7.4 | G13: 27878.5 | H13: 668.7 | I13: 34 | J13: 335.2 | K13: 1174.7 | L13: 3015 | M13: 451.2 | N13: 114.2 | O13: 97.4 | P13: 98.3 | Q13: 40.5 | R13: 87.7 | S13: 59.5 | T13: 93.1 | U13: 33.3 | V13: 122.2 | W13: 85.3 | X13: 290.9 | Y13: 1161.8 | Z13: 160.4 | AA13: 14989 | AB13: 28 | AC13: 60.4 | AD13: 33.9 | AE13: 96.7 | AF13: 34.8 | AG13: 228.4 | AH13: 991.2 | AI13: 994.4 | AJ13: 936.3 | AK13: 468.5 | AL13: 0 | AM13: 110403.4 | AN13: 0.3 | AO13: 1487.2 | AP13: 372.6 | AQ13: 109.8 | AR13: 583.8 | AS13: 53.8 | AT13: 30575.3 | AU13: -7327.9
A14: TTL_13T15: Textiles, wearing apparel, leather and related products | C14: 228.6 | D14: 38.4 | E14: 10.7 | F14: 6.9 | G14: 164 | H14: 10509.7 | I14: 3.1 | J14: 108.6 | K14: 30.3 | L14: 167.6 | M14: 151.2 | N14: 16.5 | O14: 11.2 | P14: 55.8 | Q14: 7.8 | R14: 12.7 | S14: 15.3 | T14: 374.8 | U14: 65.9 | V14: 389.3 | W14: 130.2 | X14: 216.5 | Y14: 650.2 | Z14: 75.8 | AA14: 112.6 | AB14: 23.9 | AC14: 9.3 | AD14: 5.3 | AE14: 82.5 | AF14: 7.7 | AG14: 100.3 | AH14: 238 | AI14: 75.7 | AJ14: 323.4 | AK14: 261.6 | AL14: 0 | AM14: 33181.7 | AN14: 0 | AO14: 176.4 | AP14: 151 | AQ14: 12.1 | AR14: 213.7 | AS14: 31.1 | AT14: 3595.2 | AU14: -7272.9
A15: TTL_16: Wood and of products of wood and cork (except furniture) | C15: 227.7 | D15: 2.6 | E15: 12.4 | F15: 6.4 | G15: 139.9 | H15: 10.3 | I15: 921.6 | J15: 114.9 | K15: 1.8 | L15: 24.1 | M15: 6.6 | N15: 12.4 | O15: 10.9 | P15: 66.3 | Q15: 2.4 | R15: 2.8 | S15: 79.4 | T15: 68.5 | U15: 48 | V15: 1515.3 | W15: 114.7 | X15: 1317.5 | Y15: 246.9 | Z15: 34.8 | AA15: 5.6 | AB15: 21.3 | AC15: 3.5 | AD15: 2 | AE15: 22.8 | AF15: 233.6 | AG15: 70.9 | AH15: 80.3 | AI15: 13 | AJ15: 28.2 | AK15: 112.8 | AL15: 0 | AM15: 629.3 | AN15: 0 | AO15: 24.3 | AP15: 66.1 | AQ15: 7.1 | AR15: 18.7 | AS15: 2.1 | AT15: 1946.9 | AU15: -231.7
A16: TTL_17T18: Paper products and printing | C16: 188.1 | D16: 20.7 | E16: 66.3 | F16: 5.3 | G16: 2522 | H16: 454.3 | I16: 219.3 | J16: 4083.1 | K16: 58.6 | L16: 898.6 | M16: 553.3 | N16: 536.1 | O16: 28.2 | P16: 389.4 | Q16: 372.5 | R16: 121.6 | S16: 80.4 | T16: 324.2 | U16: 32.7 | V16: 302.4 | W16: 180.4 | X16: 153.2 | Y16: 1780.9 | Z16: 253.2 | AA16: 293.1 | AB16: 882.7 | AC16: 278.2 | AD16: 274.3 | AE16: 850.9 | AF16: 81.5 | AG16: 1398.7 | AH16: 1180.6 | AI16: 452.2 | AJ16: 532.1 | AK16: 634.6 | AL16: 0 | AM16: 3926.1 | AN16: 0.1 | AO16: 89.5 | AP16: 232.6 | AQ16: -2.9 | AR16: 80.9 | AS16: 5.5 | AT16: 6840.4 | AU16: -1455.7
A17: TTL_19: Coke and refined petroleum products | C17: 5688.7 | D17: 827.5 | E17: 1510.3 | F17: 143.9 | G17: 2877.5 | H17: 364.4 | I17: 109.2 | J17: 672 | K17: 33940.1 | L17: 8081.3 | M17: 1029 | N17: 1292.1 | O17: 1540.9 | P17: 215.2 | Q17: 69.3 | R17: 320.1 | S17: 147.6 | T17: 502.1 | U17: 114.9 | V17: 269.7 | W17: 1787.7 | X17: 2515.2 | Y17: 2028.1 | Z17: 21335 | AA17: 463.2 | AB17: 29.2 | AC17: 36.4 | AD17: 38.3 | AE17: 419.7 | AF17: 148.7 | AG17: 742.5 | AH17: 1617.5 | AI17: 182.7 | AJ17: 614.9 | AK17: 473.1 | AL17: 0 | AM17: 24668 | AN17: 0 | AO17: 38.7 | AP17: 25.1 | AQ17: 44.1 | AR17: 186.4 | AS17: 15.6 | AT17: 4745.1 | AU17: -8905.2
A18: TTL_20T21: Chemicals and pharmaceutical products | C18: 19057.5 | D18: 1385.4 | E18: 418.3 | F18: 50.4 | G18: 2524.5 | H18: 2288.7 | I18: 422.4 | J18: 2499 | K18: 6057.7 | L18: 29472.8 | M18: 6115.7 | N18: 1452.5 | O18: 1014 | P18: 997.2 | Q18: 207.7 | R18: 1029.4 | S18: 215.2 | T18: 849.5 | U18: 207.3 | V18: 1179.2 | W18: 280.2 | X18: 2741.7 | Y18: 1212.3 | Z18: 740.2 | AA18: 124.3 | AB18: 99.4 | AC18: 82.1 | AD18: 31.6 | AE18: 181.1 | AF18: 180 | AG18: 565.1 | AH18: 553.1 | AI18: 329.5 | AJ18: 1797.3 | AK18: 558.7 | AL18: 0 | AM18: 33283.1 | AN18: 0.3 | AO18: 10168.3 | AP18: 1088.4 | AQ18: 27.5 | AR18: 144.2 | AS18: 10.6 | AT18: 8173.9 | AU18: -30495.7
A19: TTL_22: Rubber and plastics products | C19: 316.9 | D19: 46.8 | E19: 216.1 | F19: 31 | G19: 4089.3 | H19: 357.3 | I19: 63.5 | J19: 465.7 | K19: 59.6 | L19: 1359.2 | M19: 4231.4 | N19: 624.2 | O19: 178.3 | P19: 244.5 | Q19: 372.3 | R19: 598.8 | S19: 629 | T19: 3840 | U19: 259.5 | V19: 1055.7 | W19: 166.9 | X19: 3479.3 | Y19: 1502.1 | Z19: 2097.7 | AA19: 110.2 | AB19: 7.2 | AC19: 11.5 | AD19: 7.9 | AE19: 115 | AF19: 81.1 | AG19: 395.5 | AH19: 315.8 | AI19: 77.7 | AJ19: 335.8 | AK19: 204.9 | AL19: 0 | AM19: 4315.3 | AN19: 0 | AO19: 70.9 | AP19: 440 | AQ19: 5.2 | AR19: 6 | AS19: 1 | AT19: 2440.1 | AU19: -4614.6
A20: TTL_23: Other non-metallic mineral products | C20: 1582.3 | D20: 34.6 | E20: 110.2 | F20: 23.8 | G20: 1128.5 | H20: 32.6 | I20: 2.2 | J20: 72.6 | K20: 46.4 | L20: 469 | M20: 145.9 | N20: 2812.8 | O20: 138.4 | P20: 65 | Q20: 8.1 | R20: 103.6 | S20: 110.9 | T20: 753.8 | U20: 66.1 | V20: 230.1 | W20: 527.2 | X20: 15760.3 | Y20: 387.1 | Z20: 80.5 | AA20: 187.1 | AB20: 2.8 | AC20: 7.7 | AD20: 4.2 | AE20: 52.6 | AF20: 156.9 | AG20: 90.7 | AH20: 202.5 | AI20: 58.2 | AJ20: 153.2 | AK20: 110.2 | AL20: 0 | AM20: 1092.2 | AN20: 0 | AO20: 49.3 | AP20: 139.3 | AQ20: 16.5 | AR20: 2.6 | AS20: 0.5 | AT20: 2037.5 | AU20: -1954.8
... A49: OUTPUT: Output at basic prices | C49: 145972.1 | D49: 47609.5 | E49: 26401.3 | F49: 4831.8 | G49: 196073.8 | H49: 44770 | I49: 8044.8 | J49: 30199.9 | K49: 112965.6 | L49: 109321.4 | M49: 30611.7 | N49: 27101.2 | O49: 48034.8 | P49: 27615.6 | Q49: 25782 | R49: 21784.7 | S49: 36501.9 | T49: 65641.3 | U49: 15435.8 | V49: 40199.3 | W49: 97912.3 | X49: 191319.8 | Y49: 333062 | Z49: 152925.9 | AA49: 74861.6 | AB49: 19331.4 | AC49: 48726.2 | AD49: 37984.2 | AE49: 175880.3 | AF49: 168922.7 | AG49: 195796.7 | AH49: 217738.1 | AI49: 127026.8 | AJ49: 122794.9 | AK49: 54530.1 | AL49: 18634.7 | AM49: 0 | AN49: 0 | AO49: 0 | AP49: 0 | AQ49: 0 | AR49: 0 | AS49: 0 | AT49: 0 | AU49: 0
A50: Data extracted on 15 May 2024 14:54 UTC (GMT) from OECD.Stat

Sheet OECD ICESHR
A1: =DotStatQuery(B1) -> #NAME? | B1: Sorry, the query is too large to fit into the Excel cell. You will not be able to update your table with the .Stat Populator.
A2: Dataset: Input-Output Tables (IOTs) 2018 ed.
A3: Variable | C3: ICESHR: Imports content of exports, as % of exports
A4: Country | C4: BRA: Brazil
A5: Time | C5: 2015
A6: Unit | C6: Percentage
A7: To: (sector in column) | C7: ICESHR: Imports content of exports shares
A8: From: (sector in row)
A9: TTL_01T03: Agriculture, forestry and fishing | C9: 9.67
A10: TTL_05T06: Mining and extraction of energy producing products | C10: 16.58
A11: TTL_07T08: Mining and quarrying of non-energy producing products | C11: 12.46
A12: TTL_09: Mining support service activities | C12: 12.36
A13: TTL_10T12: Food products, beverages and tobacco | C13: 11.14
A14: TTL_13T15: Textiles, wearing apparel, leather and related products | C14: 12.15
A15: TTL_16: Wood and of products of wood and cork (except furniture) | C15: 9.96
A16: TTL_17T18: Paper products and printing | C16: 13.38
A17: TTL_19: Coke and refined petroleum products | C17: 24.54
A18: TTL_20T21: Chemicals and pharmaceutical products | C18: 18.38
A19: TTL_22: Rubber and plastics products | C19: 17.59
A20: TTL_23: Other non-metallic mineral products | C20: 12.46
... A44: TOTAL: Total | C44: 12.56
A45: Data extracted on 15 May 2024 16:48 UTC (GMT) from OECD.Stat

Sheet SCNUse128
A1: Tabela 02 - Usos de bens e serviços - 2015 | D1: SCNUse128
A3: Código do produto | B3: Matching ISIC Code | C3: Consumo intermediário das atividades (valores correntes em 1 000 000 R$) | BV3: Demanda final (valores correntes em 1 000 000 R$)
C4: Descrição do produto | D4: 0191 Agricultura, inclusive o apoio à agricultura e a pós-colheita | E4: 0192 Pecuária, inclusive o apoio à pecuária | F4: 0280 Produção florestal; pesca e aquicultura | G4: 0580 Extração de carvão mineral e de minerais não metálicos | H4: 0680 Extração de petróleo e gás, inclusive as atividades de apoio | I4: 0791 Extração de minério de ferro, inclusive beneficiamentos e a aglomeração | J4: 0792 Extração de minerais metálicos não ferrosos, inclusive beneficiamentos | K4: 1091 Abate e produtos de carne, inclusive os produtos do laticínio e da pesca | L4: 1092 Fabricação e refino de açúcar | M4: 1093 Outros produtos alimentares | N4: 1100 Fabricação de bebidas | O4: 1200 Fabricação de produtos do fumo | P4: 1300 Fabricação de produtos têxteis | Q4: 1400 Confecção de artefatos do vestuário e acessórios | R4: 1500 Fabricação de calçados e de artefatos de couro | S4: 1600 Fabricação de produtos da madeira | T4: 1700 Fabricação de celulose, papel e produtos de papel | U4: 1800 Impressão e reprodução de gravações | V4: 1991 Refino de petróleo e coquerias | W4: 1992 Fabricação de biocombustíveis | X4: 2091 Fabricação de químicos orgânicos e inorgânicos, resinas e elastômeros | Y4: 2092 Fabricação de defensivos, desinfestantes, tintas e químicos diversos | Z4: 2093 Fabricação de produtos de limpeza, cosméticos/perfumaria e higiene pessoal | AA4: 2100 Fabricação de produtos farmoquímicos e farmacêuticos | AB4: 2200 Fabricação de produtos de borracha e de material plástico | AC4: 2310 Cimento / Artefatos de cimento, gesso e semelhantes | AD4: 2320 Vidros, cerâmicos e outros prod. de minerais não-metálicos | AE4: 2491 Produção de ferro gusa/ferroligas, siderurgia e tubos de aço sem costura | AF4: 2492 Metalurgia de metais não ferosos e a fundição de metais | AG4: 2500 Fabricação de produtos de metal, exceto máquinas e equipamentos | AH4: 2600 Fabricação de equipamentos de informática, produtos eletrônicos e ópticos | AI4: 2700 Fabricação de máquinas e equipamentos elétricos | AJ4: 2800 Fabricação de máquinas e equipamentos mecânicos | AK4: 2991 Fabricação de automóveis, caminhões e ônibus, exceto peças | AL4: 2992 Fabricação de peças e acessórios para veículos automotores | AM4: 3000 Fabricação de outros equipamentos de transporte, exceto veículos automotores | AN4: 3180 Fabricação de móveis e de produtos de indústrias diversas | AO4: 3300 Manutenção, reparação e instalação de máquinas e equipamentos | AP4: 3510 Transmissão de energia elétrica | AQ4: 3520 Produção de gás; processamento de gás natural; distribuição de combustíveis gasosos por redes urbanas | AR4: 3680 Água, esgoto e gestão de resíduos | AS4: 4180 Construção | AT4: 4580 Comércio por atacado e varejo | AU4: 4900 Transporte terrestre | AV4: 5000 Transporte aquaviário | AW4: 5100 Transporte aéreo | AX4: 5280 Armazenamento, atividades auxiliares dos transportes e correio | AY4: 5500 Alojamento | AZ4: 5600 Alimentação | BA4: 5800 Edição e edição integrada à impressão | BB4: 5980 Atividades de televisão, rádio, cinema e gravação/edição de som e imagem | BC4: 6100 Telecomunicações | BD4: 6280 Desenvolvimento de sistemas e outros serviços de informação | BE4: 6480 Intermediação financeira, seguros e previdência complementar | BF4: 6800 Atividades imobiliárias | BG4: 6980 Atividades jurídicas, contábeis, consultoria e sedes de empresas | BH4: 7180 Serviços de arquitetura, engenharia, testes/análises técnicas e P & D | BI4: 7380 Outras atividades profissionais, científicas e técnicas | BJ4: 7700 Aluguéis não imobiliários e gestão de ativos de propriedade intelectual | BK4: 7880 Outras atividades administrativas e serviços complementares | BL4: 8000 Atividades de vigilância, segurança e investigação | BM4: 8400 Administração pública, defesa e seguridade social | BN4: 8591 Educação pública | BO4: 8592 Educação privada | BP4: 8691 Saúde pública | BQ4: 8692 Saúde privada | BR4: 9080 Atividades artísticas, criativas e de espetáculos | BS4: 9480 Organizações associativas e outros serviços pessoais | BT4: 9700 Serviços domésticos | BU4: Total do produto | BV4: Exportação de bens e serviços (1) | BW4: Consumo do governo | BX4: Consumo das ISFLSF | BY4: Consumo das famílias | BZ4: Formação bruta de capital fixo | CA4: Variação de estoque | CB4: Demanda final | CC4: Demanda total | CE4: 2300 Fabricação de produtos de minerais não metálicos | CF4: 3500 Energia elétrica, gás natural e outras utilidades
D5: =VALUE(LEFT(D$4,4)) -> 191 | E5: =VALUE(LEFT(E$4,4)) -> 192 | F5: =VALUE(LEFT(F$4,4)) -> 280 | G5: =VALUE(LEFT(G$4,4)) -> 580 | H5: =VALUE(LEFT(H$4,4)) -> 680 | I5: =VALUE(LEFT(I$4,4)) -> 791 | J5: =VALUE(LEFT(J$4,4)) -> 792 | K5: =VALUE(LEFT(K$4,4)) -> 1091 | ... BT5: =VALUE(LEFT(BT$4,4)) -> 9700
A6: Matching ISIC Code | D6: =IFERROR(INDEX(SCNtoISIC!$F:$F,MATCH(D$5,SCNtoISIC!$C:$C,0)),0) -> ISIC 01T03 | E6: =IFERROR(INDEX(SCNtoISIC!$F:$F,MATCH(E$5,SCNtoISIC!$C:$C,0)),0) -> ISIC 01T03 | F6: =IFERROR(INDEX(SCNtoISIC!$F:$F,MATCH(F$5,SCNtoISIC!$C:$C,0)),0) -> ISIC 01T03 | G6: =IFERROR(INDEX(SCNtoISIC!$F:$F,MATCH(G$5,SCNtoISIC!$C:$C,0)),0) -> ISIC 05 | H6: =IFERROR(INDEX(SCNtoISIC!$F:$F,MATCH(H$5,SCNtoISIC!$C:$C,0)),0) -> ISIC 06 | I6: =IFERROR(INDEX(SCNtoISIC!$F:$F,MATCH(I$5,SCNtoISIC!$C:$C,0)),0) -> ISIC 07T08 | J6: =IFERROR(INDEX(SCNtoISIC!$F:$F,MATCH(J$5,SCNtoISIC!$C:$C,0)),0) -> ISIC 09 | K6: =IFERROR(INDEX(SCNtoISIC!$F:$F,MATCH(K$5,SCNtoISIC!$C:$C,0)),0) -> ISIC 10T12 | ... BT6: =IFERROR(INDEX(SCNtoISIC!$F:$F,MATCH(BT$5,SCNtoISIC!$C:$C,0)),0) -> ISIC 97T98 | CG6: SCN67
A7: 1911 | B7: =IFERROR(INDEX(SCNtoISIC!$M:$M,MATCH($A7,SCNtoISIC!$J:$J,0)),0) -> ISIC 01T03 | C7: Arroz, trigo e outros cereais | D7: 305 | E7: 302 | F7: 0 | G7: 0 | H7: 0 | I7: 0 | J7: 0 | K7: 46 | L7: 0 | M7: 15554 | N7: 384 | O7: 0 | P7: 0 | Q7: 0 | R7: 0 | S7: 0 | T7: 0 | U7: 0 | V7: 0 | W7: 0 | X7: 0 | Y7: 0 | Z7: 0 | AA7: 0 | AB7: 0 | AC7: =0.6*CE7 -> 0 | AD7: =(1-0.6)*CE7 -> 0 | AE7: 0 | AF7: 0 | AG7: 0 | AH7: 0 | AI7: 0 | AJ7: 0 | AK7: 0 | AL7: 0 | AM7: 0 | AN7: 0 | AO7: 0 | AP7: =2/3*CF7 -> 0 | AQ7: =1/3*CF7 -> 0 | AR7: 0 | AS7: 0 | AT7: 628 | AU7: 0 | AV7: 0 | AW7: 0 | AX7: 0 | AY7: 1 | AZ7: 0 | BA7: 0 | BB7: 0 | BC7: 0 | BD7: 0 | BE7: 0 | BF7: 0 | BG7: 0 | BH7: 0 | BI7: 0 | BJ7: 0 | BK7: 0 | BL7: 0 | BM7: 189 | BN7: 0 | BO7: 0 | BP7: 0 | BQ7: 0 | BR7: 0 | BS7: 0 | BT7: 0 | BU7: 17409 | BV7: 1280 | BW7: 0 | BX7: 0 | BY7: 593 | BZ7: 0 | CA7: 192 | CB7: 2065 | CC7: 19474 | CE7: 0 | CF7: 0 | CG7: 191
A8: 1912 | B8: =IFERROR(INDEX(SCNtoISIC!$M:$M,MATCH($A8,SCNtoISIC!$J:$J,0)),0) -> ISIC 01T03 | C8: Milho em grão | D8: 877 | E8: 3394 | F8: 14 | G8: 0 | H8: 0 | I8: 0 | J8: 0 | K8: 567 | L8: 0 | M8: 9554 | N8: 0 | O8: 0 | P8: 0 | Q8: 0 | R8: 0 | S8: 0 | T8: 0 | U8: 0 | V8: 0 | W8: 0 | X8: 0 | Y8: 0 | Z8: 0 | AA8: 0 | AB8: 0 | AC8: =0.6*CE8 -> 0 | AD8: =(1-0.6)*CE8 -> 0 | AE8: 0 | AF8: 0 | AG8: 0 | AH8: 0 | AI8: 0 | AJ8: 0 | AK8: 0 | AL8: 0 | AM8: 0 | AN8: 0 | AO8: 0 | AP8: =2/3*CF8 -> 0 | AQ8: =1/3*CF8 -> 0 | AR8: 0 | AS8: 0 | AT8: 440 | AU8: 0 | AV8: 0 | AW8: 0 | AX8: 0 | AY8: 0 | AZ8: 153 | BA8: 0 | BB8: 0 | BC8: 0 | BD8: 0 | BE8: 0 | BF8: 0 | BG8: 0 | BH8: 0 | BI8: 0 | BJ8: 0 | BK8: 0 | BL8: 0 | BM8: 193 | BN8: 1 | BO8: 0 | BP8: 0 | BQ8: 2 | BR8: 0 | BS8: 0 | BT8: 0 | BU8: 15195 | BV8: 17925 | BW8: 0 | BX8: 0 | BY8: 4404 | BZ8: 0 | CA8: 389 | CB8: 22718 | CC8: 37913 | CE8: 0 | CF8: 0 | CG8: 191
A9: 1913 | B9: =IFERROR(INDEX(SCNtoISIC!$M:$M,MATCH($A9,SCNtoISIC!$J:$J,0)),0) -> ISIC 01T03 | C9: Algodão herbáceo, outras fibras da lavoura temporária | D9: 318 | E9: 27 | F9: 0 | G9: 0 | H9: 0 | I9: 0 | J9: 0 | K9: 0 | L9: 0 | M9: 569 | N9: 0 | O9: 0 | P9: 3430 | Q9: 0 | R9: 0 | S9: 0 | T9: 0 | U9: 0 | V9: 0 | W9: 59 | X9: 0 | Y9: 0 | Z9: 0 | AA9: 0 | AB9: 0 | AC9: =0.6*CE9 -> 0 | AD9: =(1-0.6)*CE9 -> 0 | AE9: 0 | AF9: 0 | AG9: 0 | AH9: 0 | AI9: 0 | AJ9: 0 | AK9: 0 | AL9: 0 | AM9: 0 | AN9: 0 | AO9: 0 | AP9: =2/3*CF9 -> 0 | AQ9: =1/3*CF9 -> 0 | AR9: 0 | AS9: 0 | AT9: 183 | AU9: 0 | AV9: 0 | AW9: 0 | AX9: 0 | AY9: 0 | AZ9: 0 | BA9: 0 | BB9: 0 | BC9: 0 | BD9: 0 | BE9: 0 | BF9: 0 | BG9: 0 | BH9: 0 | BI9: 0 | BJ9: 0 | BK9: 0 | BL9: 0 | BM9: 0 | BN9: 0 | BO9: 0 | BP9: 0 | BQ9: 0 | BR9: 0 | BS9: 0 | BT9: 0 | BU9: 4586 | BV9: 4679 | BW9: 0 | BX9: 0 | BY9: 6 | BZ9: 0 | CA9: 740 | CB9: 5425 | CC9: 10011 | CE9: 0 | CF9: 0 | CG9: 191
A10: 1914 | B10: =IFERROR(INDEX(SCNtoISIC!$M:$M,MATCH($A10,SCNtoISIC!$J:$J,0)),0) -> ISIC 01T03 | C10: Cana-de-açúcar | D10: 668 | E10: 162 | F10: 4 | G10: 0 | H10: 0 | I10: 0 | J10: 0 | K10: 0 | L10: 27287 | M10: 0 | N10: 1680 | O10: 0 | P10: 0 | Q10: 0 | R10: 0 | S10: 0 | T10: 0 | U10: 0 | V10: 0 | W10: 17784 | X10: 0 | Y10: 0 | Z10: 0 | AA10: 0 | AB10: 0 | AC10: =0.6*CE10 -> 0 | AD10: =(1-0.6)*CE10 -> 0 | AE10: 0 | AF10: 0 | AG10: 0 | AH10: 0 | AI10: 0 | AJ10: 0 | AK10: 0 | AL10: 0 | AM10: 0 | AN10: 0 | AO10: 0 | AP10: =2/3*CF10 -> 0 | AQ10: =1/3*CF10 -> 0 | AR10: 0 | AS10: 0 | AT10: 0 | AU10: 0 | AV10: 0 | AW10: 0 | AX10: 0 | AY10: 0 | AZ10: 940 | BA10: 0 | BB10: 0 | BC10: 0 | BD10: 0 | BE10: 0 | BF10: 0 | BG10: 0 | BH10: 0 | BI10: 0 | BJ10: 0 | BK10: 0 | BL10: 0 | BM10: 0 | BN10: 0 | BO10: 0 | BP10: 0 | BQ10: 0 | BR10: 0 | BS10: 0 | BT10: 0 | BU10: 48525 | BV10: 0 | BW10: 0 | BX10: 0 | BY10: 1316 | BZ10: 0 | CA10: 0 | CB10: 1316 | CC10: 49841 | CE10: 0 | CF10: 0 | CG10: 191
A11: 1915 | B11: =IFERROR(INDEX(SCNtoISIC!$M:$M,MATCH($A11,SCNtoISIC!$J:$J,0)),0) -> ISIC 01T03 | C11: Soja em grão | D11: 2238 | E11: 188 | F11: 0 | G11: 0 | H11: 0 | I11: 0 | J11: 0 | K11: 505 | L11: 0 | M11: 31899 | N11: 0 | O11: 0 | P11: 0 | Q11: 0 | R11: 0 | S11: 0 | T11: 0 | U11: 0 | V11: 0 | W11: 1573 | X11: 0 | Y11: 0 | Z11: 0 | AA11: 0 | AB11: 0 | AC11: =0.6*CE11 -> 0 | AD11: =(1-0.6)*CE11 -> 0 | AE11: 0 | AF11: 0 | AG11: 0 | AH11: 0 | AI11: 0 | AJ11: 0 | AK11: 0 | AL11: 0 | AM11: 0 | AN11: 0 | AO11: 0 | AP11: =2/3*CF11 -> 0 | AQ11: =1/3*CF11 -> 0 | AR11: 0 | AS11: 0 | AT11: 9836 | AU11: 0 | AV11: 0 | AW11: 0 | AX11: 0 | AY11: 0 | AZ11: 0 | BA11: 0 | BB11: 0 | BC11: 0 | BD11: 0 | BE11: 0 | BF11: 0 | BG11: 0 | BH11: 0 | BI11: 0 | BJ11: 0 | BK11: 0 | BL11: 0 | BM11: 0 | BN11: 0 | BO11: 0 | BP11: 0 | BQ11: 0 | BR11: 0 | BS11: 0 | BT11: 0 | BU11: 46239 | BV11: 70046 | BW11: 0 | BX11: 0 | BY11: 86 | BZ11: 0 | CA11: 522 | CB11: 70654 | CC11: 116893 | CE11: 0 | CF11: 0 | CG11: 191
A12: 1916 | B12: =IFERROR(INDEX(SCNtoISIC!$M:$M,MATCH($A12,SCNtoISIC!$J:$J,0)),0) -> ISIC 01T03 | C12: Outros produtos e serviços da lavoura temporária | D12: 4041 | E12: 1005 | F12: 71 | G12: 0 | H12: 0 | I12: 0 | J12: 0 | K12: 37 | L12: 0 | M12: 4424 | N12: 0 | O12: 6180 | P12: 0 | Q12: 0 | R12: 0 | S12: 0 | T12: 0 | U12: 0 | V12: 0 | W12: 389 | X12: 0 | Y12: 0 | Z12: 0 | AA12: 0 | AB12: 0 | AC12: =0.6*CE12 -> 0 | AD12: =(1-0.6)*CE12 -> 0 | AE12: 0 | AF12: 0 | AG12: 0 | AH12: 0 | AI12: 0 | AJ12: 0 | AK12: 0 | AL12: 0 | AM12: 0 | AN12: 0 | AO12: 0 | AP12: =2/3*CF12 -> 0 | AQ12: =1/3*CF12 -> 0 | AR12: 39 | AS12: 7 | AT12: 554 | AU12: 0 | AV12: 0 | AW12: 0 | AX12: 0 | AY12: 262 | AZ12: 2369 | BA12: 0 | BB12: 0 | BC12: 0 | BD12: 0 | BE12: 0 | BF12: 0 | BG12: 5 | BH12: 0 | BI12: 0 | BJ12: 0 | BK12: 153 | BL12: 0 | BM12: 491 | BN12: 414 | BO12: 63 | BP12: 195 | BQ12: 236 | BR12: 1 | BS12: 319 | BT12: 0 | BU12: 21255 | BV12: 1463 | BW12: 65 | BX12: 0 | BY12: 55672 | BZ12: 0 | CA12: 115 | CB12: 57315 | CC12: 78570 | CE12: 0 | CF12: 0 | CG12: 191
A13: 1917 | B13: =IFERROR(INDEX(SCNtoISIC!$M:$M,MATCH($A13,SCNtoISIC!$J:$J,0)),0) -> ISIC 01T03 | C13: Laranja | D13: 11 | E13: 9 | F13: 4 | G13: 0 | H13: 0 | I13: 0 | J13: 0 | K13: 0 | L13: 0 | M13: 6615 | N13: 0 | O13: 0 | P13: 0 | Q13: 0 | R13: 0 | S13: 0 | T13: 0 | U13: 0 | V13: 0 | W13: 0 | X13: 0 | Y13: 0 | Z13: 0 | AA13: 0 | AB13: 0 | AC13: =0.6*CE13 -> 0 | AD13: =(1-0.6)*CE13 -> 0 | AE13: 0 | AF13: 0 | AG13: 0 | AH13: 0 | AI13: 0 | AJ13: 0 | AK13: 0 | AL13: 0 | AM13: 0 | AN13: 0 | AO13: 0 | AP13: =2/3*CF13 -> 0 | AQ13: =1/3*CF13 -> 0 | AR13: 0 | AS13: 0 | AT13: 0 | AU13: 0 | AV13: 0 | AW13: 0 | AX13: 0 | AY13: 93 | AZ13: 327 | BA13: 0 | BB13: 0 | BC13: 0 | BD13: 0 | BE13: 0 | BF13: 0 | BG13: 0 | BH13: 0 | BI13: 0 | BJ13: 0 | BK13: 0 | BL13: 0 | BM13: 8 | BN13: 7 | BO13: 0 | BP13: 3 | BQ13: 0 | BR13: 0 | BS13: 6 | BT13: 0 | BU13: 7083 | BV13: 31 | BW13: 0 | BX13: 0 | BY13: 2283 | BZ13: 163 | CA13: 0 | CB13: 2477 | CC13: 9560 | CE13: 0 | CF13: 0 | CG13: 191
A14: 1918 | B14: =IFERROR(INDEX(SCNtoISIC!$M:$M,MATCH($A14,SCNtoISIC!$J:$J,0)),0) -> ISIC 01T03 | C14: Café em grão | D14: 27 | E14: 110 | F14: 1 | G14: 0 | H14: 0 | I14: 0 | J14: 0 | K14: 0 | L14: 0 | M14: 5024 | N14: 0 | O14: 0 | P14: 0 | Q14: 0 | R14: 0 | S14: 0 | T14: 0 | U14: 0 | V14: 0 | W14: 0 | X14: 0 | Y14: 0 | Z14: 0 | AA14: 0 | AB14: 0 | AC14: =0.6*CE14 -> 0 | AD14: =(1-0.6)*CE14 -> 0 | AE14: 0 | AF14: 0 | AG14: 0 | AH14: 0 | AI14: 0 | AJ14: 0 | AK14: 0 | AL14: 0 | AM14: 0 | AN14: 0 | AO14: 0 | AP14: =2/3*CF14 -> 0 | AQ14: =1/3*CF14 -> 0 | AR14: 0 | AS14: 0 | AT14: 0 | AU14: 0 | AV14: 0 | AW14: 0 | AX14: 0 | AY14: 0 | AZ14: 0 | BA14: 0 | BB14: 0 | BC14: 0 | BD14: 0 | BE14: 0 | BF14: 0 | BG14: 0 | BH14: 3 | BI14: 0 | BJ14: 0 | BK14: 0 | BL14: 0 | BM14: 13 | BN14: 0 | BO14: 0 | BP14: 0 | BQ14: 0 | BR14: 0 | BS14: 8 | BT14: 0 | BU14: 5186 | BV14: 18452 | BW14: 0 | BX14: 0 | BY14: 376 | BZ14: 113 | CA14: -6241 | CB14: 12700 | CC14: 17886 | CE14: 0 | CF14: 0 | CG14: 191
A15: 1919 | B15: =IFERROR(INDEX(SCNtoISIC!$M:$M,MATCH($A15,SCNtoISIC!$J:$J,0)),0) -> ISIC 01T03 | C15: Outros produtos da lavoura permanente | D15: 77 | E15: 19 | F15: 1 | G15: 0 | H15: 0 | I15: 0 | J15: 0 | K15: 1 | L15: 0 | M15: 2761 | N15: 21 | O15: 0 | P15: 0 | Q15: 0 | R15: 0 | S15: 0 | T15: 0 | U15: 0 | V15: 0 | W15: 0 | X15: 0 | Y15: 0 | Z15: 0 | AA15: 0 | AB15: 0 | AC15: =0.6*CE15 -> 0 | AD15: =(1-0.6)*CE15 -> 0 | AE15: 0 | AF15: 0 | AG15: 0 | AH15: 0 | AI15: 0 | AJ15: 0 | AK15: 0 | AL15: 0 | AM15: 0 | AN15: 0 | AO15: 0 | AP15: =2/3*CF15 -> 0 | AQ15: =1/3*CF15 -> 0 | AR15: 0 | AS15: 0 | AT15: 122 | AU15: 0 | AV15: 0 | AW15: 0 | AX15: 0 | AY15: 24 | AZ15: 566 | BA15: 0 | BB15: 0 | BC15: 0 | BD15: 0 | BE15: 0 | BF15: 0 | BG15: 0 | BH15: 2 | BI15: 0 | BJ15: 0 | BK15: 0 | BL15: 0 | BM15: 119 | BN15: 98 | BO15: 3 | BP15: 38 | BQ15: 24 | BR15: 0 | BS15: 4 | BT15: 0 | BU15: 3880 | BV15: 2324 | BW15: 10 | BX15: 0 | BY15: 26423 | BZ15: 130 | CA15: 0 | CB15: 28887 | CC15: 32767 | CE15: 0 | CF15: 0 | CG15: 191
A16: 1921 | B16: =IFERROR(INDEX(SCNtoISIC!$M:$M,MATCH($A16,SCNtoISIC!$J:$J,0)),0) -> ISIC 01T03 | C16: Bovinos e outros animais vivos, produtos animal, caça e serviços | D16: 435 | E16: 1981 | F16: 11 | G16: 0 | H16: 0 | I16: 0 | J16: 0 | K16: 59132 | L16: 0 | M16: 40 | N16: 0 | O16: 0 | P16: 0 | Q16: 0 | R16: 0 | S16: 0 | T16: 0 | U16: 0 | V16: 0 | W16: 0 | X16: 0 | Y16: 0 | Z16: 0 | AA16: 0 | AB16: 0 | AC16: =0.6*CE16 -> 0 | AD16: =(1-0.6)*CE16 -> 0 | AE16: 0 | AF16: 0 | AG16: 0 | AH16: 0 | AI16: 0 | AJ16: 0 | AK16: 0 | AL16: 0 | AM16: 0 | AN16: 0 | AO16: 0 | AP16: =2/3*CF16 -> 0 | AQ16: =1/3*CF16 -> 0 | AR16: 0 | AS16: 0 | AT16: 0 | AU16: 0 | AV16: 0 | AW16: 0 | AX16: 0 | AY16: 0 | AZ16: 0 | BA16: 0 | BB16: 0 | BC16: 0 | BD16: 0 | BE16: 0 | BF16: 0 | BG16: 0 | BH16: 0 | BI16: 7 | BJ16: 0 | BK16: 0 | BL16: 0 | BM16: 98 | BN16: 61 | BO16: 5 | BP16: 0 | BQ16: 119 | BR16: 0 | BS16: 0 | BT16: 0 | BU16: 61889 | BV16: 1237 | BW16: 1 | BX16: 0 | BY16: 1025 | BZ16: 13552 | CA16: 876 | CB16: 16691 | CC16: 78580 | CE16: 0 | CF16: 0 | CG16: 192
A17: 1922 | B17: =IFERROR(INDEX(SCNtoISIC!$M:$M,MATCH($A17,SCNtoISIC!$J:$J,0)),0) -> ISIC 01T03 | C17: Leite de vaca e de outros animais | D17: 64 | E17: 1351 | F17: 40 | G17: 0 | H17: 0 | I17: 0 | J17: 0 | K17: 17148 | L17: 0 | M17: 0 | N17: 0 | O17: 0 | P17: 0 | Q17: 0 | R17: 0 | S17: 0 | T17: 0 | U17: 0 | V17: 0 | W17: 0 | X17: 0 | Y17: 0 | Z17: 0 | AA17: 0 | AB17: 0 | AC17: =0.6*CE17 -> 0 | AD17: =(1-0.6)*CE17 -> 0 | AE17: 0 | AF17: 0 | AG17: 0 | AH17: 0 | AI17: 0 | AJ17: 0 | AK17: 0 | AL17: 0 | AM17: 0 | AN17: 0 | AO17: 0 | AP17: =2/3*CF17 -> 0 | AQ17: =1/3*CF17 -> 0 | AR17: 0 | AS17: 0 | AT17: 0 | AU17: 0 | AV17: 0 | AW17: 0 | AX17: 0 | AY17: 0 | AZ17: 72 | BA17: 0 | BB17: 0 | BC17: 0 | BD17: 0 | BE17: 0 | BF17: 0 | BG17: 0 | BH17: 0 | BI17: 0 | BJ17: 0 | BK17: 0 | BL17: 0 | BM17: 0 | BN17: 0 | BO17: 0 | BP17: 0 | BQ17: 0 | BR17: 0 | BS17: 11 | BT17: 0 | BU17: 18686 | BV17: 0 | BW17: 0 | BX17: 0 | BY17: 12371 | BZ17: 0 | CA17: 0 | CB17: 12371 | CC17: 31057 | CE17: 0 | CF17: 0 | CG17: 192
A18: 1923 | B18: =IFERROR(INDEX(SCNtoISIC!$M:$M,MATCH($A18,SCNtoISIC!$J:$J,0)),0) -> ISIC 01T03 | C18: Suínos | D18: 45 | E18: 225 | F18: 2 | G18: 0 | H18: 0 | I18: 0 | J18: 0 | K18: 8761 | L18: 0 | M18: 0 | N18: 0 | O18: 0 | P18: 0 | Q18: 0 | R18: 0 | S18: 0 | T18: 0 | U18: 0 | V18: 0 | W18: 0 | X18: 0 | Y18: 0 | Z18: 0 | AA18: 0 | AB18: 0 | AC18: =0.6*CE18 -> 0 | AD18: =(1-0.6)*CE18 -> 0 | AE18: 0 | AF18: 0 | AG18: 0 | AH18: 0 | AI18: 0 | AJ18: 0 | AK18: 0 | AL18: 0 | AM18: 0 | AN18: 0 | AO18: 0 | AP18: =2/3*CF18 -> 0 | AQ18: =1/3*CF18 -> 0 | AR18: 0 | AS18: 0 | AT18: 0 | AU18: 0 | AV18: 0 | AW18: 0 | AX18: 0 | AY18: 0 | AZ18: 0 | BA18: 0 | BB18: 0 | BC18: 0 | BD18: 0 | BE18: 0 | BF18: 0 | BG18: 0 | BH18: 0 | BI18: 0 | BJ18: 0 | BK18: 0 | BL18: 0 | BM18: 0 | BN18: 0 | BO18: 0 | BP18: 0 | BQ18: 0 | BR18: 0 | BS18: 0 | BT18: 0 | BU18: 9033 | BV18: 8 | BW18: 0 | BX18: 0 | BY18: 261 | BZ18: 41 | CA18: 0 | CB18: 310 | CC18: 9343 | CE18: 0 | CF18: 0 | CG18: 192
... A93: 33001 | B93: =IFERROR(INDEX(SCNtoISIC!$M:$M,MATCH($A93,SCNtoISIC!$J:$J,0)),0) -> ISIC 31T33 | C93: Manutenção, reparação e instalação de máquinas e equipamentos | D93: 87 | E93: 36 | F93: 118 | G93: 957 | H93: 3903 | I93: 1431 | J93: 1063 | K93: 1333 | L93: 640 | M93: 700 | N93: 494 | O93: 15 | P93: 199 | Q93: 338 | R93: 215 | S93: 663 | T93: 3267 | U93: 1553 | V93: 673 | W93: 900 | X93: 1265 | Y93: 661 | Z93: 171 | AA93: 800 | AB93: 611 | AC93: =0.6*CE93 -> 2061.6 | AD93: =(1-0.6)*CE93 -> 1374.4 | AE93: 10197 | AF93: 2371 | AG93: 919 | AH93: 81 | AI93: 566 | AJ93: 1645 | AK93: 201 | AL93: 682 | AM93: 816 | AN93: 912 | AO93: 1093 | AP93: =2/3*CF93 -> 1238.6667 | AQ93: =1/3*CF93 -> 619.33333 | AR93: 1281 | AS93: 2840 | AT93: 6321 | AU93: 1223 | AV93: 1635 | AW93: 796 | AX93: 3766 | AY93: 8 | AZ93: 281 | BA93: 781 | BB93: 190 | BC93: 634 | BD93: 1109 | BE93: 418 | BF93: 117 | BG93: 1136 | BH93: 257 | BI93: 165 | BJ93: 1226 | BK93: 1067 | BL93: 266 | BM93: 1438 | BN93: 156 | BO93: 0 | BP93: 1320 | BQ93: 519 | BR93: 692 | BS93: 616 | BT93: 0 | BU93: 77128 | BV93: 2388 | BW93: 0 | BX93: 0 | BY93: 504 | BZ93: 12099 | CA93: 0 | CB93: 14991 | CC93: 92119 | CE93: 3436 | CF93: 1858 | CG93: 3510
A94: 35101 | B94: =IFERROR(INDEX(SCNtoISIC!$M:$M,MATCH($A94,SCNtoISIC!$J:$J,0)),0) -> ISIC 351 | C94: Transmissão de energia elétrica | D94: =2/3*D$146 -> 4978.6667 | E94: =2/3*E$146 -> 3338 | F94: =2/3*F$146 -> 274 | G94: =2/3*G$146 -> 464.66667 | H94: =2/3*H$146 -> 206 | I94: =2/3*I$146 -> 770.66667 | J94: =2/3*J$146 -> 319.33333 | K94: =2/3*K$146 -> 1095.3333 | ... AB94: =2/3*AB$146 -> 1484.6667 | AC94: =0.6*CE94 -> 1846 | AD94: =(1-0.6)*CE94 -> 1230.6667 | AE94: =2/3*AE$146 -> 2403.3333 | AF94: =2/3*AF$146 -> 1866.6667 | AG94: =2/3*AG$146 -> 878 | AH94: =2/3*AH$146 -> 112.66667 | AI94: =2/3*AI$146 -> 438.66667 | AJ94: =2/3*AJ$146 -> 467.33333 | AK94: =2/3*AK$146 -> 337.33333 | AL94: =2/3*AL$146 -> 792.66667 | ... AO94: =2/3*AO$146 -> 173.33333 | AP94: =2/3*CF94 -> 42050.667 | AQ94: =1/3*CF94 -> 21025.333 | AR94: =2/3*AR$146 -> 2305.3333 | AS94: =2/3*AS$146 -> 426.66667 | AT94: =2/3*AT$146 -> 14080 | AU94: =2/3*AU$146 -> 936.66667 | AV94: =2/3*AV$146 -> 40.666667 | AW94: =2/3*AW$146 -> 27.333333 | AX94: =2/3*AX$146 -> 779.33333 | AY94: =2/3*AY$146 -> 909.33333 | ... CC94: =2/3*CC$146 -> 206927.33 | CE94: =2/3*CE$146 -> 3076.6667 | CF94: =2/3*CF$146 -> 63076 | CG94: 3520
A95: 35201 | B95: =IFERROR(INDEX(SCNtoISIC!$M:$M,MATCH($A95,SCNtoISIC!$J:$J,0)),0) -> ISIC 352T353 | C95: Produção de gás; processamento de gás natural; distribuição de combustíveis gasosos por redes urbanas | D95: =1/3*D$146 -> 2489.3333 | E95: =1/3*E$146 -> 1669 | F95: =1/3*F$146 -> 137 | G95: =1/3*G$146 -> 232.33333 | H95: =1/3*H$146 -> 103 | I95: =1/3*I$146 -> 385.33333 | J95: =1/3*J$146 -> 159.66667 | K95: =1/3*K$146 -> 547.66667 | ... AB95: =1/3*AB$146 -> 742.33333 | AC95: =0.6*CE95 -> 923 | AD95: =(1-0.6)*CE95 -> 615.33333 | AE95: =1/3*AE$146 -> 1201.6667 | AF95: =1/3*AF$146 -> 933.33333 | AG95: =1/3*AG$146 -> 439 | AH95: =1/3*AH$146 -> 56.333333 | AI95: =1/3*AI$146 -> 219.33333 | AJ95: =1/3*AJ$146 -> 233.66667 | AK95: =1/3*AK$146 -> 168.66667 | AL95: =1/3*AL$146 -> 396.33333 | ... AO95: =1/3*AO$146 -> 86.666667 | AP95: =2/3*CF95 -> 21025.333 | AQ95: =1/3*CF95 -> 10512.667 | AR95: =1/3*AR$146 -> 1152.6667 | AS95: =1/3*AS$146 -> 213.33333 | AT95: =1/3*AT$146 -> 7040 | AU95: =1/3*AU$146 -> 468.33333 | AV95: =1/3*AV$146 -> 20.333333 | AW95: =1/3*AW$146 -> 13.666667 | AX95: =1/3*AX$146 -> 389.66667 | AY95: =1/3*AY$146 -> 454.66667 | ... CC95: =1/3*CC$146 -> 103463.67 | CE95: =1/3*CE$146 -> 1538.3333 | CF95: =1/3*CF$146 -> 31538 | CG95: 3680
A96: 36801 | B96: =IFERROR(INDEX(SCNtoISIC!$M:$M,MATCH($A96,SCNtoISIC!$J:$J,0)),0) -> ISIC 36T39 | C96: Água, esgoto, reciclagem e gestão de resíduos | D96: 3 | E96: 1 | F96: 1 | G96: 30 | H96: 46 | I96: 184 | J96: 69 | K96: 146 | L96: 54 | M96: 294 | N96: 536 | O96: 1 | P96: 60 | Q96: 28 | R96: 22 | S96: 213 | T96: 344 | U96: 8 | V96: 426 | W96: 28 | X96: 623 | Y96: 429 | Z96: 126 | AA96: 76 | AB96: 521 | AC96: =0.6*CE96 -> 460.8 | AD96: =(1-0.6)*CE96 -> 307.2 | AE96: 4867 | AF96: 2369 | AG96: 169 | AH96: 20 | AI96: 61 | AJ96: 101 | AK96: 89 | AL96: 258 | AM96: 133 | AN96: 78 | AO96: 27 | AP96: =2/3*CF96 -> 54 | AQ96: =1/3*CF96 -> 27 | AR96: 958 | AS96: 279 | AT96: 4160 | AU96: 264 | AV96: 9 | AW96: 6 | AX96: 704 | AY96: 330 | AZ96: 1109 | BA96: 32 | BB96: 51 | BC96: 43 | BD96: 94 | BE96: 519 | BF96: 368 | BG96: 493 | BH96: 65 | BI96: 28 | BJ96: 43 | BK96: 4115 | BL96: 29 | BM96: 10446 | BN96: 1335 | BO96: 214 | BP96: 1721 | BQ96: 1874 | BR96: 94 | BS96: 1689 | BT96: 0 | BU96: 44362 | BV96: 4 | BW96: 0 | BX96: 0 | BY96: 25835 | BZ96: 0 | CA96: 439 | CB96: 26278 | CC96: 70640 | CE96: 768 | CF96: 81 | CG96: 4180
A97: 41801 | B97: =IFERROR(INDEX(SCNtoISIC!$M:$M,MATCH($A97,SCNtoISIC!$J:$J,0)),0) -> ISIC 41T43 | C97: Edificações | D97: 21 | E97: 41 | F97: 3 | G97: 1 | H97: 435 | I97: 215 | J97: 38 | K97: 0 | L97: 0 | M97: 6 | N97: 0 | O97: 0 | P97: 0 | Q97: 0 | R97: 0 | S97: 0 | T97: 10 | U97: 0 | V97: 0 | W97: 27 | X97: 71 | Y97: 0 | Z97: 0 | AA97: 0 | AB97: 0 | AC97: =0.6*CE97 -> 2.4 | AD97: =(1-0.6)*CE97 -> 1.6 | AE97: 18 | AF97: 12 | AG97: 33 | AH97: 72 | AI97: 3 | AJ97: 51 | AK97: 228 | AL97: 13 | AM97: 228 | AN97: 13 | AO97: 0 | AP97: =2/3*CF97 -> 0 | AQ97: =1/3*CF97 -> 0 | AR97: 0 | AS97: 31663 | AT97: 1077 | AU97: 18 | AV97: 5 | AW97: 2 | AX97: 298 | AY97: 236 | AZ97: 0 | BA97: 10 | BB97: 225 | BC97: 2 | BD97: 832 | BE97: 350 | BF97: 540 | BG97: 55 | BH97: 149 | BI97: 0 | BJ97: 178 | BK97: 1952 | BL97: 0 | BM97: 3566 | BN97: 1027 | BO97: 365 | BP97: 1723 | BQ97: 0 | BR97: 9 | BS97: 272 | BT97: 0 | BU97: 46097 | BV97: 236 | BW97: 0 | BX97: 0 | BY97: 0 | BZ97: 340306 | CA97: 0 | CB97: 340542 | CC97: 386639 | CE97: 4 | CF97: 0 | CG97: 4180
A98: 41802 | B98: =IFERROR(INDEX(SCNtoISIC!$M:$M,MATCH($A98,SCNtoISIC!$J:$J,0)),0) -> ISIC 41T43 | C98: Obras de infraestrutura | D98: 0 | E98: 0 | F98: 0 | G98: 0 | H98: 1251 | I98: 956 | J98: 154 | K98: 0 | L98: 0 | M98: 0 | N98: 0 | O98: 0 | P98: 0 | Q98: 0 | R98: 0 | S98: 0 | T98: 0 | U98: 0 | V98: 0 | W98: 0 | X98: 0 | Y98: 0 | Z98: 0 | AA98: 0 | AB98: 0 | AC98: =0.6*CE98 -> 0 | AD98: =(1-0.6)*CE98 -> 0 | AE98: 79 | AF98: 40 | AG98: 0 | AH98: 0 | AI98: 0 | AJ98: 0 | AK98: 0 | AL98: 0 | AM98: 0 | AN98: 0 | AO98: 0 | AP98: =2/3*CF98 -> 0 | AQ98: =1/3*CF98 -> 0 | AR98: 4426 | AS98: 8021 | AT98: 0 | AU98: 248 | AV98: 0 | AW98: 0 | AX98: 334 | AY98: 0 | AZ98: 0 | BA98: 0 | BB98: 0 | BC98: 957 | BD98: 0 | BE98: 0 | BF98: 0 | BG98: 0 | BH98: 0 | BI98: 0 | BJ98: 0 | BK98: 0 | BL98: 0 | BM98: 7973 | BN98: 2 | BO98: 0 | BP98: 0 | BQ98: 0 | BR98: 0 | BS98: 97 | BT98: 0 | BU98: 24538 | BV98: 0 | BW98: 0 | BX98: 0 | BY98: 0 | BZ98: 119076 | CA98: 0 | CB98: 119076 | CC98: 143614 | CE98: 0 | CF98: 0 | CG98: 4180
A99: 41803 | B99: =IFERROR(INDEX(SCNtoISIC!$M:$M,MATCH($A99,SCNtoISIC!$J:$J,0)),0) -> ISIC 41T43 | C99: Serviços especializados para construção | D99: 70 | E99: 152 | F99: 8 | G99: 3 | H99: 316 | I99: 11 | J99: 150 | K99: 0 | L99: 4 | M99: 1 | N99: 0 | O99: 0 | P99: 23 | Q99: 0 | R99: 0 | S99: 0 | T99: 11 | U99: 18 | V99: 22 | W99: 0 | X99: 0 | Y99: 2 | Z99: 0 | AA99: 0 | AB99: 0 | AC99: =0.6*CE99 -> 13.8 | AD99: =(1-0.6)*CE99 -> 9.2 | AE99: 18 | AF99: 1548 | AG99: 21 | AH99: 0 | AI99: 9 | AJ99: 27 | AK99: 0 | AL99: 9 | AM99: 0 | AN99: 3 | AO99: 0 | AP99: =2/3*CF99 -> 0 | AQ99: =1/3*CF99 -> 0 | AR99: 0 | AS99: 26096 | AT99: 57 | AU99: 9 | AV99: 0 | AW99: 0 | AX99: 764 | AY99: 42 | AZ99: 392 | BA99: 0 | BB99: 0 | BC99: 4087 | BD99: 0 | BE99: 1442 | BF99: 1151 | BG99: 214 | BH99: 650 | BI99: 3 | BJ99: 2 | BK99: 810 | BL99: 9 | BM99: 1874 | BN99: 258 | BO99: 0 | BP99: 1955 | BQ99: 0 | BR99: 104 | BS99: 11 | BT99: 0 | BU99: 42379 | BV99: 4462 | BW99: 0 | BX99: 0 | BY99: 0 | BZ99: 103136 | CA99: 0 | CB99: 107598 | CC99: 149977 | CE99: 23 | CF99: 0 | CG99: 4580
A100: 45801 | B100: =IFERROR(INDEX(SCNtoISIC!$M:$M,MATCH($A100,SCNtoISIC!$J:$J,0)),0) -> 0 | C100: Comércio por atacado e varejo | D100: 184 | E100: 43 | F100: 21 | G100: 100 | H100: 123 | I100: 717 | J100: 139 | K100: 6005 | L100: 275 | M100: 3826 | N100: 205 | O100: 166 | P100: 540 | Q100: 689 | R100: 880 | S100: 242 | T100: 1645 | U100: 63 | V100: 470 | W100: 418 | X100: 713 | Y100: 1077 | Z100: 77 | AA100: 1303 | AB100: 1609 | AC100: =0.6*CE100 -> 830.4 | AD100: =(1-0.6)*CE100 -> 553.6 | AE100: 1322 | AF100: 433 | AG100: 1218 | AH100: 1239 | AI100: 1040 | AJ100: 4552 | AK100: 346 | AL100: 28 | AM100: 175 | AN100: 670 | AO100: 82 | AP100: =2/3*CF100 -> 254.66667 | AQ100: =1/3*CF100 -> 127.33333 | AR100: 630 | AS100: 565 | AT100: 10138 | AU100: 6130 | AV100: 0 | AW100: 0 | AX100: 429 | AY100: 0 | AZ100: 98 | BA100: 455 | BB100: 571 | BC100: 3226 | BD100: 316 | BE100: 149 | BF100: 29 | BG100: 391 | BH100: 141 | BI100: 179 | BJ100: 862 | BK100: 350 | BL100: 196 | BM100: 1555 | BN100: 278 | BO100: 11 | BP100: 1042 | BQ100: 632 | BR100: 69 | BS100: 47 | BT100: 0 | BU100: 62890 | BV100: 5547 | BW100: 0 | BX100: 0 | BY100: 42731 | BZ100: 0 | CA100: 0 | CB100: 48278 | CC100: 111168 | CE100: 1384 | CF100: 382 | CG100: 4580
A101: 49001 | B101: =IFERROR(INDEX(SCNtoISIC!$M:$M,MATCH($A101,SCNtoISIC!$J:$J,0)),0) -> ISIC 45T47 | C101: Transporte terrestre de carga | D101: 4198 | E101: 669 | F101: 402 | G101: 753 | H101: 4660 | I101: 1826 | J101: 662 | K101: 8350 | L101: 1527 | M101: 11243 | N101: 2348 | O101: 120 | P101: 785 | Q101: 512 | R101: 771 | S101: 416 | T101: 2389 | U101: 274 | V101: 3317 | W101: 857 | X101: 4092 | Y101: 1605 | Z101: 1191 | AA101: 2338 | AB101: 2093 | AC101: =0.6*CE101 -> 1360.8 | AD101: =(1-0.6)*CE101 -> 907.2 | AE101: 3967 | AF101: 483 | AG101: 1847 | AH101: 1079 | AI101: 1117 | AJ101: 1385 | AK101: 3184 | AL101: 1043 | AM101: 554 | AN101: 1192 | AO101: 50 | AP101: =2/3*CF101 -> 2474 | AQ101: =1/3*CF101 -> 1237 | AR101: 248 | AS101: 1759 | AT101: 35632 | AU101: 32030 | AV101: 110 | AW101: 69 | AX101: 4432 | AY101: 20 | AZ101: 710 | BA101: 394 | BB101: 117 | BC101: 206 | BD101: 148 | BE101: 467 | BF101: 11 | BG101: 531 | BH101: 307 | BI101: 48 | BJ101: 339 | BK101: 119 | BL101: 62 | BM101: 1379 | BN101: 96 | BO101: 2 | BP101: 325 | BQ101: 0 | BR101: 69 | BS101: 104 | BT101: 0 | BU101: 159012 | BV101: 1202 | BW101: 0 | BX101: 0 | BY101: 1602 | BZ101: 0 | CA101: 0 | CB101: 2804 | CC101: 161816 | CE101: 2268 | CF101: 3711 | CG101: 4900
A102: 49002 | B102: =IFERROR(INDEX(SCNtoISIC!$M:$M,MATCH($A102,SCNtoISIC!$J:$J,0)),0) -> ISIC 49T53 | C102: Transporte terrestre de passageiros | D102: 5 | E102: 3 | F102: 21 | G102: 14 | H102: 406 | I102: 308 | J102: 126 | K102: 75 | L102: 35 | M102: 121 | N102: 14 | O102: 0 | P102: 2 | Q102: 129 | R102: 6 | S102: 544 | T102: 1 | U102: 0 | V102: 0 | W102: 60 | X102: 177 | Y102: 140 | Z102: 16 | AA102: 118 | AB102: 198 | AC102: =0.6*CE102 -> 179.4 | AD102: =(1-0.6)*CE102 -> 119.6 | AE102: 74 | AF102: 13 | AG102: 325 | AH102: 3 | AI102: 55 | AJ102: 484 | AK102: 0 | AL102: 244 | AM102: 2 | AN102: 9 | AO102: 75 | AP102: =2/3*CF102 -> 0 | AQ102: =1/3*CF102 -> 0 | AR102: 7 | AS102: 78 | AT102: 48 | AU102: 153 | AV102: 0 | AW102: 0 | AX102: 39 | AY102: 20 | AZ102: 56 | BA102: 0 | BB102: 99 | BC102: 16 | BD102: 184 | BE102: 370 | BF102: 24 | BG102: 8 | BH102: 817 | BI102: 39 | BJ102: 24 | BK102: 233 | BL102: 31 | BM102: 2183 | BN102: 2001 | BO102: 1149 | BP102: 892 | BQ102: 0 | BR102: 13 | BS102: 2253 | BT102: 0 | BU102: 14839 | BV102: 567 | BW102: 0 | BX102: 0 | BY102: 88885 | BZ102: 0 | CA102: 0 | CB102: 89452 | CC102: 104291 | CE102: 299 | CF102: 0 | CG102: 4900
A103: 50001 | B103: =IFERROR(INDEX(SCNtoISIC!$M:$M,MATCH($A103,SCNtoISIC!$J:$J,0)),0) -> ISIC 49T53 | C103: Transporte aquaviário | D103: 0 | E103: 0 | F103: 0 | G103: 0 | H103: 8164 | I103: 0 | J103: 18 | K103: 2064 | L103: 124 | M103: 612 | N103: 2 | O103: 1 | P103: 14 | Q103: 23 | R103: 10 | S103: 215 | T103: 1991 | U103: 30 | V103: 90 | W103: 16 | X103: 1105 | Y103: 18 | Z103: 67 | AA103: 3 | AB103: 66 | AC103: =0.6*CE103 -> 112.2 | AD103: =(1-0.6)*CE103 -> 74.8 | AE103: 518 | AF103: 19 | AG103: 50 | AH103: 74 | AI103: 71 | AJ103: 391 | AK103: 322 | AL103: 108 | AM103: 265 | AN103: 1 | AO103: 9 | AP103: =2/3*CF103 -> 0 | AQ103: =1/3*CF103 -> 0 | AR103: 0 | AS103: 6 | AT103: 1787 | AU103: 1119 | AV103: 1731 | AW103: 0 | AX103: 89 | AY103: 0 | AZ103: 25 | BA103: 0 | BB103: 3 | BC103: 0 | BD103: 24 | BE103: 0 | BF103: 0 | BG103: 1 | BH103: 3 | BI103: 0 | BJ103: 0 | BK103: 384 | BL103: 1 | BM103: 0 | BN103: 0 | BO103: 0 | BP103: 0 | BQ103: 0 | BR103: 1 | BS103: 0 | BT103: 0 | BU103: 21822 | BV103: 6619 | BW103: 0 | BX103: 0 | BY103: 1910 | BZ103: 0 | CA103: 0 | CB103: 8529 | CC103: 30351 | CE103: 187 | CF103: 0 | CG103: 5000
A104: 51001 | B104: =IFERROR(INDEX(SCNtoISIC!$M:$M,MATCH($A104,SCNtoISIC!$J:$J,0)),0) -> ISIC 49T53 | C104: Transporte aéreo | D104: 1 | E104: 0 | F104: 4 | G104: 4 | H104: 1991 | I104: 10 | J104: 28 | K104: 282 | L104: 6 | M104: 236 | N104: 50 | O104: 25 | P104: 31 | Q104: 33 | R104: 42 | S104: 41 | T104: 99 | U104: 17 | V104: 42 | W104: 4 | X104: 239 | Y104: 273 | Z104: 11 | AA104: 135 | AB104: 42 | AC104: =0.6*CE104 -> 80.4 | AD104: =(1-0.6)*CE104 -> 53.6 | AE104: 84 | AF104: 13 | AG104: 52 | AH104: 242 | AI104: 164 | AJ104: 212 | AK104: 213 | AL104: 57 | AM104: 57 | AN104: 35 | AO104: 63 | AP104: =2/3*CF104 -> 401.33333 | AQ104: =1/3*CF104 -> 200.66667 | AR104: 44 | AS104: 1437 | AT104: 3415 | AU104: 205 | AV104: 83 | AW104: 11 | AX104: 642 | AY104: 72 | AZ104: 53 | BA104: 20 | BB104: 162 | BC104: 207 | BD104: 676 | BE104: 2898 | BF104: 62 | BG104: 944 | BH104: 340 | BI104: 555 | BJ104: 91 | BK104: 323 | BL104: 25 | BM104: 1247 | BN104: 352 | BO104: 2076 | BP104: 462 | BQ104: 0 | BR104: 92 | BS104: 8775 | BT104: 0 | BU104: 30843 | BV104: 5991 | BW104: 0 | BX104: 0 | BY104: 10407 | BZ104: 0 | CA104: 0 | CB104: 16398 | CC104: 47241 | CE104: 134 | CF104: 602 | CG104: 5100
A105: 52801 | B105: =IFERROR(INDEX(SCNtoISIC!$M:$M,MATCH($A105,SCNtoISIC!$J:$J,0)),0) -> ISIC 49T53 | C105: Armazenamento e serviços auxiliares aos transportes | D105: 897 | E105: 53 | F105: 223 | G105: 26 | H105: 4005 | I105: 2590 | J105: 610 | K105: 3005 | L105: 1785 | M105: 3712 | N105: 2275 | O105: 28 | P105: 111 | Q105: 7 | R105: 77 | S105: 215 | T105: 1085 | U105: 157 | V105: 783 | W105: 865 | X105: 1000 | Y105: 434 | Z105: 422 | AA105: 601 | AB105: 192 | AC105: =0.6*CE105 -> 159 | AD105: =(1-0.6)*CE105 -> 106 | AE105: 2762 | AF105: 138 | AG105: 940 | AH105: 645 | AI105: 930 | AJ105: 315 | AK105: 3800 | AL105: 516 | AM105: 516 | AN105: 240 | AO105: 232 | AP105: =2/3*CF105 -> 60 | AQ105: =1/3*CF105 -> 30 | AR105: 9 | AS105: 323 | AT105: 12083 | AU105: 7842 | AV105: 2914 | AW105: 4651 | AX105: 3579 | AY105: 2 | AZ105: 33 | BA105: 20 | BB105: 42 | BC105: 120 | BD105: 17 | BE105: 215 | BF105: 1 | BG105: 66 | BH105: 92 | BI105: 194 | BJ105: 29 | BK105: 142 | BL105: 34 | BM105: 1668 | BN105: 121 | BO105: 0 | BP105: 181 | BQ105: 0 | BR105: 2 | BS105: 1071 | BT105: 0 | BU105: 71998 | BV105: 9008 | BW105: 0 | BX105: 0 | BY105: 24848 | BZ105: 0 | CA105: 0 | CB105: 33856 | CC105: 105854 | CE105: 265 | CF105: 90 | CG105: 5280
A106: 52802 | B106: =IFERROR(INDEX(SCNtoISIC!$M:$M,MATCH($A106,SCNtoISIC!$J:$J,0)),0) -> ISIC 49T53 | C106: Correio e outros serviços de entrega | D106: 1 | E106: 0 | F106: 1 | G106: 3 | H106: 31 | I106: 0 | J106: 7 | K106: 90 | L106: 60 | M106: 164 | N106: 26 | O106: 6 | P106: 73 | Q106: 110 | R106: 104 | S106: 21 | T106: 160 | U106: 49 | V106: 37 | W106: 21 | X106: 44 | Y106: 376 | Z106: 16 | AA106: 115 | AB106: 72 | AC106: =0.6*CE106 -> 68.4 | AD106: =(1-0.6)*CE106 -> 45.6 | AE106: 22 | AF106: 12 | AG106: 95 | AH106: 180 | AI106: 85 | AJ106: 66 | AK106: 152 | AL106: 113 | AM106: 151 | AN106: 145 | AO106: 21 | AP106: =2/3*CF106 -> 411.33333 | AQ106: =1/3*CF106 -> 205.66667 | AR106: 14 | AS106: 379 | AT106: 4547 | AU106: 152 | AV106: 9 | AW106: 9 | AX106: 1624 | AY106: 57 | AZ106: 198 | BA106: 60 | BB106: 41 | BC106: 509 | BD106: 127 | BE106: 4784 | BF106: 205 | BG106: 522 | BH106: 154 | BI106: 69 | BJ106: 186 | BK106: 540 | BL106: 37 | BM106: 1906 | BN106: 195 | BO106: 427 | BP106: 298 | BQ106: 267 | BR106: 55 | BS106: 454 | BT106: 0 | BU106: 21185 | BV106: 96 | BW106: 0 | BX106: 0 | BY106: 2269 | BZ106: 0 | CA106: 0 | CB106: 2365 | CC106: 23550 | CE106: 114 | CF106: 617 | CG106: 5280
A107: 55001 | B107: =IFERROR(INDEX(SCNtoISIC!$M:$M,MATCH($A107,SCNtoISIC!$J:$J,0)),0) -> ISIC 55T56 | C107: Serviços de alojamento em hotéis e similares | D107: 4 | E107: 1 | F107: 4 | G107: 12 | H107: 352 | I107: 81 | J107: 25 | K107: 387 | L107: 37 | M107: 377 | N107: 74 | O107: 36 | P107: 36 | Q107: 33 | R107: 40 | S107: 11 | T107: 110 | U107: 13 | V107: 41 | W107: 19 | X107: 166 | Y107: 187 | Z107: 49 | AA107: 276 | AB107: 130 | AC107: =0.6*CE107 -> 69 | AD107: =(1-0.6)*CE107 -> 46 | AE107: 228 | AF107: 59 | AG107: 223 | AH107: 206 | AI107: 172 | AJ107: 416 | AK107: 146 | AL107: 103 | AM107: 108 | AN107: 155 | AO107: 99 | AP107: =2/3*CF107 -> 214.66667 | AQ107: =1/3*CF107 -> 107.33333 | AR107: 18 | AS107: 1713 | AT107: 4307 | AU107: 252 | AV107: 7 | AW107: 105 | AX107: 266 | AY107: 0 | AZ107: 39 | BA107: 115 | BB107: 194 | BC107: 144 | BD107: 635 | BE107: 1526 | BF107: 72 | BG107: 419 | BH107: 403 | BI107: 186 | BJ107: 193 | BK107: 189 | BL107: 59 | BM107: 2947 | BN107: 346 | BO107: 458 | BP107: 470 | BQ107: 0 | BR107: 188 | BS107: 8830 | BT107: 0 | BU107: 28934 | BV107: 6574 | BW107: 0 | BX107: 0 | BY107: 11281 | BZ107: 0 | CA107: 0 | CB107: 17855 | CC107: 46789 | CE107: 115 | CF107: 322 | CG107: 5500
... A134: 97001 | B134: =IFERROR(INDEX(SCNtoISIC!$M:$M,MATCH($A134,SCNtoISIC!$J:$J,0)),0) -> ISIC 97T98 | C134: Serviços domésticos | D134: 0 | E134: 0 | F134: 0 | G134: 0 | H134: 0 | I134: 0 | J134: 0 | K134: 0 | L134: 0 | M134: 0 | N134: 0 | O134: 0 | P134: 0 | Q134: 0 | R134: 0 | S134: 0 | T134: 0 | U134: 0 | V134: 0 | W134: 0 | X134: 0 | Y134: 0 | Z134: 0 | AA134: 0 | AB134: 0 | AC134: =0.6*CE134 -> 0 | AD134: =(1-0.6)*CE134 -> 0 | AE134: 0 | AF134: 0 | AG134: 0 | AH134: 0 | AI134: 0 | AJ134: 0 | AK134: 0 | AL134: 0 | AM134: 0 | AN134: 0 | AO134: 0 | AP134: =2/3*CF134 -> 0 | AQ134: =1/3*CF134 -> 0 | AR134: 0 | AS134: 0 | AT134: 0 | AU134: 0 | AV134: 0 | AW134: 0 | AX134: 0 | AY134: 0 | AZ134: 0 | BA134: 0 | BB134: 0 | BC134: 0 | BD134: 0 | BE134: 0 | BF134: 0 | BG134: 0 | BH134: 0 | BI134: 0 | BJ134: 0 | BK134: 0 | BL134: 0 | BM134: 0 | BN134: 0 | BO134: 0 | BP134: 0 | BQ134: 0 | BR134: 0 | BS134: 0 | BT134: 0 | BU134: 0 | BV134: 0 | BW134: 0 | BX134: 0 | BY134: 61996 | BZ134: 0 | CA134: 0 | CB134: 61996 | CC134: 61996 | CE134: 0 | CF134: 0 | CG134: 9700
D135: =SUM(D7:D134) -> 146174 | E135: =SUM(E7:E134) -> 65569 | F135: =SUM(F7:F134) -> 8020 | G135: =SUM(G7:G134) -> 10878 | H135: =SUM(H7:H134) -> 98428 | I135: =SUM(I7:I134) -> 28837 | J135: =SUM(J7:J134) -> 11661 | K135: =SUM(K7:K134) -> 214821 | ... BU135: =SUM(BU7:BU134) -> 5071268
A136: Total | D136: 146174 | E136: 65569 | F136: 8020 | G136: 10878 | H136: 98428 | I136: 28837 | J136: 11661 | K136: 214821 | L136: 40678 | M136: 204687 | N136: 53521 | O136: 10826 | P136: 33055 | Q136: 36373 | R136: 26696 | S136: 16748 | T136: 57550 | U136: 11077 | V136: 336922 | W136: 34161 | X136: 120094 | Y136: 59389 | Z136: 32078 | AA136: 34825 | AB136: 75094 | AC136: =0.6*CE136 -> 37091.4 | AD136: =(1-0.6)*CE136 -> 24727.6 | AE136: 79845 | AF136: 44607 | AG136: 56967 | AH136: 71494 | AI136: 54961 | AJ136: 82995 | AK136: 124036 | AL136: 52081 | AM136: 38950 | AN136: 39022 | AO136: 40275 | AP136: =2/3*CF136 -> 116866 | AQ136: =1/3*CF136 -> 58433 | AR136: 25127 | AS136: 336290 | AT136: 415048 | AU136: 187084 | AV136: 11322 | AW136: 30456 | AX136: 50054 | AY136: 10865 | AZ136: 113919 | BA136: 11729 | BB136: 24162 | BC136: 95736 | BD136: 42835 | BE136: 209334 | BF136: 47045 | BG136: 62343 | BH136: 25978 | BI136: 60911 | BJ136: 16122 | BK136: 61584 | BL136: 7012 | BM136: 210478 | BN136: 51733 | BO136: 34132 | BP136: 60011 | BQ136: 89394 | BR136: 15492 | BS136: 74559 | BT136: 0 | BU136: 5071268 | BV136: 773468 | BW136: 1185776 | BX136: 87323 | BY136: 3747870 | BZ136: 1069397 | CA136: -25433 | CB136: 6838401 | CC136: 11909669 | CE136: 61819 | CF136: 175299
BV137: =SUM(D136:BT136) -> 5071268
C138: Remunerações | D138: 26121 | E138: 21490 | F138: 2199 | G138: 4040 | H138: 22138 | I138: 4349 | J138: 2264 | K138: 25736 | L138: 8420 | M138: 28893 | N138: 8407 | O138: 1379 | P138: 9992 | Q138: 17703 | R138: 9781 | S138: 5910 | T138: 11483 | U138: 5677 | V138: 6968 | W138: 6275 | X138: 11285 | Y138: 9342 | Z138: 5589 | AA138: 11215 | AB138: 20552 | AC138: 20003 | AE138: 12073 | AF138: 22659 | AG138: 10116 | AH138: 14442 | AI138: 28171 | AJ138: 20227 | AK138: 17896 | AL138: 9718 | AM138: 16132 | AN138: 11883 | AO138: 16133 | AP138: 16809 | AR138: 126609 | AS138: 44837 | AT138: 299831 | AU138: 78373 | AV138: 5048 | AW138: 7103 | AX138: 40882 | AY138: 9604 | AZ138: 47868 | BA138: 6996 | BB138: 10394 | BC138: 17317 | BD138: 46704 | BE138: 143243 | BF138: 6713 | BG138: 52463 | BH138: 21956 | BI138: 11200 | BJ138: 10547 | BK138: 99876 | BL138: 28312 | BM138: 438035 | BN138: 246146 | BO138: 68720 | BP138: 113676 | BQ138: 67773 | BR138: 10977 | BS138: 39513 | BT138: 61996 | BU138: 2666182 | BV138: 2666182
C139: Outros impostos sobre a produção | D139: 1255 | E139: 564 | F139: 123 | G139: 177 | H139: 1210 | I139: 354 | J139: 138 | K139: 1875 | L139: 604 | M139: 2126 | N139: 717 | O139: 101 | P139: 419 | Q139: 583 | R139: 409 | S139: 264 | T139: 645 | U139: 234 | V139: 1007 | W139: 372 | X139: 969 | Y139: 570 | Z139: 339 | AA139: 514 | AB139: 945 | AC139: 855 | AE139: 766 | AF139: 926 | AG139: 768 | AH139: 671 | AI139: 1215 | AJ139: 1160 | AK139: 775 | AL139: 474 | AM139: 643 | AN139: 387 | AO139: 2114 | AP139: 656 | AR139: 4023 | AS139: 1271 | AT139: 10006 | AU139: 2944 | AV139: 370 | AW139: 574 | AX139: 1611 | AY139: 323 | AZ139: 1374 | BA139: 237 | BB139: 1273 | BC139: 4701 | BD139: 1570 | BE139: 7277 | BF139: 358 | BG139: 2003 | BH139: 712 | BI139: 383 | BJ139: 454 | BK139: 2724 | BL139: 872 | BM139: 136 | BN139: 4 | BO139: 2064 | BP139: 1 | BQ139: 2209 | BR139: 250 | BS139: 1048 | BT139: 0 | BU139: 78696 | BV139: 78696
C140: Total industry output (basic value) | D140: =SUM(D136,D138,D139) -> 173550 | E140: =SUM(E136,E138,E139) -> 87623 | F140: =SUM(F136,F138,F139) -> 10342 | G140: =SUM(G136,G138,G139) -> 15095 | H140: =SUM(H136,H138,H139) -> 121776 | I140: =SUM(I136,I138,I139) -> 33540 | J140: =SUM(J136,J138,J139) -> 14063 | K140: =SUM(K136,K138,K139) -> 242432 | ... BU140: =SUM(BU136,BU138,BU139) -> 7816146
C141: Outros subsídios à produção | D141: -10763 | E141: -168 | F141: -42 | G141: -91 | H141: 0 | I141: -36 | J141: 0 | K141: -121 | L141: -169 | M141: -157 | N141: -47 | O141: 0 | P141: -31 | Q141: 0 | R141: 0 | S141: -46 | T141: -118 | U141: 0 | V141: -223 | W141: -198 | X141: -45 | Y141: 0 | Z141: 0 | AA141: -31 | AB141: -178 | AC141: -147 | AE141: -80 | AF141: -98 | AG141: 0 | AH141: -110 | AI141: -289 | AJ141: -326 | AK141: -266 | AL141: -74 | AM141: -42 | AN141: 0 | AO141: -807 | AP141: -46 | AR141: -540 | AS141: -42 | AT141: -1375 | AU141: -2421 | AV141: 0 | AW141: -37 | AX141: -72 | AY141: 0 | AZ141: 0 | BA141: 0 | BB141: 0 | BC141: -95 | BD141: 0 | BE141: 0 | BF141: 0 | BG141: 0 | BH141: -642 | BI141: 0 | BJ141: -230 | BK141: -72 | BL141: 0 | BM141: 0 | BN141: 0 | BO141: 0 | BP141: 0 | BQ141: -36 | BR141: 0 | BS141: 0 | BT141: 0 | BU141: -20311 | BV141: -20311
C142: Valor adicionado bruto ( PIB ) | D142: =SUM(D140,D141) -> 162787 | E142: =SUM(E140,E141) -> 87455 | F142: =SUM(F140,F141) -> 10300 | G142: =SUM(G140,G141) -> 15004 | H142: =SUM(H140,H141) -> 121776 | I142: =SUM(I140,I141) -> 33504 | J142: =SUM(J140,J141) -> 14063 | K142: =SUM(K140,K141) -> 242311 | ... BT142: =SUM(BT140,BT141) -> 61996 | BU142: =SUM(BU136:BU141) -> 15611981 | BV142: =SUM(D142:BT142) -> 7795835
CC143: x
A144: Fonte: IBGE, Diretoria de Pesquisas, Coordenação de Contas Nacionais. | CC144: x
A145: (1) Exportação de bens e serviços líquida de ajuste CIF/FOB. | CC145: x
A146: 35001 | C146: Eletricidade, gás e outras utilidades | D146: 7468 | E146: 5007 | F146: 411 | G146: 697 | H146: 309 | I146: 1156 | J146: 479 | K146: 1643 | L146: 55 | M146: 3271 | N146: 725 | O146: 63 | P146: 1513 | Q146: 242 | R146: 294 | S146: 883 | T146: 2169 | U146: 159 | V146: 39 | W146: 172 | X146: 4583 | Y146: 723 | Z146: 221 | AA146: 316 | AB146: 2227 | AE146: 3605 | AF146: 2800 | AG146: 1317 | AH146: 169 | AI146: 658 | AJ146: 701 | AK146: 506 | AL146: 1189 | AM146: 326 | AN146: 414 | AO146: 260 | AR146: 3458 | AS146: 640 | AT146: 21120 | AU146: 1405 | AV146: 61 | AW146: 41 | AX146: 1169 | AY146: 1364 | AZ146: 1742 | BA146: 169 | BB146: 410 | BC146: 2034 | BD146: 584 | BE146: 2544 | BF146: 464 | BG146: 1125 | BH146: 320 | BI146: 186 | BJ146: 163 | BK146: 7055 | BL146: 103 | BM146: 5902 | BN146: 1836 | BO146: 2459 | BP146: 1392 | BQ146: 1630 | BR146: 966 | BS146: 3464 | BT146: 0 | BU146: 209805 | BV146: 0 | BW146: 0 | BX146: 0 | BY146: 100586 | BZ146: 0 | CA146: 0 | CB146: 100586 | CC146: 310391 | CE146: 4615 | CF146: 94614

Sheet SCNSup128
A1: Tabela 01 - Recursos de bens e serviços - 2015
A3: Código do produto nível 67 | B3: Matching ISIC Code | C3: Produção das atividades (valores correntes em 1 000 000 R$)
C4: Descrição do produto nível 67 | D4: Agricultura, inclusive o apoio à agricultura e a pós-colheita | E4: Pecuária, inclusive o apoio à pecuária | F4: Produção florestal; pesca e aquicultura | G4: Extração de carvão mineral e de minerais não metálicos | H4: Extração de petróleo e gás, inclusive as atividades de apoio | I4: Extração de minério de ferro, inclusive beneficiamentos e a aglomeração | J4: Extração de minerais metálicos não ferrosos, inclusive beneficiamentos | K4: Abate e produtos de carne, inclusive os produtos do laticínio e da pesca | L4: Fabricação e refino de açúcar | M4: Outros produtos alimentares | N4: Fabricação de bebidas | O4: Fabricação de produtos do fumo | P4: Fabricação de produtos têxteis | Q4: Confecção de artefatos do vestuário e acessórios | R4: Fabricação de calçados e de artefatos de couro | S4: Fabricação de produtos da madeira | T4: Fabricação de celulose, papel e produtos de papel | U4: Impressão e reprodução de gravações | V4: Refino de petróleo e coquerias | W4: Fabricação de biocombustíveis | X4: Fabricação de químicos orgânicos e inorgânicos, resinas e elastômeros | Y4: Fabricação de defensivos, desinfestantes, tintas e químicos diversos | Z4: Fabricação de produtos de limpeza, cosméticos/perfumaria e higiene pessoal | AA4: Fabricação de produtos farmoquímicos e farmacêuticos | AB4: Fabricação de produtos de borracha e de material plástico | AC4: Cimento / Artefatos de cimento, gesso e semelhantes | AD4: Vidros, cerâmicos e outros prod. de minerais não-metálicos | AE4: Produção de ferro gusa/ferroligas, siderurgia e tubos de aço sem costura | AF4: Metalurgia de metais não ferosos e a fundição de metais | AG4: Fabricação de produtos de metal, exceto máquinas e equipamentos | AH4: Fabricação de equipamentos de informática, produtos eletrônicos e ópticos | AI4: Fabricação de máquinas e equipamentos elétricos | AJ4: Fabricação de máquinas e equipamentos mecânicos | AK4: Fabricação de automóveis, caminhões e ônibus, exceto peças | AL4: Fabricação de peças e acessórios para veículos automotores | AM4: Fabricação de outros equipamentos de transporte, exceto veículos automotores | AN4: Fabricação de móveis e de produtos de indústrias diversas | AO4: Manutenção, reparação e instalação de máquinas e equipamentos | AP4: Transmissão de energia elétrica | AQ4: Produção de gás; processamento de gás natural; distribuição de combustíveis gasosos por redes urbanas | AR4: Água, esgoto e gestão de resíduos | AS4: Construção | AT4: Comércio por atacado e varejo | AU4: Transporte terrestre | AV4: Transporte aquaviário | AW4: Transporte aéreo | AX4: Armazenamento, atividades auxiliares dos transportes e correio | AY4: Alojamento | AZ4: Alimentação | BA4: Edição e edição integrada à impressão | BB4: Atividades de televisão, rádio, cinema e gravação/edição de som e imagem | BC4: Telecomunicações | BD4: Desenvolvimento de sistemas e outros serviços de informação | BE4: Intermediação financeira, seguros e previdência complementar | BF4: Atividades imobiliárias | BG4: Atividades jurídicas, contábeis, consultoria e sedes de empresas | BH4: Serviços de arquitetura, engenharia, testes/análises técnicas e P & D | BI4: Outras atividades profissionais, científicas e técnicas | BJ4: Aluguéis não imobiliários e gestão de ativos de propriedade intelectual | BK4: Outras atividades administrativas e serviços complementares | BL4: Atividades de vigilância, segurança e investigação | BM4: Administração pública, defesa e seguridade social | BN4: Educação pública | BO4: Educação privada | BP4: Saúde pública | BQ4: Saúde privada | BR4: Atividades artísticas, criativas e de espetáculos | BS4: Organizações associativas e outros serviços pessoais | BT4: Serviços domésticos | BU4: Total do produto | BV4: Importação de bens e serviços (valores correntes em 1 000 000 R$) (1) | BX4: Fabricação de produtos de minerais não metálicos | BY4: Energia elétrica, gás natural e outras utilidades
D5: 191 | E5: 192 | F5: 280 | G5: 580 | H5: 680 | I5: 791 | J5: 792 | K5: 1091 | L5: 1092 | M5: 1093 | N5: 1100 | O5: 1200 | P5: 1300 | Q5: 1400 | R5: 1500 | S5: 1600 | T5: 1700 | U5: 1800 | V5: 1991 | W5: 1992 | X5: 2091 | Y5: 2092 | Z5: 2093 | AA5: 2100 | AB5: 2200 | AC5: 2310 | AD5: 2320 | AE5: 2491 | AF5: 2492 | AG5: 2500 | AH5: 2600 | AI5: 2700 | AJ5: 2800 | AK5: 2991 | AL5: 2992 | AM5: 3000 | AN5: 3180 | AO5: 3300 | AP5: 3510 | AQ5: 3520 | AR5: 3680 | AS5: 4180 | AT5: 4580 | AU5: 4900 | AV5: 5000 | AW5: 5100 | AX5: 5280 | AY5: 5500 | AZ5: 5600 | BA5: 5800 | BB5: 5980 | BC5: 6100 | BD5: 6280 | BE5: 6480 | BF5: 6800 | BG5: 6980 | BH5: 7180 | BI5: 7380 | BJ5: 7700 | BK5: 7880 | BL5: 8000 | BM5: 8400 | BN5: 8591 | BO5: 8592 | BP5: 8691 | BQ5: 8692 | BR5: 9080 | BS5: 9480 | BT5: 9700 | BX5: 2300 | BY5: 3500
A6: Matching ISIC Code | D6: =IFERROR(INDEX(SCNtoISIC!$F:$F,MATCH(D$5,SCNtoISIC!$C:$C,0)),0) -> ISIC 01T03 | E6: =IFERROR(INDEX(SCNtoISIC!$F:$F,MATCH(E$5,SCNtoISIC!$C:$C,0)),0) -> ISIC 01T03 | F6: =IFERROR(INDEX(SCNtoISIC!$F:$F,MATCH(F$5,SCNtoISIC!$C:$C,0)),0) -> ISIC 01T03 | G6: =IFERROR(INDEX(SCNtoISIC!$F:$F,MATCH(G$5,SCNtoISIC!$C:$C,0)),0) -> ISIC 05 | H6: =IFERROR(INDEX(SCNtoISIC!$F:$F,MATCH(H$5,SCNtoISIC!$C:$C,0)),0) -> ISIC 06 | I6: =IFERROR(INDEX(SCNtoISIC!$F:$F,MATCH(I$5,SCNtoISIC!$C:$C,0)),0) -> ISIC 07T08 | J6: =IFERROR(INDEX(SCNtoISIC!$F:$F,MATCH(J$5,SCNtoISIC!$C:$C,0)),0) -> ISIC 09 | K6: =IFERROR(INDEX(SCNtoISIC!$F:$F,MATCH(K$5,SCNtoISIC!$C:$C,0)),0) -> ISIC 10T12 | ... BT6: =IFERROR(INDEX(SCNtoISIC!$F:$F,MATCH(BT$5,SCNtoISIC!$C:$C,0)),0) -> ISIC 97T98
A7: 1911 | B7: =IFERROR(INDEX(SCNtoISIC!$M:$M,MATCH($A7,SCNtoISIC!$J:$J,0)),0) -> ISIC 01T03 | C7: Arroz, trigo e outros cereais | D7: 10551 | E7: 321 | F7: 8 | G7: 0 | H7: 0 | I7: 0 | J7: 0 | K7: 0 | L7: 0 | M7: 0 | N7: 0 | O7: 0 | P7: 0 | Q7: 0 | R7: 0 | S7: 0 | T7: 0 | U7: 0 | V7: 0 | W7: 0 | X7: 0 | Y7: 0 | Z7: 0 | AA7: 0 | AB7: 0 | AC7: 0 | AD7: 0 | AE7: 0 | AF7: 0 | AG7: 0 | AH7: 0 | AI7: 0 | AJ7: 0 | AK7: 0 | AL7: 0 | AM7: 0 | AN7: 0 | AO7: 0 | AP7: 0 | AQ7: 0 | AR7: 0 | AS7: 0 | AT7: 0 | AU7: 0 | AV7: 0 | AW7: 0 | AX7: 0 | AY7: 0 | AZ7: 0 | BA7: 0 | BB7: 0 | BC7: 0 | BD7: 0 | BE7: 0 | BF7: 0 | BG7: 0 | BH7: 0 | BI7: 0 | BJ7: 0 | BK7: 0 | BL7: 0 | BM7: 156 | BN7: 0 | BO7: 0 | BP7: 0 | BQ7: 0 | BR7: 0 | BS7: 0 | BT7: 0 | BU7: 11036 | BV7: 4924 | BX7: 0 | BY7: 0
A8: 1912 | B8: =IFERROR(INDEX(SCNtoISIC!$M:$M,MATCH($A8,SCNtoISIC!$J:$J,0)),0) -> ISIC 01T03 | C8: Milho em grão | D8: 28173 | E8: 1641 | F8: 51 | G8: 0 | H8: 0 | I8: 0 | J8: 0 | K8: 0 | L8: 0 | M8: 0 | N8: 0 | O8: 0 | P8: 0 | Q8: 0 | R8: 0 | S8: 0 | T8: 0 | U8: 0 | V8: 0 | W8: 0 | X8: 0 | Y8: 0 | Z8: 0 | AA8: 0 | AB8: 0 | AC8: 0 | AD8: 0 | AE8: 0 | AF8: 0 | AG8: 0 | AH8: 0 | AI8: 0 | AJ8: 0 | AK8: 0 | AL8: 0 | AM8: 0 | AN8: 0 | AO8: 0 | AP8: 0 | AQ8: 0 | AR8: 0 | AS8: 0 | AT8: 0 | AU8: 0 | AV8: 0 | AW8: 0 | AX8: 0 | AY8: 0 | AZ8: 0 | BA8: 0 | BB8: 0 | BC8: 0 | BD8: 0 | BE8: 0 | BF8: 0 | BG8: 0 | BH8: 0 | BI8: 0 | BJ8: 0 | BK8: 0 | BL8: 0 | BM8: 110 | BN8: 0 | BO8: 0 | BP8: 0 | BQ8: 0 | BR8: 0 | BS8: 0 | BT8: 0 | BU8: 29975 | BV8: 158 | BX8: 0 | BY8: 0
A9: 1913 | B9: =IFERROR(INDEX(SCNtoISIC!$M:$M,MATCH($A9,SCNtoISIC!$J:$J,0)),0) -> ISIC 01T03 | C9: Algodão herbáceo, outras fibras da lavoura temporária | D9: 8931 | E9: 11 | F9: 0 | G9: 0 | H9: 0 | I9: 0 | J9: 0 | K9: 0 | L9: 0 | M9: 0 | N9: 0 | O9: 0 | P9: 0 | Q9: 0 | R9: 0 | S9: 0 | T9: 0 | U9: 0 | V9: 0 | W9: 0 | X9: 0 | Y9: 0 | Z9: 0 | AA9: 0 | AB9: 0 | AC9: 0 | AD9: 0 | AE9: 0 | AF9: 0 | AG9: 0 | AH9: 0 | AI9: 0 | AJ9: 0 | AK9: 0 | AL9: 0 | AM9: 0 | AN9: 0 | AO9: 0 | AP9: 0 | AQ9: 0 | AR9: 0 | AS9: 0 | AT9: 0 | AU9: 0 | AV9: 0 | AW9: 0 | AX9: 0 | AY9: 0 | AZ9: 0 | BA9: 0 | BB9: 0 | BC9: 0 | BD9: 0 | BE9: 0 | BF9: 0 | BG9: 0 | BH9: 0 | BI9: 0 | BJ9: 0 | BK9: 0 | BL9: 0 | BM9: 1 | BN9: 0 | BO9: 0 | BP9: 0 | BQ9: 0 | BR9: 0 | BS9: 0 | BT9: 0 | BU9: 8943 | BV9: 18 | BX9: 0 | BY9: 0
A10: 1914 | B10: =IFERROR(INDEX(SCNtoISIC!$M:$M,MATCH($A10,SCNtoISIC!$J:$J,0)),0) -> ISIC 01T03 | C10: Cana-de-açúcar | D10: 45840 | E10: 239 | F10: 1 | G10: 0 | H10: 0 | I10: 0 | J10: 0 | K10: 0 | L10: 0 | M10: 0 | N10: 0 | O10: 0 | P10: 0 | Q10: 0 | R10: 0 | S10: 0 | T10: 0 | U10: 0 | V10: 0 | W10: 0 | X10: 0 | Y10: 0 | Z10: 0 | AA10: 0 | AB10: 0 | AC10: 0 | AD10: 0 | AE10: 0 | AF10: 0 | AG10: 0 | AH10: 0 | AI10: 0 | AJ10: 0 | AK10: 0 | AL10: 0 | AM10: 0 | AN10: 0 | AO10: 0 | AP10: 0 | AQ10: 0 | AR10: 0 | AS10: 0 | AT10: 0 | AU10: 0 | AV10: 0 | AW10: 0 | AX10: 0 | AY10: 0 | AZ10: 0 | BA10: 0 | BB10: 0 | BC10: 0 | BD10: 0 | BE10: 0 | BF10: 0 | BG10: 0 | BH10: 0 | BI10: 0 | BJ10: 0 | BK10: 0 | BL10: 0 | BM10: 0 | BN10: 0 | BO10: 0 | BP10: 0 | BQ10: 0 | BR10: 0 | BS10: 0 | BT10: 0 | BU10: 46080 | BV10: 0 | BX10: 0 | BY10: 0
A11: 1915 | B11: =IFERROR(INDEX(SCNtoISIC!$M:$M,MATCH($A11,SCNtoISIC!$J:$J,0)),0) -> ISIC 01T03 | C11: Soja em grão | D11: 106355 | E11: 2773 | F11: 42 | G11: 0 | H11: 0 | I11: 0 | J11: 0 | K11: 0 | L11: 0 | M11: 0 | N11: 0 | O11: 0 | P11: 0 | Q11: 0 | R11: 0 | S11: 0 | T11: 0 | U11: 0 | V11: 0 | W11: 0 | X11: 0 | Y11: 0 | Z11: 0 | AA11: 0 | AB11: 0 | AC11: 0 | AD11: 0 | AE11: 0 | AF11: 0 | AG11: 0 | AH11: 0 | AI11: 0 | AJ11: 0 | AK11: 0 | AL11: 0 | AM11: 0 | AN11: 0 | AO11: 0 | AP11: 0 | AQ11: 0 | AR11: 0 | AS11: 0 | AT11: 0 | AU11: 0 | AV11: 0 | AW11: 0 | AX11: 0 | AY11: 0 | AZ11: 0 | BA11: 0 | BB11: 0 | BC11: 0 | BD11: 0 | BE11: 0 | BF11: 0 | BG11: 0 | BH11: 0 | BI11: 0 | BJ11: 0 | BK11: 0 | BL11: 0 | BM11: 0 | BN11: 0 | BO11: 0 | BP11: 0 | BQ11: 0 | BR11: 0 | BS11: 0 | BT11: 0 | BU11: 109170 | BV11: 501 | BX11: 0 | BY11: 0
A12: 1916 | B12: =IFERROR(INDEX(SCNtoISIC!$M:$M,MATCH($A12,SCNtoISIC!$J:$J,0)),0) -> ISIC 01T03 | C12: Outros produtos e serviços da lavoura temporária | D12: 51381 | E12: 2050 | F12: 115 | G12: 0 | H12: 0 | I12: 0 | J12: 0 | K12: 0 | L12: 0 | M12: 0 | N12: 0 | O12: 0 | P12: 0 | Q12: 0 | R12: 0 | S12: 0 | T12: 0 | U12: 0 | V12: 0 | W12: 0 | X12: 0 | Y12: 0 | Z12: 0 | AA12: 0 | AB12: 0 | AC12: 0 | AD12: 0 | AE12: 0 | AF12: 0 | AG12: 0 | AH12: 0 | AI12: 0 | AJ12: 0 | AK12: 0 | AL12: 0 | AM12: 0 | AN12: 0 | AO12: 0 | AP12: 0 | AQ12: 0 | AR12: 0 | AS12: 0 | AT12: 0 | AU12: 0 | AV12: 0 | AW12: 0 | AX12: 0 | AY12: 0 | AZ12: 0 | BA12: 0 | BB12: 0 | BC12: 0 | BD12: 0 | BE12: 0 | BF12: 0 | BG12: 0 | BH12: 0 | BI12: 0 | BJ12: 0 | BK12: 0 | BL12: 0 | BM12: 187 | BN12: 1 | BO12: 0 | BP12: 0 | BQ12: 0 | BR12: 0 | BS12: 0 | BT12: 0 | BU12: 53734 | BV12: 2181 | BX12: 0 | BY12: 0
A13: 1917 | B13: =IFERROR(INDEX(SCNtoISIC!$M:$M,MATCH($A13,SCNtoISIC!$J:$J,0)),0) -> ISIC 01T03 | C13: Laranja | D13: 5840 | E13: 54 | F13: 0 | G13: 0 | H13: 0 | I13: 0 | J13: 0 | K13: 0 | L13: 0 | M13: 0 | N13: 0 | O13: 0 | P13: 0 | Q13: 0 | R13: 0 | S13: 0 | T13: 0 | U13: 0 | V13: 0 | W13: 0 | X13: 0 | Y13: 0 | Z13: 0 | AA13: 0 | AB13: 0 | AC13: 0 | AD13: 0 | AE13: 0 | AF13: 0 | AG13: 0 | AH13: 0 | AI13: 0 | AJ13: 0 | AK13: 0 | AL13: 0 | AM13: 0 | AN13: 0 | AO13: 0 | AP13: 0 | AQ13: 0 | AR13: 0 | AS13: 0 | AT13: 0 | AU13: 0 | AV13: 0 | AW13: 0 | AX13: 0 | AY13: 0 | AZ13: 0 | BA13: 0 | BB13: 0 | BC13: 0 | BD13: 0 | BE13: 0 | BF13: 0 | BG13: 0 | BH13: 0 | BI13: 0 | BJ13: 0 | BK13: 0 | BL13: 0 | BM13: 0 | BN13: 0 | BO13: 0 | BP13: 0 | BQ13: 0 | BR13: 0 | BS13: 0 | BT13: 0 | BU13: 5894 | BV13: 39 | BX13: 0 | BY13: 0
A14: 1918 | B14: =IFERROR(INDEX(SCNtoISIC!$M:$M,MATCH($A14,SCNtoISIC!$J:$J,0)),0) -> ISIC 01T03 | C14: Café em grão | D14: 15655 | E14: 526 | F14: 18 | G14: 0 | H14: 0 | I14: 0 | J14: 0 | K14: 0 | L14: 0 | M14: 0 | N14: 0 | O14: 0 | P14: 0 | Q14: 0 | R14: 0 | S14: 0 | T14: 0 | U14: 0 | V14: 0 | W14: 0 | X14: 0 | Y14: 0 | Z14: 0 | AA14: 0 | AB14: 0 | AC14: 0 | AD14: 0 | AE14: 0 | AF14: 0 | AG14: 0 | AH14: 0 | AI14: 0 | AJ14: 0 | AK14: 0 | AL14: 0 | AM14: 0 | AN14: 0 | AO14: 0 | AP14: 0 | AQ14: 0 | AR14: 0 | AS14: 0 | AT14: 0 | AU14: 0 | AV14: 0 | AW14: 0 | AX14: 0 | AY14: 0 | AZ14: 0 | BA14: 0 | BB14: 0 | BC14: 0 | BD14: 0 | BE14: 0 | BF14: 0 | BG14: 0 | BH14: 0 | BI14: 0 | BJ14: 0 | BK14: 0 | BL14: 0 | BM14: 142 | BN14: 0 | BO14: 0 | BP14: 0 | BQ14: 0 | BR14: 0 | BS14: 0 | BT14: 0 | BU14: 16341 | BV14: 0 | BX14: 0 | BY14: 0
A15: 1919 | B15: =IFERROR(INDEX(SCNtoISIC!$M:$M,MATCH($A15,SCNtoISIC!$J:$J,0)),0) -> ISIC 01T03 | C15: Outros produtos da lavoura permanente | D15: 20386 | E15: 521 | F15: 98 | G15: 0 | H15: 0 | I15: 0 | J15: 0 | K15: 0 | L15: 0 | M15: 0 | N15: 0 | O15: 0 | P15: 0 | Q15: 0 | R15: 0 | S15: 0 | T15: 0 | U15: 0 | V15: 0 | W15: 0 | X15: 0 | Y15: 0 | Z15: 0 | AA15: 0 | AB15: 0 | AC15: 0 | AD15: 0 | AE15: 0 | AF15: 0 | AG15: 0 | AH15: 0 | AI15: 0 | AJ15: 0 | AK15: 0 | AL15: 0 | AM15: 0 | AN15: 0 | AO15: 0 | AP15: 0 | AQ15: 0 | AR15: 0 | AS15: 0 | AT15: 135 | AU15: 0 | AV15: 0 | AW15: 0 | AX15: 0 | AY15: 0 | AZ15: 0 | BA15: 0 | BB15: 0 | BC15: 0 | BD15: 0 | BE15: 0 | BF15: 0 | BG15: 0 | BH15: 0 | BI15: 0 | BJ15: 0 | BK15: 0 | BL15: 0 | BM15: 8 | BN15: 0 | BO15: 0 | BP15: 0 | BQ15: 0 | BR15: 0 | BS15: 0 | BT15: 0 | BU15: 21148 | BV15: 1876 | BX15: 0 | BY15: 0
A16: 1921 | B16: =IFERROR(INDEX(SCNtoISIC!$M:$M,MATCH($A16,SCNtoISIC!$J:$J,0)),0) -> ISIC 01T03 | C16: Bovinos e outros animais vivos, produtos animal, caça e serviços | D16: 4755 | E16: 65761 | F16: 231 | G16: 0 | H16: 0 | I16: 0 | J16: 0 | K16: 0 | L16: 0 | M16: 0 | N16: 0 | O16: 0 | P16: 0 | Q16: 0 | R16: 0 | S16: 0 | T16: 0 | U16: 0 | V16: 0 | W16: 0 | X16: 0 | Y16: 0 | Z16: 0 | AA16: 0 | AB16: 0 | AC16: 0 | AD16: 0 | AE16: 0 | AF16: 0 | AG16: 0 | AH16: 0 | AI16: 0 | AJ16: 0 | AK16: 0 | AL16: 0 | AM16: 0 | AN16: 0 | AO16: 0 | AP16: 0 | AQ16: 0 | AR16: 0 | AS16: 0 | AT16: 101 | AU16: 0 | AV16: 0 | AW16: 0 | AX16: 0 | AY16: 0 | AZ16: 0 | BA16: 0 | BB16: 0 | BC16: 0 | BD16: 0 | BE16: 0 | BF16: 0 | BG16: 0 | BH16: 0 | BI16: 0 | BJ16: 0 | BK16: 0 | BL16: 0 | BM16: 11 | BN16: 7 | BO16: 0 | BP16: 0 | BQ16: 0 | BR16: 0 | BS16: 0 | BT16: 0 | BU16: 70866 | BV16: 129 | BX16: 0 | BY16: 0
A17: 1922 | B17: =IFERROR(INDEX(SCNtoISIC!$M:$M,MATCH($A17,SCNtoISIC!$J:$J,0)),0) -> ISIC 01T03 | C17: Leite de vaca e de outros animais | D17: 2476 | E17: 22740 | F17: 67 | G17: 0 | H17: 0 | I17: 0 | J17: 0 | K17: 0 | L17: 0 | M17: 0 | N17: 0 | O17: 0 | P17: 0 | Q17: 0 | R17: 0 | S17: 0 | T17: 0 | U17: 0 | V17: 0 | W17: 0 | X17: 0 | Y17: 0 | Z17: 0 | AA17: 0 | AB17: 0 | AC17: 0 | AD17: 0 | AE17: 0 | AF17: 0 | AG17: 0 | AH17: 0 | AI17: 0 | AJ17: 0 | AK17: 0 | AL17: 0 | AM17: 0 | AN17: 0 | AO17: 0 | AP17: 0 | AQ17: 0 | AR17: 0 | AS17: 0 | AT17: 0 | AU17: 0 | AV17: 0 | AW17: 0 | AX17: 0 | AY17: 0 | AZ17: 0 | BA17: 0 | BB17: 0 | BC17: 0 | BD17: 0 | BE17: 0 | BF17: 0 | BG17: 0 | BH17: 0 | BI17: 0 | BJ17: 0 | BK17: 0 | BL17: 0 | BM17: 1 | BN17: 0 | BO17: 0 | BP17: 0 | BQ17: 0 | BR17: 0 | BS17: 0 | BT17: 0 | BU17: 25284 | BV17: 0 | BX17: 0 | BY17: 0
A18: 1923 | B18: =IFERROR(INDEX(SCNtoISIC!$M:$M,MATCH($A18,SCNtoISIC!$J:$J,0)),0) -> ISIC 01T03 | C18: Suínos | D18: 503 | E18: 8107 | F18: 0 | G18: 0 | H18: 0 | I18: 0 | J18: 0 | K18: 0 | L18: 0 | M18: 0 | N18: 0 | O18: 0 | P18: 0 | Q18: 0 | R18: 0 | S18: 0 | T18: 0 | U18: 0 | V18: 0 | W18: 0 | X18: 0 | Y18: 0 | Z18: 0 | AA18: 0 | AB18: 0 | AC18: 0 | AD18: 0 | AE18: 0 | AF18: 0 | AG18: 0 | AH18: 0 | AI18: 0 | AJ18: 0 | AK18: 0 | AL18: 0 | AM18: 0 | AN18: 0 | AO18: 0 | AP18: 0 | AQ18: 0 | AR18: 0 | AS18: 0 | AT18: 0 | AU18: 0 | AV18: 0 | AW18: 0 | AX18: 0 | AY18: 0 | AZ18: 0 | BA18: 0 | BB18: 0 | BC18: 0 | BD18: 0 | BE18: 0 | BF18: 0 | BG18: 0 | BH18: 0 | BI18: 0 | BJ18: 0 | BK18: 0 | BL18: 0 | BM18: 0 | BN18: 0 | BO18: 0 | BP18: 0 | BQ18: 0 | BR18: 0 | BS18: 0 | BT18: 0 | BU18: 8610 | BV18: 6 | BX18: 0 | BY18: 0
... A69: 22002 | B69: =IFERROR(INDEX(SCNtoISIC!$M:$M,MATCH($A69,SCNtoISIC!$J:$J,0)),0) -> ISIC 22 | C69: Artigos de plástico | D69: 0 | E69: 0 | F69: 0 | G69: 0 | H69: 0 | I69: 0 | J69: 0 | K69: 27 | L69: 0 | M69: 25 | N69: 0 | O69: 0 | P69: 308 | Q69: 8 | R69: 55 | S69: 95 | T69: 499 | U69: 69 | V69: 0 | W69: 0 | X69: 555 | Y69: 70 | Z69: 92 | AA69: 39 | AB69: 68940 | AC69: 127.2 | AD69: 84.8 | AE69: 35 | AF69: 21 | AG69: 381 | AH69: 39 | AI69: 171 | AJ69: 222 | AK69: 0 | AL69: 188 | AM69: 25 | AN69: 680 | AO69: 38 | AP69: 0 | AQ69: 0 | AR69: 0 | AS69: 0 | AT69: 439 | AU69: 8 | AV69: 0 | AW69: 0 | AX69: 0 | AY69: 0 | AZ69: 0 | BA69: 0 | BB69: 0 | BC69: 0 | BD69: 0 | BE69: 0 | BF69: 0 | BG69: 0 | BH69: 30 | BI69: 0 | BJ69: 0 | BK69: 0 | BL69: 0 | BM69: 0 | BN69: 0 | BO69: 0 | BP69: 0 | BQ69: 0 | BR69: 0 | BS69: 0 | BT69: 0 | BU69: 73271 | BV69: 9009 | BX69: 212 | BY69: 0
A70: 23001 | B70: =IFERROR(INDEX(SCNtoISIC!$M:$M,MATCH($A70,SCNtoISIC!$J:$J,0)),0) -> ISIC 239 | C70: Cimento / Artefatos de cimento, gesso e semelhantes | D70: 0 | E70: 0 | F70: 0 | G70: 149 | H70: 0 | I70: 0 | J70: 0 | K70: 0 | L70: 0 | M70: 9 | N70: 0 | O70: 0 | P70: 0 | Q70: 0 | R70: 0 | S70: 12 | T70: 0 | U70: 0 | V70: 0 | W70: 0 | X70: 0 | Y70: 13 | Z70: 0 | AA70: 0 | AB70: 27 | AC70: 23869.2 | AD70: 15912.8 | AE70: 13 | AF70: 0 | AG70: 68 | AH70: 0 | AI70: 0 | AJ70: 0 | AK70: 0 | AL70: 0 | AM70: 15 | AN70: 80 | AO70: 0 | AP70: 0 | AQ70: 0 | AR70: 0 | AS70: 0 | AT70: 386 | AU70: 0 | AV70: 0 | AW70: 0 | AX70: 0 | AY70: 0 | AZ70: 0 | BA70: 0 | BB70: 0 | BC70: 0 | BD70: 0 | BE70: 0 | BF70: 0 | BG70: 0 | BH70: 0 | BI70: 0 | BJ70: 0 | BK70: 0 | BL70: 0 | BM70: 0 | BN70: 0 | BO70: 0 | BP70: 0 | BQ70: 0 | BR70: 0 | BS70: 0 | BT70: 0 | BU70: =BU141+BU142 -> 40554 | BV70: =BV141+BV142 -> 674 | BX70: 39782 | BY70: 0
A71: 23001 | B71: =IFERROR(INDEX(SCNtoISIC!$M:$M,MATCH($A71,SCNtoISIC!$J:$J,0)),0) -> ISIC 239
A72: 23003 | B72: =IFERROR(INDEX(SCNtoISIC!$M:$M,MATCH($A72,SCNtoISIC!$J:$J,0)),0) -> ISIC 231 | C72: Vidros, cerâmicos e outros produtos de minerais não metálicos | D72: 0 | E72: 0 | F72: 0 | G72: 362 | H72: 0 | I72: 0 | J72: 5 | K72: 0 | L72: 0 | M72: 0 | N72: 0 | O72: 0 | P72: 29 | Q72: 0 | R72: 0 | S72: 6 | T72: 0 | U72: 0 | V72: 0 | W72: 0 | X72: 62 | Y72: 133 | Z72: 0 | AA72: 6 | AB72: 47 | AC72: 27190.8 | AD72: 18127.2 | AE72: 0 | AF72: 0 | AG72: 103 | AH72: 0 | AI72: 42 | AJ72: 81 | AK72: 37 | AL72: 157 | AM72: 0 | AN72: 172 | AO72: 0 | AP72: 0 | AQ72: 0 | AR72: 0 | AS72: 0 | AT72: 0 | AU72: 0 | AV72: 0 | AW72: 0 | AX72: 0 | AY72: 0 | AZ72: 0 | BA72: 0 | BB72: 0 | BC72: 0 | BD72: 0 | BE72: 0 | BF72: 0 | BG72: 0 | BH72: 0 | BI72: 0 | BJ72: 0 | BK72: 0 | BL72: 0 | BM72: 0 | BN72: 0 | BO72: 0 | BP72: 0 | BQ72: 0 | BR72: 0 | BS72: 0 | BT72: 0 | BU72: 46560 | BV72: 5653 | BX72: 45318 | BY72: 0
A73: 24911 | B73: =IFERROR(INDEX(SCNtoISIC!$M:$M,MATCH($A73,SCNtoISIC!$J:$J,0)),0) -> ISIC 241 | C73: Ferro gusa e ferroligas | D73: 0 | E73: 0 | F73: 0 | G73: 0 | H73: 0 | I73: 0 | J73: 0 | K73: 0 | L73: 0 | M73: 0 | N73: 0 | O73: 0 | P73: 0 | Q73: 0 | R73: 0 | S73: 0 | T73: 0 | U73: 0 | V73: 0 | W73: 0 | X73: 69 | Y73: 65 | Z73: 0 | AA73: 0 | AB73: 0 | AC73: 0 | AD73: 0 | AE73: 11533 | AF73: 0 | AG73: 0 | AH73: 0 | AI73: 0 | AJ73: 0 | AK73: 0 | AL73: 8 | AM73: 0 | AN73: 0 | AO73: 0 | AP73: 0 | AQ73: 0 | AR73: 0 | AS73: 0 | AT73: 0 | AU73: 0 | AV73: 0 | AW73: 0 | AX73: 0 | AY73: 0 | AZ73: 0 | BA73: 0 | BB73: 0 | BC73: 0 | BD73: 0 | BE73: 0 | BF73: 0 | BG73: 0 | BH73: 0 | BI73: 0 | BJ73: 0 | BK73: 0 | BL73: 0 | BM73: 0 | BN73: 0 | BO73: 0 | BP73: 0 | BQ73: 0 | BR73: 0 | BS73: 0 | BT73: 0 | BU73: 11675 | BV73: 826 | BX73: 0 | BY73: 0
A74: 24912 | B74: =IFERROR(INDEX(SCNtoISIC!$M:$M,MATCH($A74,SCNtoISIC!$J:$J,0)),0) -> ISIC 241 | C74: Semi acabados, laminados planos, longos e tubos de aço | D74: 0 | E74: 0 | F74: 0 | G74: 0 | H74: 0 | I74: 0 | J74: 0 | K74: 0 | L74: 0 | M74: 0 | N74: 0 | O74: 0 | P74: 9 | Q74: 0 | R74: 0 | S74: 17 | T74: 0 | U74: 0 | V74: 0 | W74: 0 | X74: 0 | Y74: 0 | Z74: 0 | AA74: 0 | AB74: 24 | AC74: 12.6 | AD74: 8.4 | AE74: 81970 | AF74: 39 | AG74: 1746 | AH74: 6 | AI74: 148 | AJ74: 390 | AK74: 9 | AL74: 187 | AM74: 30 | AN74: 8 | AO74: 54 | AP74: 0 | AQ74: 0 | AR74: 0 | AS74: 0 | AT74: 0 | AU74: 9 | AV74: 0 | AW74: 0 | AX74: 0 | AY74: 0 | AZ74: 0 | BA74: 0 | BB74: 0 | BC74: 0 | BD74: 0 | BE74: 0 | BF74: 0 | BG74: 0 | BH74: 0 | BI74: 0 | BJ74: 0 | BK74: 0 | BL74: 0 | BM74: 0 | BN74: 0 | BO74: 0 | BP74: 0 | BQ74: 0 | BR74: 0 | BS74: 0 | BT74: 0 | BU74: 84667 | BV74: 11163 | BX74: 21 | BY74: 0
A75: 24921 | B75: =IFERROR(INDEX(SCNtoISIC!$M:$M,MATCH($A75,SCNtoISIC!$J:$J,0)),0) -> ISIC 242 | C75: Produtos da metalurgia de metais não ferrosos | D75: 0 | E75: 0 | F75: 0 | G75: 0 | H75: 0 | I75: 0 | J75: 380 | K75: 0 | L75: 0 | M75: 0 | N75: 0 | O75: 0 | P75: 0 | Q75: 0 | R75: 0 | S75: 0 | T75: 21 | U75: 0 | V75: 0 | W75: 0 | X75: 368 | Y75: 40 | Z75: 0 | AA75: 0 | AB75: 150 | AC75: 9 | AD75: 6 | AE75: 239 | AF75: 47156 | AG75: 513 | AH75: 0 | AI75: 473 | AJ75: 141 | AK75: 0 | AL75: 16 | AM75: 0 | AN75: 31 | AO75: 19 | AP75: 0 | AQ75: 0 | AR75: 0 | AS75: 0 | AT75: 135 | AU75: 0 | AV75: 0 | AW75: 0 | AX75: 0 | AY75: 0 | AZ75: 0 | BA75: 0 | BB75: 0 | BC75: 0 | BD75: 0 | BE75: 0 | BF75: 0 | BG75: 0 | BH75: 0 | BI75: 0 | BJ75: 0 | BK75: 0 | BL75: 0 | BM75: 0 | BN75: 0 | BO75: 0 | BP75: 0 | BQ75: 0 | BR75: 0 | BS75: 0 | BT75: 0 | BU75: 49697 | BV75: 12754 | BX75: 15 | BY75: 0
A76: 24922 | B76: =IFERROR(INDEX(SCNtoISIC!$M:$M,MATCH($A76,SCNtoISIC!$J:$J,0)),0) -> ISIC 242 | C76: Peças fundidas de aço e de metais não ferrosos | D76: 0 | E76: 0 | F76: 0 | G76: 0 | H76: 0 | I76: 0 | J76: 0 | K76: 0 | L76: 0 | M76: 0 | N76: 0 | O76: 0 | P76: 0 | Q76: 0 | R76: 0 | S76: 0 | T76: 0 | U76: 0 | V76: 0 | W76: 0 | X76: 0 | Y76: 0 | Z76: 0 | AA76: 0 | AB76: 14 | AC76: 0 | AD76: 0 | AE76: 0 | AF76: 4481 | AG76: 44 | AH76: 0 | AI76: 0 | AJ76: 69 | AK76: 6 | AL76: 30 | AM76: 10 | AN76: 71 | AO76: 0 | AP76: 0 | AQ76: 0 | AR76: 0 | AS76: 0 | AT76: 0 | AU76: 0 | AV76: 0 | AW76: 0 | AX76: 0 | AY76: 0 | AZ76: 0 | BA76: 0 | BB76: 0 | BC76: 0 | BD76: 0 | BE76: 0 | BF76: 0 | BG76: 0 | BH76: 0 | BI76: 0 | BJ76: 0 | BK76: 0 | BL76: 0 | BM76: 0 | BN76: 0 | BO76: 0 | BP76: 0 | BQ76: 0 | BR76: 0 | BS76: 0 | BT76: 0 | BU76: 4725 | BV76: 296 | BX76: 0 | BY76: 0
A77: 25001 | B77: =IFERROR(INDEX(SCNtoISIC!$M:$M,MATCH($A77,SCNtoISIC!$J:$J,0)),0) -> ISIC 25 | C77: Produtos de metal, exclusive máquinas e equipamentos | D77: 0 | E77: 0 | F77: 0 | G77: 0 | H77: 0 | I77: 0 | J77: 0 | K77: 0 | L77: 0 | M77: 0 | N77: 169 | O77: 0 | P77: 59 | Q77: 0 | R77: 24 | S77: 39 | T77: 14 | U77: 0 | V77: 0 | W77: 0 | X77: 0 | Y77: 26 | Z77: 273 | AA77: 0 | AB77: 474 | AC77: 58.8 | AD77: 39.2 | AE77: 3057 | AF77: 539 | AG77: 82490 | AH77: 170 | AI77: 727 | AJ77: 2382 | AK77: 67 | AL77: 1396 | AM77: 635 | AN77: 708 | AO77: 282 | AP77: 0 | AQ77: 0 | AR77: 0 | AS77: 0 | AT77: 803 | AU77: 0 | AV77: 0 | AW77: 0 | AX77: 0 | AY77: 0 | AZ77: 0 | BA77: 0 | BB77: 0 | BC77: 0 | BD77: 0 | BE77: 0 | BF77: 0 | BG77: 0 | BH77: 112 | BI77: 0 | BJ77: 18 | BK77: 0 | BL77: 0 | BM77: 76 | BN77: 0 | BO77: 0 | BP77: 0 | BQ77: 0 | BR77: 0 | BS77: 0 | BT77: 0 | BU77: 94638 | BV77: 13643 | BX77: 98 | BY77: 0
A78: 26001 | B78: =IFERROR(INDEX(SCNtoISIC!$M:$M,MATCH($A78,SCNtoISIC!$J:$J,0)),0) -> ISIC 26 | C78: Componentes eletrônicos | D78: 0 | E78: 0 | F78: 0 | G78: 0 | H78: 0 | I78: 0 | J78: 0 | K78: 0 | L78: 0 | M78: 0 | N78: 0 | O78: 0 | P78: 0 | Q78: 0 | R78: 0 | S78: 0 | T78: 0 | U78: 105 | V78: 0 | W78: 0 | X78: 0 | Y78: 0 | Z78: 0 | AA78: 0 | AB78: 0 | AC78: 0 | AD78: 0 | AE78: 0 | AF78: 0 | AG78: 0 | AH78: 3806 | AI78: 120 | AJ78: 11 | AK78: 0 | AL78: 0 | AM78: 0 | AN78: 0 | AO78: 0 | AP78: 0 | AQ78: 0 | AR78: 0 | AS78: 0 | AT78: 0 | AU78: 0 | AV78: 0 | AW78: 0 | AX78: 0 | AY78: 0 | AZ78: 0 | BA78: 0 | BB78: 0 | BC78: 0 | BD78: 8 | BE78: 0 | BF78: 0 | BG78: 0 | BH78: 0 | BI78: 0 | BJ78: 0 | BK78: 0 | BL78: 0 | BM78: 0 | BN78: 0 | BO78: 0 | BP78: 0 | BQ78: 0 | BR78: 0 | BS78: 0 | BT78: 0 | BU78: 4050 | BV78: 15729 | BX78: 0 | BY78: 0
A79: 26002 | B79: =IFERROR(INDEX(SCNtoISIC!$M:$M,MATCH($A79,SCNtoISIC!$J:$J,0)),0) -> ISIC 26 | C79: Máquinas para escritório e equipamentos de informática | D79: 0 | E79: 0 | F79: 0 | G79: 0 | H79: 0 | I79: 0 | J79: 0 | K79: 0 | L79: 0 | M79: 0 | N79: 0 | O79: 0 | P79: 0 | Q79: 0 | R79: 0 | S79: 0 | T79: 0 | U79: 0 | V79: 0 | W79: 0 | X79: 0 | Y79: 0 | Z79: 0 | AA79: 0 | AB79: 0 | AC79: 0 | AD79: 0 | AE79: 0 | AF79: 0 | AG79: 37 | AH79: 22432 | AI79: 20 | AJ79: 70 | AK79: 0 | AL79: 0 | AM79: 0 | AN79: 6 | AO79: 13 | AP79: 0 | AQ79: 0 | AR79: 0 | AS79: 0 | AT79: 908 | AU79: 0 | AV79: 0 | AW79: 0 | AX79: 0 | AY79: 0 | AZ79: 0 | BA79: 0 | BB79: 0 | BC79: 0 | BD79: 107 | BE79: 0 | BF79: 0 | BG79: 0 | BH79: 0 | BI79: 0 | BJ79: 0 | BK79: 0 | BL79: 0 | BM79: 0 | BN79: 0 | BO79: 0 | BP79: 0 | BQ79: 0 | BR79: 0 | BS79: 0 | BT79: 0 | BU79: 23593 | BV79: 13949 | BX79: 0 | BY79: 0
A80: 26003 | B80: =IFERROR(INDEX(SCNtoISIC!$M:$M,MATCH($A80,SCNtoISIC!$J:$J,0)),0) -> ISIC 26 | C80: Material eletrônico e equipamentos de comunicações | D80: 0 | E80: 0 | F80: 0 | G80: 0 | H80: 0 | I80: 0 | J80: 0 | K80: 0 | L80: 0 | M80: 0 | N80: 0 | O80: 0 | P80: 0 | Q80: 0 | R80: 0 | S80: 0 | T80: 0 | U80: 22 | V80: 0 | W80: 0 | X80: 0 | Y80: 0 | Z80: 0 | AA80: 0 | AB80: 150 | AC80: 0 | AD80: 0 | AE80: 0 | AF80: 0 | AG80: 68 | AH80: 42684 | AI80: 253 | AJ80: 10 | AK80: 28 | AL80: 53 | AM80: 32 | AN80: 10 | AO80: 0 | AP80: 0 | AQ80: 0 | AR80: 0 | AS80: 0 | AT80: 143 | AU80: 0 | AV80: 0 | AW80: 0 | AX80: 0 | AY80: 0 | AZ80: 0 | BA80: 0 | BB80: 0 | BC80: 0 | BD80: 0 | BE80: 0 | BF80: 0 | BG80: 0 | BH80: 0 | BI80: 0 | BJ80: 0 | BK80: 0 | BL80: 0 | BM80: 0 | BN80: 0 | BO80: 0 | BP80: 0 | BQ80: 0 | BR80: 0 | BS80: 0 | BT80: 0 | BU80: 43453 | BV80: 26026 | BX80: 0 | BY80: 0
A81: 26004 | B81: =IFERROR(INDEX(SCNtoISIC!$M:$M,MATCH($A81,SCNtoISIC!$J:$J,0)),0) -> ISIC 26 | C81: Equipamentos de medida, teste e controle, ópticos e eletromédicos | D81: 0 | E81: 0 | F81: 0 | G81: 0 | H81: 0 | I81: 0 | J81: 0 | K81: 0 | L81: 0 | M81: 0 | N81: 0 | O81: 0 | P81: 0 | Q81: 0 | R81: 0 | S81: 0 | T81: 0 | U81: 0 | V81: 0 | W81: 0 | X81: 0 | Y81: 0 | Z81: 0 | AA81: 0 | AB81: 40 | AC81: 13.8 | AD81: 9.2 | AE81: 0 | AF81: 0 | AG81: 33 | AH81: 8418 | AI81: 308 | AJ81: 290 | AK81: 0 | AL81: 157 | AM81: 0 | AN81: 157 | AO81: 95 | AP81: 0 | AQ81: 0 | AR81: 0 | AS81: 0 | AT81: 393 | AU81: 0 | AV81: 0 | AW81: 0 | AX81: 0 | AY81: 0 | AZ81: 0 | BA81: 0 | BB81: 0 | BC81: 0 | BD81: 0 | BE81: 0 | BF81: 0 | BG81: 0 | BH81: 0 | BI81: 0 | BJ81: 0 | BK81: 0 | BL81: 0 | BM81: 0 | BN81: 0 | BO81: 0 | BP81: 0 | BQ81: 0 | BR81: 0 | BS81: 0 | BT81: 0 | BU81: 9914 | BV81: 13305 | BX81: 23 | BY81: 0
A82: 27001 | B82: =IFERROR(INDEX(SCNtoISIC!$M:$M,MATCH($A82,SCNtoISIC!$J:$J,0)),0) -> ISIC 27 | C82: Máquinas, aparelhos e materiais elétricos | D82: 0 | E82: 0 | F82: 0 | G82: 0 | H82: 0 | I82: 0 | J82: 0 | K82: 0 | L82: 0 | M82: 0 | N82: 0 | O82: 0 | P82: 25 | Q82: 0 | R82: 0 | S82: 0 | T82: 0 | U82: 0 | V82: 0 | W82: 0 | X82: 8 | Y82: 0 | Z82: 0 | AA82: 0 | AB82: 153 | AC82: 15.6 | AD82: 10.4 | AE82: 185 | AF82: 311 | AG82: 566 | AH82: 1559 | AI82: 49691 | AJ82: 1261 | AK82: 881 | AL82: 836 | AM82: 35 | AN82: 51 | AO82: 723 | AP82: 0 | AQ82: 0 | AR82: 0 | AS82: 0 | AT82: 1 | AU82: 0 | AV82: 0 | AW82: 0 | AX82: 0 | AY82: 0 | AZ82: 0 | BA82: 0 | BB82: 0 | BC82: 0 | BD82: 0 | BE82: 0 | BF82: 0 | BG82: 0 | BH82: 0 | BI82: 0 | BJ82: 0 | BK82: 0 | BL82: 0 | BM82: 0 | BN82: 0 | BO82: 0 | BP82: 0 | BQ82: 0 | BR82: 0 | BS82: 0 | BT82: 0 | BU82: 56312 | BV82: 23215 | BX82: 26 | BY82: 0
A83: 27002 | B83: =IFERROR(INDEX(SCNtoISIC!$M:$M,MATCH($A83,SCNtoISIC!$J:$J,0)),0) -> ISIC 27 | C83: Eletrodomésticos | D83: 0 | E83: 0 | F83: 0 | G83: 0 | H83: 0 | I83: 0 | J83: 0 | K83: 0 | L83: 0 | M83: 0 | N83: 0 | O83: 0 | P83: 0 | Q83: 0 | R83: 0 | S83: 0 | T83: 0 | U83: 0 | V83: 0 | W83: 0 | X83: 0 | Y83: 0 | Z83: 0 | AA83: 0 | AB83: 265 | AC83: 26.4 | AD83: 17.6 | AE83: 0 | AF83: 0 | AG83: 89 | AH83: 371 | AI83: 15491 | AJ83: 858 | AK83: 0 | AL83: 14 | AM83: 6 | AN83: 12 | AO83: 0 | AP83: 0 | AQ83: 0 | AR83: 0 | AS83: 0 | AT83: 634 | AU83: 0 | AV83: 0 | AW83: 0 | AX83: 0 | AY83: 0 | AZ83: 0 | BA83: 0 | BB83: 0 | BC83: 0 | BD83: 0 | BE83: 0 | BF83: 0 | BG83: 0 | BH83: 0 | BI83: 0 | BJ83: 0 | BK83: 0 | BL83: 0 | BM83: 0 | BN83: 0 | BO83: 0 | BP83: 0 | BQ83: 0 | BR83: 0 | BS83: 0 | BT83: 0 | BU83: 17784 | BV83: 3180 | BX83: 44 | BY83: 0
... A134: 97001 | B134: =IFERROR(INDEX(SCNtoISIC!$M:$M,MATCH($A134,SCNtoISIC!$J:$J,0)),0) -> ISIC 97T98 | C134: Serviços domésticos | D134: 0 | E134: 0 | F134: 0 | G134: 0 | H134: 0 | I134: 0 | J134: 0 | K134: 0 | L134: 0 | M134: 0 | N134: 0 | O134: 0 | P134: 0 | Q134: 0 | R134: 0 | S134: 0 | T134: 0 | U134: 0 | V134: 0 | W134: 0 | X134: 0 | Y134: 0 | Z134: 0 | AA134: 0 | AB134: 0 | AC134: 0 | AD134: 0 | AE134: 0 | AF134: 0 | AG134: 0 | AH134: 0 | AI134: 0 | AJ134: 0 | AK134: 0 | AL134: 0 | AM134: 0 | AN134: 0 | AO134: 0 | AP134: 0 | AQ134: 0 | AR134: 0 | AS134: 0 | AT134: 0 | AU134: 0 | AV134: 0 | AW134: 0 | AX134: 0 | AY134: 0 | AZ134: 0 | BA134: 0 | BB134: 0 | BC134: 0 | BD134: 0 | BE134: 0 | BF134: 0 | BG134: 0 | BH134: 0 | BI134: 0 | BJ134: 0 | BK134: 0 | BL134: 0 | BM134: 0 | BN134: 0 | BO134: 0 | BP134: 0 | BQ134: 0 | BR134: 0 | BS134: 0 | BT134: 61996 | BU134: 61996 | BV134: 0 | BX134: 0 | BY134: 0
B135: =IFERROR(INDEX(SCNtoISIC!$M:$M,MATCH($A135,SCNtoISIC!$J:$J,0)),0) -> 0 | D135: =SUM(D7:D134) -> 309301 | E135: =SUM(E7:E134) -> 137018 | F135: =SUM(F7:F134) -> 32411 | G135: =SUM(G7:G134) -> 19733 | H135: =SUM(H7:H134) -> 171984 | I135: =SUM(I7:I134) -> 52753 | J135: =SUM(J7:J134) -> 16103 | K135: =SUM(K7:K134) -> 255198 | ... BV135: =SUM(BV7:BV134) -> 842614 | BX135: =SUM(BX7:BX134) -> 89569 | BY135: =SUM(BY7:BY134) -> 260753
A136: Total | D136: 309301 | E136: 137018 | F136: 32411 | G136: 19733 | H136: 171984 | I136: 52753 | J136: 16103 | K136: 255198 | L136: 48066 | M136: 253228 | N136: 76444 | O136: 15084 | P136: 46430 | Q136: 61302 | R136: 40232 | S136: 26588 | T136: 80337 | U136: 19473 | V136: 373349 | W136: 42841 | X136: 145533 | Y136: 74484 | Z136: 40475 | AA136: 57972 | AB136: 101171 | AC136: =0.6*BX136 -> 53741.4 | AD136: =0.4*BX136 -> 35827.6 | AE136: 101592 | AF136: 57162 | AG136: 91269 | AH136: 85209 | AI136: 71998 | AJ136: 120638 | AK136: 146446 | AL136: 70497 | AM136: 51015 | AN136: 70398 | AO136: 62460 | AP136: =2/3*BY136 -> 173835.33 | AQ136: =BY136/3 -> 86917.667 | AR136: 62845 | AS136: 632308 | AT136: 1100763 | AU136: 332855 | AV136: 20080 | AW136: 37338 | AX136: 115144 | AY136: 23990 | AZ136: 223426 | BA136: 20486 | BB136: 43404 | BC136: 161039 | BD136: 125537 | BE136: 574611 | BF136: 545929 | BG136: 187868 | BH136: 70844 | BI136: 94350 | BJ136: 45657 | BK136: 208430 | BL136: 39955 | BM136: 719620 | BN136: 309034 | BO136: 110787 | BP136: 179155 | BQ136: 222681 | BR136: 34631 | BS136: 145590 | BT136: 61996 | BU136: 10226869 | BV136: 842614 | BX136: 89569 | BY136: 260753
D137: =D136-D135 -> 0 | E137: =E136-E135 -> 0 | F137: =F136-F135 -> 0 | G137: =G136-G135 -> 0 | H137: =H136-H135 -> 0 | I137: =I136-I135 -> 0 | J137: =J136-J135 -> 0 | K137: =K136-K135 -> 0 | ... AB137: =AB136-AB135 -> 0 | AE137: =AE136-AE135 -> 0 | AF137: =AF136-AF135 -> 0 | AG137: =AG136-AG135 -> 0 | AH137: =AH136-AH135 -> 0 | AI137: =AI136-AI135 -> 0 | AJ137: =AJ136-AJ135 -> 0 | AK137: =AK136-AK135 -> 0 | AL137: =AL136-AL135 -> 0 | ... BV137: =BV136-BV135 -> 0 | BX137: =BX136-BX135 -> 0 | BY137: =BY136-BY135 -> 0
A138: Fonte: IBGE, Diretoria de Pesquisas, Coordenação de Contas Nacionais.
A139: (1) Importação de bens e serviços líquida de ajuste CIF/FOB.
A141: 23001 | C141: Cimento | D141: 0 | E141: 0 | F141: 0 | G141: 111 | H141: 0 | I141: 0 | J141: 0 | K141: 0 | L141: 0 | M141: 9 | N141: 0 | O141: 0 | P141: 0 | Q141: 0 | R141: 0 | S141: 0 | T141: 0 | U141: 0 | V141: 0 | W141: 0 | X141: 0 | Y141: 0 | Z141: 0 | AA141: 0 | AB141: 0 | AE141: 0 | AF141: 0 | AG141: 0 | AH141: 0 | AI141: 0 | AJ141: 0 | AK141: 0 | AL141: 0 | AM141: 0 | AN141: 0 | AO141: 0 | AR141: 0 | AS141: 0 | AT141: 0 | AU141: 0 | AV141: 0 | AW141: 0 | AX141: 0 | AY141: 0 | AZ141: 0 | BA141: 0 | BB141: 0 | BC141: 0 | BD141: 0 | BE141: 0 | BF141: 0 | BG141: 0 | BH141: 0 | BI141: 0 | BJ141: 0 | BK141: 0 | BL141: 0 | BM141: 0 | BN141: 0 | BO141: 0 | BP141: 0 | BQ141: 0 | BR141: 0 | BS141: 0 | BT141: 0 | BU141: 16383 | BV141: 410 | BX141: 16263 | BY141: 0
A142: 23002 | C142: Artefatos de cimento, gesso e semelhantes | D142: 0 | E142: 0 | F142: 0 | G142: 38 | H142: 0 | I142: 0 | J142: 0 | K142: 0 | L142: 0 | M142: 0 | N142: 0 | O142: 0 | P142: 0 | Q142: 0 | R142: 0 | S142: 12 | T142: 0 | U142: 0 | V142: 0 | W142: 0 | X142: 0 | Y142: 13 | Z142: 0 | AA142: 0 | AB142: 27 | AE142: 13 | AF142: 0 | AG142: 68 | AH142: 0 | AI142: 0 | AJ142: 0 | AK142: 0 | AL142: 0 | AM142: 15 | AN142: 80 | AO142: 0 | AR142: 0 | AS142: 0 | AT142: 386 | AU142: 0 | AV142: 0 | AW142: 0 | AX142: 0 | AY142: 0 | AZ142: 0 | BA142: 0 | BB142: 0 | BC142: 0 | BD142: 0 | BE142: 0 | BF142: 0 | BG142: 0 | BH142: 0 | BI142: 0 | BJ142: 0 | BK142: 0 | BL142: 0 | BM142: 0 | BN142: 0 | BO142: 0 | BP142: 0 | BQ142: 0 | BR142: 0 | BS142: 0 | BT142: 0 | BU142: 24171 | BV142: 264 | BX142: 23519 | BY142: 0
A143: 35001 | C143: Eletricidade, gás e outras utilidades | D143: 0 | E143: 0 | F143: 0 | G143: 0 | H143: 0 | I143: 0 | J143: 0 | K143: 0 | L143: 0 | M143: 0 | N143: 0 | O143: 0 | P143: 0 | Q143: 0 | R143: 0 | S143: 0 | T143: 0 | U143: 0 | V143: 0 | W143: 0 | X143: 0 | Y143: 0 | Z143: 0 | AA143: 0 | AB143: 0 | AE143: 0 | AF143: 0 | AG143: 0 | AH143: 0 | AI143: 0 | AJ143: 0 | AK143: 0 | AL143: 0 | AM143: 0 | AN143: 0 | AO143: 0 | AR143: 0 | AS143: 0 | AT143: 0 | AU143: 0 | AV143: 0 | AW143: 0 | AX143: 0 | AY143: 0 | AZ143: 0 | BA143: 0 | BB143: 0 | BC143: 0 | BD143: 0 | BE143: 0 | BF143: 0 | BG143: 0 | BH143: 0 | BI143: 0 | BJ143: 0 | BK143: 0 | BL143: 0 | BM143: 481 | BN143: 0 | BO143: 0 | BP143: 0 | BQ143: 0 | BR143: 0 | BS143: 0 | BT143: 0 | BU143: 257384 | BV143: 4599 | BX143: 0 | BY143: 256903

Sheet Split ISIC Code Shares
A1: Metric | B1: Unit | C1: Coal mining | D1: Oil and gas extraction | E1: Chemicals | F1: Pharmaceuticals | G1: Glass | H1: Cement and Other Nometallic Minerals | I1: Iron and steel | J1: Other metals | K1: Electricity generation and distribution | L1: Energy pipelines and gas processing | M1: Water and waste
C2: ISIC 05 | D2: ISIC 06 | E2: ISIC 20 | F2: ISIC 21 | G2: ISIC 231 | H2: ISIC 239 | I2: ISIC 241 | J2: ISIC 242 | K2: ISIC 351 | L2: ISIC 352T353 | M2: ISIC 36T39
A3: Domestic Production | B3: million $ | C3: ='OECD TTL'!$D$49*SUMIFS(SCNUse128!$D$140:$BT$140,SCNUse128!$D$6:$BT$6,C$2) -> 7.186654e+08 | D3: ='OECD TTL'!$D$49*SUMIFS(SCNUse128!$D$140:$BT$140,SCNUse128!$D$6:$BT$6,D$2) -> 5797694472 | E3: ='OECD TTL'!$D$49*SUMIFS(SCNUse128!$D$140:$BT$140,SCNUse128!$D$6:$BT$6,E$2) -> 1.1409855e+10 | F3: ='OECD TTL'!$D$49*SUMIFS(SCNUse128!$D$140:$BT$140,SCNUse128!$D$6:$BT$6,F$2) -> 2216412663 | G3: ='OECD TTL'!$D$49*SUMIFS(SCNUse128!$D$140:$BT$140,SCNUse128!$D$6:$BT$6,G$2) -> 1.1772687e+09 | H3: ='OECD TTL'!$D$49*SUMIFS(SCNUse128!$D$140:$BT$140,SCNUse128!$D$6:$BT$6,H$2) -> 2.758942e+09 | I3: ='OECD TTL'!$D$49*SUMIFS(SCNUse128!$D$140:$BT$140,SCNUse128!$D$6:$BT$6,I$2) -> 4412638898 | J3: ='OECD TTL'!$D$49*SUMIFS(SCNUse128!$D$140:$BT$140,SCNUse128!$D$6:$BT$6,J$2) -> 3246587024 | ... M3: ='OECD TTL'!$D$49*SUMIFS(SCNUse128!$D$140:$BT$140,SCNUse128!$D$6:$BT$6,M$2) -> 7.4156081e+09
A4: Imports | B4: million $ | C4: {=SUMPRODUCT(SCNSup128!$BV$7:$BV$134*(SCNUse128!$B$7:$B$134=C$2))} -> 9197 | D4: {=SUMPRODUCT(SCNSup128!$BV$7:$BV$134*(SCNUse128!$B$7:$B$134=D$2))} -> 40773 | E4: {=SUMPRODUCT(SCNSup128!$BV$7:$BV$134*(SCNUse128!$B$7:$B$134=E$2))} -> 112839 | F4: {=SUMPRODUCT(SCNSup128!$BV$7:$BV$134*(SCNUse128!$B$7:$B$134=F$2))} -> 27872 | G4: {=SUMPRODUCT(SCNSup128!$BV$7:$BV$134*(SCNUse128!$B$7:$B$134=G$2))} -> 5653 | H4: {=SUMPRODUCT(SCNSup128!$BV$7:$BV$134*(SCNUse128!$B$7:$B$134=H$2))} -> 674 | I4: {=SUMPRODUCT(SCNSup128!$BV$7:$BV$134*(SCNUse128!$B$7:$B$134=I$2))} -> 11989 | J4: {=SUMPRODUCT(SCNSup128!$BV$7:$BV$134*(SCNUse128!$B$7:$B$134=J$2))} -> 13050 | ... M4: {=SUMPRODUCT(SCNSup128!$BV$7:$BV$134*(SCNUse128!$B$7:$B$134=M$2))} -> 0
A5: Exports | B5: million $ | C5: {=SUMPRODUCT(SCNUse128!$BV$7:$BV$134*(SCNUse128!$B$7:$B$134=C$2))} -> 1911 | D5: {=SUMPRODUCT(SCNUse128!$BV$7:$BV$134*(SCNUse128!$B$7:$B$134=D$2))} -> 38789 | E5: {=SUMPRODUCT(SCNUse128!$BV$7:$BV$134*(SCNUse128!$B$7:$B$134=E$2))} -> 30498 | F5: {=SUMPRODUCT(SCNUse128!$BV$7:$BV$134*(SCNUse128!$B$7:$B$134=F$2))} -> 4462 | G5: {=SUMPRODUCT(SCNUse128!$BV$7:$BV$134*(SCNUse128!$B$7:$B$134=G$2))} -> 7455 | H5: {=SUMPRODUCT(SCNUse128!$BV$7:$BV$134*(SCNUse128!$B$7:$B$134=H$2))} -> 120 | I5: {=SUMPRODUCT(SCNUse128!$BV$7:$BV$134*(SCNUse128!$B$7:$B$134=I$2))} -> 36925 | J5: {=SUMPRODUCT(SCNUse128!$BV$7:$BV$134*(SCNUse128!$B$7:$B$134=J$2))} -> 25279 | ... M5: {=SUMPRODUCT(SCNUse128!$BV$7:$BV$134*(SCNUse128!$B$7:$B$134=M$2))} -> 4
A7: Domestic Production | B7: percent | C7: =C3/SUM($C3:$D3) -> 0.11028633 | D7: =D3/SUM($C3:$D3) -> 0.88971367 | E7: =E3/SUM($E3:$F3) -> 0.83734264 | F7: =F3/SUM($E3:$F3) -> 0.16265736 | G7: =G3/SUM($G3:$H3) -> 0.29908681 | H7: =H3/SUM($G3:$H3) -> 0.70091319 | I7: =I3/SUM($I3:$J3) -> 0.57612074 | J7: =J3/SUM($I3:$J3) -> 0.42387926 | K7: =K3/SUM($K3:$M3) -> 0.38542937 | L7: =L3/SUM($K3:$M3) -> 0.16765895 | M7: =M3/SUM($K3:$M3) -> 0.44691168
A8: Imports | B8: percent | C8: =C4/SUM($C4:$D4) -> 0.18405043 | D8: =D4/SUM($C4:$D4) -> 0.81594957 | E8: =E4/SUM($E4:$F4) -> 0.80192025 | F8: =F4/SUM($E4:$F4) -> 0.19807975 | G8: =G4/SUM($G4:$H4) -> 0.89347242 | H8: =H4/SUM($G4:$H4) -> 0.10652758 | I8: =I4/SUM($I4:$J4) -> 0.47881305 | J8: =J4/SUM($I4:$J4) -> 0.52118695 | K8: =K4/SUM($K4:$M4) -> 0.66666667 | L8: =L4/SUM($K4:$M4) -> 0.33333333 | M8: =M4/SUM($K4:$M4) -> 0
A9: Exports | B9: percent | C9: =C5/SUM($C5:$D5) -> 0.046953317 | D9: =D5/SUM($C5:$D5) -> 0.95304668 | E9: =E5/SUM($E5:$F5) -> 0.87236842 | F9: =F5/SUM($E5:$F5) -> 0.12763158 | G9: =G5/SUM($G5:$H5) -> 0.98415842 | H9: =H5/SUM($G5:$H5) -> 0.015841584 | I9: =I5/SUM($I5:$J5) -> 0.59361134 | J9: =J5/SUM($I5:$J5) -> 0.40638866 | K9: =K5/SUM($K5:$M5) -> 0 | L9: =L5/SUM($K5:$M5) -> 0 | M9: =M5/SUM($K5:$M5) -> 1

Sheet Calculations
B1: ISIC 01T03 | C1: ISIC 05 | D1: ISIC 06 | E1: ISIC 07T08 | F1: ISIC 09 | G1: ISIC 10T12 | H1: ISIC 13T15 | I1: ISIC 16 | J1: ISIC 17T18 | K1: ISIC 19 | L1: ISIC 20 | M1: ISIC 21 | N1: ISIC 22 | O1: ISIC 231 | P1: ISIC 239 | Q1: ISIC 241 | R1: ISIC 242 | S1: ISIC 25 | T1: ISIC 26 | U1: ISIC 27 | V1: ISIC 28 | W1: ISIC 29 | X1: ISIC 30 | Y1: ISIC 31T33 | Z1: ISIC 351 | AA1: ISIC 352T353 | AB1: ISIC 36T39 | AC1: ISIC 41T43 | AD1: ISIC 45T47 | AE1: ISIC 49T53 | AF1: ISIC 55T56 | AG1: ISIC 58T60 | AH1: ISIC 61 | AI1: ISIC 62T63 | AJ1: ISIC 64T66 | AK1: ISIC 68 | AL1: ISIC 69T82 | AM1: ISIC 84 | AN1: ISIC 85 | AO1: ISIC 86T88 | AP1: ISIC 90T96 | AQ1: ISIC 97T98
A2: Domestic Production | B2: ='OECD TTL'!C49 -> 145972.1 | C2: ='OECD TTL'!$D$49*'Split ISIC Code Shares'!C$7 -> 5250.6769 | D2: ='OECD TTL'!$D$49*'Split ISIC Code Shares'!D$7 -> 42358.823 | E2: ='OECD TTL'!E49 -> 26401.3 | F2: ='OECD TTL'!F49 -> 4831.8 | G2: ='OECD TTL'!G49 -> 196073.8 | H2: ='OECD TTL'!H49 -> 44770 | I2: ='OECD TTL'!I49 -> 8044.8 | J2: ='OECD TTL'!J49 -> 30199.9 | K2: ='OECD TTL'!K49 -> 112965.6 | L2: ='OECD TTL'!$L$49*'Split ISIC Code Shares'!E$7 -> 91539.47 | M2: ='OECD TTL'!$L$49*'Split ISIC Code Shares'!F$7 -> 17781.93 | N2: ='OECD TTL'!M49 -> 30611.7 | O2: ='OECD TTL'!$N$49*'Split ISIC Code Shares'!G$7 -> 8105.6114 | P2: ='OECD TTL'!$N$49*'Split ISIC Code Shares'!H$7 -> 18995.589 | Q2: ='OECD TTL'!$O$49*'Split ISIC Code Shares'!I$7 -> 27673.844 | R2: ='OECD TTL'!$O$49*'Split ISIC Code Shares'!J$7 -> 20360.956 | S2: ='OECD TTL'!P49 -> 27615.6 | T2: ='OECD TTL'!Q49 -> 25782 | U2: ='OECD TTL'!R49 -> 21784.7 | V2: ='OECD TTL'!S49 -> 36501.9 | W2: ='OECD TTL'!T49 -> 65641.3 | X2: ='OECD TTL'!U49 -> 15435.8 | Y2: ='OECD TTL'!V49 -> 40199.3 | Z2: ='OECD TTL'!$W$49*'Split ISIC Code Shares'!K$7 -> 37738.276 | AA2: ='OECD TTL'!$W$49*'Split ISIC Code Shares'!L$7 -> 16415.873 | AB2: ='OECD TTL'!$W$49*'Split ISIC Code Shares'!M$7 -> 43758.151 | AC2: ='OECD TTL'!X49 -> 191319.8 | AD2: ='OECD TTL'!Y49 -> 333062 | AE2: ='OECD TTL'!Z49 -> 152925.9 | AF2: ='OECD TTL'!AA49 -> 74861.6 | AG2: ='OECD TTL'!AB49 -> 19331.4 | AH2: ='OECD TTL'!AC49 -> 48726.2 | AI2: ='OECD TTL'!AD49 -> 37984.2 | AJ2: ='OECD TTL'!AE49 -> 175880.3 | ... AQ2: ='OECD TTL'!AL49 -> 18634.7
A3: Imports | B3: =-'OECD TTL'!AU$9+'OECD TTL'!AR$9 -> 3493.6 | C3: =(-'OECD TTL'!$AU$10+'OECD TTL'!$AR$10)*'Split ISIC Code Shares'!C8 -> 2487.6808 | D3: =(-'OECD TTL'!$AU$10+'OECD TTL'!$AR$10)*'Split ISIC Code Shares'!D8 -> 11028.619 | E3: {=-TRANSPOSE('OECD TTL'!$AU$11:$AU$17)+TRANSPOSE('OECD TTL'!$AR$11:$AR$17)} -> 2325.2 | F3: 73.7 | G3: 7911.7 | H3: 7486.6 | I3: 250.4 | J3: 1536.6 | K3: 9091.6 | L3: =(-'OECD TTL'!$AU$18+'OECD TTL'!$AR$18)*'Split ISIC Code Shares'!E$8 -> 24570.756 | M3: =(-'OECD TTL'!$AU$18+'OECD TTL'!$AR$18)*'Split ISIC Code Shares'!F$8 -> 6069.1438 | N3: =-'OECD TTL'!AU19+'OECD TTL'!AR19 -> 4620.6 | O3: =(-'OECD TTL'!$AU$20+'OECD TTL'!$AR$20)*'Split ISIC Code Shares'!G$8 -> 1748.8829 | P3: =(-'OECD TTL'!$AU$20+'OECD TTL'!$AR$20)*'Split ISIC Code Shares'!H$8 -> 208.51709 | Q3: =(-'OECD TTL'!$AU$21+'OECD TTL'!$AR$21)*'Split ISIC Code Shares'!I$8 -> 2746.5674 | R3: =(-'OECD TTL'!$AU$21+'OECD TTL'!$AR$21)*'Split ISIC Code Shares'!J$8 -> 2989.6326 | S3: {=-TRANSPOSE('OECD TTL'!AU22:AU28)+TRANSPOSE('OECD TTL'!AR22:AR28)} -> 4204.4 | T3: 16156.8 | U3: 7738.5 | V3: 13496.4 | W3: 12583.1 | X3: 10023.4 | Y3: 4651 | Z3: =(-'OECD TTL'!$AU$29+'OECD TTL'!$AR$29)*'Split ISIC Code Shares'!K$8 -> 912.93333 | AA3: =(-'OECD TTL'!$AU$29+'OECD TTL'!$AR$29)*'Split ISIC Code Shares'!L$8 -> 456.46667 | AB3: =(-'OECD TTL'!$AU$29+'OECD TTL'!$AR$29)*'Split ISIC Code Shares'!M$8 -> 0 | AC3: {=-TRANSPOSE('OECD TTL'!AU30:AU44)+TRANSPOSE('OECD TTL'!AR30:AR44)} -> 235.2 | AD3: 27066.6 | AE3: 14465.6 | AF3: 11338.7 | AG3: 1937.2 | AH3: 1359.6 | AI3: 7612.4 | AJ3: 6758.2 | AK3: 2768.2 | AL3: 27483.4 | AM3: 234.5 | AN3: 3881.4 | AO3: 570 | AP3: 2592.2 | AQ3: 0
A4: Exports | B4: ='OECD TTL'!$AT$9+'OECD TTL'!$AS$9 -> 34309.2 | C4: =('OECD TTL'!$AT$10+'OECD TTL'!$AS$10)*'Split ISIC Code Shares'!C$9 -> 540.58762 | D4: =('OECD TTL'!$AT$10+'OECD TTL'!$AS$10)*'Split ISIC Code Shares'!D$9 -> 10972.712 | E4: {=TRANSPOSE('OECD TTL'!$AT$11:$AT$17)+TRANSPOSE('OECD TTL'!$AS$11:$AS$17)} -> 15903.2 | F4: 62.1 | G4: 30629.1 | H4: 3626.3 | I4: 1949 | J4: 6845.9 | K4: 4760.7 | L4: =SUM('OECD TTL'!$AS$18:$AT$18)*'Split ISIC Code Shares'!E$9 -> 7139.8993 | M4: =SUM('OECD TTL'!$AS$18:$AT$18)*'Split ISIC Code Shares'!F$9 -> 1044.6007 | N4: ='OECD TTL'!AT19+'OECD TTL'!AS19 -> 2441.1 | O4: =SUM('OECD TTL'!$AS$20:$AT$20)*'Split ISIC Code Shares'!G$9 -> 2005.7149 | P4: =SUM('OECD TTL'!$AS$20:$AT$20)*'Split ISIC Code Shares'!H$9 -> 32.285149 | Q4: =SUM('OECD TTL'!$AS$21:$AT$21)*'Split ISIC Code Shares'!I$9 -> 10431.235 | R4: =SUM('OECD TTL'!$AS$21:$AT$21)*'Split ISIC Code Shares'!J$9 -> 7141.2647 | S4: {=TRANSPOSE('OECD TTL'!AT22:AT28)+TRANSPOSE('OECD TTL'!AS22:AS28)} -> 2091.4 | T4: 1215.1 | U4: 2118.3 | V4: 5928 | W4: 10889.3 | X4: 5643.6 | Y4: 1695.3 | Z4: =SUM('OECD TTL'!$AS$29:$AT$29)*'Split ISIC Code Shares'!K$9 -> 0 | AA4: =SUM('OECD TTL'!$AS$29:$AT$29)*'Split ISIC Code Shares'!L$9 -> 0 | AB4: =SUM('OECD TTL'!$AS$29:$AT$29)*'Split ISIC Code Shares'!M$9 -> 33.7 | AC4: {=TRANSPOSE('OECD TTL'!AT30:AT44)+TRANSPOSE('OECD TTL'!AS30:AS44)} -> 22.7 | AD4: 21966.3 | AE4: 16678.3 | AF4: 459.2 | AG4: 194.1 | AH4: 371.8 | AI4: 991.7 | AJ4: 1556.5 | AK4: 1236 | AL4: 13013.4 | AM4: 861.3 | AN4: 241.2 | AO4: 32.4 | AP4: 186.1 | AQ4: 0
A5: Domestic Consumption | B5: =B2+B3-B4 -> 115156.5 | C5: =C2+C3-C4 -> 7197.7701 | D5: =D2+D3-D4 -> 42414.73 | E5: =E2+E3-E4 -> 12823.3 | F5: =F2+F3-F4 -> 4843.4 | G5: =G2+G3-G4 -> 173356.4 | H5: =H2+H3-H4 -> 48630.3 | I5: =I2+I3-I4 -> 6346.2 | ... AQ5: =AQ2+AQ3-AQ4 -> 18634.7
A6: Imported Content Share of Exports | B6: ='OECD ICESHR'!$C$9/100 -> 0.0967 | C6: 0 | D6: ='OECD ICESHR'!C10/100 -> 0.1658 | E6: {=TRANSPOSE('OECD ICESHR'!$C$11:$C$17)/100} -> 0.1246 | F6: 0.1236 | G6: 0.1114 | H6: 0.1215 | I6: 0.0996 | J6: 0.1338 | K6: 0.2454 | L6: ='OECD ICESHR'!$C$18/100 -> 0.1838 | M6: ='OECD ICESHR'!$C$18/100 -> 0.1838 | N6: ='OECD ICESHR'!C19/100 -> 0.1759 | O6: ='OECD ICESHR'!$C$20/100 -> 0.1246 | P6: ='OECD ICESHR'!$C$20/100 -> 0.1246 | Q6: ='OECD ICESHR'!$C$21/100 -> 0.1833 | R6: ='OECD ICESHR'!$C$21/100 -> 0.1833 | S6: {=TRANSPOSE('OECD ICESHR'!C22:C28)/100} -> 0.1469 | T6: 0.2522 | U6: 0.1988 | V6: 0.1801 | W6: 0.1978 | X6: 0.2659 | Y6: 0.1354 | Z6: ='OECD ICESHR'!$C$29/100 -> 0.0918 | AA6: ='OECD ICESHR'!$C$29/100 -> 0.0918 | AB6: ='OECD ICESHR'!$C$29/100 -> 0.0918 | AC6: {=TRANSPOSE('OECD ICESHR'!C30:C44)/100} -> 0.0971 | AD6: 0.0483 | AE6: 0.1112 | AF6: 0.0632 | AG6: 0.0916 | AH6: 0.0929 | AI6: 0.0632 | AJ6: 0.037 | AK6: 0.0106 | AL6: 0.0475 | AM6: 0.0445 | AN6: 0.0343 | AO6: 0.0497 | AP6: 0.0722 | AQ6: 0.1256
A7: Imports Consumed Domestically | B7: =B3*(1-B6) -> 3155.7689 | C7: =C3*(1-C6) -> 2487.6808 | D7: =D3*(1-D6) -> 9200.0741 | E7: =E3*(1-E6) -> 2035.4801 | F7: =F3*(1-F6) -> 64.59068 | G7: =G3*(1-G6) -> 7030.3366 | H7: =H3*(1-H6) -> 6576.9781 | I7: =I3*(1-I6) -> 225.46016 | ... AQ7: =AQ3*(1-AQ6) -> 0
A8: Domestic Production Consumed Domestically | B8: =B5-B7 -> 112000.73 | C8: =C5-C7 -> 4710.0893 | D8: =D5-D7 -> 33214.656 | E8: =E5-E7 -> 10787.82 | F8: =F5-F7 -> 4778.8093 | G8: =G5-G7 -> 166326.06 | H8: =H5-H7 -> 42053.322 | I8: =I5-I7 -> 6120.7398 | ... AQ8: =AQ5-AQ7 -> 18634.7
A9: Domestic Content Share of Domestic Consumption | B9: =B8/B5 -> 0.97259582 | C9: =C8/C5 -> 0.65438173 | D9: =D8/D5 -> 0.78309247 | E9: =E8/E5 -> 0.84126706 | F9: =F8/F5 -> 0.98666419 | G9: =G8/G5 -> 0.95944576 | H9: =H8/H5 -> 0.86475555 | I9: =I8/I5 -> 0.9644732 | ... AQ9: =AQ8/AQ5 -> 1
A11: Export Share of Production | B11: =B4/B2 -> 0.23503944 | C11: =C4/C2 -> 0.1029558 | D11: =D4/D2 -> 0.25904196 | E11: =E4/E2 -> 0.60236428 | F11: =F4/F2 -> 0.012852353 | G11: =G4/G2 -> 0.1562121 | H11: =H4/H2 -> 0.080998436 | I11: =I4/I2 -> 0.2422683 | ... AQ11: =AQ4/AQ2 -> 0
A13: OECD TTL row number | B13: 9 | C13: 10 | D13: 10 | E13: 11 | F13: 12 | G13: 13 | H13: 14 | I13: 15 | J13: 16 | K13: 17 | L13: 18 | M13: 18 | N13: 19 | O13: 20 | P13: 20 | Q13: 21 | R13: 21 | S13: 22 | T13: 23 | U13: 24 | V13: 25 | W13: 26 | X13: 27 | Y13: 28 | Z13: 29 | AA13: 29 | AB13: 29 | AC13: 30 | AD13: 31 | AE13: 32 | AF13: 33 | AG13: 34 | AH13: 35 | AI13: 36 | AJ13: 37 | AK13: 38 | AL13: 39 | AM13: 40 | AN13: 41 | AO13: 42 | AP13: 43 | AQ13: 44

Sheet SCNtoISIC
B3: kidx | C3: SCN67 | D3: Descrição do produto | E3: idx | F3: ISIC Code | G3: Meaning | I3: kidx | J3: SCN128 | K3: Descrição do produto | L3: idx | M3: ISIC Code | N3: Meaning | P3: kidx | Q3: SCN128 | R3: Descrição do produto | S3: kidx | T3: SCN67 | U3: Descrição do produto | W3: SCN67 | X3: Descrição do produto
B4: 1 | C4: 191 | D4: Agricultura, inclusive o apoio à agricultura e a pós-colheita | E4: 1 | F4: ISIC 01T03 | G4: 01T03: Agriculture, forestry and fishing | I4: 1 | J4: 1911 | K4: Arroz, trigo e outros cereais | L4: 1 | M4: ISIC 01T03 | N4: 01T03: Agriculture, forestry and fishing | P4: 1 | Q4: 1911 | R4: Arroz, trigo e outros cereais | S4: 1 | T4: 191 | U4: Agricultura, inclusive o apoio à agricultura e a pós-colheita | W4: 191 | X4: Agricultura, inclusive o apoio à agricultura e a pós-colheita
B5: 2 | C5: 192 | D5: Pecuária, inclusive o apoio à pecuária | E5: 1 | F5: ISIC 01T03 | I5: 2 | J5: 1912 | K5: Milho em grão | L5: 1 | M5: ISIC 01T03 | P5: 2 | Q5: 1912 | R5: Milho em grão | S5: 1 | T5: 191 | W5: 191
B6: 3 | C6: 280 | D6: Produção florestal; pesca e aquicultura | E6: 1 | F6: ISIC 01T03 | I6: 3 | J6: 1913 | K6: Algodão herbáceo, outras fibras da lav. temporária | L6: 1 | M6: ISIC 01T03 | P6: 3 | Q6: 1913 | R6: Algodão herbáceo, outras fibras da lav. temporária | S6: 1 | T6: 191 | W6: 191
B7: 4 | C7: 580 | D7: Extração de carvão mineral e de minerais não metálicos | E7: 2 | F7: ISIC 05 | G7: 05: Coal mining | I7: 4 | J7: 1914 | K7: Cana-de-açúcar | L7: 1 | M7: ISIC 01T03 | P7: 4 | Q7: 1914 | R7: Cana-de-açúcar | S7: 1 | T7: 191 | W7: 191
B8: 5 | C8: 680 | D8: Extração de petróleo e gás, inclusive as atividades de apoio | E8: 3 | F8: ISIC 06 | G8: 06: Oil and gas extraction | I8: 5 | J8: 1915 | K8: Soja em grão | L8: 1 | M8: ISIC 01T03 | P8: 5 | Q8: 1915 | R8: Soja em grão | S8: 1 | T8: 191 | W8: 191
B9: 6 | C9: 791 | D9: Extração de minério de ferro, inclusive beneficiamentos e a aglomeração | E9: 4 | F9: ISIC 07T08 | G9: 07T08: Mining and quarrying of non-energy producing products | I9: 6 | J9: 1916 | K9: Outros produtos e serviços da lavoura temporária | L9: 1 | M9: ISIC 01T03 | P9: 6 | Q9: 1916 | R9: Outros produtos e serviços da lavoura temporária | S9: 1 | T9: 191 | W9: 191
B10: 7 | C10: 792 | D10: Extração de minerais metálicos não ferrosos, inclusive beneficiamentos | E10: 5 | F10: ISIC 09 | G10: 09: Mining support service activities | I10: 7 | J10: 1917 | K10: Laranja | L10: 1 | M10: ISIC 01T03 | P10: 7 | Q10: 1917 | R10: Laranja | S10: 1 | T10: 191 | W10: 191
B11: 8 | C11: 1091 | D11: Abate e produtos de carne, inclusive os produtos do laticínio e da pesca | E11: 6 | F11: ISIC 10T12 | G11: 10T12: Food products, beverages and tobacco | I11: 8 | J11: 1918 | K11: Café em grão | L11: 1 | M11: ISIC 01T03 | P11: 8 | Q11: 1918 | R11: Café em grão | S11: 1 | T11: 191 | W11: 191
B12: 9 | C12: 1092 | D12: Fabricação e refino de açúcar | E12: 6 | F12: ISIC 10T12 | I12: 9 | J12: 1919 | K12: Outros produtos da lavoura permanente | L12: 1 | M12: ISIC 01T03 | P12: 9 | Q12: 1919 | R12: Outros produtos da lavoura permanente | S12: 1 | T12: 191 | W12: 191
B13: 10 | C13: 1093 | D13: Outros produtos alimentares | E13: 6 | F13: ISIC 10T12 | I13: 10 | J13: 1921 | K13: Bovinos e outros animais vivos, prods. animal, caça e serv. | L13: 1 | M13: ISIC 01T03 | P13: 10 | Q13: 1921 | R13: Bovinos e outros animais vivos, prods. animal, caça e serv. | S13: 2 | T13: 192 | U13: Pecuária, inclusive o apoio à pecuária | W13: 192 | X13: Pecuária, inclusive o apoio à pecuária
B14: 11 | C14: 1100 | D14: Fabricação de bebidas | E14: 6 | F14: ISIC 10T12 | I14: 11 | J14: 1922 | K14: Leite de vaca e de outros animais | L14: 1 | M14: ISIC 01T03 | P14: 11 | Q14: 1922 | R14: Leite de vaca e de outros animais | S14: 2 | T14: 192 | W14: 192
B15: 12 | C15: 1200 | D15: Fabricação de produtos do fumo | E15: 6 | F15: ISIC 10T12 | I15: 12 | J15: 1923 | K15: Suínos | L15: 1 | M15: ISIC 01T03 | P15: 12 | Q15: 1923 | R15: Suínos | S15: 2 | T15: 192 | W15: 192
B16: 13 | C16: 1300 | D16: Fabricação de produtos têxteis | E16: 7 | F16: ISIC 13T15 | G16: 13T15: Textiles, wearing apparel, leather and related products | I16: 13 | J16: 1924 | K16: Aves e ovos | L16: 1 | M16: ISIC 01T03 | P16: 13 | Q16: 1924 | R16: Aves e ovos | S16: 2 | T16: 192 | W16: 192
B17: 14 | C17: 1400 | D17: Confecção de artefatos do vestuário e acessórios | E17: 7 | F17: ISIC 13T15 | I17: 14 | J17: 2801 | K17: Produtos da exploração florestal e da silvicultura | L17: 1 | M17: ISIC 01T03 | P17: 14 | Q17: 2801 | R17: Produtos da exploração florestal e da silvicultura | S17: 3 | T17: 280 | U17: Produção florestal; pesca e aquicultura | W17: 280 | X17: Produção florestal; pesca e aquicultura
B18: 15 | C18: 1500 | D18: Fabricação de calçados e de artefatos de couro | E18: 7 | F18: ISIC 13T15 | I18: 15 | J18: 2802 | K18: Pesca e aquicultura (peixe, crustáceos e moluscos) | L18: 1 | M18: ISIC 01T03 | P18: 15 | Q18: 2802 | R18: Pesca e aquicultura (peixe, crustáceos e moluscos) | S18: 3 | T18: 280 | W18: 280
B19: 16 | C19: 1600 | D19: Fabricação de produtos da madeira | E19: 8 | F19: ISIC 16 | G19: 16: Wood and of products of wood and cork (except furniture) | I19: 16 | J19: 5801 | K19: Carvão mineral | L19: 2 | M19: ISIC 05 | N19: 05: Coal mining | P19: 16 | Q19: 5801 | R19: Carvão mineral | S19: 4 | T19: 580 | U19: Extração de carvão mineral e de minerais não metálicos | W19: 580 | X19: Extração de carvão mineral e de minerais não metálicos
B20: 17 | C20: 1700 | D20: Fabricação de celulose, papel e produtos de papel | E20: 9 | F20: ISIC 17T18 | G20: 17T18: Paper products and printing | I20: 17 | J20: 5802 | K20: Minerais não-metálicos | L20: 2 | M20: ISIC 05 | P20: 17 | Q20: 5802 | R20: Minerais não-metálicos | S20: 4 | T20: 580 | W20: 580
B21: 18 | C21: 1800 | D21: Impressão e reprodução de gravações | E21: 9 | F21: ISIC 17T18 | I21: 18 | J21: 6801 | K21: Petróleo, gás natural e serviços de apoio | L21: 3 | M21: ISIC 06 | N21: 06: Oil and gas extraction | P21: 18 | Q21: 6801 | R21: Petróleo, gás natural e serviços de apoio | S21: 5 | T21: 680 | U21: Extração de petróleo e gás, inclusive as atividades de apoio | W21: 680 | X21: Extração de petróleo e gás, inclusive as atividades de apoio
B22: 19 | C22: 1991 | D22: Refino de petróleo e coquerias | E22: 10 | F22: ISIC 19 | G22: 19: Coke and refined petroleum products | I22: 19 | J22: 7911 | K22: Minério de ferro | L22: 4 | M22: ISIC 07T08 | N22: 07T08: Mining and quarrying of non-energy producing products | P22: 19 | Q22: 7911 | R22: Minério de ferro | S22: 6 | T22: 791 | U22: Extração de minério de ferro, inclusive beneficiamentos e a aglomeração | W22: 791 | X22: Extração de minério de ferro, inclusive beneficiamentos e a aglomeração
B23: 20 | C23: 1992 | D23: Fabricação de biocombustíveis | E23: 10 | F23: ISIC 19 | I23: 20 | J23: 7921 | K23: Minerais metálicos não-ferrosos | L23: 5 | M23: ISIC 09 | N23: 09: Mining support service activities | P23: 20 | Q23: 7921 | R23: Minerais metálicos não-ferrosos | S23: 7 | T23: 792 | U23: Extração de minerais metálicos não ferrosos, inclusive beneficiamentos | W23: 792 | X23: Extração de minerais metálicos não ferrosos, inclusive beneficiamentos
B24: 21 | C24: 2091 | D24: Fabricação de químicos orgânicos e inorgânicos, resinas e elastômeros | E24: 11 | F24: ISIC 20 | G24: 20: Chemicals | I24: 21 | J24: 10911 | K24: Carne de bovinos e outros prod. de carne | L24: 6 | M24: ISIC 10T12 | N24: 10T12: Food products, beverages and tobacco | P24: 21 | Q24: 10911 | R24: Carne de bovinos e outros prod. de carne | S24: 8 | T24: 1091 | U24: Abate e produtos de carne, inclusive os produtos do laticínio e da pesca | W24: 1091 | X24: Abate e produtos de carne, inclusive os produtos do laticínio e da pesca
B25: 22 | C25: 2092 | D25: Fabricação de defensivos, desinfestantes, tintas e químicos diversos | E25: 11 | F25: ISIC 20 | I25: 22 | J25: 10912 | K25: Carne de suíno | L25: 6 | M25: ISIC 10T12 | P25: 22 | Q25: 10912 | R25: Carne de suíno | S25: 8 | T25: 1091 | W25: 1091
B26: 23 | C26: 2093 | D26: Fabricação de produtos de limpeza, cosméticos/perfumaria e higiene pessoal | E26: 11 | F26: ISIC 20 | I26: 23 | J26: 10913 | K26: Carne de aves | L26: 6 | M26: ISIC 10T12 | P26: 23 | Q26: 10913 | R26: Carne de aves | S26: 8 | T26: 1091 | W26: 1091
B27: 24 | C27: 2100 | D27: Fabricação de produtos farmoquímicos e farmacêuticos | E27: 12 | F27: ISIC 21 | G27: 21: Pharmaceuticals | I27: 24 | J27: 10914 | K27: Pescado industrializado | L27: 6 | M27: ISIC 10T12 | P27: 24 | Q27: 10914 | R27: Pescado industrializado | S27: 8 | T27: 1091 | W27: 1091
B28: 25 | C28: 2200 | D28: Fabricação de produtos de borracha e de material plástico | E28: 13 | F28: ISIC 22 | G28: 22: Rubber and plastics products | I28: 25 | J28: 10915 | K28: Leite resfriado, esterilizado e pasteurizado | L28: 6 | M28: ISIC 10T12 | P28: 25 | Q28: 10915 | R28: Leite resfriado, esterilizado e pasteurizado | S28: 8 | T28: 1091 | W28: 1091
B29: 26 | C29: 2300 | D29: Fabricação de produtos de minerais não metálicos | E29: x | F29: x | I29: 26 | J29: 10916 | K29: Outros produtos do laticínio | L29: 6 | M29: ISIC 10T12 | P29: 26 | Q29: 10916 | R29: Outros produtos do laticínio | S29: 8 | T29: 1091 | W29: 1091
B30: 26.333 | C30: 2310 | D30: Cimento / Artefatos de cimento, gesso e semelhantes | E30: 14 | F30: ISIC 239 | G30: 239: Cement and other nometallic minerals | I30: 27 | J30: 10921 | K30: Açúcar | L30: 6 | M30: ISIC 10T12 | P30: 27 | Q30: 10921 | R30: Açúcar | S30: 9 | T30: 1092 | U30: Fabricação e refino de açúcar | W30: 1092 | X30: Fabricação e refino de açúcar
B31: 26.666 | C31: 2320 | D31: Vidros, cerâmicos e outros prod. de minerais não-metálicos | E31: 15 | F31: ISIC 231 | G31: 231: Glass | I31: 28 | J31: 10931 | K31: Conservas de frutas, legumes, outros vegetais e sucos de frutas | L31: 6 | M31: ISIC 10T12 | P31: 28 | Q31: 10931 | R31: Conservas de frutas, legumes, outros vegetais e sucos de frutas | S31: 10 | T31: 1093 | U31: Outros produtos alimentares | W31: 1093 | X31: Outros produtos alimentares
B32: 27 | C32: 2491 | D32: Produção de ferro gusa/ferroligas, siderurgia e tubos de aço sem costura | E32: 16 | F32: ISIC 241 | G32: 241: Iron and steel | I32: 29 | J32: 10932 | K32: Óleos e gorduras vegetais e animais | L32: 6 | M32: ISIC 10T12 | P32: 29 | Q32: 10932 | R32: Óleos e gorduras vegetais e animais | S32: 10 | T32: 1093 | W32: 1093
B33: 28 | C33: 2492 | D33: Metalurgia de metais não ferosos e a fundição de metais | E33: 17 | F33: ISIC 242 | G33: 242: Other metals | I33: 30 | J33: 10933 | K33: Café beneficiado | L33: 6 | M33: ISIC 10T12 | P33: 30 | Q33: 10933 | R33: Café beneficiado | S33: 10 | T33: 1093 | W33: 1093
B34: 29 | C34: 2500 | D34: Fabricação de produtos de metal, exceto máquinas e equipamentos | E34: 17 | F34: ISIC 25 | G34: 25: Fabricated metal products, except machinery and equipment | I34: 31 | J34: 10934 | K34: Arroz beneficiado e produtos derivados do arroz | L34: 6 | M34: ISIC 10T12 | P34: 31 | Q34: 10934 | R34: Arroz beneficiado e produtos derivados do arroz | S34: 10 | T34: 1093 | W34: 1093
B35: 30 | C35: 2600 | D35: Fabricação de equipamentos de informática, produtos eletrônicos e ópticos | E35: 18 | F35: ISIC 26 | G35: 26: Computer, electronic and optical products | I35: 32 | J35: 10935 | K35: Produtos derivados do trigo, mandioca ou milho | L35: 6 | M35: ISIC 10T12 | P35: 32 | Q35: 10935 | R35: Produtos derivados do trigo, mandioca ou milho | S35: 10 | T35: 1093 | W35: 1093
B36: 31 | C36: 2700 | D36: Fabricação de máquinas e equipamentos elétricos | E36: 19 | F36: ISIC 27 | G36: 27: Electrical equipment | I36: 33 | J36: 10936 | K36: Rações balanceadas para animais | L36: 6 | M36: ISIC 10T12 | P36: 33 | Q36: 10936 | R36: Rações balanceadas para animais | S36: 10 | T36: 1093 | W36: 1093
B37: 32 | C37: 2800 | D37: Fabricação de máquinas e equipamentos mecânicos | E37: 20 | F37: ISIC 28 | G37: 28: Machinery and equipment n.e.c. | I37: 34 | J37: 10937 | K37: Outros produtos alimentares | L37: 6 | M37: ISIC 10T12 | P37: 34 | Q37: 10937 | R37: Outros produtos alimentares | S37: 10 | T37: 1093 | W37: 1093
B38: 33 | C38: 2991 | D38: Fabricação de automóveis, caminhões e ônibus, exceto peças | E38: 21 | F38: ISIC 29 | G38: 29: Motor vehicles, trailers and semi-trailers | I38: 35 | J38: 11001 | K38: Bebidas | L38: 6 | M38: ISIC 10T12 | P38: 35 | Q38: 11001 | R38: Bebidas | S38: 11 | T38: 1100 | U38: Fabricação de bebidas | W38: 1100 | X38: Fabricação de bebidas
B39: 34 | C39: 2992 | D39: Fabricação de peças e acessórios para veículos automotores | E39: 21 | F39: ISIC 29 | I39: 36 | J39: 12001 | K39: Produtos do fumo | L39: 6 | M39: ISIC 10T12 | P39: 36 | Q39: 12001 | R39: Produtos do fumo | S39: 12 | T39: 1200 | U39: Fabricação de produtos do fumo | W39: 1200 | X39: Fabricação de produtos do fumo
B40: 35 | C40: 3000 | D40: Fabricação de outros equipamentos de transporte, exceto veículos automotores | E40: 22 | F40: ISIC 30 | G40: 30: Other transport equipment | I40: 37 | J40: 13001 | K40: Fios e fibras têxteis beneficiadas | L40: 7 | M40: ISIC 13T15 | N40: 13T15: Textiles, wearing apparel, leather and related products | P40: 37 | Q40: 13001 | R40: Fios e fibras têxteis beneficiadas | S40: 13 | T40: 1300 | U40: Fabricação de produtos têxteis | W40: 1300 | X40: Fabricação de produtos têxteis
B41: 36 | C41: 3180 | D41: Fabricação de móveis e de produtos de indústrias diversas | E41: 22 | F41: ISIC 30 | I41: 38 | J41: 13002 | K41: Tecidos | L41: 7 | M41: ISIC 13T15 | P41: 38 | Q41: 13002 | R41: Tecidos | S41: 13 | T41: 1300 | W41: 1300
B42: 37 | C42: 3300 | D42: Manutenção, reparação e instalação de máquinas e equipamentos | E42: 24 | F42: ISIC 31T33 | G42: 31T33: Other manufacturing; repair and installation of machinery and equipment | I42: 39 | J42: 13003 | K42: Art. têxteis de uso doméstico e outros têxteis | L42: 7 | M42: ISIC 13T15 | P42: 39 | Q42: 13003 | R42: Art. têxteis de uso doméstico e outros têxteis | S42: 13 | T42: 1300 | W42: 1300
B43: 38 | C43: 3500 | D43: Energia elétrica, gás natural e outras utilidades | E43: x | F43: x | I43: 40 | J43: 14001 | K43: Artigos do vestuário e acessórios | L43: 7 | M43: ISIC 13T15 | P43: 40 | Q43: 14001 | R43: Artigos do vestuário e acessórios | S43: 14 | T43: 1400 | U43: Confecção de artefatos do vestuário e acessórios | W43: 1400 | X43: Confecção de artefatos do vestuário e acessórios
B44: 38.33 | C44: 3510 | D44: Transmissão de energia elétrica | E44: 25 | F44: ISIC 351 | G44: 351: Electricity generation and distribution | I44: 41 | J44: 15001 | K44: Calçados e artefatos de couro | L44: 7 | M44: ISIC 13T15 | P44: 41 | Q44: 15001 | R44: Calçados e artefatos de couro | S44: 15 | T44: 1500 | U44: Fabricação de calçados e de artefatos de couro | W44: 1500 | X44: Fabricação de calçados e de artefatos de couro
B45: 38.66 | C45: 3520 | D45: Produção de gás; processamento de gás natural; distribuição de combustíveis gasosos por redes urbanas | E45: 26 | F45: ISIC 352T353 | G45: 352T353: Energy pipelines and gas processing | I45: 42 | J45: 16001 | K45: Produtos de madeira, exclusive móveis | L45: 8 | M45: ISIC 16 | N45: 16: Wood and of products of wood and cork (except furniture) | P45: 42 | Q45: 16001 | R45: Produtos de madeira, exclusive móveis | S45: 16 | T45: 1600 | U45: Fabricação de produtos da madeira | W45: 1600 | X45: Fabricação de produtos da madeira
B46: 39 | C46: 3680 | D46: Água, esgoto e gestão de resíduos | E46: 27 | F46: ISIC 36T39 | G46: 36T39: Water and waste | I46: 43 | J46: 17001 | K46: Celulose | L46: 8 | M46: ISIC 16 | P46: 43 | Q46: 17001 | R46: Celulose | S46: 17 | T46: 1700 | U46: Fabricação de celulose, papel e produtos de papel | W46: 1700 | X46: Fabricação de celulose, papel e produtos de papel
B47: 40 | C47: 4180 | D47: Construção | E47: 28 | F47: ISIC 41T43 | G47: 41T43: Construction | I47: 44 | J47: 17002 | K47: Papel, papelão, embalagens e artefatos de papel | L47: 9 | M47: ISIC 17T18 | N47: 17T18: Paper products and printing | P47: 44 | Q47: 17002 | R47: Papel, papelão, embalagens e artefatos de papel | S47: 17 | T47: 1700 | W47: 1700
B48: 41 | C48: 4580 | D48: Comércio por atacado e varejo | E48: 29 | F48: ISIC 45T47 | G48: 45T47: Wholesale and retail trade; repair of motor vehicles | I48: 45 | J48: 18001 | K48: Serviços de impressão e reprodução | L48: 9 | M48: ISIC 17T18 | P48: 45 | Q48: 18001 | R48: Serviços de impressão e reprodução | S48: 18 | T48: 1800 | U48: Impressão e reprodução de gravações | W48: 1800 | X48: Impressão e reprodução de gravações
B49: 42 | C49: 4900 | D49: Transporte terrestre | E49: 30 | F49: ISIC 49T53 | G49: 49T53: Transportation and storage | I49: 46 | J49: 19911 | K49: Combustíveis para aviação | L49: 10 | M49: ISIC 19 | N49: 19: Coke and refined petroleum products | P49: 46 | Q49: 19911 | R49: Combustíveis para aviação | S49: 19 | T49: 1991 | U49: Refino de petróleo e coquerias | W49: 1991 | X49: Refino de petróleo e coquerias
B50: 43 | C50: 5000 | D50: Transporte aquaviário | E50: 30 | F50: ISIC 49T53 | I50: 47 | J50: 19912 | K50: Gasoálcool | L50: 10 | M50: ISIC 19 | P50: 47 | Q50: 19912 | R50: Gasoálcool | S50: 19 | T50: 1991 | W50: 1991
B51: 44 | C51: 5100 | D51: Transporte aéreo | E51: 30 | F51: ISIC 49T53 | I51: 48 | J51: 19913 | K51: Naftas para petroquímica | L51: 10 | M51: ISIC 19 | P51: 48 | Q51: 19913 | R51: Naftas para petroquímica | S51: 19 | T51: 1991 | W51: 1991
B52: 45 | C52: 5280 | D52: Armazenamento, atividades auxiliares dos transportes e correio | E52: 30 | F52: ISIC 49T53 | I52: 49 | J52: 19914 | K52: Óleo combustível | L52: 10 | M52: ISIC 19 | P52: 49 | Q52: 19914 | R52: Óleo combustível | S52: 19 | T52: 1991 | W52: 1991
B53: 46 | C53: 5500 | D53: Alojamento | E53: 31 | F53: ISIC 55T56 | G53: 55T56: Accomodation and food services | I53: 50 | J53: 19915 | K53: Diesel - biodiesel | L53: 10 | M53: ISIC 19 | P53: 50 | Q53: 19915 | R53: Diesel - biodiesel | S53: 19 | T53: 1991 | W53: 1991
B54: 47 | C54: 5600 | D54: Alimentação | E54: 31 | F54: ISIC 55T56 | I54: 51 | J54: 19916 | K54: Outros produtos do refino do petróleo | L54: 10 | M54: ISIC 19 | P54: 51 | Q54: 19916 | R54: Outros produtos do refino do petróleo | S54: 19 | T54: 1991 | W54: 1991
B55: 48 | C55: 5800 | D55: Edição e edição integrada à impressão | E55: 32 | F55: ISIC 58T60 | G55: 58T60: Publishing, audiovisual and broadcasting activities | I55: 52 | J55: 19921 | K55: Etanol e outros biocombustíveis | L55: 10 | M55: ISIC 19 | N55: ISIC does not have a group for biofuels | P55: 52 | Q55: 19921 | R55: Etanol e outros biocombustíveis | S55: 20 | T55: 1992 | U55: Fabricação de biocombustíveis | W55: 1992 | X55: Fabricação de biocombustíveis
B56: 49 | C56: 5980 | D56: Atividades de televisão, rádio, cinema e gravação/edição de som e imagem | E56: 32 | F56: ISIC 58T60 | I56: 53 | J56: 20911 | K56: Produtos químicos inorgânicos | L56: 11 | M56: ISIC 20 | N56: 20: Chemicals | P56: 53 | Q56: 20911 | R56: Produtos químicos inorgânicos | S56: 21 | T56: 2091 | U56: Fabricação de químicos orgânicos e inorgânicos, resinas e elastômeros | W56: 2091 | X56: Fabricação de químicos orgânicos e inorgânicos, resinas e elastômeros
B57: 50 | C57: 6100 | D57: Telecomunicações | E57: 33 | F57: ISIC 61 | G57: 61: Telecommunications | I57: 54 | J57: 20912 | K57: Adubos e fertilizantes | L57: 11 | M57: ISIC 20 | P57: 54 | Q57: 20912 | R57: Adubos e fertilizantes | S57: 21 | T57: 2091 | W57: 2091
B58: 51 | C58: 6280 | D58: Desenvolvimento de sistemas e outros serviços de informação | E58: 34 | F58: ISIC 62T63 | G58: 62T63: IT and other information services | I58: 55 | J58: 20913 | K58: Produtos químicos orgânicos | L58: 11 | M58: ISIC 20 | P58: 55 | Q58: 20913 | R58: Produtos químicos orgânicos | S58: 21 | T58: 2091 | W58: 2091
B59: 52 | C59: 6480 | D59: Intermediação financeira, seguros e previdência complementar | E59: 35 | F59: ISIC 64T66 | G59: 64T66: Financial and insurance activities | I59: 56 | J59: 20914 | K59: Resinas,elastômeros e fibras artif. e sintéticas | L59: 11 | M59: ISIC 20 | P59: 56 | Q59: 20914 | R59: Resinas,elastômeros e fibras artif. e sintéticas | S59: 21 | T59: 2091 | W59: 2091
B60: 53 | C60: 6800 | D60: Atividades imobiliárias | E60: 36 | F60: ISIC 68 | G60: 68: Real estate activities | I60: 57 | J60: 20921 | K60: Defensivos agrícolas e desinfestantes domissanitários | L60: 11 | M60: ISIC 20 | P60: 57 | Q60: 20921 | R60: Defensivos agrícolas e desinfestantes domissanitários | S60: 22 | T60: 2092 | U60: Fabricação de defensivos, desinfestantes, tintas e químicos diversos | W60: 2092 | X60: Fabricação de defensivos, desinfestantes, tintas e químicos diversos
B61: 54 | C61: 6980 | D61: Atividades jurídicas, contábeis, consultoria e sedes de empresas | E61: 37 | F61: ISIC 69T82 | G61: 69T82: Other business sector services | I61: 58 | J61: 20922 | K61: Produtos químicos diversos | L61: 11 | M61: ISIC 20 | P61: 58 | Q61: 20922 | R61: Produtos químicos diversos | S61: 22 | T61: 2092 | W61: 2092
B62: 55 | C62: 7180 | D62: Serviços de arquitetura, engenharia, testes/análises técnicas e P & D | E62: 37 | F62: ISIC 69T82 | I62: 59 | J62: 20923 | K62: Tintas, vernizes, esmaltes e lacas | L62: 11 | M62: ISIC 20 | P62: 59 | Q62: 20923 | R62: Tintas, vernizes, esmaltes e lacas | S62: 22 | T62: 2092 | W62: 2092
B63: 56 | C63: 7380 | D63: Outras atividades profissionais, científicas e técnicas | E63: 37 | F63: ISIC 69T82 | I63: 60 | J63: 20931 | K63: Perfumaria, sabões e artigos de limpeza | L63: 11 | M63: ISIC 20 | P63: 60 | Q63: 20931 | R63: Perfumaria, sabões e artigos de limpeza | S63: 23 | T63: 2093 | U63: Fabricação de produtos de limpeza, cosméticos/perfumaria e higiene pessoal | W63: 2093 | X63: Fabricação de produtos de limpeza, cosméticos/perfumaria e higiene pessoal
B64: 57 | C64: 7700 | D64: Aluguéis não imobiliários e gestão de ativos de propriedade intelectual | E64: 37 | F64: ISIC 69T82 | I64: 61 | J64: 21001 | K64: Produtos farmacêuticos | L64: 12 | M64: ISIC 21 | N64: 21: Pharmaceuticals | P64: 61 | Q64: 21001 | R64: Produtos farmacêuticos | S64: 24 | T64: 2100 | U64: Fabricação de produtos farmoquímicos e farmacêuticos | W64: 2100 | X64: Fabricação de produtos farmoquímicos e farmacêuticos
B65: 58 | C65: 7880 | D65: Outras atividades administrativas e serviços complementares | E65: 37 | F65: ISIC 69T82 | I65: 62 | J65: 22001 | K65: Artigos de borracha | L65: 13 | M65: ISIC 22 | N65: 22: Rubber and plastics products | P65: 62 | Q65: 22001 | R65: Artigos de borracha | S65: 25 | T65: 2200 | U65: Fabricação de produtos de borracha e de material plástico | W65: 2200 | X65: Fabricação de produtos de borracha e de material plástico
B66: 59 | C66: 8000 | D66: Atividades de vigilância, segurança e investigação | E66: 37 | F66: ISIC 69T82 | I66: 63 | J66: 22002 | K66: Artigos de plástico | L66: 13 | M66: ISIC 22 | P66: 63 | Q66: 22002 | R66: Artigos de plástico | S66: 25 | T66: 2200 | W66: 2200
B67: 60 | C67: 8400 | D67: Administração pública, defesa e seguridade social | E67: 38 | F67: ISIC 84 | G67: 84: Public administration and defence; compulsory social security | I67: 64 | J67: 23001 | K67: Cimento | L67: 15 | M67: ISIC 239 | N67: 239: Cement and other nometallic minerals | P67: 64 | Q67: 23001 | R67: Cimento | S67: 26 | T67: 2300 | U67: Fabricação de produtos de minerais não metálicos | W67: 2310 | X67: Cimento / Artefatos de cimento, gesso e semelhantes
B68: 61 | C68: 8591 | D68: Educação pública | E68: 39 | F68: ISIC 85 | G68: 85: Education | I68: 65 | J68: 23002 | K68: Artefatos de cimento, gesso e semelhantes | L68: 15 | M68: ISIC 239 | P68: 65 | Q68: 23002 | R68: Artefatos de cimento, gesso e semelhantes | S68: 26.333 | T68: 2310 | U68: Cimento / Artefatos de cimento, gesso e semelhantes | W68: 2320 | X68: Vidros, cerâmicos e outros prod. de minerais não-metálicos
B69: 62 | C69: 8592 | D69: Educação privada | E69: 39 | F69: ISIC 85 | I69: 66 | J69: 23003 | K69: Vidros, cerâmicos e outros prod. de minerais não-metálicos | L69: 14 | M69: ISIC 231 | N69: 231: Glass | P69: 66 | Q69: 23003 | R69: Vidros, cerâmicos e outros prod. de minerais não-metálicos | S69: 26.666 | T69: 2320 | U69: Vidros, cerâmicos e outros prod. de minerais não-metálicos | W69: 2491 | X69: Produção de ferro gusa/ferroligas, siderurgia e tubos de aço sem costura
B70: 63 | C70: 8691 | D70: Saúde pública | E70: 40 | F70: ISIC 86T88 | G70: 86T88: Human health and social work | I70: 67 | J70: 24911 | K70: Ferro-gusa e ferroligas | L70: 16 | M70: ISIC 241 | N70: 241: Iron and steel | P70: 67 | Q70: 24911 | R70: Ferro-gusa e ferroligas | S70: 27 | T70: 2491 | U70: Produção de ferro gusa/ferroligas, siderurgia e tubos de aço sem costura | W70: 2491
B71: 64 | C71: 8692 | D71: Saúde privada | E71: 40 | F71: ISIC 86T88 | I71: 68 | J71: 24912 | K71: Semi-acabacados, laminados planos, longos e tubos de aço | L71: 16 | M71: ISIC 241 | P71: 68 | Q71: 24912 | R71: Semi-acabacados, laminados planos, longos e tubos de aço | S71: 27 | T71: 2491 | W71: 2491
B72: 65 | C72: 9080 | D72: Atividades artísticas, criativas e de espetáculos | E72: 41 | F72: ISIC 90T96 | G72: 90T96: Arts, entertainment, recreation and other service activities | I72: 69 | J72: 24921 | K72: Produtos da metalurgia de metais não-ferrosos | L72: 17 | M72: ISIC 242 | N72: 242: Other metals | P72: 69 | Q72: 24921 | R72: Produtos da metalurgia de metais não-ferrosos | S72: 27 | T72: 2491 | W72: 2492 | X72: Metalurgia de metais não ferosos e a fundição de metais
B73: 66 | C73: 9480 | D73: Organizações associativas e outros serviços pessoais | E73: 41 | F73: ISIC 90T96 | I73: 70 | J73: 24922 | K73: Peças fundidas de aço e de metais não ferrosos | L73: 17 | M73: ISIC 242 | N73: 242: Other metals | P73: 70 | Q73: 24922 | R73: Peças fundidas de aço e de metais não ferrosos | S73: 28 | T73: 2492 | U73: Metalurgia de metais não ferosos e a fundição de metais | W73: 2492 | X73: Fabricação de produtos de metal, exceto máquinas e equipamentos
B74: 67 | C74: 9700 | D74: Serviços domésticos | E74: 42 | F74: ISIC 97T98 | G74: 97T98: Private households with employed persons | I74: 71 | J74: 25001 | K74: Produtos de metal, excl. máquinas e equipamentos | L74: 18 | M74: ISIC 25 | N74: 25: Fabricated metal products, except machinery and equipment | P74: 71 | Q74: 25001 | R74: Produtos de metal, excl. máquinas e equipamentos | S74: 29 | T74: 2500 | U74: Fabricação de produtos de metal, exceto máquinas e equipamentos | W74: 2600 | X74: Fabricação de equipamentos de informática, produtos eletrônicos e ópticos
I75: 72 | J75: 26001 | K75: Componentes eletrônicos | L75: 19 | M75: ISIC 26 | N75: 26: Computer, electronic and optical products | P75: 72 | Q75: 26001 | R75: Componentes eletrônicos | S75: 30 | T75: 2600 | U75: Fabricação de equipamentos de informática, produtos eletrônicos e ópticos | W75: 2600
I76: 73 | J76: 26002 | K76: Máquinas para escritório e equip. de informática | L76: 19 | M76: ISIC 26 | P76: 73 | Q76: 26002 | R76: Máquinas para escritório e equip. de informática | S76: 30 | T76: 2600 | W76: 2600
I77: 74 | J77: 26003 | K77: Material eletrônico e equip. de comunicações | L77: 19 | M77: ISIC 26 | P77: 74 | Q77: 26003 | R77: Material eletrônico e equip. de comunicações | S77: 30 | T77: 2600 | W77: 2600
I78: 75 | J78: 26004 | K78: Equip. de medida, teste e controle, ópticos e eletromédicos | L78: 19 | M78: ISIC 26 | P78: 75 | Q78: 26004 | R78: Equip. de medida, teste e controle, ópticos e eletromédicos | S78: 30 | T78: 2600 | W78: 2700 | X78: Fabricação de máquinas e equipamentos elétricos
I79: 76 | J79: 27001 | K79: Máquinas, aparelhos e materiais elétricos | L79: 20 | M79: ISIC 27 | N79: 27: Electrical equipment | P79: 76 | Q79: 27001 | R79: Máquinas, aparelhos e materiais elétricos | S79: 31 | T79: 2700 | U79: Fabricação de máquinas e equipamentos elétricos | W79: 2700
I80: 77 | J80: 27002 | K80: Eletrodomésticos | L80: 20 | M80: ISIC 27 | P80: 77 | Q80: 27002 | R80: Eletrodomésticos | S80: 31 | T80: 2700 | W80: 2800 | X80: Fabricação de máquinas e equipamentos mecânicos
I81: 78 | J81: 28001 | K81: Tratores e outras máquinas agrícolas | L81: 21 | M81: ISIC 28 | N81: 28: Machinery and equipment n.e.c. | P81: 78 | Q81: 28001 | R81: Tratores e outras máquinas agrícolas | S81: 32 | T81: 2800 | U81: Fabricação de máquinas e equipamentos mecânicos | W81: 2800
I82: 79 | J82: 28002 | K82: Máquinas para a extração mineral e a construção | L82: 21 | M82: ISIC 28 | P82: 79 | Q82: 28002 | R82: Máquinas para a extração mineral e a construção | S82: 32 | T82: 2800 | W82: 2800
I83: 80 | J83: 28003 | K83: Outras máquinas e equipamentos mecânicos | L83: 21 | M83: ISIC 28 | P83: 80 | Q83: 28003 | R83: Outras máquinas e equipamentos mecânicos | S83: 32 | T83: 2800 | W83: 2991 | X83: Fabricação de automóveis, caminhões e ônibus, exceto peças
I84: 81 | J84: 29911 | K84: Automóveis, camionetas e utilitários | L84: 22 | M84: ISIC 29 | N84: 29: Motor vehicles, trailers and semi-trailers | P84: 81 | Q84: 29911 | R84: Automóveis, camionetas e utilitários | S84: 33 | T84: 2991 | U84: Fabricação de automóveis, caminhões e ônibus, exceto peças | W84: 2991
I85: 82 | J85: 29912 | K85: Caminhões e ônibus, incl. cabines, carrocerias e reboques | L85: 22 | M85: ISIC 29 | P85: 82 | Q85: 29912 | R85: Caminhões e ônibus, incl. cabines, carrocerias e reboques | S85: 33 | T85: 2991 | W85: 2992 | X85: Fabricação de peças e acessórios para veículos automotores
I86: 83 | J86: 29921 | K86: Peças e acessórios para veículos automotores | L86: 22 | M86: ISIC 29 | P86: 83 | Q86: 29921 | R86: Peças e acessórios para veículos automotores | S86: 34 | T86: 2992 | U86: Fabricação de peças e acessórios para veículos automotores | W86: 3000 | X86: Fabricação de outros equipamentos de transporte, exceto veículos automotores
I87: 84 | J87: 30001 | K87: Aeronaves, embarcações e outros equipamentos de transporte | L87: 23 | M87: ISIC 30 | N87: 30: Other transport equipment | P87: 84 | Q87: 30001 | R87: Aeronaves, embarcações e outros equipamentos de transporte | S87: 35 | T87: 3000 | U87: Fabricação de outros equipamentos de transporte, exceto veículos automotores | W87: 3180 | X87: Fabricação de móveis e de produtos de indústrias diversas
I88: 85 | J88: 31801 | K88: Móveis | L88: 23 | M88: ISIC 30 | P88: 85 | Q88: 31801 | R88: Móveis | S88: 36 | T88: 3180 | U88: Fabricação de móveis e de produtos de indústrias diversas | W88: 3180
I89: 86 | J89: 31802 | K89: Produtos de industrias diversas | L89: 23 | M89: ISIC 30 | P89: 86 | Q89: 31802 | R89: Produtos de industrias diversas | S89: 36 | T89: 3180 | W89: 3300 | X89: Manutenção, reparação e instalação de máquinas e equipamentos
I90: 87 | J90: 33001 | K90: Manutenção, reparação e instalação de máquinas e equipamentos | L90: 24 | M90: ISIC 31T33 | N90: 31T33: Other manufacturing; repair and installation of machinery and equipment | P90: 87 | Q90: 33001 | R90: Manutenção, reparação e instalação de máquinas e equipamentos | S90: 37 | T90: 3300 | U90: Manutenção, reparação e instalação de máquinas e equipamentos | W90: 3510 | X90: Transmissão de energia elétrica
I91: 88 | J91: 35001 | K91: Eletricidade, gás e outras utilidades | L91: - | M91: - | P91: 88 | Q91: 35001 | R91: Eletricidade, gás e outras utilidades | S91: 38 | T91: 3500 | U91: Energia elétrica, gás natural e outras utilidades | W91: 3520 | X91: Produção de gás; processamento de gás natural; distribuição de combustíveis gasosos por redes urbanas
I92: 88.333333 | J92: 35101 | K92: Transmissão de energia elétrica | L92: 25 | M92: ISIC 351 | N92: 351: Electricity generation and distribution | P92: 88.333333 | Q92: 35101 | R92: Transmissão de energia elétrica | S92: 38.33 | T92: 3510 | U92: Transmissão de energia elétrica | W92: 3680 | X92: Água, esgoto e gestão de resíduos
I93: 88.66666 | J93: 35201 | K93: Produção de gás; processamento de gás natural; distribuição de combustíveis gasosos por redes urbanas | L93: 26 | M93: ISIC 352T353 | N93: 352T353: Energy pipelines and gas processing | P93: 88.66666 | Q93: 35201 | R93: Produção de gás; processamento de gás natural; distribuição de combustíveis gasosos por redes urbanas | S93: 38.66 | T93: 3520 | U93: Produção de gás; processamento de gás natural; distribuição de combustíveis gasosos por redes urbanas | W93: 4180 | X93: Construção
I94: 89 | J94: 36801 | K94: Água, esgoto, reciclagem e gestão de resíduos | L94: 27 | M94: ISIC 36T39 | N94: 36T39: Water and waste | P94: 89 | Q94: 36801 | R94: Água, esgoto, reciclagem e gestão de resíduos | S94: 39 | T94: 3680 | U94: Água, esgoto e gestão de resíduos | W94: 4180
I95: 90 | J95: 41801 | K95: Edificações | L95: 28 | M95: ISIC 41T43 | N95: 41T43: Construction | P95: 90 | Q95: 41801 | R95: Edificações | S95: 40 | T95: 4180 | U95: Construção | W95: 4180
I96: 91 | J96: 41802 | K96: Obras de infra-estrutura | L96: 28 | M96: ISIC 41T43 | P96: 91 | Q96: 41802 | R96: Obras de infra-estrutura | S96: 40 | T96: 4180 | W96: 4580 | X96: Comércio por atacado e varejo
I97: 92 | J97: 41803 | K97: Serviços especializados para construção | L97: 28 | M97: ISIC 41T43 | P97: 92 | Q97: 41803 | R97: Serviços especializados para construção | S97: 40 | T97: 4180 | W97: 4580
I98: 93 | J98: 45001 | K98: Comércio e reparação de veículos | L98: 29 | M98: ISIC 45T47 | N98: 45T47: Wholesale and retail trade; repair of motor vehicles | P98: 93 | Q98: 45001 | R98: Comércio e reparação de veículos | S98: 41 | T98: 4580 | U98: Comércio por atacado e varejo | W98: 4900 | X98: Transporte terrestre
I99: 94 | J99: 46801 | K99: Comércio por atacado e a varejo, exceto veículos automotores | L99: 29 | M99: ISIC 45T47 | P99: 94 | Q99: 46801 | R99: Comércio por atacado e a varejo, exceto veículos automotores | S99: 41 | T99: 4580 | W99: 4900
I100: 95 | J100: 49001 | K100: Transporte terrestre de carga | L100: 29 | M100: ISIC 45T47 | P100: 95 | Q100: 49001 | R100: Transporte terrestre de carga | S100: 42 | T100: 4900 | U100: Transporte terrestre | W100: 5000 | X100: Transporte aquaviário
I101: 96 | J101: 49002 | K101: Transporte terrestre de passageiros | L101: 30 | M101: ISIC 49T53 | N101: 49T53: Transportation and storage | P101: 96 | Q101: 49002 | R101: Transporte terrestre de passageiros | S101: 42 | T101: 4900 | W101: 5100 | X101: Transporte aéreo
I102: 97 | J102: 50001 | K102: Transporte aquaviário | L102: 30 | M102: ISIC 49T53 | P102: 97 | Q102: 50001 | R102: Transporte aquaviário | S102: 43 | T102: 5000 | U102: Transporte aquaviário | W102: 5280 | X102: Armazenamento, atividades auxiliares dos transportes e correio
...

Sheet BDCSoCbIC
A1: Unit: dimensionless (%) | B1: ISIC 01T03 | C1: ISIC 05 | D1: ISIC 06 | E1: ISIC 07T08 | F1: ISIC 09 | G1: ISIC 10T12 | H1: ISIC 13T15 | I1: ISIC 16 | J1: ISIC 17T18 | K1: ISIC 19 | L1: ISIC 20 | M1: ISIC 21 | N1: ISIC 22 | O1: ISIC 231 | P1: ISIC 239 | Q1: ISIC 241 | R1: ISIC 242 | S1: ISIC 25 | T1: ISIC 26 | U1: ISIC 27 | V1: ISIC 28 | W1: ISIC 29 | X1: ISIC 30 | Y1: ISIC 31T33 | Z1: ISIC 351 | AA1: ISIC 352T353 | AB1: ISIC 36T39 | AC1: ISIC 41T43 | AD1: ISIC 45T47 | AE1: ISIC 49T53 | AF1: ISIC 55T56 | AG1: ISIC 58T60 | AH1: ISIC 61 | AI1: ISIC 62T63 | AJ1: ISIC 64T66 | AK1: ISIC 68 | AL1: ISIC 69T82 | AM1: ISIC 84 | AN1: ISIC 85 | AO1: ISIC 86T88 | AP1: ISIC 90T96 | AQ1: ISIC 97T98
A2: Percent of Consumption that is Domestic Content | B2: =Calculations!B9 -> 0.97259582 | C2: =Calculations!C9 -> 0.65438173 | D2: =Calculations!D9 -> 0.78309247 | E2: =Calculations!E9 -> 0.84126706 | F2: =Calculations!F9 -> 0.98666419 | G2: =Calculations!G9 -> 0.95944576 | H2: =Calculations!H9 -> 0.86475555 | I2: =Calculations!I9 -> 0.9644732 | ... AQ2: =Calculations!AQ9 -> 1

Sheet BESoP
A1: Unit: dimensionless (%) | B1: ISIC 01T03 | C1: ISIC 05 | D1: ISIC 06 | E1: ISIC 07T08 | F1: ISIC 09 | G1: ISIC 10T12 | H1: ISIC 13T15 | I1: ISIC 16 | J1: ISIC 17T18 | K1: ISIC 19 | L1: ISIC 20 | M1: ISIC 21 | N1: ISIC 22 | O1: ISIC 231 | P1: ISIC 239 | Q1: ISIC 241 | R1: ISIC 242 | S1: ISIC 25 | T1: ISIC 26 | U1: ISIC 27 | V1: ISIC 28 | W1: ISIC 29 | X1: ISIC 30 | Y1: ISIC 31T33 | Z1: ISIC 351 | AA1: ISIC 352T353 | AB1: ISIC 36T39 | AC1: ISIC 41T43 | AD1: ISIC 45T47 | AE1: ISIC 49T53 | AF1: ISIC 55T56 | AG1: ISIC 58T60 | AH1: ISIC 61 | AI1: ISIC 62T63 | AJ1: ISIC 64T66 | AK1: ISIC 68 | AL1: ISIC 69T82 | AM1: ISIC 84 | AN1: ISIC 85 | AO1: ISIC 86T88 | AP1: ISIC 90T96 | AQ1: ISIC 97T98
A2: Export Share of Production | B2: =Calculations!B11 -> 0.23503944 | C2: =Calculations!C11 -> 0.1029558 | D2: =Calculations!D11 -> 0.25904196 | E2: =Calculations!E11 -> 0.60236428 | F2: =Calculations!F11 -> 0.012852353 | G2: =Calculations!G11 -> 0.1562121 | H2: =Calculations!H11 -> 0.080998436 | I2: =Calculations!I11 -> 0.2422683 | ... AQ2: =Calculations!AQ11 -> 0
