Workbook
Name dollars_2020_2012: [1]About!$A$104
Name dollars_2021_2012: [1]About!$A$103
Name lignite_multiplier: '[1]Hard Coal and Lig Multipliers'!$N$15
Name nonlignite_multiplier: '[1]Hard Coal and Lig Multipliers'!$N$16
Name nonlignite_multiplier: '[1]Hard Coal and Lig Multipliers'!$N$16
Name nonlignite_multiplier: '[1]Hard Coal and Lig Multipliers'!$N$16
Name nonlignite_multiplier: '[2]Hard Coal and Lig Multipliers'!$N$15

Sheet About
A1: IMFPbFT International Market Fuel Price by Fuel Type
A3: Source: | B3: see fuels/BFPaT and EPS outputs referenced in BAU Fuel Use by Sector tab
A4: Natural Gas Price Source:
B5: AEO Table 60 | C5: https://www.eia.gov/outlooks/aeo/data/browser/#/?id=76-AEO2021&region=0-0&cases=highogs&start=2019&end=2050&f=A&sourcekey=0
B6: AEO Table 13 | C6: https://www.eia.gov/outlooks/aeo/data/browser/#/?id=13-AEO2021&cases=ref2021&sourcekey=0
B7: EIA Natural Gas Prices | C7: https://www.eia.gov/dnav/ng/ng_pri_sum_dcu_nus_m.htm
B8: Henry Hub Prices | C8: https://www.eia.gov/dnav/ng/hist/rngwhhdA.htm
A9: Notes
A10: The prices in this variable should include export taxes, if any. In other words, they should be
A11: the prices paid on the global market. For more details on export taxes, see variable fuels/ETRbF.
A13: Electricity exports are handled separately (in the power sector), not in this variable.
A15: Nuclear here refers to nuclear fuel, i.e. uranium oxide, not electricity from nuclear plants.
A17: We estimate this value based on the prices seen within the United States.
A18: For fuels that vary by sector, we take a weighted average based on the first year consumption in the model.
A20: Natural gas prices
A21: Estimated by creating an average multiplier for pipeline and lng gas compared to henry hub prices.
A22: Use futures prices forecast of henry hub prices multiplied by pipeline and lng multiplier to get forecasted natural gas export prices for 2022-2025.
A23: Linearly interpolated between 2025 and 2030.
A24: Use AEO forecast of henry hub prices multiplied by pipeline and lng multiplier to get forecasted natural gas export prices for 2030-2050.
A25: Created weighted total natural gas export price based on forecasted export volumes of pipeline and lng (AEO 60).
A27: mmbtu per thousand cubic feet | B27: 1.037
A28: 2020 to 2012 $ | B28: 0.887
A29: 2021 to 2012 $ | B29: =0.847 -> 0.847

Sheet AEO21 Table13
A1: Table 13. Natural Gas Supply, Disposition, and Prices
A2: https://www.eia.gov/outlooks/aeo/data/browser/#/?id=13-AEO2021&cases=ref2021&sourcekey=0
A3: Fri Mar 19 2021 13:32:00 GMT-0700 (Pacific Daylight Time)
A4: Source: U.S. Energy Information Administration
B5: full name | C5: api key | D5: units | E5: 2019 | F5: 2020 | G5: 2021 | H5: 2022 | I5: 2023 | J5: 2024 | K5: 2025 | L5: 2026 | M5: 2027 | N5: 2028 | O5: 2029 | P5: 2030 | Q5: 2031 | R5: 2032 | S5: 2033 | T5: 2034 | U5: 2035 | V5: 2036 | W5: 2037 | X5: 2038 | Y5: 2039 | Z5: 2040 | AA5: 2041 | AB5: 2042 | AC5: 2043 | AD5: 2044 | AE5: 2045 | AF5: 2046 | AG5: 2047 | AH5: 2048 | AI5: 2049 | AJ5: 2050 | AK5: Growth (2020-2050)
A6: Production | C6: 13-AEO2021.2.
A7: Dry Gas Production | B7: Natural Gas: Production: Dry Gas Production: Reference case | C7: 13-AEO2021.3.ref2021-d113020a | D7: Tcf | F7: 33.890736 | G7: 32.309692 | H7: 32.780651 | I7: 34.02206 | J7: 34.964745 | K7: 36.261745 | L7: 36.88525 | M7: 37.021378 | N7: 37.19635 | O7: 37.54443 | P7: 37.881168 | Q7: 38.134373 | R7: 38.298534 | S7: 38.468994 | T7: 38.611877 | U7: 38.613323 | V7: 38.774208 | W7: 38.983143 | X7: 39.289341 | Y7: 39.585915 | Z7: 39.916763 | AA7: 40.111534 | AB7: 40.487705 | AC7: 40.920616 | AD7: 41.286839 | AE7: 41.538971 | AF7: 41.804253 | AG7: 42.065693 | AH7: 42.392258 | AI7: 42.658817 | AJ7: 42.992821 | AK7: 0.008
A8: Supplemental Natural Gas | B8: Natural Gas: Production: Supplemental Natural Gas: Reference case | C8: 13-AEO2021.4.ref2021-d113020a | D8: Tcf | F8: 0.06535 | G8: 0.06094 | H8: 0.061172 | I8: 0.061404 | J8: 0.061636 | K8: 0.061867 | L8: 0.062099 | M8: 0.062099 | N8: 0.062099 | O8: 0.062099 | P8: 0.062099 | Q8: 0.062099 | R8: 0.062099 | S8: 0.062099 | T8: 0.062099 | U8: 0.062099 | V8: 0.062099 | W8: 0.062099 | X8: 0.062099 | Y8: 0.062099 | Z8: 0.062099 | AA8: 0.062099 | AB8: 0.062099 | AC8: 0.062099 | AD8: 0.062099 | AE8: 0.062099 | AF8: 0.062099 | AG8: 0.062099 | AH8: 0.062099 | AI8: 0.062099 | AJ8: 0.062099 | AK8: -0.002
A9: Net Imports | B9: Natural Gas: Net Imports: Reference case | C9: 13-AEO2021.6.ref2021-d113020a | D9: Tcf | F9: -2.670551 | G9: -3.649866 | H9: -3.840418 | I9: -4.24364 | J9: -4.846223 | K9: -5.320686 | L9: -5.550917 | M9: -5.669797 | N9: -5.930669 | O9: -6.238175 | P9: -6.688156 | Q9: -6.812176 | R9: -6.892396 | S9: -7.006797 | T9: -7.029311 | U9: -7.027888 | V9: -7.064267 | W9: -7.053469 | X9: -7.046336 | Y9: -7.060203 | Z9: -7.092656 | AA9: -7.083726 | AB9: -7.127188 | AC9: -7.165261 | AD9: -7.237316 | AE9: -7.247638 | AF9: -7.295463 | AG9: -7.328695 | AH9: -7.393071 | AI9: -7.388108 | AJ9: -7.403225 | AK9: 0.035
A10: Pipeline | B10: Natural Gas: Net Imports: Pipeline: Reference case | C10: 13-AEO2021.7.ref2021-d113020a | D10: Tcf | F10: -0.421029 | G10: -0.546257 | H10: -0.791407 | I10: -1.155499 | J10: -1.383807 | K10: -1.301577 | L10: -1.202922 | M10: -1.321801 | N10: -1.470551 | O10: -1.590179 | P10: -1.84016 | Q10: -1.864181 | R10: -1.932277 | S10: -2.058801 | T10: -2.081315 | U10: -2.079893 | V10: -2.104148 | W10: -2.105474 | X10: -2.09834 | Y10: -2.112207 | Z10: -2.132536 | AA10: -2.13573 | AB10: -2.179192 | AC10: -2.217265 | AD10: -2.277197 | AE10: -2.299642 | AF10: -2.347467 | AG10: -2.380699 | AH10: -2.432952 | AI10: -2.440112 | AJ10: -2.455229 | AK10: 0.061
A11: Liquefied Natural Gas | B11: Natural Gas: Net Imports: Liquefied Natural Gas: Reference case | C11: 13-AEO2021.8.ref2021-d113020a | D11: Tcf | F11: -2.249521 | G11: -3.10361 | H11: -3.049012 | I11: -3.08814 | J11: -3.462417 | K11: -4.019109 | L11: -4.347996 | M11: -4.347996 | N11: -4.460119 | O11: -4.647996 | P11: -4.847996 | Q11: -4.947996 | R11: -4.960119 | S11: -4.947996 | T11: -4.947996 | U11: -4.947996 | V11: -4.960119 | W11: -4.947996 | X11: -4.947996 | Y11: -4.947996 | Z11: -4.960119 | AA11: -4.947996 | AB11: -4.947996 | AC11: -4.947996 | AD11: -4.960119 | AE11: -4.947996 | AF11: -4.947996 | AG11: -4.947996 | AH11: -4.960119 | AI11: -4.947996 | AJ11: -4.947996 | AK11: 0.027
A12: Total Supply | B12: Natural Gas: Total Supply: Reference case | C12: 13-AEO2021.10.ref2021-d113020a | D12: Tcf | F12: 31.285534 | G12: 28.720766 | H12: 29.001406 | I12: 29.839825 | J12: 30.180155 | K12: 31.002926 | L12: 31.396433 | M12: 31.413681 | N12: 31.32778 | O12: 31.368355 | P12: 31.255112 | Q12: 31.384296 | R12: 31.468239 | S12: 31.524296 | T12: 31.644665 | U12: 31.647533 | V12: 31.772041 | W12: 31.991774 | X12: 32.305103 | Y12: 32.587811 | Z12: 32.886208 | AA12: 33.089909 | AB12: 33.422615 | AC12: 33.817455 | AD12: 34.111622 | AE12: 34.353432 | AF12: 34.570889 | AG12: 34.799099 | AH12: 35.061287 | AI12: 35.332809 | AJ12: 35.651695 | AK12: 0.004
A13: Consumption by Sector | B13: Natural Gas: Use by Sector: Total: Reference case | C13: 13-AEO2021.12.ref2021-d113020a | D13: Tcf | F13: 30.759628 | G13: 28.969814 | H13: 29.133207 | I13: 29.864119 | J13: 30.095409 | K13: 30.814251 | L13: 31.112349 | M13: 31.129002 | N13: 31.027622 | O13: 31.079346 | P13: 30.969501 | Q13: 31.118366 | R13: 31.182737 | S13: 31.255699 | T13: 31.386862 | U13: 31.384893 | V13: 31.516623 | W13: 31.740519 | X13: 32.048031 | Y13: 32.346977 | Z13: 32.653408 | AA13: 32.848423 | AB13: 33.185112 | AC13: 33.58342 | AD13: 33.875362 | AE13: 34.116329 | AF13: 34.339634 | AG13: 34.553959 | AH13: 34.812855 | AI13: 35.075024 | AJ13: 35.391342 | AK13: 0.005
A14: Residential | B14: Natural Gas: Use by Sector: Residential: Reference case | C14: 13-AEO2021.13.ref2021-d113020a | D14: Tcf | F14: 4.78282 | G14: 4.659657 | H14: 4.791546 | I14: 4.784126 | J14: 4.785736 | K14: 4.781549 | L14: 4.770129 | M14: 4.757244 | N14: 4.746172 | O14: 4.735456 | P14: 4.719688 | Q14: 4.708289 | R14: 4.699761 | S14: 4.691553 | T14: 4.683408 | U14: 4.677774 | V14: 4.673339 | W14: 4.668981 | X14: 4.664959 | Y14: 4.661228 | Z14: 4.659263 | AA14: 4.657234 | AB14: 4.655647 | AC14: 4.654244 | AD14: 4.653849 | AE14: 4.652879 | AF14: 4.652227 | AG14: 4.650692 | AH14: 4.64872 | AI14: 4.645582 | AJ14: 4.642358 | AK14: -0.001
A15: Commercial | B15: Natural Gas: Use by Sector: Commercial: Reference case | C15: 13-AEO2021.14.ref2021-d113020a | D15: Tcf | F15: 3.18868 | G15: 3.293635 | H15: 3.266141 | I15: 3.372137 | J15: 3.435285 | K15: 3.491935 | L15: 3.498285 | M15: 3.500263 | N15: 3.501419 | O15: 3.50007 | P15: 3.491981 | Q15: 3.493029 | R15: 3.498033 | S15: 3.502732 | T15: 3.506851 | U15: 3.513099 | V15: 3.520664 | W15: 3.527468 | X15: 3.533231 | Y15: 3.53841 | Z15: 3.544436 | AA15: 3.551436 | AB15: 3.558698 | AC15: 3.56541 | AD15: 3.572658 | AE15: 3.578047 | AF15: 3.583146 | AG15: 3.586689 | AH15: 3.58899 | AI15: 3.589589 | AJ15: 3.58919 | AK15: 0.004
A16: Industrial | B16: Natural Gas: Use by Sector: Industrial: Reference case | C16: 13-AEO2021.15.ref2021-d113020a | D16: Tcf | F16: 10.307474 | G16: 10.324542 | H16: 10.423319 | I16: 10.710521 | J16: 11.029292 | K16: 11.326619 | L16: 11.520507 | M16: 11.549958 | N16: 11.634205 | O16: 11.729107 | P16: 11.80891 | Q16: 11.905672 | R16: 11.966723 | S16: 12.03717 | T16: 12.138468 | U16: 12.221153 | V16: 12.301403 | W16: 12.389917 | X16: 12.489612 | Y16: 12.605134 | Z16: 12.706349 | AA16: 12.799595 | AB16: 12.950118 | AC16: 13.115742 | AD16: 13.225972 | AE16: 13.295372 | AF16: 13.43231 | AG16: 13.543573 | AH16: 13.651255 | AI16: 13.769857 | AJ16: 13.904431 | AK16: 0.01
A17: Other Industrial | B17: Natural Gas: Use by Sector: Industrial: Other: Reference case | C17: 13-AEO2021.16.ref2021-d113020a | D17: Tcf | F17: 8.161885 | G17: 8.103975 | H17: 8.140368 | I17: 8.363998 | J17: 8.611549 | K17: 8.774698 | L17: 8.886193 | M17: 8.900866 | N17: 8.950128 | O17: 8.999684 | P17: 9.019031 | Q17: 9.0755 | R17: 9.115315 | S17: 9.152719 | T17: 9.230459 | U17: 9.311929 | V17: 9.389535 | W17: 9.471344 | X17: 9.563922 | Y17: 9.661481 | Z17: 9.740618 | AA17: 9.821562 | AB17: 9.945354 | AC17: 10.071958 | AD17: 10.160589 | AE17: 10.23168 | AF17: 10.348585 | AG17: 10.451379 | AH17: 10.546 | AI17: 10.665246 | AJ17: 10.796975 | AK17: 0.009
A18: Lease and Plant Fuel | B18: Natural Gas: Use by Sector: Industrial: Lease and Plant Fuel: Reference case | C18: 13-AEO2021.17.ref2021-d113020a | D18: Tcf | F18: 1.798462 | G18: 1.743226 | H18: 1.813852 | I18: 1.871607 | J18: 1.88674 | K18: 1.937467 | L18: 1.970579 | M18: 1.985358 | N18: 2.003525 | O18: 2.020688 | P18: 2.051146 | Q18: 2.076438 | R18: 2.095855 | S18: 2.130717 | T18: 2.154274 | U18: 2.15549 | V18: 2.156316 | W18: 2.164839 | X18: 2.171955 | Y18: 2.189918 | Z18: 2.21018 | AA18: 2.224298 | AB18: 2.25103 | AC18: 2.290049 | AD18: 2.30983 | AE18: 2.309958 | AF18: 2.329991 | AG18: 2.338459 | AH18: 2.349702 | AI18: 2.350877 | AJ18: 2.353721 | AK18: 0.009
A19: Fuel Used to Liquefy Gas for Export | B19: Natural Gas: Use by Sector: Industrial: Liquefaction for Export: Reference case | C19: 13-AEO2021.18.ref2021-d113020a | D19: Tcf | F19: 0.347127 | G19: 0.477341 | H19: 0.469098 | I19: 0.474914 | J19: 0.531003 | K19: 0.614454 | L19: 0.663734 | M19: 0.663734 | N19: 0.680553 | O19: 0.708734 | P19: 0.738734 | Q19: 0.753734 | R19: 0.755553 | S19: 0.753734 | T19: 0.753734 | U19: 0.753734 | V19: 0.755553 | W19: 0.753734 | X19: 0.753734 | Y19: 0.753734 | Z19: 0.755553 | AA19: 0.753734 | AB19: 0.753734 | AC19: 0.753734 | AD19: 0.755553 | AE19: 0.753734 | AF19: 0.753734 | AG19: 0.753734 | AH19: 0.755553 | AI19: 0.753734 | AJ19: 0.753734 | AK19: 0.026
A20: Natural Gas-to-Liquids Heat and Power | B20: Natural Gas: Use by Sector: Industrial: GTL Heat and Power: Reference case | C20: 13-AEO2021.19.ref2021-d113020a | D20: Tcf | F20: 0 | G20: 0 | H20: 0 | I20: 0 | J20: 0 | K20: 0 | L20: 0 | M20: 0 | N20: 0 | O20: 0 | P20: 0 | Q20: 0 | R20: 0 | S20: 0 | T20: 0 | U20: 0 | V20: 0 | W20: 0 | X20: 0 | Y20: 0 | Z20: 0 | AA20: 0 | AB20: 0 | AC20: 0 | AD20: 0 | AE20: 0 | AF20: 0 | AG20: 0 | AH20: 0 | AI20: 0 | AJ20: 0 | AK20: - -
A21: Natural Gas to Liquids Production | B21: Natural Gas: Use by Sector: Industrial: GTL Liquids: Reference case | C21: 13-AEO2021.20.ref2021-d113020a | D21: Tcf | F21: 0 | G21: 0 | H21: 0 | I21: 0 | J21: 0 | K21: 0 | L21: 0 | M21: 0 | N21: 0 | O21: 0 | P21: 0 | Q21: 0 | R21: 0 | S21: 0 | T21: 0 | U21: 0 | V21: 0 | W21: 0 | X21: 0 | Y21: 0 | Z21: 0 | AA21: 0 | AB21: 0 | AC21: 0 | AD21: 0 | AE21: 0 | AF21: 0 | AG21: 0 | AH21: 0 | AI21: 0 | AJ21: 0 | AK21: - -
A22: Transportation | B22: Natural Gas: Use by Sector: Transportation: Reference case | C22: 13-AEO2021.21.ref2021-d113020a | D22: Tcf | F22: 0.765735 | G22: 0.843826 | H22: 0.824717 | I22: 0.79586 | J22: 0.767088 | K22: 0.765038 | L22: 0.730884 | M22: 0.734135 | N22: 0.742233 | O22: 0.750429 | P22: 0.747803 | Q22: 0.763764 | R22: 0.779739 | S22: 0.792384 | T22: 0.805472 | U22: 0.821334 | V22: 0.834601 | W22: 0.848805 | X22: 0.866594 | Y22: 0.881065 | Z22: 0.909393 | AA22: 0.92513 | AB22: 0.949754 | AC22: 0.97281 | AD22: 0.996973 | AE22: 1.013085 | AF22: 1.039627 | AG22: 1.060481 | AH22: 1.080297 | AI22: 1.102157 | AJ22: 1.126101 | AK22: 0.013
A23: Motor Vehicles | B23: Trains | C23: and Ships | D23: Natural Gas: Use by Sector: Transportation: Vehicles: Reference case | E23: 13-AEO2021.22.ref2021-d113020a | F23: Tcf | H23: 0.084656 | I23: 0.109117 | J23: 0.095128 | K23: 0.103537 | L23: 0.111005 | M23: 0.123857 | N23: 0.129723 | O23: 0.138251 | P23: 0.147405 | Q23: 0.156129 | R23: 0.158139 | S23: 0.172918 | T23: 0.183914 | U23: 0.194109 | V23: 0.205109 | W23: 0.216278 | X23: 0.226467 | Y23: 0.236582 | Z23: 0.249709 | AA23: 0.260067 | AB23: 0.281876 | AC23: 0.293851 | AD23: 0.313053 | AE23: 0.328496 | AF23: 0.345042 | AG23: 0.356012 | AH23: 0.374896 | AI23: 0.391496 | AJ23: 0.405643 | AK23: 0.420723 | AL23: 0.437008 | AM23: 0.056
A24: Pipeline and Distribution Fuel | B24: Natural Gas: Use by Sector: Transportation: Pipeline Fuel: Reference case | C24: 13-AEO2021.23.ref2021-d113020a | D24: Tcf | F24: 0.681079 | G24: 0.734709 | H24: 0.729589 | I24: 0.692323 | J24: 0.656083 | K24: 0.64118 | L24: 0.601161 | M24: 0.595884 | N24: 0.594828 | O24: 0.594301 | P24: 0.589664 | Q24: 0.590846 | R24: 0.595825 | S24: 0.598276 | T24: 0.600363 | U24: 0.605056 | V24: 0.608135 | W24: 0.612223 | X24: 0.616885 | Y24: 0.620998 | Z24: 0.627518 | AA24: 0.631279 | AB24: 0.636701 | AC24: 0.644314 | AD24: 0.651931 | AE24: 0.657074 | AF24: 0.664731 | AG24: 0.668984 | AH24: 0.674654 | AI24: 0.681434 | AJ24: 0.689093 | AK24: 0
A25: Electric Power | B25: Natural Gas: Use by Sector: Electric Power: Reference case | C25: 13-AEO2021.24.ref2021-d113020a | D25: Tcf | F25: 11.71492 | G25: 9.848155 | H25: 9.827483 | I25: 10.201474 | J25: 10.078012 | K25: 10.449108 | L25: 10.592544 | M25: 10.587401 | N25: 10.40359 | O25: 10.364284 | P25: 10.201119 | Q25: 10.247613 | R25: 10.238481 | S25: 10.231859 | T25: 10.252663 | U25: 10.151533 | V25: 10.186614 | W25: 10.305348 | X25: 10.493639 | Y25: 10.661141 | Z25: 10.833966 | AA25: 10.915029 | AB25: 11.070894 | AC25: 11.275215 | AD25: 11.425906 | AE25: 11.576945 | AF25: 11.632323 | AG25: 11.712527 | AH25: 11.843592 | AI25: 11.967836 | AJ25: 12.12926 | AK25: 0.001
A26: Discrepancy | B26: Natural Gas: Discrepancy: Reference case | C26: 13-AEO2021.26.ref2021-d113020a | D26: Tcf | F26: 0.525906 | G26: -0.249048 | H26: -0.131802 | I26: -0.024294 | J26: 0.084745 | K26: 0.188675 | L26: 0.284084 | M26: 0.284679 | N26: 0.300158 | O26: 0.289009 | P26: 0.28561 | Q26: 0.26593 | R26: 0.285501 | S26: 0.268597 | T26: 0.257803 | U26: 0.26264 | V26: 0.255419 | W26: 0.251255 | X26: 0.257072 | Y26: 0.240833 | Z26: 0.2328 | AA26: 0.241486 | AB26: 0.237503 | AC26: 0.234035 | AD26: 0.236259 | AE26: 0.237103 | AF26: 0.231255 | AG26: 0.24514 | AH26: 0.248432 | AI26: 0.257786 | AJ26: 0.260353 | AK26: - -
A27: Natural Gas Prices | C27: 13-AEO2021.28.
A28: Natural Gas Spot Price at Henry Hub | C28: 13-AEO2021.30.
A29: (2020 dollars per million Btu) | B29: Natural Gas: Henry Hub Spot Price: Reference case | C29: 13-AEO2021.31.ref2021-d113020a | D29: 2020 $/MMBtu | F29: 2.066472 | G29: 3.10073 | H29: 3.225684 | I29: 2.992324 | J29: 2.801792 | K29: 2.880324 | L29: 2.984331 | M29: 3.042141 | N29: 3.17551 | O29: 3.290631 | P29: 3.343955 | Q29: 3.358484 | R29: 3.423043 | S29: 3.48721 | T29: 3.51704 | U29: 3.532698 | V29: 3.537317 | W29: 3.52832 | X29: 3.54974 | Y29: 3.550356 | Z29: 3.549253 | AA29: 3.549023 | AB29: 3.528726 | AC29: 3.505651 | AD29: 3.501869 | AE29: 3.507699 | AF29: 3.521007 | AG29: 3.547183 | AH29: 3.59621 | AI29: 3.654005 | AJ29: 3.693939 | AK29: 0.02
A30: Delivered Prices | C30: 13-AEO2021.33.
A31: (2020 dollars per thousand cubic feet) | C31: 13-AEO2021.34.
A32: Residential | B32: Natural Gas: Delivered Prices: Residential: Reference case | C32: 13-AEO2021.35.ref2021-d113020a | D32: 2020 $/Mcf | F32: 10.537243 | G32: 10.814795 | H32: 10.740482 | I32: 10.613196 | J32: 10.451303 | K32: 10.547084 | L32: 10.694221 | M32: 10.79739 | N32: 10.914479 | O32: 11.0551 | P32: 11.419861 | Q32: 11.468187 | R32: 11.564026 | S32: 11.677169 | T32: 11.745335 | U32: 11.781732 | V32: 11.798117 | W32: 11.826159 | X32: 11.858226 | Y32: 11.879637 | Z32: 11.886778 | AA32: 11.91252 | AB32: 11.921178 | AC32: 11.935447 | AD32: 11.940625 | AE32: 11.975809 | AF32: 11.995084 | AG32: 12.039871 | AH32: 12.087629 | AI32: 12.154815 | AJ32: 12.216571 | AK32: 0.005
A33: Commercial | B33: Natural Gas: Delivered Prices: Commercial: Reference case | C33: 13-AEO2021.36.ref2021-d113020a | D33: 2020 $/Mcf | F33: 7.509337 | G33: 7.950109 | H33: 8.195803 | I33: 8.02144 | J33: 7.832705 | K33: 7.89473 | L33: 8.004504 | M33: 8.068838 | N33: 8.151382 | O33: 8.259359 | P33: 8.515853 | Q33: 8.52672 | R33: 8.583048 | S33: 8.67097 | T33: 8.719043 | U33: 8.738714 | V33: 8.740422 | W33: 8.753948 | X33: 8.771951 | Y33: 8.782027 | Z33: 8.779941 | AA33: 8.796523 | AB33: 8.795634 | AC33: 8.80281 | AD33: 8.799577 | AE33: 8.826352 | AF33: 8.838455 | AG33: 8.874834 | AH33: 8.914612 | AI33: 8.971898 | AJ33: 9.024093 | AK33: 0.006
A34: Industrial | B34: Natural Gas: Delivered Prices: Industrial: Reference case | C34: 13-AEO2021.37.ref2021-d113020a | D34: 2020 $/Mcf | F34: 3.180391 | G34: 4.162838 | H34: 4.314582 | I34: 4.083631 | J34: 3.864322 | K34: 3.927631 | L34: 4.02624 | M34: 4.089579 | N34: 4.214507 | O34: 4.329679 | P34: 4.361543 | Q34: 4.370373 | R34: 4.424331 | S34: 4.498998 | T34: 4.53306 | U34: 4.544279 | V34: 4.544791 | W34: 4.533345 | X34: 4.552034 | Y34: 4.544717 | Z34: 4.535112 | AA34: 4.531607 | AB34: 4.51222 | AC34: 4.494655 | AD34: 4.485391 | AE34: 4.492876 | AF34: 4.495961 | AG34: 4.518952 | AH34: 4.560307 | AI34: 4.615804 | AJ34: 4.655444 | AK34: 0.013
A35: Transportation | B35: Natural Gas: Delivered Prices: Transportation: Reference case | C35: 13-AEO2021.38.ref2021-d113020a | D35: 2020 $/Mcf | F35: 13.520962 | G35: 14.078305 | H35: 14.653452 | I35: 14.196401 | J35: 13.728652 | K35: 13.486947 | L35: 13.341523 | M35: 13.131707 | N35: 12.934259 | O35: 12.743641 | P35: 13.253026 | Q35: 12.973546 | R35: 12.892562 | S35: 12.76227 | T35: 12.617708 | U35: 12.479836 | V35: 12.351564 | W35: 12.229142 | X35: 12.174371 | Y35: 12.077763 | Z35: 12.032022 | AA35: 11.955648 | AB35: 11.89168 | AC35: 11.826577 | AD35: 11.777018 | AE35: 11.745801 | AF35: 11.726257 | AG35: 11.724689 | AH35: 11.734485 | AI35: 11.769066 | AJ35: 11.790224 | AK35: -0.005
A36: Electric Power | B36: Natural Gas: Delivered Prices: Electric Power: Reference case | C36: 13-AEO2021.39.ref2021-d113020a | D36: 2020 $/Mcf | F36: 2.530745 | G36: 3.61926 | H36: 3.726939 | I36: 3.487904 | J36: 3.256875 | K36: 3.348767 | L36: 3.439697 | M36: 3.485474 | N36: 3.600854 | O36: 3.708318 | P36: 3.732601 | Q36: 3.730784 | R36: 3.78701 | S36: 3.856758 | T36: 3.891376 | U36: 3.891621 | V36: 3.89395 | W36: 3.873144 | X36: 3.903093 | Y36: 3.901399 | Z36: 3.900083 | AA36: 3.889824 | AB36: 3.875112 | AC36: 3.858833 | AD36: 3.858512 | AE36: 3.866042 | AF36: 3.870427 | AG36: 3.890644 | AH36: 3.940309 | AI36: 3.991955 | AJ36: 4.034189 | AK36: 0.016
A37: Average | B37: Natural Gas: Delivered Prices: Average: Reference case | C37: 13-AEO2021.40.ref2021-d113020a | D37: 2020 $/Mcf | F37: 4.693558 | G37: 5.66904 | H37: 5.794549 | I37: 5.555105 | J37: 5.348705 | K37: 5.398383 | L37: 5.486406 | M37: 5.548413 | N37: 5.672808 | O37: 5.787228 | P37: 5.912332 | Q37: 5.917324 | R37: 5.978648 | S37: 6.057963 | T37: 6.093779 | U37: 6.110519 | V37: 6.108442 | W37: 6.090482 | X37: 6.0977 | Y37: 6.08242 | Z37: 6.06673 | AA37: 6.059522 | AB37: 6.034441 | AC37: 6.006975 | AD37: 5.992235 | AE37: 5.994117 | AF37: 5.99522 | AG37: 6.014273 | AH37: 6.048097 | AI37: 6.091946 | AJ37: 6.122423 | AK37: 0.009
A38: Natural Gas Spot Price at Henry Hub | C38: 13-AEO2021.59.
A39: (nominal dollars per million Btu) | B39: Natural Gas: Henry Hub Spot Price: Reference case | C39: 13-AEO2021.60.ref2021-d113020a | D39: nom $/MMBtu | F39: 2.066472 | G39: 3.133435 | H39: 3.297882 | I39: 3.100855 | J39: 2.952188 | K39: 3.098166 | L39: 3.286463 | M39: 3.435213 | N39: 3.680265 | O39: 3.914186 | P39: 4.080595 | Q39: 4.201032 | R39: 4.385629 | S39: 4.572134 | T39: 4.714931 | U39: 4.840396 | V39: 4.951261 | W39: 5.042459 | X39: 5.179508 | Y39: 5.287582 | Z39: 5.397773 | AA39: 5.513302 | AB39: 5.602274 | AC39: 5.69328 | AD39: 5.822867 | AE39: 5.976249 | AF39: 6.154725 | AG39: 6.367115 | AH39: 6.63338 | AI39: 6.931768 | AJ39: 7.213103 | AK39: 0.043
A40: Delivered Prices | C40: 13-AEO2021.66.
A41: (nominal dollars per thousand cubic feet) | C41: 13-AEO2021.67.
A42: Residential | B42: Natural Gas: Delivered Prices: Residential: Reference case | C42: 13-AEO2021.68.ref2021-d113020a | D42: nom $/Mcf | F42: 10.537243 | G42: 10.928864 | H42: 10.980878 | I42: 10.998133 | J42: 11.012316 | K42: 11.344769 | L42: 11.776898 | M42: 12.19251 | N42: 12.64936 | O42: 13.14998 | P42: 13.935544 | Q42: 14.345226 | R42: 14.815917 | S42: 15.310114 | T42: 15.745749 | U42: 16.142973 | V42: 16.514086 | W42: 16.901222 | X42: 17.302614 | Y42: 17.692469 | Z42: 18.077641 | AA42: 18.505747 | AB42: 18.926294 | AC42: 19.383518 | AD42: 19.854734 | AE42: 20.403805 | AF42: 20.967421 | AG42: 21.6113 | AH42: 22.296206 | AI42: 23.058088 | AJ42: 23.855129 | AK42: 0.028
A43: Commercial | B43: Natural Gas: Delivered Prices: Commercial: Reference case | C43: 13-AEO2021.69.ref2021-d113020a | D43: nom $/Mcf | F43: 7.509337 | G43: 8.033963 | H43: 8.379243 | I43: 8.312374 | J43: 8.253154 | K43: 8.491816 | L43: 8.814876 | M43: 9.111404 | N43: 9.447062 | O43: 9.824461 | P43: 10.39181 | Q43: 10.66583 | R43: 10.996665 | S43: 11.36864 | T43: 11.688713 | U43: 11.973523 | V43: 12.234162 | W43: 12.510606 | X43: 12.799357 | Y43: 13.079166 | Z43: 13.352703 | AA43: 13.665138 | AB43: 13.964121 | AC43: 14.296023 | AD43: 14.631834 | AE43: 15.037912 | AF43: 15.449629 | AG43: 15.930128 | AH43: 16.443424 | AI43: 17.019991 | AJ43: 17.62122 | AK43: 0.029
A44: Industrial | B44: Natural Gas: Delivered Prices: Industrial: Reference case | C44: 13-AEO2021.70.ref2021-d113020a | D44: nom $/Mcf | F44: 3.180391 | G44: 4.206745 | H44: 4.411152 | I44: 4.231743 | J44: 4.071754 | K44: 4.224681 | L44: 4.433855 | M44: 4.61799 | N44: 4.884412 | O44: 5.150128 | P44: 5.322347 | Q44: 5.466774 | R44: 5.668487 | S44: 5.898705 | T44: 6.077002 | U44: 6.226434 | V44: 6.361445 | W44: 6.478779 | X44: 6.641979 | Y44: 6.768495 | Z44: 6.897086 | AA44: 7.039717 | AB44: 7.16369 | AC44: 7.299453 | AD44: 7.458256 | AE44: 7.654746 | AF44: 7.858944 | AG44: 8.111418 | AH44: 8.411703 | AI44: 8.756334 | AJ44: 9.090622 | AK44: 0.036
A45: Transportation | B45: Natural Gas: Delivered Prices: Transportation: Reference case | C45: 13-AEO2021.71.ref2021-d113020a | D45: nom $/Mcf | F45: 13.520962 | G45: 14.226797 | H45: 14.981429 | I45: 14.7113 | J45: 14.465588 | K45: 14.506977 | L45: 14.692211 | M45: 14.828442 | N45: 14.990189 | O45: 15.158488 | P45: 16.172537 | Q45: 16.228237 | R45: 16.518045 | S45: 16.732807 | T45: 16.915249 | U45: 17.099495 | V45: 17.288759 | W45: 17.47714 | X45: 17.763908 | Y45: 17.987539 | Z45: 18.298531 | AA45: 18.572744 | AB45: 18.879465 | AC45: 19.206713 | AD45: 19.582689 | AE45: 20.011929 | AF45: 20.497513 | AG45: 21.045555 | AH45: 21.644814 | AI45: 22.326311 | AJ45: 23.022608 | AK45: 0.018
A46: Electric Power | B46: Natural Gas: Delivered Prices: Electric Power: Reference case | C46: 13-AEO2021.72.ref2021-d113020a | D46: nom $/Mcf | F46: 2.530745 | G46: 3.657434 | H46: 3.810356 | I46: 3.614409 | J46: 3.4317 | K46: 3.602038 | L46: 3.78793 | M46: 3.935829 | N46: 4.173218 | O46: 4.411023 | P46: 4.554857 | Q46: 4.666731 | R46: 4.851946 | S46: 5.056654 | T46: 5.216763 | U46: 5.332182 | V46: 5.450448 | W46: 5.53526 | X46: 5.695094 | Y46: 5.810395 | Z46: 5.931321 | AA46: 6.042726 | AB46: 6.152204 | AC46: 6.266859 | AD46: 6.415889 | AE46: 6.586776 | AF46: 6.765511 | AG46: 6.983618 | AH46: 7.268087 | AI46: 7.572871 | AJ46: 7.877505 | AK46: 0.039
A47: Average | B47: Natural Gas: Delivered Prices: Average: Reference case | C47: 13-AEO2021.73.ref2021-d113020a | D47: nom $/Mcf | F47: 4.693558 | G47: 5.728835 | H47: 5.924244 | I47: 5.756587 | J47: 5.635816 | K47: 5.806668 | L47: 6.041847 | M47: 6.265317 | N47: 6.574513 | O47: 6.883874 | P47: 7.214759 | Q47: 7.401811 | R47: 7.659888 | S47: 7.942688 | T47: 8.169295 | U47: 8.372448 | V47: 8.550122 | W47: 8.704144 | X47: 8.897296 | Y47: 9.058612 | Z47: 9.226399 | AA47: 9.413288 | AB47: 9.580396 | AC47: 9.755505 | AD47: 9.96382 | AE47: 10.212487 | AF47: 10.479651 | AG47: 10.795485 | AH47: 11.156001 | AI47: 11.556625 | AJ47: 11.955172 | AK47: 0.032

Sheet AEO22 Table13
A1: Table 13. Natural Gas Supply, Disposition, and Prices
A2: https://www.eia.gov/outlooks/aeo/data/browser/#/?id=13-AEO2022&region=0-0&cases=ref2022&start=2020&end=2050&f=A&sourcekey=0
A3: Fri Jun 03 2022 14:36:16 GMT-0700 (Pacific Daylight Time)
A4: Source: U.S. Energy Information Administration
B5: full name | C5: api key | D5: units | E5: 2020 | F5: 2021 | G5: 2022 | H5: 2023 | I5: 2024 | J5: 2025 | K5: 2026 | L5: 2027 | M5: 2028 | N5: 2029 | O5: 2030 | P5: 2031 | Q5: 2032 | R5: 2033 | S5: 2034 | T5: 2035 | U5: 2036 | V5: 2037 | W5: 2038 | X5: 2039 | Y5: 2040 | Z5: 2041 | AA5: 2042 | AB5: 2043 | AC5: 2044 | AD5: 2045 | AE5: 2046 | AF5: 2047 | AG5: 2048 | AH5: 2049 | AI5: 2050 | AJ5: Growth (2021-2050)
A6: Production | C6: 13-AEO2022.2.
A7: Dry Gas Production | B7: Natural Gas: Production: Dry Gas Production: Low economic growth | C7: 13-AEO2022.3.lowmacro-d011222a | D7: Tcf | F7: 34.409626 | G7: 35.322708 | H7: 35.604687 | I7: 35.806705 | J7: 35.905468 | K7: 35.882885 | L7: 35.810017 | M7: 36.400112 | N7: 36.655968 | O7: 36.721214 | P7: 36.966469 | Q7: 37.231819 | R7: 37.474743 | S7: 37.30827 | T7: 37.172085 | U7: 37.122219 | V7: 37.233501 | W7: 37.447079 | X7: 37.700321 | Y7: 37.972595 | Z7: 38.092804 | AA7: 38.278564 | AB7: 38.60881 | AC7: 38.921223 | AD7: 39.147614 | AE7: 39.39146 | AF7: 39.666965 | AG7: 39.861118 | AH7: 40.032658 | AI7: 40.400124 | AJ7: 0.006
A8: Supplemental Natural Gas | B8: Natural Gas: Production: Supplemental Natural Gas: Low economic growth | C8: 13-AEO2022.4.lowmacro-d011222a | D8: Tcf | F8: 0.05953 | G8: 0.06312 | H8: 0.062993 | I8: 0.062865 | J8: 0.062738 | K8: 0.062611 | L8: 0.062483 | M8: 0.062483 | N8: 0.062483 | O8: 0.062483 | P8: 0.062483 | Q8: 0.062483 | R8: 0.062483 | S8: 0.062483 | T8: 0.062483 | U8: 0.062483 | V8: 0.062483 | W8: 0.062483 | X8: 0.062483 | Y8: 0.062483 | Z8: 0.062483 | AA8: 0.062483 | AB8: 0.062483 | AC8: 0.062483 | AD8: 0.062483 | AE8: 0.062483 | AF8: 0.062483 | AG8: 0.062483 | AH8: 0.062483 | AI8: 0.062483 | AJ8: 0.002
A9: Net Imports | B9: Natural Gas: Net Imports: Low economic growth | C9: 13-AEO2022.6.lowmacro-d011222a | D9: Tcf | F9: -4.018888 | G9: -5.032922 | H9: -5.319394 | I9: -5.505922 | J9: -5.795665 | K9: -5.835703 | L9: -6.007035 | M9: -6.346346 | N9: -6.726242 | O9: -7.007736 | P9: -7.372563 | Q9: -7.634319 | R9: -7.706789 | S9: -7.787818 | T9: -7.890796 | U9: -7.918286 | V9: -7.883421 | W9: -7.908661 | X9: -7.962761 | Y9: -8.031993 | Z9: -8.043514 | AA9: -8.068309 | AB9: -8.137873 | AC9: -8.294017 | AD9: -8.36681 | AE9: -8.370378 | AF9: -8.386253 | AG9: -8.38794 | AH9: -8.39177 | AI9: -8.429087 | AJ9: 0.026
A10: Pipeline | B10: Natural Gas: Net Imports: Pipeline: Low economic growth | C10: 13-AEO2022.7.lowmacro-d011222a | D10: Tcf | F10: -0.476819 | G10: -0.916066 | H10: -0.959442 | I10: -1.099447 | J10: -1.217244 | K10: -1.243205 | L10: -1.312514 | M10: -1.43905 | N10: -1.631721 | O10: -1.713215 | P10: -1.878042 | Q10: -1.927022 | R10: -1.912268 | S10: -1.993297 | T10: -2.096275 | U10: -2.11099 | V10: -2.088901 | W10: -2.11414 | X10: -2.16824 | Y10: -2.224696 | Z10: -2.248994 | AA10: -2.273788 | AB10: -2.343352 | AC10: -2.486721 | AD10: -2.572289 | AE10: -2.575856 | AF10: -2.591733 | AG10: -2.580644 | AH10: -2.59725 | AI10: -2.634566 | AJ10: 0.061
A11: Liquefied Natural Gas | B11: Natural Gas: Net Imports: Liquefied Natural Gas: Low economic growth | C11: 13-AEO2022.8.lowmacro-d011222a | D11: Tcf | F11: -3.542069 | G11: -4.116855 | H11: -4.359952 | I11: -4.406474 | J11: -4.578421 | K11: -4.592499 | L11: -4.694521 | M11: -4.907297 | N11: -5.094521 | O11: -5.294521 | P11: -5.494521 | Q11: -5.707297 | R11: -5.794521 | S11: -5.794521 | T11: -5.794521 | U11: -5.807297 | V11: -5.794521 | W11: -5.794521 | X11: -5.794521 | Y11: -5.807297 | Z11: -5.794521 | AA11: -5.794521 | AB11: -5.794521 | AC11: -5.807297 | AD11: -5.794521 | AE11: -5.794521 | AF11: -5.794521 | AG11: -5.807297 | AH11: -5.794521 | AI11: -5.794521 | AJ11: 0.017
A12: Total Supply | B12: Natural Gas: Total Supply: Low economic growth | C12: 13-AEO2022.10.lowmacro-d011222a | D12: Tcf | F12: 30.450266 | G12: 30.352909 | H12: 30.348286 | I12: 30.363649 | J12: 30.172539 | K12: 30.109793 | L12: 29.865467 | M12: 30.116251 | N12: 29.99221 | O12: 29.775963 | P12: 29.656391 | Q12: 29.659985 | R12: 29.830439 | S12: 29.582935 | T12: 29.343773 | U12: 29.266418 | V12: 29.412565 | W12: 29.600903 | X12: 29.800045 | Y12: 30.003086 | Z12: 30.111774 | AA12: 30.272739 | AB12: 30.533422 | AC12: 30.68969 | AD12: 30.843288 | AE12: 31.083569 | AF12: 31.343197 | AG12: 31.535664 | AH12: 31.703373 | AI12: 32.033524 | AJ12: 0.002
A13: Consumption by Sector | B13: Natural Gas: Use by Sector: Total: Low economic growth | C13: 13-AEO2022.12.lowmacro-d011222a | D13: Tcf | F13: 30.242594 | G13: 30.085173 | H13: 30.064831 | I13: 30.056604 | J13: 29.859272 | K13: 29.777143 | L13: 29.518978 | M13: 29.768036 | N13: 29.655115 | O13: 29.44602 | P13: 29.328667 | Q13: 29.327215 | R13: 29.514547 | S13: 29.269196 | T13: 29.029827 | U13: 28.959255 | V13: 29.105549 | W13: 29.295654 | X13: 29.500248 | Y13: 29.703928 | Z13: 29.806578 | AA13: 29.968973 | AB13: 30.229542 | AC13: 30.386457 | AD13: 30.550423 | AE13: 30.797487 | AF13: 31.028425 | AG13: 31.22183 | AH13: 31.388659 | AI13: 31.717159 | AJ13: 0.002
A14: Residential | B14: Natural Gas: Use by Sector: Residential: Low economic growth | C14: 13-AEO2022.13.lowmacro-d011222a | D14: Tcf | F14: 4.819419 | G14: 4.87988 | H14: 4.803436 | I14: 4.816045 | J14: 4.830301 | K14: 4.835493 | L14: 4.835128 | M14: 4.826184 | N14: 4.811259 | O14: 4.796466 | P14: 4.782578 | Q14: 4.765706 | R14: 4.748952 | S14: 4.735481 | T14: 4.726693 | U14: 4.720163 | V14: 4.712776 | W14: 4.704755 | X14: 4.69628 | Y14: 4.689078 | Z14: 4.680464 | AA14: 4.673137 | AB14: 4.667832 | AC14: 4.663457 | AD14: 4.659014 | AE14: 4.653883 | AF14: 4.647811 | AG14: 4.64085 | AH14: 4.632444 | AI14: 4.623201 | AJ14: -0.001
A15: Commercial | B15: Natural Gas: Use by Sector: Commercial: Low economic growth | C15: 13-AEO2022.14.lowmacro-d011222a | D15: Tcf | F15: 3.350484 | G15: 3.482587 | H15: 3.428924 | I15: 3.434704 | J15: 3.444488 | K15: 3.443654 | L15: 3.458211 | M15: 3.461361 | N15: 3.456904 | O15: 3.452962 | P15: 3.453952 | Q15: 3.451528 | R15: 3.448314 | S15: 3.448515 | T15: 3.454259 | U15: 3.462657 | V15: 3.468118 | W15: 3.470585 | X15: 3.471409 | Y15: 3.472769 | Z15: 3.472588 | AA15: 3.475296 | AB15: 3.481176 | AC15: 3.487429 | AD15: 3.493799 | AE15: 3.499022 | AF15: 3.502862 | AG15: 3.505532 | AH15: 3.505991 | AI15: 3.505614 | AJ15: 0.002
A16: Industrial | B16: Natural Gas: Use by Sector: Industrial: Low economic growth | C16: 13-AEO2022.15.lowmacro-d011222a | D16: Tcf | F16: 10.38806 | G16: 10.575246 | H16: 10.486811 | I16: 10.540606 | J16: 10.645499 | K16: 10.709901 | L16: 10.719416 | M16: 10.767504 | N16: 10.779654 | O16: 10.815272 | P16: 10.848524 | Q16: 10.876146 | R16: 10.905524 | S16: 10.913145 | T16: 10.922623 | U16: 10.966375 | V16: 10.982613 | W16: 11.020459 | X16: 11.064152 | Y16: 11.106756 | Z16: 11.119011 | AA16: 11.164563 | AB16: 11.248596 | AC16: 11.29722 | AD16: 11.350711 | AE16: 11.430659 | AF16: 11.498 | AG16: 11.531771 | AH16: 11.566927 | AI16: 11.694829 | AJ16: 0.004
A17: Other Industrial | B17: Natural Gas: Use by Sector: Industrial: Other: Low economic growth | C17: 13-AEO2022.16.lowmacro-d011222a | D17: Tcf | F17: 8.25777 | G17: 8.328052 | H17: 8.209694 | I17: 8.235285 | J17: 8.295445 | K17: 8.354473 | L17: 8.355721 | M17: 8.349208 | N17: 8.332207 | O17: 8.328288 | P17: 8.329494 | Q17: 8.313449 | R17: 8.315689 | S17: 8.332453 | T17: 8.340832 | U17: 8.390054 | V17: 8.412317 | W17: 8.446038 | X17: 8.472146 | Y17: 8.496502 | Z17: 8.513413 | AA17: 8.551575 | AB17: 8.608138 | AC17: 8.642073 | AD17: 8.672221 | AE17: 8.737638 | AF17: 8.794087 | AG17: 8.814433 | AH17: 8.846367 | AI17: 8.932115 | AJ17: 0.003
A18: Lease and Plant Fuel | B18: Natural Gas: Use by Sector: Industrial: Lease and Plant Fuel: Low economic growth | C18: 13-AEO2022.17.lowmacro-d011222a | D18: Tcf | F18: 1.840362 | G18: 1.90736 | H18: 1.917754 | I18: 1.942354 | J18: 1.973323 | K18: 1.97772 | L18: 1.977887 | M18: 2.015253 | N18: 2.029239 | O18: 2.052577 | P18: 2.068422 | Q18: 2.094856 | R18: 2.114927 | S18: 2.105785 | T18: 2.106883 | U18: 2.100379 | V18: 2.095387 | W18: 2.099513 | X18: 2.117098 | Y18: 2.134312 | Z18: 2.130689 | AA18: 2.138081 | AB18: 2.16555 | AC18: 2.179204 | AD18: 2.203582 | AE18: 2.218113 | AF18: 2.229005 | AG18: 2.241395 | AH18: 2.245652 | AI18: 2.287807 | AJ18: 0.008
A19: Fuel Used to Liquefy Gas for Export | B19: Natural Gas: Use by Sector: Industrial: Liquefaction for Export: Low economic growth | C19: 13-AEO2022.18.lowmacro-d011222a | D19: Tcf | F19: 0.289928 | G19: 0.339835 | H19: 0.359363 | I19: 0.362967 | J19: 0.376731 | K19: 0.377708 | L19: 0.385808 | M19: 0.403042 | N19: 0.418208 | O19: 0.434408 | P19: 0.450608 | Q19: 0.467842 | R19: 0.474908 | S19: 0.474908 | T19: 0.474908 | U19: 0.475942 | V19: 0.474908 | W19: 0.474908 | X19: 0.474908 | Y19: 0.475942 | Z19: 0.474908 | AA19: 0.474908 | AB19: 0.474908 | AC19: 0.475942 | AD19: 0.474908 | AE19: 0.474908 | AF19: 0.474908 | AG19: 0.475942 | AH19: 0.474908 | AI19: 0.474908 | AJ19: 0.017
A20: Natural Gas-to-Liquids Heat and Power | B20: Natural Gas: Use by Sector: Industrial: GTL Heat and Power: Low economic growth | C20: 13-AEO2022.19.lowmacro-d011222a | D20: Tcf | F20: 0 | G20: 0 | H20: 0 | I20: 0 | J20: 0 | K20: 0 | L20: 0 | M20: 0 | N20: 0 | O20: 0 | P20: 0 | Q20: 0 | R20: 0 | S20: 0 | T20: 0 | U20: 0 | V20: 0 | W20: 0 | X20: 0 | Y20: 0 | Z20: 0 | AA20: 0 | AB20: 0 | AC20: 0 | AD20: 0 | AE20: 0 | AF20: 0 | AG20: 0 | AH20: 0 | AI20: 0 | AJ20: - -
A21: Natural Gas to Liquids Production | B21: Natural Gas: Use by Sector: Industrial: GTL Liquids: Low economic growth | C21: 13-AEO2022.20.lowmacro-d011222a | D21: Tcf | F21: 0 | G21: 0 | H21: 0 | I21: 0 | J21: 0 | K21: 0 | L21: 0 | M21: 0 | N21: 0 | O21: 0 | P21: 0 | Q21: 0 | R21: 0 | S21: 0 | T21: 0 | U21: 0 | V21: 0 | W21: 0 | X21: 0 | Y21: 0 | Z21: 0 | AA21: 0 | AB21: 0 | AC21: 0 | AD21: 0 | AE21: 0 | AF21: 0 | AG21: 0 | AH21: 0 | AI21: 0 | AJ21: - -
A22: Transportation | B22: Natural Gas: Use by Sector: Transportation: Low economic growth | C22: 13-AEO2022.21.lowmacro-d011222a | D22: Tcf | F22: 0.82787 | G22: 0.770456 | H22: 0.769016 | I22: 0.759091 | J22: 0.754646 | K22: 0.751995 | L22: 0.746852 | M22: 0.759835 | N22: 0.761848 | O22: 0.761588 | P22: 0.766947 | Q22: 0.773339 | R22: 0.783053 | S22: 0.781493 | T22: 0.786302 | U22: 0.794828 | V22: 0.808952 | W22: 0.8245 | X22: 0.837743 | Y22: 0.857536 | Z22: 0.870359 | AA22: 0.884783 | AB22: 0.901461 | AC22: 0.921563 | AD22: 0.930299 | AE22: 0.946389 | AF22: 0.964842 | AG22: 0.981295 | AH22: 0.998166 | AI22: 1.012687 | AJ22: 0.007
A23: Motor Vehicles | B23: Trains | C23: and Ships | D23: Natural Gas: Use by Sector: Transportation: Vehicles: Low economic growth | E23: 13-AEO2022.22.lowmacro-d011222a | F23: Tcf | H23: 0.10664 | I23: 0.096182 | J23: 0.113294 | K23: 0.119665 | L23: 0.126026 | M23: 0.135944 | N23: 0.146969 | O23: 0.154949 | P23: 0.162695 | Q23: 0.171487 | R23: 0.180423 | S23: 0.184107 | T23: 0.191779 | U23: 0.199366 | V23: 0.206543 | W23: 0.214237 | X23: 0.222566 | Y23: 0.231628 | Z23: 0.239112 | AA23: 0.253512 | AB23: 0.263027 | AC23: 0.272002 | AD23: 0.284502 | AE23: 0.297652 | AF23: 0.308227 | AG23: 0.321112 | AH23: 0.331511 | AI23: 0.340022 | AJ23: 0.349799 | AK23: 0.405344 | AL23: 0.047
A24: Pipeline and Distribution Fuel | B24: Natural Gas: Use by Sector: Transportation: Pipeline Fuel: Low economic growth | C24: 13-AEO2022.23.lowmacro-d011222a | D24: Tcf | F24: 0.72123 | G24: 0.674274 | H24: 0.655722 | I24: 0.639426 | J24: 0.62862 | K24: 0.616051 | L24: 0.599883 | M24: 0.604886 | N24: 0.599153 | O24: 0.590101 | P24: 0.586524 | Q24: 0.589232 | R24: 0.591273 | S24: 0.582127 | T24: 0.57976 | U24: 0.580591 | V24: 0.586386 | W24: 0.592872 | X24: 0.598631 | Y24: 0.604024 | Z24: 0.607332 | AA24: 0.61278 | AB24: 0.616958 | AC24: 0.623911 | AD24: 0.622073 | AE24: 0.625277 | AF24: 0.633331 | AG24: 0.641273 | AH24: 0.648367 | AI24: 0.653551 | AJ24: -0.003
A25: Electric Power | B25: Natural Gas: Use by Sector: Electric Power: Low economic growth | C25: 13-AEO2022.24.lowmacro-d011222a | D25: Tcf | F25: 10.85676 | G25: 10.377003 | H25: 10.576644 | I25: 10.506159 | J25: 10.184333 | K25: 10.036098 | L25: 9.759375 | M25: 9.953151 | N25: 9.845448 | O25: 9.61973 | P25: 9.476666 | Q25: 9.460497 | R25: 9.628703 | S25: 9.390562 | T25: 9.139952 | U25: 9.015231 | V25: 9.13309 | W25: 9.275352 | X25: 9.430664 | Y25: 9.577788 | Z25: 9.664156 | AA25: 9.771195 | AB25: 9.930477 | AC25: 10.016788 | AD25: 10.116599 | AE25: 10.267536 | AF25: 10.414912 | AG25: 10.56238 | AH25: 10.685132 | AI25: 10.88083 | AJ25: 0
A26: Discrepancy | B26: Natural Gas: Discrepancy: Low economic growth | C26: 13-AEO2022.26.lowmacro-d011222a | D26: Tcf | F26: 0.207672 | G26: 0.267736 | H26: 0.283455 | I26: 0.307045 | J26: 0.313267 | K26: 0.332649 | L26: 0.346489 | M26: 0.348215 | N26: 0.337095 | O26: 0.329943 | P26: 0.327724 | Q26: 0.332769 | R26: 0.315891 | S26: 0.31374 | T26: 0.313946 | U26: 0.307163 | V26: 0.307016 | W26: 0.305248 | X26: 0.299797 | Y26: 0.299158 | Z26: 0.305197 | AA26: 0.303766 | AB26: 0.303881 | AC26: 0.303232 | AD26: 0.292866 | AE26: 0.286081 | AF26: 0.314772 | AG26: 0.313833 | AH26: 0.314714 | AI26: 0.316364 | AJ26: - -
A27: Natural Gas Prices | C27: 13-AEO2022.28.
A28: Natural Gas Spot Price at Henry Hub | C28: 13-AEO2022.30.
A29: (2021 dollars per million Btu) | B29: Natural Gas: Henry Hub Spot Price: Low economic growth | C29: 13-AEO2022.31.lowmacro-d011222a | D29: 2021 $/MMBtu | F29: 4.115437 | G29: 3.837557 | H29: 3.471147 | I29: 3.126585 | J29: 2.953741 | K29: 2.906966 | L29: 2.954549 | M29: 3.136157 | N29: 3.292231 | O29: 3.388971 | P29: 3.454448 | Q29: 3.491858 | R29: 3.59329 | S29: 3.594153 | T29: 3.524364 | U29: 3.485305 | V29: 3.48693 | W29: 3.51827 | X29: 3.545613 | Y29: 3.577658 | Z29: 3.63465 | AA29: 3.652029 | AB29: 3.589562 | AC29: 3.561126 | AD29: 3.469676 | AE29: 3.425366 | AF29: 3.400315 | AG29: 3.392432 | AH29: 3.403568 | AI29: 3.409512 | AJ29: -0.006
A30: Delivered Prices | C30: 13-AEO2022.33.
A31: (2021 dollars per thousand cubic feet) | C31: 13-AEO2022.34.
A32: Residential | B32: Natural Gas: Delivered Prices: Residential: Low economic growth | C32: 13-AEO2022.35.lowmacro-d011222a | D32: 2021 $/Mcf | F32: 12.171644 | G32: 12.625865 | H32: 11.979866 | I32: 11.480213 | J32: 11.157559 | K32: 10.968821 | L32: 10.837678 | M32: 10.981541 | N32: 11.152151 | O32: 11.246775 | P32: 11.342472 | Q32: 11.68836 | R32: 11.833169 | S32: 11.888336 | T32: 11.88853 | U32: 11.856069 | V32: 11.895705 | W32: 11.930015 | X32: 11.970271 | Y32: 12.000363 | Z32: 12.084126 | AA32: 12.079756 | AB32: 12.043774 | AC32: 12.028834 | AD32: 11.998742 | AE32: 11.996384 | AF32: 12.001075 | AG32: 12.006783 | AH32: 12.045881 | AI32: 12.069625 | AJ32: 0
A33: Commercial | B33: Natural Gas: Delivered Prices: Commercial: Low economic growth | C33: 13-AEO2022.36.lowmacro-d011222a | D33: 2021 $/Mcf | F33: 8.771839 | G33: 9.162567 | H33: 8.828384 | I33: 8.499667 | J33: 8.33059 | K33: 8.281426 | L33: 8.273354 | M33: 8.399084 | N33: 8.544633 | O33: 8.616765 | P33: 8.690123 | Q33: 8.905362 | R33: 9.008744 | S33: 9.037756 | T33: 9.009416 | U33: 8.96355 | V33: 8.989129 | W33: 9.011681 | X33: 9.040559 | Y33: 9.060416 | Z33: 9.132076 | AA33: 9.116379 | AB33: 9.069324 | AC33: 9.045333 | AD33: 9.007052 | AE33: 8.995634 | AF33: 8.99243 | AG33: 8.990973 | AH33: 9.022299 | AI33: 9.039542 | AJ33: 0.001
A34: Industrial | B34: Natural Gas: Delivered Prices: Industrial: Low economic growth | C34: 13-AEO2022.37.lowmacro-d011222a | D34: 2021 $/Mcf | F34: 5.269056 | G34: 5.03236 | H34: 4.688 | I34: 4.317468 | J34: 4.135796 | K34: 4.079431 | L34: 4.111363 | M34: 4.275023 | N34: 4.428134 | O34: 4.517744 | P34: 4.577354 | Q34: 4.57688 | R34: 4.677366 | S34: 4.682547 | T34: 4.609011 | U34: 4.556269 | V34: 4.554906 | W34: 4.577663 | X34: 4.599112 | Y34: 4.622378 | Z34: 4.678865 | AA34: 4.686431 | AB34: 4.620964 | AC34: 4.584721 | AD34: 4.508954 | AE34: 4.477705 | AF34: 4.458506 | AG34: 4.452824 | AH34: 4.463304 | AI34: 4.471565 | AJ34: -0.006
A35: Transportation | B35: Natural Gas: Delivered Prices: Transportation: Low economic growth | C35: 13-AEO2022.38.lowmacro-d011222a | D35: 2021 $/Mcf | F35: 15.22551 | G35: 15.189867 | H35: 14.413707 | I35: 13.82573 | J35: 13.402384 | K35: 13.030856 | L35: 12.741631 | M35: 12.603173 | N35: 12.474068 | O35: 12.308931 | P35: 12.141323 | Q35: 12.813327 | R35: 12.722208 | S35: 12.575328 | T35: 12.46647 | U35: 12.278451 | V35: 12.158415 | W35: 12.07103 | X35: 11.987044 | Y35: 11.964777 | Z35: 11.952209 | AA35: 11.886301 | AB35: 11.783961 | AC35: 11.709952 | AD35: 11.603604 | AE35: 11.546721 | AF35: 11.496274 | AG35: 11.448224 | AH35: 11.422692 | AI35: 11.379571 | AJ35: -0.01
A36: Electric Power | B36: Natural Gas: Delivered Prices: Electric Power: Low economic growth | C36: 13-AEO2022.39.lowmacro-d011222a | D36: 2021 $/Mcf | F36: 5.332857 | G36: 4.178648 | H36: 3.885905 | I36: 3.547021 | J36: 3.377793 | K36: 3.342421 | L36: 3.381722 | M36: 3.556563 | N36: 3.688859 | O36: 3.763834 | P36: 3.807873 | Q36: 3.82572 | R36: 3.921008 | S36: 3.904177 | T36: 3.798467 | U36: 3.750271 | V36: 3.744769 | W36: 3.767939 | X36: 3.793509 | Y36: 3.829679 | Z36: 3.882215 | AA36: 3.881239 | AB36: 3.803053 | AC36: 3.765003 | AD36: 3.692361 | AE36: 3.66632 | AF36: 3.650438 | AG36: 3.654424 | AH36: 3.66035 | AI36: 3.687017 | AJ36: -0.013
A37: Average | B37: Natural Gas: Delivered Prices: Average: Low economic growth | C37: 13-AEO2022.40.lowmacro-d011222a | D37: 2021 $/Mcf | F37: 6.975946 | G37: 6.635291 | H37: 6.229839 | I37: 5.862714 | J37: 5.690771 | K37: 5.630795 | L37: 5.656798 | M37: 5.799069 | N37: 5.953547 | O37: 6.053108 | P37: 6.125708 | Q37: 6.227705 | R37: 6.316007 | S37: 6.343978 | T37: 6.301665 | U37: 6.264091 | V37: 6.259395 | W37: 6.268137 | X37: 6.278011 | Y37: 6.292707 | Z37: 6.344999 | AA37: 6.332001 | AB37: 6.253158 | AC37: 6.213667 | AD37: 6.142462 | AE37: 6.105012 | AF37: 6.077645 | AG37: 6.06405 | AH37: 6.067497 | AI37: 6.06418 | AJ37: -0.005
A38: Natural Gas Spot Price at Henry Hub | C38: 13-AEO2022.59.
A39: (nominal dollars per million Btu) | B39: Natural Gas: Henry Hub Spot Price: Low economic growth | C39: 13-AEO2022.60.lowmacro-d011222a | D39: nom $/MMBtu | F39: 4.115437 | G39: 3.961129 | H39: 3.67353 | I39: 3.407579 | J39: 3.321223 | K39: 3.380046 | L39: 3.55681 | M39: 3.909547 | N39: 4.247153 | O39: 4.519075 | P39: 4.759894 | Q39: 4.967306 | R39: 5.278396 | S39: 5.456114 | T39: 5.532805 | U39: 5.659725 | V39: 5.858712 | W39: 6.116162 | X39: 6.373682 | Y39: 6.653007 | Z39: 6.991181 | AA39: 7.266311 | AB39: 7.385303 | AC39: 7.573573 | AD39: 7.62625 | AE39: 7.781052 | AF39: 7.982764 | AG39: 8.228611 | AH39: 8.525277 | AI39: 8.814068 | AJ39: 0.027
A40: Delivered Prices | C40: 13-AEO2022.66.
A41: (nominal dollars per thousand cubic feet) | C41: 13-AEO2022.67.
A42: Residential | B42: Natural Gas: Delivered Prices: Residential: Low economic growth | C42: 13-AEO2022.68.lowmacro-d011222a | D42: nom $/Mcf | F42: 12.171644 | G42: 13.032427 | H42: 12.678345 | I42: 12.511969 | J42: 12.5457 | K42: 12.753887 | L42: 13.046851 | M42: 13.689635 | N42: 14.386866 | O42: 14.997186 | P42: 15.628823 | Q42: 16.627151 | R42: 17.382442 | S42: 18.047121 | T42: 18.663486 | U42: 19.252861 | V42: 19.98707 | W42: 20.73914 | X42: 21.518059 | Y42: 22.315857 | Z42: 23.243591 | AA42: 24.034658 | AB42: 24.779325 | AC42: 25.582144 | AD42: 26.372894 | AE42: 27.250956 | AF42: 28.174376 | AG42: 29.1234 | AH42: 30.172592 | AI42: 31.201681 | AJ42: 0.033
A43: Commercial | B43: Natural Gas: Delivered Prices: Commercial: Low economic growth | C43: 13-AEO2022.69.lowmacro-d011222a | D43: nom $/Mcf | F43: 8.771839 | G43: 9.457608 | H43: 9.343118 | I43: 9.263554 | J43: 9.367021 | K43: 9.629147 | L43: 9.95981 | M43: 10.470333 | N43: 11.023029 | O43: 11.490159 | P43: 11.974144 | Q43: 12.668225 | R43: 13.233478 | S43: 13.71979 | T43: 14.143641 | U43: 14.555749 | V43: 15.103463 | W43: 15.665908 | X43: 16.251535 | Y43: 16.848736 | Z43: 17.56538 | AA43: 18.138533 | AB43: 18.659576 | AC43: 19.237028 | AD43: 19.797245 | AE43: 20.43446 | AF43: 21.111115 | AG43: 21.808311 | AH43: 22.599108 | AI43: 23.36849 | AJ43: 0.034
A44: Industrial | B44: Natural Gas: Delivered Prices: Industrial: Low economic growth | C44: 13-AEO2022.70.lowmacro-d011222a | D44: nom $/Mcf | F44: 5.269056 | G44: 5.194405 | H44: 4.961331 | I44: 4.70549 | J44: 4.650341 | K44: 4.743318 | L44: 4.949431 | M44: 5.329262 | N44: 5.712528 | O44: 6.024255 | P44: 6.307149 | Q44: 6.510792 | R44: 6.87086 | S44: 7.108353 | T44: 7.235563 | U44: 7.398845 | V44: 7.653116 | W44: 7.95781 | X44: 8.267478 | Y44: 8.595767 | Z44: 8.999711 | AA44: 9.324426 | AB44: 9.50735 | AC44: 9.750486 | AD44: 9.910552 | AE44: 10.171543 | AF44: 10.46703 | AG44: 10.800675 | AH44: 11.179709 | AI44: 11.559625 | AJ44: 0.027
A45: Transportation | B45: Natural Gas: Delivered Prices: Transportation: Low economic growth | C45: 13-AEO2022.71.lowmacro-d011222a | D45: nom $/Mcf | F45: 15.22551 | G45: 15.678991 | H45: 15.254088 | I45: 15.068284 | J45: 15.06981 | K45: 15.151498 | L45: 15.33891 | M45: 15.711169 | N45: 16.092209 | O45: 16.413536 | P45: 16.729563 | Q45: 18.227459 | R45: 18.688402 | S45: 19.090012 | T45: 19.570778 | U45: 19.938759 | V45: 20.428473 | W45: 20.984282 | X45: 21.54821 | Y45: 22.24968 | Z45: 22.989855 | AA45: 23.649748 | AB45: 24.244778 | AC45: 24.903967 | AD45: 25.504393 | AE45: 26.229502 | AF45: 26.989277 | AG45: 27.76857 | AH45: 28.611628 | AI45: 29.417795 | AJ45: 0.023
A46: Electric Power | B46: Natural Gas: Delivered Prices: Electric Power: Low economic growth | C46: 13-AEO2022.72.lowmacro-d011222a | D46: nom $/Mcf | F46: 5.332857 | G46: 4.313203 | H46: 4.112471 | I46: 3.865801 | J46: 3.798033 | K46: 3.886366 | L46: 4.071059 | M46: 4.433627 | N46: 4.758823 | O46: 5.018943 | P46: 5.24688 | Q46: 5.442236 | R46: 5.7598 | S46: 5.926747 | T46: 5.963112 | U46: 6.089999 | V46: 6.291931 | W46: 6.550187 | X46: 6.819307 | Y46: 7.121665 | Z46: 7.46737 | AA46: 7.722362 | AB46: 7.824549 | AC46: 8.007165 | AD46: 8.115704 | AE46: 8.328403 | AF46: 8.569965 | AG46: 8.864093 | AH46: 9.168466 | AI46: 9.531458 | AJ46: 0.02
A47: Average | B47: Natural Gas: Delivered Prices: Average: Low economic growth | C47: 13-AEO2022.73.lowmacro-d011222a | D47: nom $/Mcf | F47: 6.975946 | G47: 6.848952 | H47: 6.593066 | I47: 6.389611 | J47: 6.398775 | K47: 6.547151 | L47: 6.809891 | M47: 7.229145 | N47: 7.680391 | O47: 8.071611 | P47: 8.44063 | Q47: 8.859155 | R47: 9.277956 | S47: 9.630492 | T47: 9.892816 | U47: 10.172147 | V47: 10.516985 | W47: 10.89653 | X47: 11.28551 | Y47: 11.701908 | Z47: 12.204488 | AA47: 12.598556 | AB47: 12.865489 | AC47: 13.214825 | AD47: 13.500958 | AE47: 13.868131 | AF47: 14.268209 | AG47: 14.708831 | AH47: 15.197902 | AI47: 15.67676 | AJ47: 0.028

Sheet AEO21 Table60
A1: Table 60. Natural Gas Imports and Exports
A2: https://www.eia.gov/outlooks/aeo/data/browser/#/?id=76-AEO2021&region=0-0&cases=highogs&start=2019&end=2050&f=A&sourcekey=0
A3: Fri Mar 19 2021 13:31:12 GMT-0700 (Pacific Daylight Time)
A4: Source: U.S. Energy Information Administration
B5: full name | C5: api key | D5: units | E5: 2019 | F5: 2020 | G5: 2021 | H5: 2022 | I5: 2023 | J5: 2024 | K5: 2025 | L5: 2026 | M5: 2027 | N5: 2028 | O5: 2029 | P5: 2030 | Q5: 2031 | R5: 2032 | S5: 2033 | T5: 2034 | U5: 2035 | V5: 2036 | W5: 2037 | X5: 2038 | Y5: 2039 | Z5: 2040 | AA5: 2041 | AB5: 2042 | AC5: 2043 | AD5: 2044 | AE5: 2045 | AF5: 2046 | AG5: 2047 | AH5: 2048 | AI5: 2049 | AJ5: 2050 | AK5: Growth (2020-2050)
A6: Volumes (trillion cubic feet) | C6: 76-AEO2021.2.
A7: Imports | B7: Natural Gas: Volumes: Imports: High oil and gas supply | C7: 76-AEO2021.3.highogs-d120120a | D7: Tcf | F7: 2.591845 | G7: 2.658888 | H7: 2.581335 | I7: 2.23374 | J7: 2.022558 | K7: 2.154527 | L7: 2.254248 | M7: 2.17263 | N7: 2.059658 | O7: 1.933034 | P7: 1.705166 | Q7: 1.695373 | R7: 1.588383 | S7: 1.443764 | T7: 1.408442 | U7: 1.381659 | V7: 1.372678 | W7: 1.378547 | X7: 1.372888 | Y7: 1.353339 | Z7: 1.349054 | AA7: 1.339908 | AB7: 1.309852 | AC7: 1.259662 | AD7: 1.237417 | AE7: 1.190565 | AF7: 1.152394 | AG7: 1.128619 | AH7: 1.06587 | AI7: 1.032826 | AJ7: 1.02677 | AK7: -0.03
A8: Pipeline Imports from Canada | B8: Natural Gas: Volumes: Imports: Pipeline Imports from Canada: High oil and gas supply | C8: 76-AEO2021.4.highogs-d120120a | D8: Tcf | F8: 2.527186 | G8: 2.580227 | H8: 2.503026 | I8: 2.155784 | J8: 1.944892 | K8: 2.076816 | L8: 2.17677 | M8: 2.095063 | N8: 1.982531 | O8: 1.855707 | P8: 1.628266 | Q8: 1.618474 | R8: 1.511483 | S8: 1.366865 | T8: 1.331543 | U8: 1.30476 | V8: 1.295779 | W8: 1.301647 | X8: 1.295988 | Y8: 1.27644 | Z8: 1.272155 | AA8: 1.263009 | AB8: 1.232953 | AC8: 1.182763 | AD8: 1.160517 | AE8: 1.113665 | AF8: 1.075495 | AG8: 1.05172 | AH8: 0.988971 | AI8: 0.955927 | AJ8: 0.94987 | AK8: -0.032
A9: Pipeline Imports from Mexico | B9: Natural Gas: Volumes: Imports: Pipeline Imports from Mexico: High oil and gas supply | C9: 76-AEO2021.5.highogs-d120120a | D9: Tcf | F9: 0 | G9: 0 | H9: 0 | I9: 0 | J9: 6.2e-05 | K9: 0.000459 | L9: 0.000579 | M9: 0.000668 | N9: 0.000228 | O9: 0.000427 | P9: 0 | Q9: 0 | R9: 0 | S9: 0 | T9: 0 | U9: 0 | V9: 0 | W9: 0 | X9: 0 | Y9: 0 | Z9: 0 | AA9: 0 | AB9: 0 | AC9: 0 | AD9: 0 | AE9: 0 | AF9: 0 | AG9: 0 | AH9: 0 | AI9: 0 | AJ9: 0 | AK9: - -
A10: Liquefied Natural Gas Imports | B10: Natural Gas: Volumes: Imports: Liquefied Natural Gas Imports: High oil and gas supply | C10: 76-AEO2021.6.highogs-d120120a | D10: Tcf | F10: 0.064659 | G10: 0.078661 | H10: 0.078309 | I10: 0.077956 | J10: 0.077604 | K10: 0.077252 | L10: 0.076899 | M10: 0.076899 | N10: 0.076899 | O10: 0.076899 | P10: 0.076899 | Q10: 0.076899 | R10: 0.076899 | S10: 0.076899 | T10: 0.076899 | U10: 0.076899 | V10: 0.076899 | W10: 0.076899 | X10: 0.076899 | Y10: 0.076899 | Z10: 0.076899 | AA10: 0.076899 | AB10: 0.076899 | AC10: 0.076899 | AD10: 0.076899 | AE10: 0.076899 | AF10: 0.076899 | AG10: 0.076899 | AH10: 0.076899 | AI10: 0.076899 | AJ10: 0.076899 | AK10: 0.006
A11: Exports | B11: Natural Gas: Volumes: Exports: High oil and gas supply | C11: 76-AEO2021.7.highogs-d120120a | D11: Tcf | F11: 5.260553 | G11: 6.296653 | H11: 6.521109 | I11: 6.762466 | J11: 7.25752 | K11: 7.86409 | L11: 8.32939 | M11: 8.588181 | N11: 8.927889 | O11: 9.361116 | P11: 9.833778 | Q11: 10.080954 | R11: 10.344864 | S11: 10.563437 | T11: 10.789639 | U11: 11.01073 | V11: 11.253021 | W11: 11.458885 | X11: 11.687817 | Y11: 11.909035 | Z11: 12.158211 | AA11: 12.256628 | AB11: 12.283306 | AC11: 12.311003 | AD11: 12.357313 | AE11: 12.357868 | AF11: 12.383665 | AG11: 12.409163 | AH11: 12.465016 | AI11: 12.467362 | AJ11: 12.477144 | AK11: 0.029
A12: Pipeline Exports to Canada | B12: Natural Gas: Volumes: Exports: Pipeline Exports to Canada: High oil and gas supply | C12: 76-AEO2021.8.highogs-d120120a | D12: Tcf | F12: 0.881853 | G12: 0.938842 | H12: 0.907451 | I12: 0.966469 | J12: 0.989208 | K12: 0.980991 | L12: 0.973344 | M12: 0.983885 | N12: 1.021513 | O12: 1.03111 | P12: 1.068119 | Q12: 1.081704 | R12: 1.100447 | S12: 1.111323 | T12: 1.111028 | U12: 1.12156 | V12: 1.134434 | W12: 1.144015 | X12: 1.1574 | Y12: 1.163259 | Z12: 1.176172 | AA12: 1.177003 | AB12: 1.186794 | AC12: 1.196353 | AD12: 1.208235 | AE12: 1.208432 | AF12: 1.216575 | AG12: 1.226854 | AH12: 1.245973 | AI12: 1.248916 | AJ12: 1.263373 | AK12: 0.012
A13: Pipeline Exports to Mexico | B13: Natural Gas: Volumes: Exports: Pipeline Exports to Mexico: High oil and gas supply | C13: 76-AEO2021.9.highogs-d120120a | D13: Tcf | F13: 2.06452 | G13: 2.190212 | H13: 2.486337 | I13: 2.6299 | J13: 2.728291 | K13: 2.786738 | L13: 2.83115 | M13: 2.879399 | N13: 2.969358 | O13: 3.005112 | P13: 3.040764 | Q13: 3.074354 | R13: 3.107399 | S13: 3.127219 | T13: 3.153715 | U13: 3.164275 | V13: 3.181569 | W13: 3.189975 | X13: 3.205522 | Y13: 3.220881 | Z13: 3.24502 | AA13: 3.25473 | AB13: 3.271617 | AC13: 3.289755 | AD13: 3.31206 | AE13: 3.324541 | AF13: 3.342195 | AG13: 3.357413 | AH13: 3.382025 | AI13: 3.393551 | AJ13: 3.388876 | AK13: 0.017
A14: Liquefied Natural Gas Exports | B14: Natural Gas: Volumes: Exports: Liquefied Natural Gas Exports: High oil and gas supply | C14: 76-AEO2021.10.highogs-d120120a | D14: Tcf | F14: 2.31418 | G14: 3.167598 | H14: 3.12732 | I14: 3.166097 | J14: 3.540021 | K14: 4.096361 | L14: 4.524895 | M14: 4.724895 | N14: 4.937018 | O14: 5.324895 | P14: 5.724895 | Q14: 5.924895 | R14: 6.137018 | S14: 6.324895 | T14: 6.524895 | U14: 6.724895 | V14: 6.937018 | W14: 7.124896 | X14: 7.324895 | Y14: 7.524895 | Z14: 7.737019 | AA14: 7.824895 | AB14: 7.824895 | AC14: 7.824895 | AD14: 7.837018 | AE14: 7.824895 | AF14: 7.824895 | AG14: 7.824895 | AH14: 7.837018 | AI14: 7.824895 | AJ14: 7.824895 | AK14: 0.041
A15: Net Imports | B15: Natural Gas: Volumes: Net Imports: High oil and gas supply | C15: 76-AEO2021.11.highogs-d120120a | D15: Tcf | F15: -2.668709 | G15: -3.637765 | H15: -3.939773 | I15: -4.528727 | J15: -5.234962 | K15: -5.709562 | L15: -6.075141 | M15: -6.41555 | N15: -6.868231 | O15: -7.428083 | P15: -8.128613 | Q15: -8.38558 | R15: -8.756481 | S15: -9.119673 | T15: -9.381196 | U15: -9.62907 | V15: -9.880342 | W15: -10.080339 | X15: -10.31493 | Y15: -10.555696 | Z15: -10.809156 | AA15: -10.916719 | AB15: -10.973454 | AC15: -11.051341 | AD15: -11.119896 | AE15: -11.167303 | AF15: -11.231272 | AG15: -11.280543 | AH15: -11.399146 | AI15: -11.434536 | AJ15: -11.450375 | AK15: 0.05
A16: Canada | B16: Natural Gas: Volumes: Net Imports: Canada: High oil and gas supply | C16: 76-AEO2021.12.highogs-d120120a | D16: Tcf | F16: 1.645333 | G16: 1.641385 | H16: 1.595575 | I16: 1.189314 | J16: 0.955684 | K16: 1.095825 | L16: 1.203426 | M16: 1.111177 | N16: 0.961019 | O16: 0.824597 | P16: 0.560147 | Q16: 0.53677 | R16: 0.411037 | S16: 0.255542 | T16: 0.220514 | U16: 0.1832 | V16: 0.161345 | W16: 0.157632 | X16: 0.138588 | Y16: 0.113181 | Z16: 0.095983 | AA16: 0.086006 | AB16: 0.046158 | AC16: -0.013591 | AD16: -0.047718 | AE16: -0.094766 | AF16: -0.141081 | AG16: -0.175134 | AH16: -0.257002 | AI16: -0.29299 | AJ16: -0.313502 | AK16: - -
A17: Mexico | B17: Natural Gas: Volumes: Net Imports: Mexico: High oil and gas supply | C17: 76-AEO2021.13.highogs-d120120a | D17: Tcf | F17: -2.06452 | G17: -2.190212 | H17: -2.486337 | I17: -2.6299 | J17: -2.728229 | K17: -2.786279 | L17: -2.830571 | M17: -2.878732 | N17: -2.969131 | O17: -3.004684 | P17: -3.040764 | Q17: -3.074354 | R17: -3.107399 | S17: -3.127219 | T17: -3.153715 | U17: -3.164275 | V17: -3.181569 | W17: -3.189975 | X17: -3.205522 | Y17: -3.220881 | Z17: -3.24502 | AA17: -3.25473 | AB17: -3.271617 | AC17: -3.289755 | AD17: -3.31206 | AE17: -3.324541 | AF17: -3.342195 | AG17: -3.357413 | AH17: -3.382025 | AI17: -3.393551 | AJ17: -3.388876 | AK17: 0.017
A18: Liquefied Natural Gas | B18: Natural Gas: Volumes: Net Imports: Liquefied Natural Gas: High oil and gas supply | C18: 76-AEO2021.14.highogs-d120120a | D18: Tcf | F18: -2.249521 | G18: -3.088938 | H18: -3.049012 | I18: -3.08814 | J18: -3.462417 | K18: -4.019109 | L18: -4.447996 | M18: -4.647996 | N18: -4.860119 | O18: -5.247996 | P18: -5.647996 | Q18: -5.847996 | R18: -6.060119 | S18: -6.247996 | T18: -6.447996 | U18: -6.647996 | V18: -6.860119 | W18: -7.047996 | X18: -7.247996 | Y18: -7.447996 | Z18: -7.660119 | AA18: -7.747996 | AB18: -7.747996 | AC18: -7.747996 | AD18: -7.760119 | AE18: -7.747996 | AF18: -7.747996 | AG18: -7.747996 | AH18: -7.760119 | AI18: -7.747996 | AJ18: -7.747996 | AK18: 0.042
B21: Transposed
C22: Pipeline Exports to Canada | D22: Pipeline Exports to Mexico | E22: Liquefied Natural Gas Exports
B23: {=TRANSPOSE(F5:AK5)} -> 2020 | C23: {=TRANSPOSE(F12:AK12)} -> 0.881853 | D23: {=TRANSPOSE(F13:AK13)} -> 2.06452 | E23: {=TRANSPOSE(F14:AK14)} -> 2.31418
B24: 2021 | C24: 0.938842 | D24: 2.190212 | E24: 3.167598
B25: 2022 | C25: 0.907451 | D25: 2.486337 | E25: 3.12732
B26: 2023 | C26: 0.966469 | D26: 2.6299 | E26: 3.166097
B27: 2024 | C27: 0.989208 | D27: 2.728291 | E27: 3.540021
B28: 2025 | C28: 0.980991 | D28: 2.786738 | E28: 4.096361
B29: 2026 | C29: 0.973344 | D29: 2.83115 | E29: 4.524895
B30: 2027 | C30: 0.983885 | D30: 2.879399 | E30: 4.724895
B31: 2028 | C31: 1.021513 | D31: 2.969358 | E31: 4.937018
B32: 2029 | C32: 1.03111 | D32: 3.005112 | E32: 5.324895
B33: 2030 | C33: 1.068119 | D33: 3.040764 | E33: 5.724895
B34: 2031 | C34: 1.081704 | D34: 3.074354 | E34: 5.924895
B35: 2032 | C35: 1.100447 | D35: 3.107399 | E35: 6.137018
... B53: 2050 | C53: 1.263373 | D53: 3.388876 | E53: 7.824895
B54: Growth (2020-2050) | C54: 0.012 | D54: 0.017 | E54: 0.041

Sheet AEO22 Table60
A1: Table 60. Natural Gas Imports and Exports
A2: https://www.eia.gov/outlooks/aeo/data/browser/#/?id=76-AEO2022&region=0-0&cases=ref2022&start=2020&end=2050&f=A&linechart=&ctype=linechart&sourcekey=0
A3: Fri Jun 03 2022 14:37:41 GMT-0700 (Pacific Daylight Time)
A4: Source: U.S. Energy Information Administration
B5: full name | C5: api key | D5: units | E5: 2020 | F5: 2021 | G5: 2022 | H5: 2023 | I5: 2024 | J5: 2025 | K5: 2026 | L5: 2027 | M5: 2028 | N5: 2029 | O5: 2030 | P5: 2031 | Q5: 2032 | R5: 2033 | S5: 2034 | T5: 2035 | U5: 2036 | V5: 2037 | W5: 2038 | X5: 2039 | Y5: 2040 | Z5: 2041 | AA5: 2042 | AB5: 2043 | AC5: 2044 | AD5: 2045 | AE5: 2046 | AF5: 2047 | AG5: 2048 | AH5: 2049 | AI5: 2050 | AJ5: Growth (2021-2050)
A6: Volumes (trillion cubic feet) | C6: 76-AEO2022.2.
A7: Imports | B7: Natural Gas: Volumes: Imports: Low economic growth | C7: 76-AEO2022.3.lowmacro-d011222a | D7: Tcf | F7: 2.730044 | G7: 2.478948 | H7: 2.399872 | I7: 2.299369 | J7: 2.227211 | K7: 2.201699 | L7: 2.167048 | M7: 2.117685 | N7: 1.987127 | O7: 1.935035 | P7: 1.844631 | Q7: 1.832976 | R7: 1.877825 | S7: 1.8405 | T7: 1.799475 | U7: 1.794174 | V7: 1.827648 | W7: 1.824522 | X7: 1.795108 | Y7: 1.761056 | Z7: 1.736678 | AA7: 1.728937 | AB7: 1.669057 | AC7: 1.548609 | AD7: 1.472641 | AE7: 1.452845 | AF7: 1.425173 | AG7: 1.428671 | AH7: 1.39673 | AI7: 1.353371 | AJ7: -0.024
A8: Pipeline Imports from Canada | B8: Natural Gas: Volumes: Imports: Pipeline Imports from Canada: Low economic growth | C8: 76-AEO2022.4.lowmacro-d011222a | D8: Tcf | F8: 2.692753 | G8: 2.400303 | H8: 2.323249 | I8: 2.224767 | J8: 2.154631 | K8: 2.13114 | L8: 2.098511 | M8: 2.049148 | N8: 1.91859 | O8: 1.866498 | P8: 1.776095 | Q8: 1.76444 | R8: 1.809288 | S8: 1.771963 | T8: 1.730938 | U8: 1.725637 | V8: 1.759111 | W8: 1.755986 | X8: 1.726571 | Y8: 1.69252 | Z8: 1.668141 | AA8: 1.6604 | AB8: 1.60052 | AC8: 1.480073 | AD8: 1.404104 | AE8: 1.384308 | AF8: 1.356636 | AG8: 1.360134 | AH8: 1.328193 | AI8: 1.284834 | AJ8: -0.025
A9: Pipeline Imports from Mexico | B9: Natural Gas: Volumes: Imports: Pipeline Imports from Mexico: Low economic growth | C9: 76-AEO2022.5.lowmacro-d011222a | D9: Tcf | F9: 0 | G9: 0 | H9: 0 | I9: 0 | J9: 0 | K9: 0 | L9: 0 | M9: 0 | N9: 0 | O9: 0 | P9: 0 | Q9: 0 | R9: 0 | S9: 0 | T9: 0 | U9: 0 | V9: 0 | W9: 0 | X9: 0 | Y9: 0 | Z9: 0 | AA9: 0 | AB9: 0 | AC9: 0 | AD9: 0 | AE9: 0 | AF9: 0 | AG9: 0 | AH9: 0 | AI9: 0 | AJ9: - -
A10: Liquefied Natural Gas Imports | B10: Natural Gas: Volumes: Imports: Liquefied Natural Gas Imports: Low economic growth | C10: 76-AEO2022.6.lowmacro-d011222a | D10: Tcf | F10: 0.037291 | G10: 0.078645 | H10: 0.076623 | I10: 0.074602 | J10: 0.07258 | K10: 0.070558 | L10: 0.068537 | M10: 0.068537 | N10: 0.068537 | O10: 0.068537 | P10: 0.068537 | Q10: 0.068537 | R10: 0.068537 | S10: 0.068537 | T10: 0.068537 | U10: 0.068537 | V10: 0.068537 | W10: 0.068537 | X10: 0.068537 | Y10: 0.068537 | Z10: 0.068537 | AA10: 0.068537 | AB10: 0.068537 | AC10: 0.068537 | AD10: 0.068537 | AE10: 0.068537 | AF10: 0.068537 | AG10: 0.068537 | AH10: 0.068537 | AI10: 0.068537 | AJ10: 0.021
A11: Exports | B11: Natural Gas: Volumes: Exports: Low economic growth | C11: 76-AEO2022.7.lowmacro-d011222a | D11: Tcf | F11: 6.748932 | G11: 7.511869 | H11: 7.719266 | I11: 7.80529 | J11: 8.022876 | K11: 8.037402 | L11: 8.174084 | M11: 8.464031 | N11: 8.713368 | O11: 8.942771 | P11: 9.217195 | Q11: 9.467295 | R11: 9.584615 | S11: 9.628318 | T11: 9.690271 | U11: 9.712461 | V11: 9.711069 | W11: 9.733184 | X11: 9.75787 | Y11: 9.793049 | Z11: 9.780193 | AA11: 9.797247 | AB11: 9.80693 | AC11: 9.842627 | AD11: 9.839452 | AE11: 9.823222 | AF11: 9.811426 | AG11: 9.816612 | AH11: 9.788502 | AI11: 9.782457 | AJ11: 0.013
A12: Pipeline Exports to Canada | B12: Natural Gas: Volumes: Exports: Pipeline Exports to Canada: Low economic growth | C12: 76-AEO2022.8.lowmacro-d011222a | D12: Tcf | F12: 0.950934 | G12: 0.994317 | H12: 0.966944 | I12: 0.984799 | J12: 0.99467 | K12: 0.984524 | L12: 0.989653 | M12: 0.998102 | N12: 1.021865 | O12: 1.021977 | P12: 1.059877 | Q12: 1.06349 | R12: 1.063998 | S12: 1.071854 | T12: 1.096582 | U12: 1.10407 | V12: 1.110207 | W12: 1.121564 | X12: 1.137337 | Y12: 1.150079 | Z12: 1.158589 | AA12: 1.182333 | AB12: 1.198976 | AC12: 1.231174 | AD12: 1.24635 | AE12: 1.254089 | AF12: 1.263327 | AG12: 1.274598 | AH12: 1.27874 | AI12: 1.289769 | AJ12: 0.011
A13: Pipeline Exports to Mexico | B13: Natural Gas: Volumes: Exports: Pipeline Exports to Mexico: Low economic growth | C13: 76-AEO2022.9.lowmacro-d011222a | D13: Tcf | F13: 2.218637 | G13: 2.322052 | H13: 2.315747 | I13: 2.339416 | J13: 2.377205 | K13: 2.389821 | L13: 2.421372 | M13: 2.490095 | N13: 2.528445 | O13: 2.557736 | P13: 2.59426 | Q13: 2.627972 | R13: 2.657558 | S13: 2.693406 | T13: 2.730632 | U13: 2.732557 | V13: 2.737805 | W13: 2.748562 | X13: 2.757474 | Y13: 2.767137 | Z13: 2.758546 | AA13: 2.751855 | AB13: 2.744895 | AC13: 2.735619 | AD13: 2.730044 | AE13: 2.706074 | AF13: 2.685041 | AG13: 2.666181 | AH13: 2.646703 | AI13: 2.62963 | AJ13: 0.006
A14: Liquefied Natural Gas Exports | B14: Natural Gas: Volumes: Exports: Liquefied Natural Gas Exports: Low economic growth | C14: 76-AEO2022.10.lowmacro-d011222a | D14: Tcf | F14: 3.57936 | G14: 4.1955 | H14: 4.436575 | I14: 4.481076 | J14: 4.651001 | K14: 4.663058 | L14: 4.763058 | M14: 4.975833 | N14: 5.163058 | O14: 5.363058 | P14: 5.563058 | Q14: 5.775833 | R14: 5.863058 | S14: 5.863058 | T14: 5.863058 | U14: 5.875834 | V14: 5.863058 | W14: 5.863058 | X14: 5.863058 | Y14: 5.875834 | Z14: 5.863058 | AA14: 5.863058 | AB14: 5.863058 | AC14: 5.875834 | AD14: 5.863058 | AE14: 5.863058 | AF14: 5.863058 | AG14: 5.875834 | AH14: 5.863058 | AI14: 5.863058 | AJ14: 0.017
A15: Net Imports | B15: Natural Gas: Volumes: Net Imports: Low economic growth | C15: 76-AEO2022.11.lowmacro-d011222a | D15: Tcf | F15: -4.018888 | G15: -5.032922 | H15: -5.319394 | I15: -5.505921 | J15: -5.795666 | K15: -5.835704 | L15: -6.007035 | M15: -6.346347 | N15: -6.726242 | O15: -7.007736 | P15: -7.372563 | Q15: -7.634318 | R15: -7.706789 | S15: -7.787818 | T15: -7.890796 | U15: -7.918287 | V15: -7.883422 | W15: -7.908662 | X15: -7.962761 | Y15: -8.031993 | Z15: -8.043514 | AA15: -8.06831 | AB15: -8.137873 | AC15: -8.294018 | AD15: -8.366811 | AE15: -8.370377 | AF15: -8.386254 | AG15: -8.387941 | AH15: -8.391771 | AI15: -8.429087 | AJ15: 0.026
A16: Canada | B16: Natural Gas: Volumes: Net Imports: Canada: Low economic growth | C16: 76-AEO2022.12.lowmacro-d011222a | D16: Tcf | F16: 1.741819 | G16: 1.405986 | H16: 1.356305 | I16: 1.239969 | J16: 1.159961 | K16: 1.146616 | L16: 1.108858 | M16: 1.051045 | N16: 0.896725 | O16: 0.844522 | P16: 0.716218 | Q16: 0.70095 | R16: 0.74529 | S16: 0.700109 | T16: 0.634357 | U16: 0.621567 | V16: 0.648904 | W16: 0.634422 | X16: 0.589234 | Y16: 0.54244 | Z16: 0.509553 | AA16: 0.478067 | AB16: 0.401543 | AC16: 0.248898 | AD16: 0.157755 | AE16: 0.130219 | AF16: 0.093309 | AG16: 0.085537 | AH16: 0.049454 | AI16: -0.004935 | AJ16: - -
A17: Mexico | B17: Natural Gas: Volumes: Net Imports: Mexico: Low economic growth | C17: 76-AEO2022.13.lowmacro-d011222a | D17: Tcf | F17: -2.218637 | G17: -2.322052 | H17: -2.315747 | I17: -2.339416 | J17: -2.377205 | K17: -2.389821 | L17: -2.421372 | M17: -2.490095 | N17: -2.528445 | O17: -2.557736 | P17: -2.59426 | Q17: -2.627972 | R17: -2.657558 | S17: -2.693406 | T17: -2.730632 | U17: -2.732557 | V17: -2.737805 | W17: -2.748562 | X17: -2.757474 | Y17: -2.767137 | Z17: -2.758546 | AA17: -2.751855 | AB17: -2.744895 | AC17: -2.735619 | AD17: -2.730044 | AE17: -2.706074 | AF17: -2.685041 | AG17: -2.666181 | AH17: -2.646703 | AI17: -2.62963 | AJ17: 0.006
A18: Liquefied Natural Gas | B18: Natural Gas: Volumes: Net Imports: Liquefied Natural Gas: Low economic growth | C18: 76-AEO2022.14.lowmacro-d011222a | D18: Tcf | F18: -3.542069 | G18: -4.116856 | H18: -4.359952 | I18: -4.406474 | J18: -4.578421 | K18: -4.592499 | L18: -4.694521 | M18: -4.907297 | N18: -5.094521 | O18: -5.294521 | P18: -5.494521 | Q18: -5.707296 | R18: -5.794521 | S18: -5.794521 | T18: -5.794521 | U18: -5.807297 | V18: -5.794521 | W18: -5.794521 | X18: -5.794521 | Y18: -5.807297 | Z18: -5.794521 | AA18: -5.794521 | AB18: -5.794521 | AC18: -5.807297 | AD18: -5.794521 | AE18: -5.794521 | AF18: -5.794521 | AG18: -5.807297 | AH18: -5.794521 | AI18: -5.794521 | AJ18: 0.017
B21: Transposed
C22: Pipeline Exports to Canada | D22: Pipeline Exports to Mexico | E22: Liquefied Natural Gas Exports
B23: 2021 | C23: 0.950934 | D23: 2.218661 | E23: 3.57936
B24: 2022 | C24: 0.993488 | D24: 2.321824 | E24: 4.1955
B25: 2023 | C25: 0.962994 | D25: 2.313414 | E25: 4.436575
B26: 2024 | C26: 0.979468 | D26: 2.334801 | E26: 4.481076
B27: 2025 | C27: 0.994414 | D27: 2.372 | E27: 4.651001
B28: 2026 | C28: 0.984083 | D28: 2.381717 | E28: 4.663058
B29: 2027 | C29: 0.982755 | D29: 2.409727 | E29: 4.763058
B30: 2028 | C30: 0.994677 | D30: 2.477914 | E30: 4.975833
B31: 2029 | C31: 1.026718 | D31: 2.513206 | E31: 5.163058
B32: 2030 | C32: 1.024433 | D32: 2.539065 | E32: 5.363058
B33: 2031 | C33: 1.059514 | D33: 2.574106 | E33: 5.563058
B34: 2032 | C34: 1.065948 | D34: 2.607545 | E34: 5.775833
... B52: 2050 | C52: 1.307339 | D52: 2.577559 | E52: 5.863058
B53: Growth (2021-2050) | C53: 0.011 | D53: 0.005 | E53: 0.017

Sheet Historical Monthly Gas Cons
A1: Back to Contents | B1: Data 1: Natural Gas Delivered to Consumers in the U.S. (MMcf)
A2: Sourcekey | B2: N3060US2
A3: Date | B3: Natural Gas Delivered to Consumers in the U.S. (MMcf)
A4: 36906 | B4: 2505011 | C4: =MONTH(A4) -> 1 | D4: =YEAR(A4) -> 2001
A5: 36937 | B5: 2156873 | C5: =MONTH(A5) -> 2 | D5: =YEAR(A5) -> 2001
A6: 36965 | B6: 2086568 | C6: =MONTH(A6) -> 3 | D6: =YEAR(A6) -> 2001
A7: 36996 | B7: 1663832 | C7: =MONTH(A7) -> 4 | D7: =YEAR(A7) -> 2001
A8: 37026 | B8: 1385163 | C8: =MONTH(A8) -> 5 | D8: =YEAR(A8) -> 2001
A9: 37057 | B9: 1313119 | C9: =MONTH(A9) -> 6 | D9: =YEAR(A9) -> 2001
A10: 37087 | B10: 1459919 | C10: =MONTH(A10) -> 7 | D10: =YEAR(A10) -> 2001
A11: 37118 | B11: 1528483 | C11: =MONTH(A11) -> 8 | D11: =YEAR(A11) -> 2001
A12: 37149 | B12: 1360871 | C12: =MONTH(A12) -> 9 | D12: =YEAR(A12) -> 2001
A13: 37179 | B13: 1507428 | C13: =MONTH(A13) -> 10 | D13: =YEAR(A13) -> 2001
A14: 37210 | B14: 1561970 | C14: =MONTH(A14) -> 11 | D14: =YEAR(A14) -> 2001
A15: 37240 | B15: 1965873 | C15: =MONTH(A15) -> 12 | D15: =YEAR(A15) -> 2001
... A257: 44607 | B257: 2797164 | C257: =MONTH(A257) -> 2 | D257: =YEAR(A257) -> 2022

Sheet EIA Henry Hub Nat Gas Spot
A1: Back to Contents | B1: Data 1: Henry Hub Natural Gas Spot Price (Dollars per Million Btu)
A2: Sourcekey | B2: RNGWHHD
A3: Date | B3: Henry Hub Natural Gas Spot Price (Dollars per Million Btu)
A4: 35611 | B4: 2.49
A5: 35976 | B5: 2.09
A6: 36341 | B6: 2.27
A7: 36707 | B7: 4.31
A8: 37072 | B8: 3.96
A9: 37437 | B9: 3.38
A10: 37802 | B10: 5.47
A11: 38168 | B11: 5.89
A12: 38533 | B12: 8.69
A13: 38898 | B13: 6.73
A14: 39263 | B14: 6.97
A15: 39629 | B15: 8.86
... A28: 44377 | B28: 3.89

Sheet NG Sector Price Historicals
A1: Back to Contents | B1: Data 1: U.S. Natural Gas Prices | U1: Converted to mmbtu
A2: Sourcekey | B2: N9190US3 | C2: N9100US3 | D2: N9102US3 | E2: N9103US3 | F2: N9130US3 | G2: N9132US3 | H2: N9133US3 | I2: NA1480_NUS_3 | J2: N3050US3 | K2: N3010US3 | L2: NA1504_NUS_4 | M2: N3020US3 | N2: N3020US4 | O2: N3035US3 | P2: N3035US4 | Q2: NA1570_NUS_3 | R2: N3045US3 | U2: Pipeline | V2: lng
A3: Date | B3: U.S. Natural Gas Wellhead Price (Dollars per Thousand Cubic Feet) | C3: Price of U.S. Natural Gas Imports (Dollars per Thousand Cubic Feet) | D3: U.S. Natural Gas Pipeline Imports Price (Dollars per Thousand Cubic Feet) | E3: Price of U.S. Natural Gas LNG Imports (Dollars per Thousand Cubic Feet) | F3: Price of U.S. Natural Gas Exports (Dollars per Thousand Cubic Feet) | G3: Price of U.S. Natural Gas Pipeline Exports (Dollars per Thousand Cubic Feet) | H3: Price of Liquefied U.S. Natural Gas Exports (Dollars per Thousand Cubic Feet) | I3: U.S. Natural Gas Pipeline and Distribution Use Price (Dollars per Thousand Cubic Feet) | J3: U.S. Natural Gas Citygate Price (Dollars per Thousand Cubic Feet) | K3: U.S. Price of Natural Gas Delivered to Residential Consumers (Dollars per Thousand Cubic Feet) | L3: U.S. Natural Gas % of Total Residential - Sales (%) | M3: U.S. Price of Natural Gas Sold to Commercial Consumers (Dollars per Thousand Cubic Feet) | N3: Percent of Commercial Natural Gas Deliveries in U.S. Total Represented by the Price (%) | O3: United States Natural Gas Industrial Price (Dollars per Thousand Cubic Feet) | P3: Percent of Industrial Natural Gas Deliveries in U.S. Total Represented by the Price (%) | Q3: U.S. Natural Gas Vehicle Fuel Price (Dollars per Thousand Cubic Feet) | R3: U.S. Natural Gas Electric Power Price (Dollars per Thousand Cubic Feet) | S3: Year | U3: dollars per million btu | V3: dollars per million btu
A4: 8217 | B4: 0.11 | S4: =YEAR(A4) -> 1922
A5: 8582 | B5: 0.1 | S5: =YEAR(A5) -> 1923
A6: 8948 | B6: 0.09 | S6: =YEAR(A6) -> 1924
A7: 9313 | B7: 0.09 | S7: =YEAR(A7) -> 1925
A8: 9678 | B8: 0.1 | S8: =YEAR(A8) -> 1926
A9: 10043 | B9: 0.09 | S9: =YEAR(A9) -> 1927
A10: 10409 | B10: 0.09 | S10: =YEAR(A10) -> 1928
A11: 10774 | B11: 0.08 | S11: =YEAR(A11) -> 1929
A12: 11139 | B12: 0.08 | S12: =YEAR(A12) -> 1930
A13: 11504 | B13: 0.07 | S13: =YEAR(A13) -> 1931
A14: 11870 | B14: 0.06 | S14: =YEAR(A14) -> 1932
A15: 12235 | B15: 0.06 | S15: =YEAR(A15) -> 1933
... A48: 24288 | B48: 0.16 | S48: =YEAR(A48) -> 1966
A49: 24653 | B49: 0.16 | I49: 0.2 | K49: 1.04 | M49: 0.74 | S49: =YEAR(A49) -> 1967
A50: 25019 | B50: 0.16 | I50: 0.2 | K50: 1.04 | M50: 0.73 | S50: =YEAR(A50) -> 1968
A51: 25384 | B51: 0.17 | I51: 0.21 | K51: 1.05 | M51: 0.74 | S51: =YEAR(A51) -> 1969
A52: 25749 | B52: 0.17 | I52: 0.21 | K52: 1.09 | M52: 0.77 | S52: =YEAR(A52) -> 1970
A53: 26114 | B53: 0.18 | I53: 0.22 | K53: 1.15 | M53: 0.82 | S53: =YEAR(A53) -> 1971
A54: 26480 | B54: 0.19 | I54: 0.23 | K54: 1.21 | M54: 0.88 | S54: =YEAR(A54) -> 1972
A55: 26845 | B55: 0.22 | I55: 0.25 | K55: 1.29 | M55: 0.94 | S55: =YEAR(A55) -> 1973
A56: 27210 | B56: 0.3 | I56: 0.3 | K56: 1.43 | M56: 1.07 | S56: =YEAR(A56) -> 1974
A57: 27575 | B57: 0.44 | I57: 0.4 | K57: 1.71 | M57: 1.35 | S57: =YEAR(A57) -> 1975
A58: 27941 | B58: 0.58 | I58: 0.51 | K58: 1.98 | M58: 1.64 | S58: =YEAR(A58) -> 1976
A59: 28306 | B59: 0.79 | I59: 0.77 | K59: 2.35 | M59: 2.04 | S59: =YEAR(A59) -> 1977
A60: 28671 | B60: 0.91 | I60: 0.9 | K60: 2.56 | M60: 2.23 | S60: =YEAR(A60) -> 1978
... A65: 30497 | B65: 2.59 | I65: 3.15 | K65: 6.06 | M65: 5.59 | S65: =YEAR(A65) -> 1983
A66: 30863 | B66: 2.66 | I66: 3.04 | J66: 3.95 | K66: 6.12 | M66: 5.55 | S66: =YEAR(A66) -> 1984
A67: 31228 | B67: 2.51 | C67: 3.21 | D67: 3.17 | E67: 4.6 | F67: 4.77 | G67: 3.92 | H67: 4.81 | I67: 2.92 | J67: 3.75 | K67: 6.12 | M67: 5.5 | S67: =YEAR(A67) -> 1985
A68: 31593 | B68: 1.94 | C68: 2.43 | D68: 2.42 | E68: 4.62 | F68: 2.81 | G68: 2.35 | H68: 2.91 | I68: 2.52 | J68: 3.22 | K68: 5.83 | M68: 5.08 | S68: =YEAR(A68) -> 1986
A69: 31958 | B69: 1.67 | C69: 1.95 | D69: 1.95 | F69: 3.07 | G69: 2.35 | H69: 3.15 | I69: 2.17 | J69: 2.87 | K69: 5.54 | M69: 4.77 | N69: 93.1 | S69: =YEAR(A69) -> 1987
A70: 32324 | B70: 1.69 | C70: 1.84 | D70: 1.83 | E70: 2.71 | F70: 2.74 | G70: 2.14 | H70: 2.98 | I70: 2.1 | J70: 2.92 | K70: 5.47 | M70: 4.63 | N70: 90.8 | S70: =YEAR(A70) -> 1988
A71: 32689 | B71: 1.69 | C71: 1.82 | D71: 1.81 | E71: 2.22 | F71: 2.51 | G71: 2.05 | H71: 3.01 | I71: 2.01 | J71: 3.01 | K71: 5.64 | L71: 99.9 | M71: 4.74 | N71: 89.1 | Q71: 4.17 | S71: =YEAR(A71) -> 1989
A72: 33054 | B72: 1.71 | C72: 1.94 | D72: 1.91 | E72: 2.47 | F72: 3.1 | G72: 2.31 | H72: 3.59 | I72: 1.95 | J72: 3.03 | K72: 5.8 | L72: 99.2 | M72: 4.83 | N72: 86.6 | Q72: 3.39 | S72: =YEAR(A72) -> 1990
A73: 33419 | B73: 1.64 | C73: 1.83 | D73: 1.81 | E73: 2.36 | F73: 2.59 | G73: 1.79 | H73: 3.71 | I73: 1.87 | J73: 2.9 | K73: 5.82 | L73: 99.2 | M73: 4.81 | N73: 85.1 | Q73: 3.96 | S73: =YEAR(A73) -> 1991
A74: 33785 | B74: 1.74 | C74: 1.85 | D74: 1.84 | E74: 2.54 | F74: 2.25 | G74: 1.88 | H74: 3.43 | I74: 2.07 | J74: 3.01 | K74: 5.89 | L74: 99.1 | M74: 4.88 | N74: 83.2 | Q74: 4.05 | S74: =YEAR(A74) -> 1992
A75: 34150 | B75: 2.04 | C75: 2.03 | D75: 2.02 | E75: 2.2 | F75: 2.59 | G75: 2.08 | H75: 3.34 | I75: 1.97 | J75: 3.21 | K75: 6.16 | L75: 99.1 | M75: 5.22 | N75: 83.9 | Q75: 4.27 | S75: =YEAR(A75) -> 1993
A76: 34515 | B76: 1.85 | C76: 1.87 | D76: 1.86 | E76: 2.28 | F76: 2.5 | G76: 2.08 | H76: 3.18 | I76: 1.7 | J76: 3.07 | K76: 6.41 | L76: 99.1 | M76: 5.44 | N76: 79.3 | Q76: 4.11 | S76: =YEAR(A76) -> 1994
A77: 34880 | B77: 1.55 | C77: 1.49 | D77: 1.48 | E77: 2.3 | F77: 2.39 | G77: 1.64 | H77: 3.41 | I77: 1.49 | J77: 2.78 | K77: 6.06 | L77: 99 | M77: 5.05 | N77: 76.7 | Q77: 3.98 | S77: =YEAR(A77) -> 1995
A78: 35246 | B78: 2.17 | C78: 1.97 | D78: 1.96 | E78: 2.8 | F78: 2.97 | G78: 2.45 | H78: 3.65 | I78: 2.27 | J78: 3.27 | K78: 6.34 | L78: 99 | M78: 5.4 | N78: 77.6 | Q78: 4.34 | S78: =YEAR(A78) -> 1996
A79: 35611 | B79: 2.32 | C79: 2.17 | D79: 2.15 | E79: 2.74 | F79: 3.02 | G79: 2.49 | H79: 3.83 | I79: 2.29 | J79: 3.66 | K79: 6.94 | L79: 98.8 | M79: 5.8 | N79: 70.8 | O79: 3.59 | P79: 18.1 | Q79: 4.44 | R79: 2.78 | S79: =YEAR(A79) -> 1997
A80: 35976 | B80: 1.96 | C80: 1.97 | D80: 1.95 | E80: 2.63 | F80: 2.45 | G80: 2.13 | H80: 2.91 | I80: 2.01 | J80: 3.07 | K80: 6.82 | L80: 97.7 | M80: 5.48 | N80: 67 | O80: 3.14 | P80: 16.1 | Q80: 4.59 | R80: 2.4 | S80: =YEAR(A80) -> 1998
A81: 36341 | B81: 2.19 | C81: 2.24 | D81: 2.23 | E81: 2.47 | F81: 2.61 | G81: 2.3 | H81: 3.1 | I81: 1.88 | J81: 3.1 | K81: 6.69 | L81: 95.2 | M81: 5.33 | N81: 66.1 | O81: 3.12 | P81: 18.8 | Q81: 4.34 | R81: 2.62 | S81: =YEAR(A81) -> 1999
A82: 36707 | B82: 3.68 | C82: 3.95 | D82: 3.98 | E82: 3.5 | F82: 4.1 | G82: 4.02 | H82: 4.32 | I82: 2.97 | J82: 4.62 | K82: 7.76 | L82: 92.6 | M82: 6.59 | N82: 63.9 | O82: 4.45 | P82: 19.8 | Q82: 5.54 | R82: 4.38 | S82: =YEAR(A82) -> 2000
A83: 37072 | B83: 4 | C83: 4.43 | D83: 4.44 | E83: 4.35 | F83: 4.19 | G83: 4.14 | H83: 4.4 | I83: 3.55 | J83: 5.72 | K83: 9.63 | L83: 92.4 | M83: 8.43 | N83: 66 | O83: 5.24 | P83: 20.8 | Q83: 6.6 | R83: 4.61 | S83: =YEAR(A83) -> 2001 | U83: =G83*About!$B$27 -> 4.29318 | V83: =H83*About!$B$27 -> 4.5628
A84: 37437 | B84: 2.95 | C84: 3.15 | D84: 3.13 | E84: 3.41 | F84: 3.41 | G84: 3.32 | H84: 4.08 | J84: 4.12 | K84: 7.89 | L84: 97.9 | M84: 6.63 | N84: 77.4 | O84: 4.02 | P84: 22.7 | Q84: 5.1 | R84: 3.68 | S84: =YEAR(A84) -> 2002 | U84: =G84*About!$B$27 -> 3.44284 | V84: =H84*About!$B$27 -> 4.23096
A85: 37802 | B85: 4.88 | C85: 5.17 | D85: 5.23 | E85: 4.79 | F85: 5.54 | G85: 5.66 | H85: 4.47 | J85: 5.85 | K85: 9.63 | L85: 97.5 | M85: 8.4 | N85: 78.2 | O85: 5.89 | P85: 22.1 | Q85: 6.19 | R85: 5.57 | S85: =YEAR(A85) -> 2003 | U85: =G85*About!$B$27 -> 5.86942 | V85: =H85*About!$B$27 -> 4.63539
A86: 38168 | B86: 5.46 | C86: 5.81 | D86: 5.8 | E86: 5.82 | F86: 6.09 | G86: 6.18 | H86: 4.96 | J86: 6.65 | K86: 10.75 | L86: 97.7 | M86: 9.43 | N86: 78 | O86: 6.53 | P86: 23.6 | Q86: 7.16 | R86: 6.11 | S86: =YEAR(A86) -> 2004 | U86: =G86*About!$B$27 -> 6.40866 | V86: =H86*About!$B$27 -> 5.14352
A87: 38533 | B87: 7.33 | C87: 8.12 | D87: 8.09 | E87: 8.26 | F87: 7.59 | G87: 7.77 | H87: 5.79 | J87: 8.67 | K87: 12.7 | L87: 98.1 | M87: 11.34 | N87: 82.1 | O87: 8.56 | P87: 24 | Q87: 9.14 | R87: 8.47 | S87: =YEAR(A87) -> 2005 | U87: =G87*About!$B$27 -> 8.05749 | V87: =H87*About!$B$27 -> 6.00423
A88: 38898 | B88: 6.39 | C88: 6.88 | D88: 6.83 | E88: 7.19 | F88: 6.83 | G88: 6.9 | H88: 6.02 | J88: 8.61 | K88: 13.73 | L88: 98.1 | M88: 12 | N88: 80.8 | O88: 7.87 | P88: 23.4 | Q88: 8.72 | R88: 7.11 | S88: =YEAR(A88) -> 2006 | U88: =G88*About!$B$27 -> 7.1553 | V88: =H88*About!$B$27 -> 6.24274
A89: 39263 | B89: 6.25 | C89: 6.87 | D89: 6.83 | E89: 7.07 | F89: 6.92 | G89: 6.96 | H89: 6.23 | J89: 8.16 | K89: 13.08 | L89: 98 | M89: 11.34 | N89: 80.4 | O89: 7.68 | P89: 22.2 | Q89: 8.5 | R89: 7.31 | S89: =YEAR(A89) -> 2007 | U89: =G89*About!$B$27 -> 7.21752 | V89: =H89*About!$B$27 -> 6.46051
A90: 39629 | B90: 7.97 | C90: 8.7 | D90: 8.57 | E90: 10.03 | F90: 8.58 | G90: 8.62 | H90: 7.69 | J90: 9.18 | K90: 13.89 | L90: 97.5 | M90: 12.23 | N90: 79.7 | O90: 9.65 | P90: 20.4 | Q90: 11.75 | R90: 9.26 | S90: =YEAR(A90) -> 2008 | U90: =G90*About!$B$27 -> 8.93894 | V90: =H90*About!$B$27 -> 7.97453
A91: 39994 | B91: 3.67 | C91: 4.19 | D91: 4.13 | E91: 4.59 | F91: 4.47 | G91: 4.34 | H91: 8.4 | J91: 6.48 | K91: 12.14 | L91: 97.4 | M91: 10.06 | N91: 77.8 | O91: 5.33 | P91: 18.8 | Q91: 8.13 | R91: 4.93 | S91: =YEAR(A91) -> 2009 | U91: =G91*About!$B$27 -> 4.50058 | V91: =H91*About!$B$27 -> 8.7108
A92: 40359 | B92: 4.48 | C92: 4.52 | D92: 4.46 | E92: 4.94 | F92: 5.02 | G92: 4.75 | H92: 9.53 | J92: 6.18 | K92: 11.39 | L92: 97.4 | M92: 9.47 | N92: 77.5 | O92: 5.49 | P92: 18 | Q92: 6.25 | R92: 5.27 | S92: =YEAR(A92) -> 2010 | U92: =G92*About!$B$27 -> 4.92575 | V92: =H92*About!$B$27 -> 9.88261
A93: 40724 | B93: 3.95 | C93: 4.24 | D93: 4.09 | E93: 5.63 | F93: 4.64 | G93: 4.35 | H93: 10.54 | J93: 5.63 | K93: 11.03 | L93: 96.3 | M93: 8.91 | N93: 67.3 | O93: 5.13 | P93: 16.3 | Q93: 7.48 | R93: 4.89 | S93: =YEAR(A93) -> 2011 | U93: =G93*About!$B$27 -> 4.51095 | V93: =H93*About!$B$27 -> 10.92998
A94: 41090 | B94: 2.66 | C94: 2.88 | D94: 2.79 | E94: 4.27 | F94: 3.25 | G94: 3.08 | H94: 12.82 | J94: 4.73 | K94: 10.65 | L94: 95.8 | M94: 8.1 | N94: 65.2 | O94: 3.88 | P94: 16.2 | Q94: 8.04 | R94: 3.54 | S94: =YEAR(A94) -> 2012 | U94: =G94*About!$B$27 -> 3.19396 | V94: =H94*About!$B$27 -> 13.29434
A95: 41455 | C95: 3.83 | D95: 3.73 | E95: 6.8 | F95: 4.08 | G95: 4.06 | H95: 13.36 | J95: 4.88 | K95: 10.32 | L95: 95.7 | M95: 8.08 | N95: 65.8 | O95: 4.64 | P95: 16.6 | R95: 4.49 | S95: =YEAR(A95) -> 2013 | U95: =G95*About!$B$27 -> 4.21022 | V95: =H95*About!$B$27 -> 13.85432
A96: 41820 | C96: 5.3 | D96: 5.21 | E96: 8.85 | F96: 5.51 | G96: 5.4 | H96: 15.66 | J96: 5.71 | K96: 10.97 | L96: 95.5 | M96: 8.9 | N96: 65.8 | O96: 5.62 | P96: 15.9 | R96: 5.19 | S96: =YEAR(A96) -> 2014 | U96: =G96*About!$B$27 -> 5.5998 | V96: =H96*About!$B$27 -> 16.23942
A97: 42185 | C97: 2.99 | D97: 2.84 | E97: 7.37 | F97: 3.07 | G97: 2.95 | H97: 10.92 | J97: 4.26 | K97: 10.38 | L97: 95.6 | M97: 7.91 | N97: 65.7 | O97: 3.93 | P97: 14.8 | R97: 3.38 | S97: =YEAR(A97) -> 2015 | U97: =G97*About!$B$27 -> 3.05915 | V97: =H97*About!$B$27 -> 11.32404
A98: 42551 | C98: 2.24 | D98: 2.18 | E98: 4.07 | F98: 2.79 | G98: 2.63 | H98: 4.71 | J98: 3.71 | K98: 10.05 | L98: 95.8 | M98: 7.28 | N98: 64.8 | O98: 3.51 | P98: 14.9 | R98: 2.99 | S98: =YEAR(A98) -> 2016 | U98: =G98*About!$B$27 -> 2.72731 | V98: =H98*About!$B$27 -> 4.88427
A99: 42916 | C99: 2.6 | D99: 2.55 | E99: 4.58 | F99: 3.54 | G99: 3.2 | H99: 4.69 | J99: 4.16 | K99: 10.91 | L99: 95.9 | M99: 7.88 | N99: 65.4 | O99: 4.08 | P99: 14.8 | R99: 3.51 | S99: =YEAR(A99) -> 2017 | U99: =G99*About!$B$27 -> 3.3184 | V99: =H99*About!$B$27 -> 4.86353
A100: 43281 | C100: 2.69 | D100: 2.58 | E100: 6.56 | F100: 3.89 | G100: 3.34 | H100: 5.2 | J100: 4.23 | K100: 10.5 | L100: 96 | M100: 7.79 | N100: 65.8 | O100: 4.19 | P100: 14.5 | R100: 3.68 | S100: =YEAR(A100) -> 2018 | U100: =G100*About!$B$27 -> 3.46358 | V100: =H100*About!$B$27 -> 5.3924
A101: 43646 | C101: 2.55 | D101: 2.46 | E101: 7.44 | F101: 3.64 | G101: 2.64 | H101: 5.21 | J101: 3.81 | K101: 10.51 | L101: 96.2 | M101: 7.61 | N101: 65.5 | O101: 3.9 | P101: 13 | R101: 2.99 | S101: =YEAR(A101) -> 2019 | U101: =G101*About!$B$27 -> 2.73768 | V101: =H101*About!$B$27 -> 5.40277
A102: 44012 | C102: 2.07 | D102: 2.02 | E102: 4.6 | F102: 3.7 | G102: 2.1 | H102: 5.64 | J102: 3.43 | K102: 10.78 | L102: 96.3 | M102: 7.49 | N102: 64.6 | O102: 3.32 | P102: 13.2 | R102: 2.48 | S102: =YEAR(A102) -> 2020 | U102: =G102*About!$B$27 -> 2.1777 | V102: =H102*About!$B$27 -> 5.84868
A103: 44377 | C103: 3.78 | D103: 3.72 | E103: 12.21 | F103: 6.38 | G103: 4.94 | H103: 7.62 | J103: 6.11 | K103: 12.24 | L103: 96.6 | M103: 8.78 | N103: 65.1 | O103: 5.5 | P103: 13.4 | R103: 5.16 | S103: =YEAR(A103) -> 2021 | U103: =G103*About!$B$27 -> 5.12278 | V103: =H103*About!$B$27 -> 7.90194

Sheet NG Calcs
A1: Historical Monthly Consumption Average
A2: 1 | B2: {=SUMPRODUCT(IF('Historical Monthly Gas Cons'!$C$4:$C$257='NG Calcs'!A2,IF('Historical Monthly Gas Cons'!$D$4:$D$257>2015,'Historical Monthly Gas Cons'!$B$4:$B$257))/SUMPRODUCT(IF('Historical Monthly Gas Cons'!$D$4:$D$257>2015,'Historical Monthly Gas Cons'!$B$4:$B$257)))} -> 0.12704635
A3: 2 | B3: {=SUMPRODUCT(IF('Historical Monthly Gas Cons'!$C$4:$C$257='NG Calcs'!A3,IF('Historical Monthly Gas Cons'!$D$4:$D$257>2015,'Historical Monthly Gas Cons'!$B$4:$B$257))/SUMPRODUCT(IF('Historical Monthly Gas Cons'!$D$4:$D$257>2015,'Historical Monthly Gas Cons'!$B$4:$B$257)))} -> 0.10957724
A4: 3 | B4: {=SUMPRODUCT(IF('Historical Monthly Gas Cons'!$C$4:$C$257='NG Calcs'!A4,IF('Historical Monthly Gas Cons'!$D$4:$D$257>2015,'Historical Monthly Gas Cons'!$B$4:$B$257))/SUMPRODUCT(IF('Historical Monthly Gas Cons'!$D$4:$D$257>2015,'Historical Monthly Gas Cons'!$B$4:$B$257)))} -> 0.08724036
A5: 4 | B5: {=SUMPRODUCT(IF('Historical Monthly Gas Cons'!$C$4:$C$257='NG Calcs'!A5,IF('Historical Monthly Gas Cons'!$D$4:$D$257>2015,'Historical Monthly Gas Cons'!$B$4:$B$257))/SUMPRODUCT(IF('Historical Monthly Gas Cons'!$D$4:$D$257>2015,'Historical Monthly Gas Cons'!$B$4:$B$257)))} -> 0.070786697
A6: 5 | B6: {=SUMPRODUCT(IF('Historical Monthly Gas Cons'!$C$4:$C$257='NG Calcs'!A6,IF('Historical Monthly Gas Cons'!$D$4:$D$257>2015,'Historical Monthly Gas Cons'!$B$4:$B$257))/SUMPRODUCT(IF('Historical Monthly Gas Cons'!$D$4:$D$257>2015,'Historical Monthly Gas Cons'!$B$4:$B$257)))} -> 0.065746454
A7: 6 | B7: {=SUMPRODUCT(IF('Historical Monthly Gas Cons'!$C$4:$C$257='NG Calcs'!A7,IF('Historical Monthly Gas Cons'!$D$4:$D$257>2015,'Historical Monthly Gas Cons'!$B$4:$B$257))/SUMPRODUCT(IF('Historical Monthly Gas Cons'!$D$4:$D$257>2015,'Historical Monthly Gas Cons'!$B$4:$B$257)))} -> 0.067228772
A8: 7 | B8: {=SUMPRODUCT(IF('Historical Monthly Gas Cons'!$C$4:$C$257='NG Calcs'!A8,IF('Historical Monthly Gas Cons'!$D$4:$D$257>2015,'Historical Monthly Gas Cons'!$B$4:$B$257))/SUMPRODUCT(IF('Historical Monthly Gas Cons'!$D$4:$D$257>2015,'Historical Monthly Gas Cons'!$B$4:$B$257)))} -> 0.075765383
A9: 8 | B9: {=SUMPRODUCT(IF('Historical Monthly Gas Cons'!$C$4:$C$257='NG Calcs'!A9,IF('Historical Monthly Gas Cons'!$D$4:$D$257>2015,'Historical Monthly Gas Cons'!$B$4:$B$257))/SUMPRODUCT(IF('Historical Monthly Gas Cons'!$D$4:$D$257>2015,'Historical Monthly Gas Cons'!$B$4:$B$257)))} -> 0.075220401
A10: 9 | B10: {=SUMPRODUCT(IF('Historical Monthly Gas Cons'!$C$4:$C$257='NG Calcs'!A10,IF('Historical Monthly Gas Cons'!$D$4:$D$257>2015,'Historical Monthly Gas Cons'!$B$4:$B$257))/SUMPRODUCT(IF('Historical Monthly Gas Cons'!$D$4:$D$257>2015,'Historical Monthly Gas Cons'!$B$4:$B$257)))} -> 0.067544195
A11: 10 | B11: {=SUMPRODUCT(IF('Historical Monthly Gas Cons'!$C$4:$C$257='NG Calcs'!A11,IF('Historical Monthly Gas Cons'!$D$4:$D$257>2015,'Historical Monthly Gas Cons'!$B$4:$B$257))/SUMPRODUCT(IF('Historical Monthly Gas Cons'!$D$4:$D$257>2015,'Historical Monthly Gas Cons'!$B$4:$B$257)))} -> 0.070774681
A12: 11 | B12: {=SUMPRODUCT(IF('Historical Monthly Gas Cons'!$C$4:$C$257='NG Calcs'!A12,IF('Historical Monthly Gas Cons'!$D$4:$D$257>2015,'Historical Monthly Gas Cons'!$B$4:$B$257))/SUMPRODUCT(IF('Historical Monthly Gas Cons'!$D$4:$D$257>2015,'Historical Monthly Gas Cons'!$B$4:$B$257)))} -> 0.082458275
A13: 12 | B13: {=SUMPRODUCT(IF('Historical Monthly Gas Cons'!$C$4:$C$257='NG Calcs'!A13,IF('Historical Monthly Gas Cons'!$D$4:$D$257>2015,'Historical Monthly Gas Cons'!$B$4:$B$257))/SUMPRODUCT(IF('Historical Monthly Gas Cons'!$D$4:$D$257>2015,'Historical Monthly Gas Cons'!$B$4:$B$257)))} -> 0.1006112
A15: from variable fuels/BFPaT:
A16: Future Prices | B16: 2021 | C16: 2022 | D16: 2023 | E16: 2024 | F16: 2025
A17: 1 | B17: 2.71 | C17: 4.38 | D17: 8.983 | E17: 5.628 | F17: 4.977
A18: 2 | B18: 5.35 | C18: 4.69 | D18: 8.625 | E18: 5.432 | F18: 4.844
A19: 3 | B19: 2.62 | C19: 4.9 | D19: 7.169 | E19: 4.996 | F19: 4.522
A20: 4 | B20: 2.66 | C20: 6.6 | D20: 5.173 | E20: 4.191 | F20: 3.932
A21: 5 | B21: 2.91 | C21: 7.365 | D21: 4.967 | E21: 4.114 | F21: 3.892
A22: 6 | B22: 3.26 | C22: 8.13 | D22: 5.021 | E22: 4.172 | F22: 3.952
A23: 7 | B23: 3.84 | C23: 8.895 | D23: 5.06 | E23: 4.229 | F23: 4.006
A24: 8 | B24: 4.07 | C24: 8.88 | D24: 5.042 | E24: 4.24 | F24: 4.031
A25: 9 | B25: 5.16 | C25: 8.837 | D25: 5.008 | E25: 4.222 | F25: 4.021
A26: 10 | B26: 5.51 | C26: 8.802 | D26: 5.069 | E26: 4.278 | F26: 4.088
A27: 11 | B27: 5.05 | C27: 8.834 | D27: 5.219 | E27: 4.455 | F27: 4.274
A28: 12 | B28: 3.76 | C28: 8.905 | D28: 5.492 | E28: 4.811 | F28: 4.641
A31: Annual Average | B31: 2021 | C31: 2022 | D31: 2023 | E31: 2024 | F31: 2025
B32: =SUMPRODUCT(B17:B28,$B$2:$B$13) -> 3.8881792 | C32: =SUMPRODUCT(C17:C28,$B$2:$B$13) -> 7.1819589 | D32: =SUMPRODUCT(D17:D28,$B$2:$B$13) -> 6.1846438 | E32: =SUMPRODUCT(E17:E28,$B$2:$B$13) -> 4.6724037 | F32: =SUMPRODUCT(F17:F28,$B$2:$B$13) -> 4.3445242

Sheet Natural Gas Prices
A1: Historical Data
B2: Historical | C2: Pipeline | D2: LNG | E2: Henry Hub Prices ($/mmbtu) | F2: Pipeline multiplier | G2: LNG multiplier
B3: 2001 | C3: ='NG Sector Price Historicals'!U83 -> 4.29318 | D3: ='NG Sector Price Historicals'!V83 -> 4.5628 | E3: ='EIA Henry Hub Nat Gas Spot'!B8 -> 3.96 | F3: =C3/E3 -> 1.0841364 | G3: =D3/E3 -> 1.1522222
B4: 2002 | C4: ='NG Sector Price Historicals'!U84 -> 3.44284 | D4: ='NG Sector Price Historicals'!V84 -> 4.23096 | E4: ='EIA Henry Hub Nat Gas Spot'!B9 -> 3.38 | F4: =C4/E4 -> 1.0185917 | G4: =D4/E4 -> 1.2517633
B5: 2003 | C5: ='NG Sector Price Historicals'!U85 -> 5.86942 | D5: ='NG Sector Price Historicals'!V85 -> 4.63539 | E5: ='EIA Henry Hub Nat Gas Spot'!B10 -> 5.47 | F5: =C5/E5 -> 1.0730201 | G5: =D5/E5 -> 0.84742048
B6: 2004 | C6: ='NG Sector Price Historicals'!U86 -> 6.40866 | D6: ='NG Sector Price Historicals'!V86 -> 5.14352 | E6: ='EIA Henry Hub Nat Gas Spot'!B11 -> 5.89 | F6: =C6/E6 -> 1.0880577 | G6: =D6/E6 -> 0.87326316
B7: 2005 | C7: ='NG Sector Price Historicals'!U87 -> 8.05749 | D7: ='NG Sector Price Historicals'!V87 -> 6.00423 | E7: ='EIA Henry Hub Nat Gas Spot'!B12 -> 8.69 | F7: =C7/E7 -> 0.92721404 | G7: =D7/E7 -> 0.69093556
B8: 2006 | C8: ='NG Sector Price Historicals'!U88 -> 7.1553 | D8: ='NG Sector Price Historicals'!V88 -> 6.24274 | E8: ='EIA Henry Hub Nat Gas Spot'!B13 -> 6.73 | F8: =C8/E8 -> 1.0631947 | G8: =D8/E8 -> 0.92759881
B9: 2007 | C9: ='NG Sector Price Historicals'!U89 -> 7.21752 | D9: ='NG Sector Price Historicals'!V89 -> 6.46051 | E9: ='EIA Henry Hub Nat Gas Spot'!B14 -> 6.97 | F9: =C9/E9 -> 1.0355122 | G9: =D9/E9 -> 0.92690244
B10: 2008 | C10: ='NG Sector Price Historicals'!U90 -> 8.93894 | D10: ='NG Sector Price Historicals'!V90 -> 7.97453 | E10: ='EIA Henry Hub Nat Gas Spot'!B15 -> 8.86 | F10: =C10/E10 -> 1.0089097 | G10: =D10/E10 -> 0.90005982
B11: 2009 | C11: ='NG Sector Price Historicals'!U91 -> 4.50058 | D11: ='NG Sector Price Historicals'!V91 -> 8.7108 | E11: ='EIA Henry Hub Nat Gas Spot'!B16 -> 3.94 | F11: =C11/E11 -> 1.1422792 | G11: =D11/E11 -> 2.2108629
B12: 2010 | C12: ='NG Sector Price Historicals'!U92 -> 4.92575 | D12: ='NG Sector Price Historicals'!V92 -> 9.88261 | E12: ='EIA Henry Hub Nat Gas Spot'!B17 -> 4.37 | F12: =C12/E12 -> 1.1271739 | G12: =D12/E12 -> 2.2614668
B13: 2011 | C13: ='NG Sector Price Historicals'!U93 -> 4.51095 | D13: ='NG Sector Price Historicals'!V93 -> 10.92998 | E13: ='EIA Henry Hub Nat Gas Spot'!B18 -> 4 | F13: =C13/E13 -> 1.1277375 | G13: =D13/E13 -> 2.732495
B14: 2012 | C14: ='NG Sector Price Historicals'!U94 -> 3.19396 | D14: ='NG Sector Price Historicals'!V94 -> 13.29434 | E14: ='EIA Henry Hub Nat Gas Spot'!B19 -> 2.75 | F14: =C14/E14 -> 1.16144 | G14: =D14/E14 -> 4.8343055
... B23: 2021 | C23: ='NG Sector Price Historicals'!U103 -> 5.12278 | D23: ='NG Sector Price Historicals'!V103 -> 7.90194 | E23: ='EIA Henry Hub Nat Gas Spot'!B28 -> 3.89 | F23: =C23/E23 -> 1.31691 | G23: =D23/E23 -> 2.031347
A24: Average | E24: =AVERAGE(E3:E23) -> 4.422381 | F24: =AVERAGE(F3:F23) -> 1.1040842 | G24: =AVERAGE(G3:G23) -> 2.0791171
A26: Forecast ($) | C26: Pipeline | D26: LNG
B27: 2022 | C27: =$E27*F$24 -> 7.9294874 | D27: =$E27*G$24 -> 14.932134 | E27: {=TRANSPOSE('NG Calcs'!C32:F32)} -> 7.1819589 | G27: futures prices
B28: 2023 | C28: =$E28*F$24 -> 6.8283675 | D28: =$E28*G$24 -> 12.858599 | E28: 6.1846438 | G28: transition back to AEO22 ref
B29: 2024 | C29: =$E29*F$24 -> 5.1587272 | D29: =$E29*G$24 -> 9.7144745 | E29: 4.6724037 | G29: AEO22 ref
B30: 2025 | C30: =$E30*F$24 -> 4.7967206 | D30: =$E30*G$24 -> 9.0327746 | E30: 4.3445242
B31: 2026 | C31: =$E31*F$24 -> 4.5857183 | D31: =$E31*G$24 -> 8.6354332 | E31: =E30-(($E$30-$E$35)/5) -> 4.1534136
B32: 2027 | C32: =$E32*F$24 -> 4.3747161 | D32: =$E32*G$24 -> 8.2380918 | E32: =E31-(($E$30-$E$35)/5) -> 3.9623029
B33: 2028 | C33: =$E33*F$24 -> 4.1637139 | D33: =$E33*G$24 -> 7.8407504 | E33: =E32-(($E$30-$E$35)/5) -> 3.7711923
B34: 2029 | C34: =$E34*F$24 -> 3.9527116 | D34: =$E34*G$24 -> 7.443409 | E34: =E33-(($E$30-$E$35)/5) -> 3.5800816
B35: 2030 | C35: =$E35*F$24 -> 3.7417094 | D35: =$E35*G$24 -> 7.0460676 | E35: {=TRANSPOSE('AEO22 Table13'!O29:AI29)} -> 3.388971
B36: 2031 | C36: =$E36*F$24 -> 3.8140015 | D36: =$E36*G$24 -> 7.1822019 | E36: 3.454448
B37: 2032 | C37: =$E37*F$24 -> 3.8553053 | D37: =$E37*G$24 -> 7.2599817 | E37: 3.491858
B38: 2033 | C38: =$E38*F$24 -> 3.9672948 | D38: =$E38*G$24 -> 7.4708707 | E38: 3.59329
B39: 2034 | C39: =$E39*F$24 -> 3.9682476 | D39: =$E39*G$24 -> 7.472665 | E39: 3.594153
B40: 2035 | C40: =$E40*F$24 -> 3.8911946 | D40: =$E40*G$24 -> 7.3275655 | E40: 3.524364
B41: 2036 | C41: =$E41*F$24 -> 3.8480702 | D41: =$E41*G$24 -> 7.2463573 | E41: 3.485305
B42: 2037 | C42: =$E42*F$24 -> 3.8498644 | D42: =$E42*G$24 -> 7.2497358 | E42: 3.48693
B43: 2038 | C43: =$E43*F$24 -> 3.8844664 | D43: =$E43*G$24 -> 7.3148954 | E43: 3.51827
B44: 2039 | C44: =$E44*F$24 -> 3.9146553 | D44: =$E44*G$24 -> 7.3717447 | E44: 3.545613
B45: 2040 | C45: =$E45*F$24 -> 3.9500357 | D45: =$E45*G$24 -> 7.43837 | E45: 3.577658
B46: 2041 | C46: =$E46*F$24 -> 4.0129597 | D46: =$E46*G$24 -> 7.556863 | E46: 3.63465
B47: 2042 | C47: =$E47*F$24 -> 4.0321476 | D47: =$E47*G$24 -> 7.592996 | E47: 3.652029
... B55: 2050 | C55: =$E55*F$24 -> 3.7643884 | D55: =$E55*G$24 -> 7.0887747 | E55: 3.409512
A57: Forecasted Volume (Tcf) | C57: Pipeline | D57: LNG | E57: % pipeline | F57: % lng
B58: 2020 | C58: =SUM('AEO21 Table60'!C23:D23) -> 2.946373 | D58: ='AEO21 Table60'!E23 -> 2.31418 | E58: =C58/SUM(C58:D58) -> 0.56008807 | F58: =D58/SUM(C58:D58) -> 0.43991193
B59: 2021 | C59: =SUM('AEO22 Table60'!C23:D23) -> 3.169595 | D59: ='AEO22 Table60'!E23 -> 3.57936 | E59: =C59/SUM(C59:D59) -> 0.46964234 | F59: =D59/SUM(C59:D59) -> 0.53035766
B60: 2022 | C60: =SUM('AEO22 Table60'!C24:D24) -> 3.315312 | D60: ='AEO22 Table60'!E24 -> 4.1955 | E60: =C60/SUM(C60:D60) -> 0.44140527 | F60: =D60/SUM(C60:D60) -> 0.55859473
B61: 2023 | C61: =SUM('AEO22 Table60'!C25:D25) -> 3.276408 | D61: ='AEO22 Table60'!E25 -> 4.436575 | E61: =C61/SUM(C61:D61) -> 0.42479129 | F61: =D61/SUM(C61:D61) -> 0.57520871
B62: 2024 | C62: =SUM('AEO22 Table60'!C26:D26) -> 3.314269 | D62: ='AEO22 Table60'!E26 -> 4.481076 | E62: =C62/SUM(C62:D62) -> 0.42516002 | F62: =D62/SUM(C62:D62) -> 0.57483998
B63: 2025 | C63: =SUM('AEO22 Table60'!C27:D27) -> 3.366414 | D63: ='AEO22 Table60'!E27 -> 4.651001 | E63: =C63/SUM(C63:D63) -> 0.41988771 | F63: =D63/SUM(C63:D63) -> 0.58011229
B64: 2026 | C64: =SUM('AEO22 Table60'!C28:D28) -> 3.3658 | D64: ='AEO22 Table60'!E28 -> 4.663058 | E64: =C64/SUM(C64:D64) -> 0.41921279 | F64: =D64/SUM(C64:D64) -> 0.58078721
B65: 2027 | C65: =SUM('AEO22 Table60'!C29:D29) -> 3.392482 | D65: ='AEO22 Table60'!E29 -> 4.763058 | E65: =C65/SUM(C65:D65) -> 0.4159727 | F65: =D65/SUM(C65:D65) -> 0.5840273
B66: 2028 | C66: =SUM('AEO22 Table60'!C30:D30) -> 3.472591 | D66: ='AEO22 Table60'!E30 -> 4.975833 | E66: =C66/SUM(C66:D66) -> 0.41103418 | F66: =D66/SUM(C66:D66) -> 0.58896582
B67: 2029 | C67: =SUM('AEO22 Table60'!C31:D31) -> 3.539924 | D67: ='AEO22 Table60'!E31 -> 5.163058 | E67: =C67/SUM(C67:D67) -> 0.4067484 | F67: =D67/SUM(C67:D67) -> 0.5932516
B68: 2030 | C68: =SUM('AEO22 Table60'!C32:D32) -> 3.563498 | D68: ='AEO22 Table60'!E32 -> 5.363058 | E68: =C68/SUM(C68:D68) -> 0.39920189 | F68: =D68/SUM(C68:D68) -> 0.60079811
B69: 2031 | C69: =SUM('AEO22 Table60'!C33:D33) -> 3.63362 | D69: ='AEO22 Table60'!E33 -> 5.563058 | E69: =C69/SUM(C69:D69) -> 0.39510136 | F69: =D69/SUM(C69:D69) -> 0.60489864
B70: 2032 | C70: =SUM('AEO22 Table60'!C34:D34) -> 3.673493 | D70: ='AEO22 Table60'!E34 -> 5.775833 | E70: =C70/SUM(C70:D70) -> 0.38875715 | F70: =D70/SUM(C70:D70) -> 0.61124285
... B88: 2050 | C88: =SUM('AEO22 Table60'!C52:D52) -> 3.884898 | D88: ='AEO22 Table60'!E52 -> 5.863058 | E88: =C88/SUM(C88:D88) -> 0.39853463 | F88: =D88/SUM(C88:D88) -> 0.60146537
A90: Prices ( | B90: Total Gas Prices ($2020/mmbtu for 2020, then $2021/mmbtu) | D90: $2012/btu
B91: 2020 | C91: =E58*C22+F58*D22 -> 3.7926079 | D91: =C91*About!$B$28/10^6 -> 3.3640432e-06
B92: 2021 | C92: =E59*C23+F59*D23 -> 6.5967288 | D92: =C92*About!$B$29/10^6 -> 5.5874293e-06
B93: 2022 | C93: =E60*C27+D27*F60 -> 11.841129 | D93: =C93*About!$B$29/10^6 -> 1.0029436e-05
B94: 2023 | C94: =E61*C28+D28*F61 -> 10.297009 | D94: =C94*About!$B$29/10^6 -> 8.7215666e-06
B95: 2024 | C95: =E62*C29+D29*F62 -> 7.7775529 | D95: =C95*About!$B$29/10^6 -> 6.5875873e-06
B96: 2025 | C96: =E63*C30+D30*F63 -> 7.2541076 | D96: =C96*About!$B$29/10^6 -> 6.1442291e-06
B97: 2026 | C97: =E64*C31+D31*F64 -> 6.9377409 | D97: =C97*About!$B$29/10^6 -> 5.8762666e-06
B98: 2027 | C98: =E65*C32+D32*F65 -> 6.631033 | D98: =C98*About!$B$29/10^6 -> 5.6164849e-06
B99: 2028 | C99: =E66*C33+D33*F66 -> 6.3293627 | D99: =C99*About!$B$29/10^6 -> 5.3609702e-06
B100: 2029 | C100: =E67*C34+D34*F67 -> 6.0235734 | D100: =C100*About!$B$29/10^6 -> 5.1019667e-06
B101: 2030 | C101: =E68*C35+D35*F68 -> 5.7269616 | D101: =C101*About!$B$29/10^6 -> 4.8507364e-06
B102: 2031 | C102: =E69*C36+D36*F69 -> 5.8514214 | D102: =C102*About!$B$29/10^6 -> 4.9561539e-06
B103: 2032 | C103: =E70*C37+D37*F70 -> 5.9363894 | D103: =C103*About!$B$29/10^6 -> 5.0281218e-06
B104: 2033 | C104: =E71*C38+D38*F71 -> 6.1139178 | D104: =C104*About!$B$29/10^6 -> 5.1784884e-06
... B121: 2050 | C121: =E88*C55+D55*F88 -> 5.7638917 | D121: =C121*About!$B$29/10^6 -> 4.8820162e-06

Sheet Pretax Fuel Prices
B1: 2020 | C1: 2021 | D1: 2022 | E1: 2023 | F1: 2024 | G1: 2025 | H1: 2026 | I1: 2027 | J1: 2028 | K1: 2029 | L1: 2030 | M1: 2031 | N1: 2032 | O1: 2033 | P1: 2034 | Q1: 2035 | R1: 2036 | S1: 2037 | T1: 2038 | U1: 2039 | V1: 2040 | W1: 2041 | X1: 2042 | Y1: 2043 | Z1: 2044 | AA1: 2045 | AB1: 2046 | AC1: 2047 | AD1: 2048 | AE1: 2049 | AF1: 2050 | AG1: 2051 | AH1: 2052 | AI1: 2053 | AJ1: 2054 | AK1: 2055 | AL1: 2056 | AM1: 2057 | AN1: 2058 | AO1: 2059 | AP1: 2060 | AQ1: 2061 | AR1: 2062 | AS1: 2063 | AT1: 2064 | AU1: 2065 | AV1: 2066 | AW1: 2067 | AX1: 2068 | AY1: 2069 | AZ1: 2070
A2: Hard Coal
A3: Year | B3: 2020 | C3: 2021 | D3: 2022 | E3: 2023 | F3: 2024 | G3: 2025 | H3: 2026 | I3: 2027 | J3: 2028 | K3: 2029 | L3: 2030 | M3: 2031 | N3: 2032 | O3: 2033 | P3: 2034 | Q3: 2035 | R3: 2036 | S3: 2037 | T3: 2038 | U3: 2039 | V3: 2040 | W3: 2041 | X3: 2042 | Y3: 2043 | Z3: 2044 | AA3: 2045 | AB3: 2046 | AC3: 2047 | AD3: 2048 | AE3: 2049 | AF3: 2050 | AG3: 2051 | AH3: 2052 | AI3: 2053 | AJ3: 2054 | AK3: 2055 | AL3: 2056 | AM3: 2057 | AN3: 2058 | AO3: 2059 | AP3: 2060 | AQ3: 2061 | AR3: 2062 | AS3: 2063 | AT3: 2064 | AU3: 2065 | AV3: 2066 | AW3: 2067 | AX3: 2068 | AY3: 2069 | AZ3: 2070
A4: Transportation Sector | B4: 0 | C4: 0 | D4: 0 | E4: 0 | F4: 0 | G4: 0 | H4: 0 | I4: 0 | J4: 0 | K4: 0 | L4: 0 | M4: 0 | N4: 0 | O4: 0 | P4: 0 | Q4: 0 | R4: 0 | S4: 0 | T4: 0 | U4: 0 | V4: 0 | W4: 0 | X4: 0 | Y4: 0 | Z4: 0 | AA4: 0 | AB4: 0 | AC4: 0 | AD4: 0 | AE4: 0 | AF4: 0 | AG4: 0 | AH4: 0 | AI4: 0 | AJ4: 0 | AK4: 0 | AL4: 0 | AM4: 0 | AN4: 0 | AO4: 0 | AP4: 0 | AQ4: 0 | AR4: 0 | AS4: 0 | AT4: 0 | AU4: 0 | AV4: 0 | AW4: 0 | AX4: 0 | AY4: 0 | AZ4: 0
A5: Electricity Sector | B5: 1.6291066e-06 | C5: 1.6305051e-06 | D5: 1.6084037e-06 | E5: 1.5947891e-06 | F5: 1.5940766e-06 | G5: 1.5547972e-06 | H5: 1.5291016e-06 | I5: 1.5279777e-06 | J5: 1.5198991e-06 | K5: 1.5256222e-06 | L5: 1.5233389e-06 | M5: 1.5223521e-06 | N5: 1.5135016e-06 | O5: 1.5107213e-06 | P5: 1.5052423e-06 | Q5: 1.4944318e-06 | R5: 1.4823611e-06 | S5: 1.4798375e-06 | T5: 1.4793034e-06 | U5: 1.4772054e-06 | V5: 1.4811532e-06 | W5: 1.4778546e-06 | X5: 1.4693702e-06 | Y5: 1.4604126e-06 | Z5: 1.4562224e-06 | AA5: 1.4537868e-06 | AB5: 1.4515439e-06 | AC5: 1.447184e-06 | AD5: 1.4403616e-06 | AE5: 1.4414086e-06 | AF5: 1.4392608e-06 | AG5: =_xlfn.FORECAST.ETS(AG3,$B$5:$AF$5,$B$3:$AF$3) -> 1.4350353e-06 | AH5: =_xlfn.FORECAST.ETS(AH3,$B$5:$AF$5,$B$3:$AF$3) -> 1.4308144e-06 | AI5: =_xlfn.FORECAST.ETS(AI3,$B$5:$AF$5,$B$3:$AF$3) -> 1.4265936e-06 | AJ5: =_xlfn.FORECAST.ETS(AJ3,$B$5:$AF$5,$B$3:$AF$3) -> 1.4223727e-06 | AK5: =_xlfn.FORECAST.ETS(AK3,$B$5:$AF$5,$B$3:$AF$3) -> 1.4181519e-06 | AL5: =_xlfn.FORECAST.ETS(AL3,$B$5:$AF$5,$B$3:$AF$3) -> 1.413931e-06 | AM5: =_xlfn.FORECAST.ETS(AM3,$B$5:$AF$5,$B$3:$AF$3) -> 1.4097101e-06 | AN5: =_xlfn.FORECAST.ETS(AN3,$B$5:$AF$5,$B$3:$AF$3) -> 1.4054893e-06 | ... AZ5: =_xlfn.FORECAST.ETS(AZ3,$B$5:$AF$5,$B$3:$AF$3) -> 1.354839e-06
A6: Residential Buildings Sector | B6: 0 | C6: 0 | D6: 0 | E6: 0 | F6: 0 | G6: 0 | H6: 0 | I6: 0 | J6: 0 | K6: 0 | L6: 0 | M6: 0 | N6: 0 | O6: 0 | P6: 0 | Q6: 0 | R6: 0 | S6: 0 | T6: 0 | U6: 0 | V6: 0 | W6: 0 | X6: 0 | Y6: 0 | Z6: 0 | AA6: 0 | AB6: 0 | AC6: 0 | AD6: 0 | AE6: 0 | AF6: 0 | AG6: 0 | AH6: 0 | AI6: 0 | AJ6: 0 | AK6: 0 | AL6: 0 | AM6: 0 | AN6: 0 | AO6: 0 | AP6: 0 | AQ6: 0 | AR6: 0 | AS6: 0 | AT6: 0 | AU6: 0 | AV6: 0 | AW6: 0 | AX6: 0 | AY6: 0 | AZ6: 0
A7: Commercial Buildings Sector | B7: 0 | C7: 0 | D7: 0 | E7: 0 | F7: 0 | G7: 0 | H7: 0 | I7: 0 | J7: 0 | K7: 0 | L7: 0 | M7: 0 | N7: 0 | O7: 0 | P7: 0 | Q7: 0 | R7: 0 | S7: 0 | T7: 0 | U7: 0 | V7: 0 | W7: 0 | X7: 0 | Y7: 0 | Z7: 0 | AA7: 0 | AB7: 0 | AC7: 0 | AD7: 0 | AE7: 0 | AF7: 0 | AG7: 0 | AH7: 0 | AI7: 0 | AJ7: 0 | AK7: 0 | AL7: 0 | AM7: 0 | AN7: 0 | AO7: 0 | AP7: 0 | AQ7: 0 | AR7: 0 | AS7: 0 | AT7: 0 | AU7: 0 | AV7: 0 | AW7: 0 | AX7: 0 | AY7: 0 | AZ7: 0
A8: Industry Sector | B8: 2.8308895e-06 | C8: 2.6161745e-06 | D8: 2.4732867e-06 | E8: 2.4145632e-06 | F8: 2.343279e-06 | G8: 2.3026125e-06 | H8: 2.2736442e-06 | I8: 2.2572892e-06 | J8: 2.2564289e-06 | K8: 2.2600211e-06 | L8: 2.2709221e-06 | M8: 2.2801664e-06 | N8: 2.2940978e-06 | O8: 2.3052553e-06 | P8: 2.3164662e-06 | Q8: 2.3263273e-06 | R8: 2.3366029e-06 | S8: 2.3490501e-06 | T8: 2.3621242e-06 | U8: 2.372045e-06 | V8: 2.3830873e-06 | W8: 2.3956625e-06 | X8: 2.4042075e-06 | Y8: 2.415395e-06 | Z8: 2.428085e-06 | AA8: 2.4411162e-06 | AB8: 2.4546342e-06 | AC8: 2.4651949e-06 | AD8: 2.4721521e-06 | AE8: 2.4821589e-06 | AF8: 2.4959149e-06 | AG8: =_xlfn.FORECAST.ETS(AG3,$B$8:$AF$8,$B$3:$AF$3) -> 2.5085984e-06 | AH8: =_xlfn.FORECAST.ETS(AH3,$B$8:$AF$8,$B$3:$AF$3) -> 2.5212904e-06 | AI8: =_xlfn.FORECAST.ETS(AI3,$B$8:$AF$8,$B$3:$AF$3) -> 2.5339824e-06 | AJ8: =_xlfn.FORECAST.ETS(AJ3,$B$8:$AF$8,$B$3:$AF$3) -> 2.5466743e-06 | AK8: =_xlfn.FORECAST.ETS(AK3,$B$8:$AF$8,$B$3:$AF$3) -> 2.5593663e-06 | AL8: =_xlfn.FORECAST.ETS(AL3,$B$8:$AF$8,$B$3:$AF$3) -> 2.5720583e-06 | AM8: =_xlfn.FORECAST.ETS(AM3,$B$8:$AF$8,$B$3:$AF$3) -> 2.5847503e-06 | AN8: =_xlfn.FORECAST.ETS(AN3,$B$8:$AF$8,$B$3:$AF$3) -> 2.5974423e-06 | ... AZ8: =_xlfn.FORECAST.ETS(AZ3,$B$8:$AF$8,$B$3:$AF$3) -> 2.749746e-06
A9: District Heating Sector | B9: 1.6291066e-06 | C9: 1.6305051e-06 | D9: 1.6084037e-06 | E9: 1.5947891e-06 | F9: 1.5940766e-06 | G9: 1.5547972e-06 | H9: 1.5291016e-06 | I9: 1.5279777e-06 | J9: 1.5198991e-06 | K9: 1.5256222e-06 | L9: 1.5233389e-06 | M9: 1.5223521e-06 | N9: 1.5135016e-06 | O9: 1.5107213e-06 | P9: 1.5052423e-06 | Q9: 1.4944318e-06 | R9: 1.4823611e-06 | S9: 1.4798375e-06 | T9: 1.4793034e-06 | U9: 1.4772054e-06 | V9: 1.4811532e-06 | W9: 1.4778546e-06 | X9: 1.4693702e-06 | Y9: 1.4604126e-06 | Z9: 1.4562224e-06 | AA9: 1.4537868e-06 | AB9: 1.4515439e-06 | AC9: 1.447184e-06 | AD9: 1.4403616e-06 | AE9: 1.4414086e-06 | AF9: 1.4392608e-06 | AG9: =_xlfn.FORECAST.ETS(AG3,$B$9:$AF$9,$B$3:$AF$3) -> 1.4350353e-06 | AH9: =_xlfn.FORECAST.ETS(AH3,$B$9:$AF$9,$B$3:$AF$3) -> 1.4308144e-06 | AI9: =_xlfn.FORECAST.ETS(AI3,$B$9:$AF$9,$B$3:$AF$3) -> 1.4265936e-06 | AJ9: =_xlfn.FORECAST.ETS(AJ3,$B$9:$AF$9,$B$3:$AF$3) -> 1.4223727e-06 | AK9: =_xlfn.FORECAST.ETS(AK3,$B$9:$AF$9,$B$3:$AF$3) -> 1.4181519e-06 | AL9: =_xlfn.FORECAST.ETS(AL3,$B$9:$AF$9,$B$3:$AF$3) -> 1.413931e-06 | AM9: =_xlfn.FORECAST.ETS(AM3,$B$9:$AF$9,$B$3:$AF$3) -> 1.4097101e-06 | AN9: =_xlfn.FORECAST.ETS(AN3,$B$9:$AF$9,$B$3:$AF$3) -> 1.4054893e-06 | ... AZ9: =_xlfn.FORECAST.ETS(AZ3,$B$9:$AF$9,$B$3:$AF$3) -> 1.354839e-06
A10: LULUCF Sector | B10: 0 | C10: 0 | D10: 0 | E10: 0 | F10: 0 | G10: 0 | H10: 0 | I10: 0 | J10: 0 | K10: 0 | L10: 0 | M10: 0 | N10: 0 | O10: 0 | P10: 0 | Q10: 0 | R10: 0 | S10: 0 | T10: 0 | U10: 0 | V10: 0 | W10: 0 | X10: 0 | Y10: 0 | Z10: 0 | AA10: 0 | AB10: 0 | AC10: 0 | AD10: 0 | AE10: 0 | AF10: 0 | AG10: 0 | AH10: 0 | AI10: 0 | AJ10: 0 | AK10: 0 | AL10: 0 | AM10: 0 | AN10: 0 | AO10: 0 | AP10: 0 | AQ10: 0 | AR10: 0 | AS10: 0 | AT10: 0 | AU10: 0 | AV10: 0 | AW10: 0 | AX10: 0 | AY10: 0 | AZ10: 0
A11: Geoengineering Sector | B11: 2.8308895e-06 | C11: 2.6161745e-06 | D11: 2.4732867e-06 | E11: 2.4145632e-06 | F11: 2.343279e-06 | G11: 2.3026125e-06 | H11: 2.2736442e-06 | I11: 2.2572892e-06 | J11: 2.2564289e-06 | K11: 2.2600211e-06 | L11: 2.2709221e-06 | M11: 2.2801664e-06 | N11: 2.2940978e-06 | O11: 2.3052553e-06 | P11: 2.3164662e-06 | Q11: 2.3263273e-06 | R11: 2.3366029e-06 | S11: 2.3490501e-06 | T11: 2.3621242e-06 | U11: 2.372045e-06 | V11: 2.3830873e-06 | W11: 2.3956625e-06 | X11: 2.4042075e-06 | Y11: 2.415395e-06 | Z11: 2.428085e-06 | AA11: 2.4411162e-06 | AB11: 2.4546342e-06 | AC11: 2.4651949e-06 | AD11: 2.4721521e-06 | AE11: 2.4821589e-06 | AF11: 2.4959149e-06 | AG11: =_xlfn.FORECAST.ETS(AG3,$B$11:$AF$11,$B$3:$AF$3) -> 2.5085984e-06 | AH11: =_xlfn.FORECAST.ETS(AH3,$B$11:$AF$11,$B$3:$AF$3) -> 2.5212904e-06 | AI11: =_xlfn.FORECAST.ETS(AI3,$B$11:$AF$11,$B$3:$AF$3) -> 2.5339824e-06 | AJ11: =_xlfn.FORECAST.ETS(AJ3,$B$11:$AF$11,$B$3:$AF$3) -> 2.5466743e-06 | AK11: =_xlfn.FORECAST.ETS(AK3,$B$11:$AF$11,$B$3:$AF$3) -> 2.5593663e-06 | AL11: =_xlfn.FORECAST.ETS(AL3,$B$11:$AF$11,$B$3:$AF$3) -> 2.5720583e-06 | AM11: =_xlfn.FORECAST.ETS(AM3,$B$11:$AF$11,$B$3:$AF$3) -> 2.5847503e-06 | AN11: =_xlfn.FORECAST.ETS(AN3,$B$11:$AF$11,$B$3:$AF$3) -> 2.5974423e-06 | ... AZ11: =_xlfn.FORECAST.ETS(AZ3,$B$11:$AF$11,$B$3:$AF$3) -> 2.749746e-06
A12: Natural Gas
A13: Year | B13: 2020 | C13: 2021 | D13: 2022 | E13: 2023 | F13: 2024 | G13: 2025 | H13: 2026 | I13: 2027 | J13: 2028 | K13: 2029 | L13: 2030 | M13: 2031 | N13: 2032 | O13: 2033 | P13: 2034 | Q13: 2035 | R13: 2036 | S13: 2037 | T13: 2038 | U13: 2039 | V13: 2040 | W13: 2041 | X13: 2042 | Y13: 2043 | Z13: 2044 | AA13: 2045 | AB13: 2046 | AC13: 2047 | AD13: 2048 | AE13: 2049 | AF13: 2050 | AG13: 2051 | AH13: 2052 | AI13: 2053 | AJ13: 2054 | AK13: 2055 | AL13: 2056 | AM13: 2057 | AN13: 2058 | AO13: 2059 | AP13: 2060 | AQ13: 2061 | AR13: 2062 | AS13: 2063 | AT13: 2064 | AU13: 2065 | AV13: 2066 | AW13: 2067 | AX13: 2068 | AY13: 2069 | AZ13: 2070
A14: Transportation Sector | B14: 1.0759342e-05 | C14: 1.1803274e-05 | D14: 2.180214e-05 | E14: 1.8774609e-05 | F14: 1.418393e-05 | G14: 1.3188592e-05 | H14: 1.26601e-05 | I14: 1.2131608e-05 | J14: 1.1603116e-05 | K14: 1.1074624e-05 | L14: 1.0546132e-05 | M14: 1.0323735e-05 | N14: 1.0259292e-05 | O14: 1.0155612e-05 | P14: 1.0040577e-05 | Q14: 9.9308645e-06 | R14: 9.8287918e-06 | S14: 9.7313732e-06 | T14: 9.6877891e-06 | U14: 9.6109136e-06 | V14: 9.5745151e-06 | W14: 9.5137405e-06 | X14: 9.4628368e-06 | Y14: 9.4110312e-06 | Z14: 9.3715943e-06 | AA14: 9.3467534e-06 | AB14: 9.3312016e-06 | AC14: 9.329954e-06 | AD14: 9.3377489e-06 | AE14: 9.3652669e-06 | AF14: 9.3821036e-06 | AG14: =_xlfn.FORECAST.ETS(AG1,$L$14:$AF$14,$L$13:$AF$13) -> 9.3250488e-06 | AH14: =_xlfn.FORECAST.ETS(AH1,$L$14:$AF$14,$L$13:$AF$13) -> 9.2679941e-06 | AI14: =_xlfn.FORECAST.ETS(AI1,$L$14:$AF$14,$L$13:$AF$13) -> 9.2109394e-06 | AJ14: =_xlfn.FORECAST.ETS(AJ1,$L$14:$AF$14,$L$13:$AF$13) -> 9.1538846e-06 | AK14: =_xlfn.FORECAST.ETS(AK1,$L$14:$AF$14,$L$13:$AF$13) -> 9.0968299e-06 | AL14: =_xlfn.FORECAST.ETS(AL1,$L$14:$AF$14,$L$13:$AF$13) -> 9.0397752e-06 | AM14: =_xlfn.FORECAST.ETS(AM1,$L$14:$AF$14,$L$13:$AF$13) -> 8.9827204e-06 | AN14: =_xlfn.FORECAST.ETS(AN1,$L$14:$AF$14,$L$13:$AF$13) -> 8.9256657e-06 | ... AZ14: =_xlfn.FORECAST.ETS(AZ1,$L$14:$AF$14,$L$13:$AF$13) -> 8.2410089e-06
A15: Electricity Sector | B15: 2.0235855e-06 | C15: 3.7117625e-06 | D15: 6.8560949e-06 | E15: 5.9040305e-06 | F15: 4.4604047e-06 | G15: 4.1474019e-06 | H15: 3.9148397e-06 | I15: 3.6822775e-06 | J15: 3.4497153e-06 | K15: 3.217153e-06 | L15: 2.9845908e-06 | M15: 2.9831373e-06 | N15: 3.0280963e-06 | O15: 3.0838664e-06 | P15: 3.1115465e-06 | Q15: 3.1117432e-06 | R15: 3.1136052e-06 | S15: 3.0969685e-06 | T15: 3.1209156e-06 | U15: 3.1195613e-06 | V15: 3.1185088e-06 | W15: 3.1103054e-06 | X15: 3.0985427e-06 | Y15: 3.0855258e-06 | Z15: 3.0852687e-06 | AA15: 3.0912902e-06 | AB15: 3.0947957e-06 | AC15: 3.1109619e-06 | AD15: 3.1506742e-06 | AE15: 3.1919697e-06 | AF15: 3.2257406e-06 | AG15: =_xlfn.FORECAST.ETS(AG1,$B$15:$AF$15,$B$13:$AF$13) -> 3.2323523e-06 | AH15: =_xlfn.FORECAST.ETS(AH1,$B$15:$AF$15,$B$13:$AF$13) -> 3.2390243e-06 | AI15: =_xlfn.FORECAST.ETS(AI1,$B$15:$AF$15,$B$13:$AF$13) -> 3.2456964e-06 | AJ15: =_xlfn.FORECAST.ETS(AJ1,$B$15:$AF$15,$B$13:$AF$13) -> 3.2523684e-06 | AK15: =_xlfn.FORECAST.ETS(AK1,$B$15:$AF$15,$B$13:$AF$13) -> 3.2590404e-06 | AL15: =_xlfn.FORECAST.ETS(AL1,$B$15:$AF$15,$B$13:$AF$13) -> 3.2657124e-06 | AM15: =_xlfn.FORECAST.ETS(AM1,$B$15:$AF$15,$B$13:$AF$13) -> 3.2723845e-06 | AN15: =_xlfn.FORECAST.ETS(AN1,$B$15:$AF$15,$B$13:$AF$13) -> 3.2790565e-06 | ... AZ15: =_xlfn.FORECAST.ETS(AZ1,$B$15:$AF$15,$B$13:$AF$13) -> 3.3591208e-06
A16: Residential Buildings Sector | B16: 8.3850404e-06 | C16: 1.1803274e-05 | D16: 2.180214e-05 | E16: 1.8774609e-05 | F16: 1.418393e-05 | G16: 1.3188592e-05 | H16: 1.2368351e-05 | I16: 1.1548109e-05 | J16: 1.0727868e-05 | K16: 9.9076267e-06 | L16: 9.0873854e-06 | M16: 9.1258417e-06 | N16: 9.2021054e-06 | O16: 9.2921392e-06 | P16: 9.346383e-06 | Q16: 9.3753454e-06 | R16: 9.3883838e-06 | S16: 9.4106996e-06 | T16: 9.4362159e-06 | U16: 9.4532544e-06 | V16: 9.4589369e-06 | W16: 9.4794205e-06 | X16: 9.4863102e-06 | Y16: 9.4976644e-06 | Z16: 9.5017851e-06 | AA16: 9.5297826e-06 | AB16: 9.5451212e-06 | AC16: 9.5807607e-06 | AD16: 9.6187639e-06 | AE16: 9.6722273e-06 | AF16: 9.7213699e-06 | AG16: =_xlfn.FORECAST.ETS(AG1,$B$16:$AF$16,$B$13:$AF$13) -> 9.7139259e-06 | AH16: =_xlfn.FORECAST.ETS(AH1,$B$16:$AF$16,$B$13:$AF$13) -> 9.7066075e-06 | AI16: =_xlfn.FORECAST.ETS(AI1,$B$16:$AF$16,$B$13:$AF$13) -> 9.6992892e-06 | AJ16: =_xlfn.FORECAST.ETS(AJ1,$B$16:$AF$16,$B$13:$AF$13) -> 9.6919708e-06 | AK16: =_xlfn.FORECAST.ETS(AK1,$B$16:$AF$16,$B$13:$AF$13) -> 9.6846525e-06 | AL16: =_xlfn.FORECAST.ETS(AL1,$B$16:$AF$16,$B$13:$AF$13) -> 9.6773341e-06 | AM16: =_xlfn.FORECAST.ETS(AM1,$B$16:$AF$16,$B$13:$AF$13) -> 9.6700158e-06 | AN16: =_xlfn.FORECAST.ETS(AN1,$B$16:$AF$16,$B$13:$AF$13) -> 9.6626974e-06 | ... AZ16: =_xlfn.FORECAST.ETS(AZ1,$B$16:$AF$16,$B$13:$AF$13) -> 9.5748773e-06
A17: Commercial Buildings Sector | B17: 5.975576e-06 | C17: 8.6732306e-06 | D17: 1.6020554e-05 | E17: 1.3795877e-05 | F17: 1.0422574e-05 | G17: 9.6911841e-06 | H17: 9.1082498e-06 | I17: 8.5253156e-06 | J17: 7.9423813e-06 | K17: 7.3594471e-06 | L17: 6.7765128e-06 | M17: 6.785161e-06 | N17: 6.8299844e-06 | O17: 6.899948e-06 | P17: 6.9382026e-06 | Q17: 6.9538562e-06 | R17: 6.9552154e-06 | S17: 6.9659785e-06 | T17: 6.9803043e-06 | U17: 6.9883224e-06 | V17: 6.9866623e-06 | W17: 6.999857e-06 | X17: 6.99915e-06 | Y17: 7.0048598e-06 | Z17: 7.0022877e-06 | AA17: 7.023594e-06 | AB17: 7.0332253e-06 | AC17: 7.0621736e-06 | AD17: 7.0938271e-06 | AE17: 7.1394128e-06 | AF17: 7.1809465e-06 | AG17: =_xlfn.FORECAST.ETS(AG1,$B$17:$AF$17,$B$13:$AF$13) -> 7.1768901e-06 | AH17: =_xlfn.FORECAST.ETS(AH1,$B$17:$AF$17,$B$13:$AF$13) -> 7.172935e-06 | AI17: =_xlfn.FORECAST.ETS(AI1,$B$17:$AF$17,$B$13:$AF$13) -> 7.1689798e-06 | AJ17: =_xlfn.FORECAST.ETS(AJ1,$B$17:$AF$17,$B$13:$AF$13) -> 7.1650247e-06 | AK17: =_xlfn.FORECAST.ETS(AK1,$B$17:$AF$17,$B$13:$AF$13) -> 7.1610696e-06 | AL17: =_xlfn.FORECAST.ETS(AL1,$B$17:$AF$17,$B$13:$AF$13) -> 7.1571144e-06 | AM17: =_xlfn.FORECAST.ETS(AM1,$B$17:$AF$17,$B$13:$AF$13) -> 7.1531593e-06 | AN17: =_xlfn.FORECAST.ETS(AN1,$B$17:$AF$17,$B$13:$AF$13) -> 7.1492041e-06 | ... AZ17: =_xlfn.FORECAST.ETS(AZ1,$B$17:$AF$17,$B$13:$AF$13) -> 7.1017425e-06
A18: Industry Sector | B18: 2.5308054e-06 | C18: 4.4088165e-06 | D18: 8.1436418e-06 | E18: 7.0127836e-06 | F18: 5.2980507e-06 | G18: 4.9262673e-06 | H18: 4.6351557e-06 | I18: 4.3440441e-06 | J18: 4.0529325e-06 | K18: 3.761821e-06 | L18: 3.4707094e-06 | M18: 3.4777363e-06 | N18: 3.5206738e-06 | O18: 3.58009e-06 | P18: 3.6071946e-06 | Q18: 3.6161222e-06 | R18: 3.6165299e-06 | S18: 3.607422e-06 | T18: 3.6222942e-06 | U18: 3.6164712e-06 | V18: 3.6088283e-06 | W18: 3.6060388e-06 | X18: 3.5906117e-06 | Y18: 3.5766341e-06 | Z18: 3.5692624e-06 | AA18: 3.5752186e-06 | AB18: 3.5776733e-06 | AC18: 3.5959693e-06 | AD18: 3.6288771e-06 | AE18: 3.6730391e-06 | AF18: 3.7045827e-06 | AG18: =_xlfn.FORECAST.ETS(AG1,$B$18:$AF$18,$B$13:$AF$13) -> 3.707504e-06 | AH18: =_xlfn.FORECAST.ETS(AH1,$B$18:$AF$18,$B$13:$AF$13) -> 3.710489e-06 | AI18: =_xlfn.FORECAST.ETS(AI1,$B$18:$AF$18,$B$13:$AF$13) -> 3.713474e-06 | AJ18: =_xlfn.FORECAST.ETS(AJ1,$B$18:$AF$18,$B$13:$AF$13) -> 3.7164589e-06 | AK18: =_xlfn.FORECAST.ETS(AK1,$B$18:$AF$18,$B$13:$AF$13) -> 3.7194439e-06 | AL18: =_xlfn.FORECAST.ETS(AL1,$B$18:$AF$18,$B$13:$AF$13) -> 3.7224289e-06 | AM18: =_xlfn.FORECAST.ETS(AM1,$B$18:$AF$18,$B$13:$AF$13) -> 3.7254138e-06 | AN18: =_xlfn.FORECAST.ETS(AN1,$B$18:$AF$18,$B$13:$AF$13) -> 3.7283988e-06 | ... AZ18: =_xlfn.FORECAST.ETS(AZ1,$B$18:$AF$18,$B$13:$AF$13) -> 3.7642184e-06
A19: District Heating Sector | B19: 2.0235855e-06 | C19: 3.7117625e-06 | D19: 6.8560949e-06 | E19: 5.9040305e-06 | F19: 4.4604047e-06 | G19: 4.1474019e-06 | H19: 3.9148397e-06 | I19: 3.6822775e-06 | J19: 3.4497153e-06 | K19: 3.217153e-06 | L19: 2.9845908e-06 | M19: 2.9831373e-06 | N19: 3.0280963e-06 | O19: 3.0838664e-06 | P19: 3.1115465e-06 | Q19: 3.1117432e-06 | R19: 3.1136052e-06 | S19: 3.0969685e-06 | T19: 3.1209156e-06 | U19: 3.1195613e-06 | V19: 3.1185088e-06 | W19: 3.1103054e-06 | X19: 3.0985427e-06 | Y19: 3.0855258e-06 | Z19: 3.0852687e-06 | AA19: 3.0912902e-06 | AB19: 3.0947957e-06 | AC19: 3.1109619e-06 | AD19: 3.1506742e-06 | AE19: 3.1919697e-06 | AF19: 3.2257406e-06 | AG19: =_xlfn.FORECAST.ETS(AG1,$B$19:$AF$19,$B$13:$AF$13) -> 3.2323523e-06 | AH19: =_xlfn.FORECAST.ETS(AH1,$B$19:$AF$19,$B$13:$AF$13) -> 3.2390243e-06 | AI19: =_xlfn.FORECAST.ETS(AI1,$B$19:$AF$19,$B$13:$AF$13) -> 3.2456964e-06 | AJ19: =_xlfn.FORECAST.ETS(AJ1,$B$19:$AF$19,$B$13:$AF$13) -> 3.2523684e-06 | AK19: =_xlfn.FORECAST.ETS(AK1,$B$19:$AF$19,$B$13:$AF$13) -> 3.2590404e-06 | AL19: =_xlfn.FORECAST.ETS(AL1,$B$19:$AF$19,$B$13:$AF$13) -> 3.2657124e-06 | AM19: =_xlfn.FORECAST.ETS(AM1,$B$19:$AF$19,$B$13:$AF$13) -> 3.2723845e-06 | AN19: =_xlfn.FORECAST.ETS(AN1,$B$19:$AF$19,$B$13:$AF$13) -> 3.2790565e-06 | ... AZ19: =_xlfn.FORECAST.ETS(AZ1,$B$19:$AF$19,$B$13:$AF$13) -> 3.3591208e-06
A20: LULUCF Sector | B20: 0 | C20: 0 | D20: 0 | E20: 0 | F20: 0 | G20: 0 | H20: 0 | I20: 0 | J20: 0 | K20: 0 | L20: 0 | M20: 0 | N20: 0 | O20: 0 | P20: 0 | Q20: 0 | R20: 0 | S20: 0 | T20: 0 | U20: 0 | V20: 0 | W20: 0 | X20: 0 | Y20: 0 | Z20: 0 | AA20: 0 | AB20: 0 | AC20: 0 | AD20: 0 | AE20: 0 | AF20: 0 | AG20: 0 | AH20: 0 | AI20: 0 | AJ20: 0 | AK20: 0 | AL20: 0 | AM20: 0 | AN20: 0 | AO20: 0 | AP20: 0 | AQ20: 0 | AR20: 0 | AS20: 0 | AT20: 0 | AU20: 0 | AV20: 0 | AW20: 0 | AX20: 0 | AY20: 0 | AZ20: 0
A21: Geoengineering Sector | B21: 2.5308054e-06 | C21: 4.4088165e-06 | D21: 8.1436418e-06 | E21: 7.0127836e-06 | F21: 5.2980507e-06 | G21: 4.9262673e-06 | H21: 4.6351557e-06 | I21: 4.3440441e-06 | J21: 4.0529325e-06 | K21: 3.761821e-06 | L21: 3.4707094e-06 | M21: 3.4777363e-06 | N21: 3.5206738e-06 | O21: 3.58009e-06 | P21: 3.6071946e-06 | Q21: 3.6161222e-06 | R21: 3.6165299e-06 | S21: 3.607422e-06 | T21: 3.6222942e-06 | U21: 3.6164712e-06 | V21: 3.6088283e-06 | W21: 3.6060388e-06 | X21: 3.5906117e-06 | Y21: 3.5766341e-06 | Z21: 3.5692624e-06 | AA21: 3.5752186e-06 | AB21: 3.5776733e-06 | AC21: 3.5959693e-06 | AD21: 3.6288771e-06 | AE21: 3.6730391e-06 | AF21: 3.7045827e-06 | AG21: =_xlfn.FORECAST.ETS(AG1,$B$21:$AF$21,$B$13:$AF$13) -> 3.707504e-06 | AH21: =_xlfn.FORECAST.ETS(AH1,$B$21:$AF$21,$B$13:$AF$13) -> 3.710489e-06 | AI21: =_xlfn.FORECAST.ETS(AI1,$B$21:$AF$21,$B$13:$AF$13) -> 3.713474e-06 | AJ21: =_xlfn.FORECAST.ETS(AJ1,$B$21:$AF$21,$B$13:$AF$13) -> 3.7164589e-06 | AK21: =_xlfn.FORECAST.ETS(AK1,$B$21:$AF$21,$B$13:$AF$13) -> 3.7194439e-06 | AL21: =_xlfn.FORECAST.ETS(AL1,$B$21:$AF$21,$B$13:$AF$13) -> 3.7224289e-06 | AM21: =_xlfn.FORECAST.ETS(AM1,$B$21:$AF$21,$B$13:$AF$13) -> 3.7254138e-06 | AN21: =_xlfn.FORECAST.ETS(AN1,$B$21:$AF$21,$B$13:$AF$13) -> 3.7283988e-06 | ... AZ21: =_xlfn.FORECAST.ETS(AZ1,$B$21:$AF$21,$B$13:$AF$13) -> 3.7642184e-06
A22: Nuclear
A23: Year | B23: 2020 | C23: 2021 | D23: 2022 | E23: 2023 | F23: 2024 | G23: 2025 | H23: 2026 | I23: 2027 | J23: 2028 | K23: 2029 | L23: 2030 | M23: 2031 | N23: 2032 | O23: 2033 | P23: 2034 | Q23: 2035 | R23: 2036 | S23: 2037 | T23: 2038 | U23: 2039 | V23: 2040 | W23: 2041 | X23: 2042 | Y23: 2043 | Z23: 2044 | AA23: 2045 | AB23: 2046 | AC23: 2047 | AD23: 2048 | AE23: 2049 | AF23: 2050 | AG23: 2051 | AH23: 2052 | AI23: 2053 | AJ23: 2054 | AK23: 2055 | AL23: 2056 | AM23: 2057 | AN23: 2058 | AO23: 2059 | AP23: 2060 | AQ23: 2061 | AR23: 2062 | AS23: 2063 | AT23: 2064 | AU23: 2065 | AV23: 2066 | AW23: 2067 | AX23: 2068 | AY23: 2069 | AZ23: 2070
A24: Transportation Sector | B24: 0 | C24: 0 | D24: 0 | E24: 0 | F24: 0 | G24: 0 | H24: 0 | I24: 0 | J24: 0 | K24: 0 | L24: 0 | M24: 0 | N24: 0 | O24: 0 | P24: 0 | Q24: 0 | R24: 0 | S24: 0 | T24: 0 | U24: 0 | V24: 0 | W24: 0 | X24: 0 | Y24: 0 | Z24: 0 | AA24: 0 | AB24: 0 | AC24: 0 | AD24: 0 | AE24: 0 | AF24: 0 | AG24: 0 | AH24: 0 | AI24: 0 | AJ24: 0 | AK24: 0 | AL24: 0 | AM24: 0 | AN24: 0 | AO24: 0 | AP24: 0 | AQ24: 0 | AR24: 0 | AS24: 0 | AT24: 0 | AU24: 0 | AV24: 0 | AW24: 0 | AX24: 0 | AY24: 0 | AZ24: 0
A25: Electricity Sector | B25: 5.6727768e-07 | C25: 5.6594057e-07 | D25: 5.6676895e-07 | E25: 5.684265e-07 | F25: 5.6925488e-07 | G25: 5.7091165e-07 | H25: 5.7174082e-07 | I25: 5.7339758e-07 | J25: 5.7422597e-07 | K25: 5.7588352e-07 | L25: 5.7754107e-07 | M25: 5.7836946e-07 | N25: 5.8002701e-07 | O25: 5.8168377e-07 | P25: 5.8251216e-07 | Q25: 5.8416971e-07 | R25: 5.8582726e-07 | S25: 5.8665565e-07 | T25: 5.8831241e-07 | U25: 5.8996997e-07 | V25: 5.9162752e-07 | W25: 5.9328428e-07 | X25: 5.9494184e-07 | Y25: 5.965986e-07 | Z25: 5.9825616e-07 | AA25: 5.9991371e-07 | AB25: 6.0157047e-07 | AC25: 6.0322803e-07 | AD25: 6.0488479e-07 | AE25: 6.0654235e-07 | AF25: 6.0819911e-07 | AG25: =_xlfn.FORECAST.ETS(AG13,$B$25:$AF$25,$B$23:$AF$23) -> 6.0985671e-07 | AH25: =_xlfn.FORECAST.ETS(AH13,$B$25:$AF$25,$B$23:$AF$23) -> 6.1151417e-07 | AI25: =_xlfn.FORECAST.ETS(AI13,$B$25:$AF$25,$B$23:$AF$23) -> 6.1317164e-07 | AJ25: =_xlfn.FORECAST.ETS(AJ13,$B$25:$AF$25,$B$23:$AF$23) -> 6.1482911e-07 | AK25: =_xlfn.FORECAST.ETS(AK13,$B$25:$AF$25,$B$23:$AF$23) -> 6.1648657e-07 | AL25: =_xlfn.FORECAST.ETS(AL13,$B$25:$AF$25,$B$23:$AF$23) -> 6.1814404e-07 | AM25: =_xlfn.FORECAST.ETS(AM13,$B$25:$AF$25,$B$23:$AF$23) -> 6.1980151e-07 | AN25: =_xlfn.FORECAST.ETS(AN13,$B$25:$AF$25,$B$23:$AF$23) -> 6.2145897e-07 | ... AZ25: =_xlfn.FORECAST.ETS(AZ13,$B$25:$AF$25,$B$23:$AF$23) -> 6.4134857e-07
A26: Residential Buildings Sector | B26: 0 | C26: 0 | D26: 0 | E26: 0 | F26: 0 | G26: 0 | H26: 0 | I26: 0 | J26: 0 | K26: 0 | L26: 0 | M26: 0 | N26: 0 | O26: 0 | P26: 0 | Q26: 0 | R26: 0 | S26: 0 | T26: 0 | U26: 0 | V26: 0 | W26: 0 | X26: 0 | Y26: 0 | Z26: 0 | AA26: 0 | AB26: 0 | AC26: 0 | AD26: 0 | AE26: 0 | AF26: 0 | AG26: 0 | AH26: 0 | AI26: 0 | AJ26: 0 | AK26: 0 | AL26: 0 | AM26: 0 | AN26: 0 | AO26: 0 | AP26: 0 | AQ26: 0 | AR26: 0 | AS26: 0 | AT26: 0 | AU26: 0 | AV26: 0 | AW26: 0 | AX26: 0 | AY26: 0 | AZ26: 0
A27: Commercial Buildings Sector | B27: 0 | C27: 0 | D27: 0 | E27: 0 | F27: 0 | G27: 0 | H27: 0 | I27: 0 | J27: 0 | K27: 0 | L27: 0 | M27: 0 | N27: 0 | O27: 0 | P27: 0 | Q27: 0 | R27: 0 | S27: 0 | T27: 0 | U27: 0 | V27: 0 | W27: 0 | X27: 0 | Y27: 0 | Z27: 0 | AA27: 0 | AB27: 0 | AC27: 0 | AD27: 0 | AE27: 0 | AF27: 0 | AG27: 0 | AH27: 0 | AI27: 0 | AJ27: 0 | AK27: 0 | AL27: 0 | AM27: 0 | AN27: 0 | AO27: 0 | AP27: 0 | AQ27: 0 | AR27: 0 | AS27: 0 | AT27: 0 | AU27: 0 | AV27: 0 | AW27: 0 | AX27: 0 | AY27: 0 | AZ27: 0
A28: Industry Sector | B28: 0 | C28: 0 | D28: 0 | E28: 0 | F28: 0 | G28: 0 | H28: 0 | I28: 0 | J28: 0 | K28: 0 | L28: 0 | M28: 0 | N28: 0 | O28: 0 | P28: 0 | Q28: 0 | R28: 0 | S28: 0 | T28: 0 | U28: 0 | V28: 0 | W28: 0 | X28: 0 | Y28: 0 | Z28: 0 | AA28: 0 | AB28: 0 | AC28: 0 | AD28: 0 | AE28: 0 | AF28: 0 | AG28: 0 | AH28: 0 | AI28: 0 | AJ28: 0 | AK28: 0 | AL28: 0 | AM28: 0 | AN28: 0 | AO28: 0 | AP28: 0 | AQ28: 0 | AR28: 0 | AS28: 0 | AT28: 0 | AU28: 0 | AV28: 0 | AW28: 0 | AX28: 0 | AY28: 0 | AZ28: 0
A29: District Heating Sector | B29: 0 | C29: 0 | D29: 0 | E29: 0 | F29: 0 | G29: 0 | H29: 0 | I29: 0 | J29: 0 | K29: 0 | L29: 0 | M29: 0 | N29: 0 | O29: 0 | P29: 0 | Q29: 0 | R29: 0 | S29: 0 | T29: 0 | U29: 0 | V29: 0 | W29: 0 | X29: 0 | Y29: 0 | Z29: 0 | AA29: 0 | AB29: 0 | AC29: 0 | AD29: 0 | AE29: 0 | AF29: 0 | AG29: 0 | AH29: 0 | AI29: 0 | AJ29: 0 | AK29: 0 | AL29: 0 | AM29: 0 | AN29: 0 | AO29: 0 | AP29: 0 | AQ29: 0 | AR29: 0 | AS29: 0 | AT29: 0 | AU29: 0 | AV29: 0 | AW29: 0 | AX29: 0 | AY29: 0 | AZ29: 0
A30: LULUCF Sector | B30: 0 | C30: 0 | D30: 0 | E30: 0 | F30: 0 | G30: 0 | H30: 0 | I30: 0 | J30: 0 | K30: 0 | L30: 0 | M30: 0 | N30: 0 | O30: 0 | P30: 0 | Q30: 0 | R30: 0 | S30: 0 | T30: 0 | U30: 0 | V30: 0 | W30: 0 | X30: 0 | Y30: 0 | Z30: 0 | AA30: 0 | AB30: 0 | AC30: 0 | AD30: 0 | AE30: 0 | AF30: 0 | AG30: 0 | AH30: 0 | AI30: 0 | AJ30: 0 | AK30: 0 | AL30: 0 | AM30: 0 | AN30: 0 | AO30: 0 | AP30: 0 | AQ30: 0 | AR30: 0 | AS30: 0 | AT30: 0 | AU30: 0 | AV30: 0 | AW30: 0 | AX30: 0 | AY30: 0 | AZ30: 0
A31: Geoengineering Sector | B31: 0 | C31: 0 | D31: 0 | E31: 0 | F31: 0 | G31: 0 | H31: 0 | I31: 0 | J31: 0 | K31: 0 | L31: 0 | M31: 0 | N31: 0 | O31: 0 | P31: 0 | Q31: 0 | R31: 0 | S31: 0 | T31: 0 | U31: 0 | V31: 0 | W31: 0 | X31: 0 | Y31: 0 | Z31: 0 | AA31: 0 | AB31: 0 | AC31: 0 | AD31: 0 | AE31: 0 | AF31: 0 | AG31: 0 | AH31: 0 | AI31: 0 | AJ31: 0 | AK31: 0 | AL31: 0 | AM31: 0 | AN31: 0 | AO31: 0 | AP31: 0 | AQ31: 0 | AR31: 0 | AS31: 0 | AT31: 0 | AU31: 0 | AV31: 0 | AW31: 0 | AX31: 0 | AY31: 0 | AZ31: 0
A32: Biomass
A33: Year | B33: 2020 | C33: 2021 | D33: 2022 | E33: 2023 | F33: 2024 | G33: 2025 | H33: 2026 | I33: 2027 | J33: 2028 | K33: 2029 | L33: 2030 | M33: 2031 | N33: 2032 | O33: 2033 | P33: 2034 | Q33: 2035 | R33: 2036 | S33: 2037 | T33: 2038 | U33: 2039 | V33: 2040 | W33: 2041 | X33: 2042 | Y33: 2043 | Z33: 2044 | AA33: 2045 | AB33: 2046 | AC33: 2047 | AD33: 2048 | AE33: 2049 | AF33: 2050 | AG33: 2051 | AH33: 2052 | AI33: 2053 | AJ33: 2054 | AK33: 2055 | AL33: 2056 | AM33: 2057 | AN33: 2058 | AO33: 2059 | AP33: 2060 | AQ33: 2061 | AR33: 2062 | AS33: 2063 | AT33: 2064 | AU33: 2065 | AV33: 2066 | AW33: 2067 | AX33: 2068 | AY33: 2069 | AZ33: 2070
A34: Transportation Sector | B34: 0 | C34: 0 | D34: 0 | E34: 0 | F34: 0 | G34: 0 | H34: 0 | I34: 0 | J34: 0 | K34: 0 | L34: 0 | M34: 0 | N34: 0 | O34: 0 | P34: 0 | Q34: 0 | R34: 0 | S34: 0 | T34: 0 | U34: 0 | V34: 0 | W34: 0 | X34: 0 | Y34: 0 | Z34: 0 | AA34: 0 | AB34: 0 | AC34: 0 | AD34: 0 | AE34: 0 | AF34: 0 | AG34: 0 | AH34: 0 | AI34: 0 | AJ34: 0 | AK34: 0 | AL34: 0 | AM34: 0 | AN34: 0 | AO34: 0 | AP34: 0 | AQ34: 0 | AR34: 0 | AS34: 0 | AT34: 0 | AU34: 0 | AV34: 0 | AW34: 0 | AX34: 0 | AY34: 0 | AZ34: 0
A35: Electricity Sector | B35: 1.8911026e-06 | C35: 1.8911026e-06 | D35: 1.8911026e-06 | E35: 1.8911026e-06 | F35: 1.8911026e-06 | G35: 1.8911026e-06 | H35: 1.8911026e-06 | I35: 1.8911026e-06 | J35: 1.8911026e-06 | K35: 1.8911026e-06 | L35: 1.8911026e-06 | M35: 1.8911026e-06 | N35: 1.8911026e-06 | O35: 1.8911026e-06 | P35: 1.8911026e-06 | Q35: 1.8911026e-06 | R35: 1.8911026e-06 | S35: 1.8911026e-06 | T35: 1.8911026e-06 | U35: 1.8911026e-06 | V35: 1.8911026e-06 | W35: 1.8911026e-06 | X35: 1.8911026e-06 | Y35: 1.8911026e-06 | Z35: 1.8911026e-06 | AA35: 1.8911026e-06 | AB35: 1.8911026e-06 | AC35: 1.8911026e-06 | AD35: 1.8911026e-06 | AE35: 1.8911026e-06 | AF35: 1.8911026e-06 | AG35: 1.8911026e-06 | AH35: 1.8911026e-06 | AI35: 1.8911026e-06 | AJ35: 1.8911026e-06 | AK35: 1.8911026e-06 | AL35: 1.8911026e-06 | AM35: 1.8911026e-06 | AN35: 1.8911026e-06 | AO35: 1.8911026e-06 | AP35: 1.8911026e-06 | AQ35: 1.8911026e-06 | AR35: 1.8911026e-06 | AS35: 1.8911026e-06 | AT35: 1.8911026e-06 | AU35: 1.8911026e-06 | AV35: 1.8911026e-06 | AW35: 1.8911026e-06 | AX35: 1.8911026e-06 | AY35: 1.8911026e-06 | AZ35: 1.8911026e-06
A36: Residential Buildings Sector | B36: 7.5388548e-06 | C36: 7.5388548e-06 | D36: 7.5388548e-06 | E36: 7.5388548e-06 | F36: 7.5388548e-06 | G36: 7.5388548e-06 | H36: 7.5388548e-06 | I36: 7.5388548e-06 | J36: 7.5388548e-06 | K36: 7.5388548e-06 | L36: 7.5388548e-06 | M36: 7.5388548e-06 | N36: 7.5388548e-06 | O36: 7.5388548e-06 | P36: 7.5388548e-06 | Q36: 7.5388548e-06 | R36: 7.5388548e-06 | S36: 7.5388548e-06 | T36: 7.5388548e-06 | U36: 7.5388548e-06 | V36: 7.5388548e-06 | W36: 7.5388548e-06 | X36: 7.5388548e-06 | Y36: 7.5388548e-06 | Z36: 7.5388548e-06 | AA36: 7.5388548e-06 | AB36: 7.5388548e-06 | AC36: 7.5388548e-06 | AD36: 7.5388548e-06 | AE36: 7.5388548e-06 | AF36: 7.5388548e-06 | AG36: 7.5388548e-06 | AH36: 7.5388548e-06 | AI36: 7.5388548e-06 | AJ36: 7.5388548e-06 | AK36: 7.5388548e-06 | AL36: 7.5388548e-06 | AM36: 7.5388548e-06 | AN36: 7.5388548e-06 | AO36: 7.5388548e-06 | AP36: 7.5388548e-06 | AQ36: 7.5388548e-06 | AR36: 7.5388548e-06 | AS36: 7.5388548e-06 | AT36: 7.5388548e-06 | AU36: 7.5388548e-06 | AV36: 7.5388548e-06 | AW36: 7.5388548e-06 | AX36: 7.5388548e-06 | AY36: 7.5388548e-06 | AZ36: 7.5388548e-06
A37: Commercial Buildings Sector | B37: 3.5010953e-06 | C37: 3.5010953e-06 | D37: 3.5010953e-06 | E37: 3.5010953e-06 | F37: 3.5010953e-06 | G37: 3.5010953e-06 | H37: 3.5010953e-06 | I37: 3.5010953e-06 | J37: 3.5010953e-06 | K37: 3.5010953e-06 | L37: 3.5010953e-06 | M37: 3.5010953e-06 | N37: 3.5010953e-06 | O37: 3.5010953e-06 | P37: 3.5010953e-06 | Q37: 3.5010953e-06 | R37: 3.5010953e-06 | S37: 3.5010953e-06 | T37: 3.5010953e-06 | U37: 3.5010953e-06 | V37: 3.5010953e-06 | W37: 3.5010953e-06 | X37: 3.5010953e-06 | Y37: 3.5010953e-06 | Z37: 3.5010953e-06 | AA37: 3.5010953e-06 | AB37: 3.5010953e-06 | AC37: 3.5010953e-06 | AD37: 3.5010953e-06 | AE37: 3.5010953e-06 | AF37: 3.5010953e-06 | AG37: 3.5010953e-06 | AH37: 3.5010953e-06 | AI37: 3.5010953e-06 | AJ37: 3.5010953e-06 | AK37: 3.5010953e-06 | AL37: 3.5010953e-06 | AM37: 3.5010953e-06 | AN37: 3.5010953e-06 | AO37: 3.5010953e-06 | AP37: 3.5010953e-06 | AQ37: 3.5010953e-06 | AR37: 3.5010953e-06 | AS37: 3.5010953e-06 | AT37: 3.5010953e-06 | AU37: 3.5010953e-06 | AV37: 3.5010953e-06 | AW37: 3.5010953e-06 | AX37: 3.5010953e-06 | AY37: 3.5010953e-06 | AZ37: 3.5010953e-06
A38: Industry Sector | B38: 2.2403602e-06 | C38: 2.2403602e-06 | D38: 2.2403602e-06 | E38: 2.2403602e-06 | F38: 2.2403602e-06 | G38: 2.2403602e-06 | H38: 2.2403602e-06 | I38: 2.2403602e-06 | J38: 2.2403602e-06 | K38: 2.2403602e-06 | L38: 2.2403602e-06 | M38: 2.2403602e-06 | N38: 2.2403602e-06 | O38: 2.2403602e-06 | P38: 2.2403602e-06 | Q38: 2.2403602e-06 | R38: 2.2403602e-06 | S38: 2.2403602e-06 | T38: 2.2403602e-06 | U38: 2.2403602e-06 | V38: 2.2403602e-06 | W38: 2.2403602e-06 | X38: 2.2403602e-06 | Y38: 2.2403602e-06 | Z38: 2.2403602e-06 | AA38: 2.2403602e-06 | AB38: 2.2403602e-06 | AC38: 2.2403602e-06 | AD38: 2.2403602e-06 | AE38: 2.2403602e-06 | AF38: 2.2403602e-06 | AG38: 2.2403602e-06 | AH38: 2.2403602e-06 | AI38: 2.2403602e-06 | AJ38: 2.2403602e-06 | AK38: 2.2403602e-06 | AL38: 2.2403602e-06 | AM38: 2.2403602e-06 | AN38: 2.2403602e-06 | AO38: 2.2403602e-06 | AP38: 2.2403602e-06 | AQ38: 2.2403602e-06 | AR38: 2.2403602e-06 | AS38: 2.2403602e-06 | AT38: 2.2403602e-06 | AU38: 2.2403602e-06 | AV38: 2.2403602e-06 | AW38: 2.2403602e-06 | AX38: 2.2403602e-06 | AY38: 2.2403602e-06 | AZ38: 2.2403602e-06
A39: District Heating Sector | B39: 1.8911026e-06 | C39: 1.8911026e-06 | D39: 1.8911026e-06 | E39: 1.8911026e-06 | F39: 1.8911026e-06 | G39: 1.8911026e-06 | H39: 1.8911026e-06 | I39: 1.8911026e-06 | J39: 1.8911026e-06 | K39: 1.8911026e-06 | L39: 1.8911026e-06 | M39: 1.8911026e-06 | N39: 1.8911026e-06 | O39: 1.8911026e-06 | P39: 1.8911026e-06 | Q39: 1.8911026e-06 | R39: 1.8911026e-06 | S39: 1.8911026e-06 | T39: 1.8911026e-06 | U39: 1.8911026e-06 | V39: 1.8911026e-06 | W39: 1.8911026e-06 | X39: 1.8911026e-06 | Y39: 1.8911026e-06 | Z39: 1.8911026e-06 | AA39: 1.8911026e-06 | AB39: 1.8911026e-06 | AC39: 1.8911026e-06 | AD39: 1.8911026e-06 | AE39: 1.8911026e-06 | AF39: 1.8911026e-06 | AG39: 1.8911026e-06 | AH39: 1.8911026e-06 | AI39: 1.8911026e-06 | AJ39: 1.8911026e-06 | AK39: 1.8911026e-06 | AL39: 1.8911026e-06 | AM39: 1.8911026e-06 | AN39: 1.8911026e-06 | AO39: 1.8911026e-06 | AP39: 1.8911026e-06 | AQ39: 1.8911026e-06 | AR39: 1.8911026e-06 | AS39: 1.8911026e-06 | AT39: 1.8911026e-06 | AU39: 1.8911026e-06 | AV39: 1.8911026e-06 | AW39: 1.8911026e-06 | AX39: 1.8911026e-06 | AY39: 1.8911026e-06 | AZ39: 1.8911026e-06
A40: LULUCF Sector | B40: 0 | C40: 0 | D40: 0 | E40: 0 | F40: 0 | G40: 0 | H40: 0 | I40: 0 | J40: 0 | K40: 0 | L40: 0 | M40: 0 | N40: 0 | O40: 0 | P40: 0 | Q40: 0 | R40: 0 | S40: 0 | T40: 0 | U40: 0 | V40: 0 | W40: 0 | X40: 0 | Y40: 0 | Z40: 0 | AA40: 0 | AB40: 0 | AC40: 0 | AD40: 0 | AE40: 0 | AF40: 0 | AG40: 0 | AH40: 0 | AI40: 0 | AJ40: 0 | AK40: 0 | AL40: 0 | AM40: 0 | AN40: 0 | AO40: 0 | AP40: 0 | AQ40: 0 | AR40: 0 | AS40: 0 | AT40: 0 | AU40: 0 | AV40: 0 | AW40: 0 | AX40: 0 | AY40: 0 | AZ40: 0
A41: Geoengineering Sector | B41: 2.2403602e-06 | C41: 2.2403602e-06 | D41: 2.2403602e-06 | E41: 2.2403602e-06 | F41: 2.2403602e-06 | G41: 2.2403602e-06 | H41: 2.2403602e-06 | I41: 2.2403602e-06 | J41: 2.2403602e-06 | K41: 2.2403602e-06 | L41: 2.2403602e-06 | M41: 2.2403602e-06 | N41: 2.2403602e-06 | O41: 2.2403602e-06 | P41: 2.2403602e-06 | Q41: 2.2403602e-06 | R41: 2.2403602e-06 | S41: 2.2403602e-06 | T41: 2.2403602e-06 | U41: 2.2403602e-06 | V41: 2.2403602e-06 | W41: 2.2403602e-06 | X41: 2.2403602e-06 | Y41: 2.2403602e-06 | Z41: 2.2403602e-06 | AA41: 2.2403602e-06 | AB41: 2.2403602e-06 | AC41: 2.2403602e-06 | AD41: 2.2403602e-06 | AE41: 2.2403602e-06 | AF41: 2.2403602e-06 | AG41: 2.2403602e-06 | AH41: 2.2403602e-06 | AI41: 2.2403602e-06 | AJ41: 2.2403602e-06 | AK41: 2.2403602e-06 | AL41: 2.2403602e-06 | AM41: 2.2403602e-06 | AN41: 2.2403602e-06 | AO41: 2.2403602e-06 | AP41: 2.2403602e-06 | AQ41: 2.2403602e-06 | AR41: 2.2403602e-06 | AS41: 2.2403602e-06 | AT41: 2.2403602e-06 | AU41: 2.2403602e-06 | AV41: 2.2403602e-06 | AW41: 2.2403602e-06 | AX41: 2.2403602e-06 | AY41: 2.2403602e-06 | AZ41: 2.2403602e-06
A42: Petroleum Gasoline
A43: Year | B43: 2020 | C43: 2021 | D43: 2022 | E43: 2023 | F43: 2024 | G43: 2025 | H43: 2026 | I43: 2027 | J43: 2028 | K43: 2029 | L43: 2030 | M43: 2031 | N43: 2032 | O43: 2033 | P43: 2034 | Q43: 2035 | R43: 2036 | S43: 2037 | T43: 2038 | U43: 2039 | V43: 2040 | W43: 2041 | X43: 2042 | Y43: 2043 | Z43: 2044 | AA43: 2045 | AB43: 2046 | AC43: 2047 | AD43: 2048 | AE43: 2049 | AF43: 2050 | AG43: 2051 | AH43: 2052 | AI43: 2053 | AJ43: 2054 | AK43: 2055 | AL43: 2056 | AM43: 2057 | AN43: 2058 | AO43: 2059 | AP43: 2060 | AQ43: 2061 | AR43: 2062 | AS43: 2063 | AT43: 2064 | AU43: 2065 | AV43: 2066 | AW43: 2067 | AX43: 2068 | AY43: 2069 | AZ43: 2070
A44: Transportation Sector | B44: 1.153852e-05 | C44: 1.6215569e-05 | D44: 2.0531291e-05 | E44: 1.9182771e-05 | F44: 1.8075816e-05 | G44: 1.6968861e-05 | H44: 1.5861906e-05 | I44: 1.4754951e-05 | J44: 1.3647996e-05 | K44: 1.3907132e-05 | L44: 1.4617966e-05 | M44: 1.5115773e-05 | N44: 1.5402923e-05 | O44: 1.5625271e-05 | P44: 1.5908e-05 | Q44: 1.5934819e-05 | R44: 1.6102773e-05 | S44: 1.6305217e-05 | T44: 1.6576197e-05 | U44: 1.6628326e-05 | V44: 1.6830835e-05 | W44: 1.7009761e-05 | X44: 1.7063714e-05 | Y44: 1.7291078e-05 | Z44: 1.7527339e-05 | AA44: 1.7666187e-05 | AB44: 1.7860355e-05 | AC44: 1.7971446e-05 | AD44: 1.7976062e-05 | AE44: 1.8054796e-05 | AF44: 1.811959e-05 | AG44: =_xlfn.FORECAST.ETS(AG43,$B$44:$AF$44,$B$43:$AF$43) -> 1.8248177e-05 | AH44: =_xlfn.FORECAST.ETS(AH43,$B$44:$AF$44,$B$43:$AF$43) -> 1.8376623e-05 | AI44: =_xlfn.FORECAST.ETS(AI43,$B$44:$AF$44,$B$43:$AF$43) -> 1.8505068e-05 | AJ44: =_xlfn.FORECAST.ETS(AJ43,$B$44:$AF$44,$B$43:$AF$43) -> 1.8633514e-05 | AK44: =_xlfn.FORECAST.ETS(AK43,$B$44:$AF$44,$B$43:$AF$43) -> 1.876196e-05 | AL44: =_xlfn.FORECAST.ETS(AL43,$B$44:$AF$44,$B$43:$AF$43) -> 1.8890405e-05 | AM44: =_xlfn.FORECAST.ETS(AM43,$B$44:$AF$44,$B$43:$AF$43) -> 1.9018851e-05 | AN44: =_xlfn.FORECAST.ETS(AN43,$B$44:$AF$44,$B$43:$AF$43) -> 1.9147296e-05 | ... AZ44: =_xlfn.FORECAST.ETS(AZ43,$B$44:$AF$44,$B$43:$AF$43) -> 2.0688644e-05
A45: Electricity Sector | B45: 0 | C45: 0 | D45: 0 | E45: 0 | F45: 0 | G45: 0 | H45: 0 | I45: 0 | J45: 0 | K45: 0 | L45: 0 | M45: 0 | N45: 0 | O45: 0 | P45: 0 | Q45: 0 | R45: 0 | S45: 0 | T45: 0 | U45: 0 | V45: 0 | W45: 0 | X45: 0 | Y45: 0 | Z45: 0 | AA45: 0 | AB45: 0 | AC45: 0 | AD45: 0 | AE45: 0 | AF45: 0 | AG45: 0 | AH45: 0 | AI45: 0 | AJ45: 0 | AK45: 0 | AL45: 0 | AM45: 0 | AN45: 0 | AO45: 0 | AP45: 0 | AQ45: 0 | AR45: 0 | AS45: 0 | AT45: 0 | AU45: 0 | AV45: 0 | AW45: 0 | AX45: 0 | AY45: 0 | AZ45: 0
A46: Residential Buildings Sector | B46: 0 | C46: 0 | D46: 0 | E46: 0 | F46: 0 | G46: 0 | H46: 0 | I46: 0 | J46: 0 | K46: 0 | L46: 0 | M46: 0 | N46: 0 | O46: 0 | P46: 0 | Q46: 0 | R46: 0 | S46: 0 | T46: 0 | U46: 0 | V46: 0 | W46: 0 | X46: 0 | Y46: 0 | Z46: 0 | AA46: 0 | AB46: 0 | AC46: 0 | AD46: 0 | AE46: 0 | AF46: 0 | AG46: 0 | AH46: 0 | AI46: 0 | AJ46: 0 | AK46: 0 | AL46: 0 | AM46: 0 | AN46: 0 | AO46: 0 | AP46: 0 | AQ46: 0 | AR46: 0 | AS46: 0 | AT46: 0 | AU46: 0 | AV46: 0 | AW46: 0 | AX46: 0 | AY46: 0 | AZ46: 0
A47: Commercial Buildings Sector | B47: 0 | C47: 0 | D47: 0 | E47: 0 | F47: 0 | G47: 0 | H47: 0 | I47: 0 | J47: 0 | K47: 0 | L47: 0 | M47: 0 | N47: 0 | O47: 0 | P47: 0 | Q47: 0 | R47: 0 | S47: 0 | T47: 0 | U47: 0 | V47: 0 | W47: 0 | X47: 0 | Y47: 0 | Z47: 0 | AA47: 0 | AB47: 0 | AC47: 0 | AD47: 0 | AE47: 0 | AF47: 0 | AG47: 0 | AH47: 0 | AI47: 0 | AJ47: 0 | AK47: 0 | AL47: 0 | AM47: 0 | AN47: 0 | AO47: 0 | AP47: 0 | AQ47: 0 | AR47: 0 | AS47: 0 | AT47: 0 | AU47: 0 | AV47: 0 | AW47: 0 | AX47: 0 | AY47: 0 | AZ47: 0
A48: Industry Sector | B48: 0 | C48: 0 | D48: 0 | E48: 0 | F48: 0 | G48: 0 | H48: 0 | I48: 0 | J48: 0 | K48: 0 | L48: 0 | M48: 0 | N48: 0 | O48: 0 | P48: 0 | Q48: 0 | R48: 0 | S48: 0 | T48: 0 | U48: 0 | V48: 0 | W48: 0 | X48: 0 | Y48: 0 | Z48: 0 | AA48: 0 | AB48: 0 | AC48: 0 | AD48: 0 | AE48: 0 | AF48: 0 | AG48: 0 | AH48: 0 | AI48: 0 | AJ48: 0 | AK48: 0 | AL48: 0 | AM48: 0 | AN48: 0 | AO48: 0 | AP48: 0 | AQ48: 0 | AR48: 0 | AS48: 0 | AT48: 0 | AU48: 0 | AV48: 0 | AW48: 0 | AX48: 0 | AY48: 0 | AZ48: 0
A49: District Heating Sector | B49: 0 | C49: 0 | D49: 0 | E49: 0 | F49: 0 | G49: 0 | H49: 0 | I49: 0 | J49: 0 | K49: 0 | L49: 0 | M49: 0 | N49: 0 | O49: 0 | P49: 0 | Q49: 0 | R49: 0 | S49: 0 | T49: 0 | U49: 0 | V49: 0 | W49: 0 | X49: 0 | Y49: 0 | Z49: 0 | AA49: 0 | AB49: 0 | AC49: 0 | AD49: 0 | AE49: 0 | AF49: 0 | AG49: 0 | AH49: 0 | AI49: 0 | AJ49: 0 | AK49: 0 | AL49: 0 | AM49: 0 | AN49: 0 | AO49: 0 | AP49: 0 | AQ49: 0 | AR49: 0 | AS49: 0 | AT49: 0 | AU49: 0 | AV49: 0 | AW49: 0 | AX49: 0 | AY49: 0 | AZ49: 0
A50: LULUCF Sector | B50: 0 | C50: 0 | D50: 0 | E50: 0 | F50: 0 | G50: 0 | H50: 0 | I50: 0 | J50: 0 | K50: 0 | L50: 0 | M50: 0 | N50: 0 | O50: 0 | P50: 0 | Q50: 0 | R50: 0 | S50: 0 | T50: 0 | U50: 0 | V50: 0 | W50: 0 | X50: 0 | Y50: 0 | Z50: 0 | AA50: 0 | AB50: 0 | AC50: 0 | AD50: 0 | AE50: 0 | AF50: 0 | AG50: 0 | AH50: 0 | AI50: 0 | AJ50: 0 | AK50: 0 | AL50: 0 | AM50: 0 | AN50: 0 | AO50: 0 | AP50: 0 | AQ50: 0 | AR50: 0 | AS50: 0 | AT50: 0 | AU50: 0 | AV50: 0 | AW50: 0 | AX50: 0 | AY50: 0 | AZ50: 0
A51: Geoengineering Sector | B51: 0 | C51: 0 | D51: 0 | E51: 0 | F51: 0 | G51: 0 | H51: 0 | I51: 0 | J51: 0 | K51: 0 | L51: 0 | M51: 0 | N51: 0 | O51: 0 | P51: 0 | Q51: 0 | R51: 0 | S51: 0 | T51: 0 | U51: 0 | V51: 0 | W51: 0 | X51: 0 | Y51: 0 | Z51: 0 | AA51: 0 | AB51: 0 | AC51: 0 | AD51: 0 | AE51: 0 | AF51: 0 | AG51: 0 | AH51: 0 | AI51: 0 | AJ51: 0 | AK51: 0 | AL51: 0 | AM51: 0 | AN51: 0 | AO51: 0 | AP51: 0 | AQ51: 0 | AR51: 0 | AS51: 0 | AT51: 0 | AU51: 0 | AV51: 0 | AW51: 0 | AX51: 0 | AY51: 0 | AZ51: 0
A52: Petroleum Diesel
A53: Year | B53: 2020 | C53: 2021 | D53: 2022 | E53: 2023 | F53: 2024 | G53: 2025 | H53: 2026 | I53: 2027 | J53: 2028 | K53: 2029 | L53: 2030 | M53: 2031 | N53: 2032 | O53: 2033 | P53: 2034 | Q53: 2035 | R53: 2036 | S53: 2037 | T53: 2038 | U53: 2039 | V53: 2040 | W53: 2041 | X53: 2042 | Y53: 2043 | Z53: 2044 | AA53: 2045 | AB53: 2046 | AC53: 2047 | AD53: 2048 | AE53: 2049 | AF53: 2050 | AG53: 2051 | AH53: 2052 | AI53: 2053 | AJ53: 2054 | AK53: 2055 | AL53: 2056 | AM53: 2057 | AN53: 2058 | AO53: 2059 | AP53: 2060 | AQ53: 2061 | AR53: 2062 | AS53: 2063 | AT53: 2064 | AU53: 2065 | AV53: 2066 | AW53: 2067 | AX53: 2068 | AY53: 2069 | AZ53: 2070
A54: Transportation Sector | B54: 1.2089986e-05 | C54: 1.5656388e-05 | D54: 2.2795693e-05 | E54: 1.9719122e-05 | F54: 1.8757337e-05 | G54: 1.7795552e-05 | H54: 1.6833767e-05 | I54: 1.5871982e-05 | J54: 1.4910197e-05 | K54: 1.5112213e-05 | L54: 1.5312719e-05 | M54: 1.580879e-05 | N54: 1.5983322e-05 | O54: 1.6151428e-05 | P54: 1.6243407e-05 | Q54: 1.6295299e-05 | R54: 1.6438007e-05 | S54: 1.6650181e-05 | T54: 1.6813377e-05 | U54: 1.6876561e-05 | V54: 1.7118274e-05 | W54: 1.7253424e-05 | X54: 1.7307135e-05 | Y54: 1.7541562e-05 | Z54: 1.7803519e-05 | AA54: 1.7946476e-05 | AB54: 1.8131512e-05 | AC54: 1.8224218e-05 | AD54: 1.8232475e-05 | AE54: 1.8273568e-05 | AF54: 1.8284554e-05 | AG54: =_xlfn.FORECAST.ETS(AG53,$B$54:$AF$54,$B$53:$AF$53) -> 1.8340585e-05 | AH54: =_xlfn.FORECAST.ETS(AH53,$B$54:$AF$54,$B$53:$AF$53) -> 1.8392383e-05 | AI54: =_xlfn.FORECAST.ETS(AI53,$B$54:$AF$54,$B$53:$AF$53) -> 1.8444182e-05 | AJ54: =_xlfn.FORECAST.ETS(AJ53,$B$54:$AF$54,$B$53:$AF$53) -> 1.8495981e-05 | AK54: =_xlfn.FORECAST.ETS(AK53,$B$54:$AF$54,$B$53:$AF$53) -> 1.854778e-05 | AL54: =_xlfn.FORECAST.ETS(AL53,$B$54:$AF$54,$B$53:$AF$53) -> 1.8599579e-05 | AM54: =_xlfn.FORECAST.ETS(AM53,$B$54:$AF$54,$B$53:$AF$53) -> 1.8651378e-05 | AN54: =_xlfn.FORECAST.ETS(AN53,$B$54:$AF$54,$B$53:$AF$53) -> 1.8703177e-05 | ... AZ54: =_xlfn.FORECAST.ETS(AZ53,$B$54:$AF$54,$B$53:$AF$53) -> 1.9324763e-05
A55: Electricity Sector | B55: 1.168118e-05 | C55: 1.4337337e-05 | D55: 2.201884e-05 | E55: 1.8279626e-05 | F55: 1.7129578e-05 | G55: 1.597953e-05 | H55: 1.4829482e-05 | I55: 1.3679434e-05 | J55: 1.2529387e-05 | K55: 1.2718015e-05 | L55: 1.291421e-05 | M55: 1.3112993e-05 | N55: 1.3292261e-05 | O55: 1.3385306e-05 | P55: 1.3522711e-05 | Q55: 1.3576444e-05 | R55: 1.3718558e-05 | S55: 1.3922841e-05 | T55: 1.40511e-05 | U55: 1.4099777e-05 | V55: 1.4333271e-05 | W55: 1.4442315e-05 | X55: 1.4505156e-05 | Y55: 1.4711251e-05 | Z55: 1.4951808e-05 | AA55: 1.5083351e-05 | AB55: 1.5300769e-05 | AC55: 1.5390797e-05 | AD55: 1.539076e-05 | AE55: 1.5433488e-05 | AF55: 1.5440184e-05 | AG55: =_xlfn.FORECAST.ETS(AG53,$B$55:$AF$55,$B$53:$AF$53) -> 1.5430569e-05 | AH55: =_xlfn.FORECAST.ETS(AH53,$B$55:$AF$55,$B$53:$AF$53) -> 1.5422915e-05 | AI55: =_xlfn.FORECAST.ETS(AI53,$B$55:$AF$55,$B$53:$AF$53) -> 1.5415261e-05 | AJ55: =_xlfn.FORECAST.ETS(AJ53,$B$55:$AF$55,$B$53:$AF$53) -> 1.5407607e-05 | AK55: =_xlfn.FORECAST.ETS(AK53,$B$55:$AF$55,$B$53:$AF$53) -> 1.5399953e-05 | AL55: =_xlfn.FORECAST.ETS(AL53,$B$55:$AF$55,$B$53:$AF$53) -> 1.5392299e-05 | AM55: =_xlfn.FORECAST.ETS(AM53,$B$55:$AF$55,$B$53:$AF$53) -> 1.5384645e-05 | AN55: =_xlfn.FORECAST.ETS(AN53,$B$55:$AF$55,$B$53:$AF$53) -> 1.5376991e-05 | ... AZ55: =_xlfn.FORECAST.ETS(AZ53,$B$55:$AF$55,$B$53:$AF$53) -> 1.5285145e-05
A56: Residential Buildings Sector | B56: 1.1706844e-05 | C56: 1.4334381e-05 | D56: 2.2022129e-05 | E56: 1.9460449e-05 | F56: 1.8817701e-05 | G56: 1.8174953e-05 | H56: 1.7532205e-05 | I56: 1.6889457e-05 | J56: 1.6246709e-05 | K56: 1.6450274e-05 | L56: 1.6671053e-05 | M56: 1.6948503e-05 | N56: 1.7135933e-05 | O56: 1.7263537e-05 | P56: 1.7366366e-05 | Q56: 1.7403554e-05 | R56: 1.7539201e-05 | S56: 1.7767301e-05 | T56: 1.7930644e-05 | U56: 1.798029e-05 | V56: 1.824256e-05 | W56: 1.8369184e-05 | X56: 1.8426138e-05 | Y56: 1.8640136e-05 | Z56: 1.8886527e-05 | AA56: 1.9030794e-05 | AB56: 1.9236185e-05 | AC56: 1.9310359e-05 | AD56: 1.9301863e-05 | AE56: 1.93505e-05 | AF56: 1.9370497e-05 | AG56: =_xlfn.FORECAST.ETS(AG53,$B$56:$AF$56,$B$53:$AF$53) -> 1.9476777e-05 | AH56: =_xlfn.FORECAST.ETS(AH53,$B$56:$AF$56,$B$53:$AF$53) -> 1.9574658e-05 | AI56: =_xlfn.FORECAST.ETS(AI53,$B$56:$AF$56,$B$53:$AF$53) -> 1.967254e-05 | AJ56: =_xlfn.FORECAST.ETS(AJ53,$B$56:$AF$56,$B$53:$AF$53) -> 1.9770421e-05 | AK56: =_xlfn.FORECAST.ETS(AK53,$B$56:$AF$56,$B$53:$AF$53) -> 1.9868303e-05 | AL56: =_xlfn.FORECAST.ETS(AL53,$B$56:$AF$56,$B$53:$AF$53) -> 1.9966184e-05 | AM56: =_xlfn.FORECAST.ETS(AM53,$B$56:$AF$56,$B$53:$AF$53) -> 2.0064065e-05 | AN56: =_xlfn.FORECAST.ETS(AN53,$B$56:$AF$56,$B$53:$AF$53) -> 2.0161947e-05 | ... AZ56: =_xlfn.FORECAST.ETS(AZ53,$B$56:$AF$56,$B$53:$AF$53) -> 2.1336524e-05
A57: Commercial Buildings Sector | B57: 1.1757432e-05 | C57: 1.4386042e-05 | D57: 2.2105069e-05 | E57: 1.849744e-05 | F57: 1.7356168e-05 | G57: 1.6214896e-05 | H57: 1.5073624e-05 | I57: 1.3932353e-05 | J57: 1.2791081e-05 | K57: 1.2964664e-05 | L57: 1.3135487e-05 | M57: 1.3602247e-05 | N57: 1.3770093e-05 | O57: 1.3915194e-05 | P57: 1.4007466e-05 | Q57: 1.4057366e-05 | R57: 1.4191151e-05 | S57: 1.4405462e-05 | T57: 1.4557178e-05 | U57: 1.4606365e-05 | V57: 1.4836662e-05 | W57: 1.495692e-05 | X57: 1.5007381e-05 | Y57: 1.5224082e-05 | Z57: 1.5470671e-05 | AA57: 1.5607054e-05 | AB57: 1.5790854e-05 | AC57: 1.586686e-05 | AD57: 1.5863356e-05 | AE57: 1.5897204e-05 | AF57: 1.5892782e-05 | AG57: =_xlfn.FORECAST.ETS(AG53,$B$57:$AF$57,$B$53:$AF$53) -> 1.5899851e-05 | AH57: =_xlfn.FORECAST.ETS(AH53,$B$57:$AF$57,$B$53:$AF$53) -> 1.5906125e-05 | AI57: =_xlfn.FORECAST.ETS(AI53,$B$57:$AF$57,$B$53:$AF$53) -> 1.5912398e-05 | AJ57: =_xlfn.FORECAST.ETS(AJ53,$B$57:$AF$57,$B$53:$AF$53) -> 1.5918671e-05 | AK57: =_xlfn.FORECAST.ETS(AK53,$B$57:$AF$57,$B$53:$AF$53) -> 1.5924945e-05 | AL57: =_xlfn.FORECAST.ETS(AL53,$B$57:$AF$57,$B$53:$AF$53) -> 1.5931218e-05 | AM57: =_xlfn.FORECAST.ETS(AM53,$B$57:$AF$57,$B$53:$AF$53) -> 1.5937492e-05 | AN57: =_xlfn.FORECAST.ETS(AN53,$B$57:$AF$57,$B$53:$AF$53) -> 1.5943765e-05 | ... AZ57: =_xlfn.FORECAST.ETS(AZ53,$B$57:$AF$57,$B$53:$AF$53) -> 1.6019047e-05
A58: Industry Sector | B58: 1.1708485e-05 | C58: 1.4339363e-05 | D58: 2.2028825e-05 | E58: 1.8501723e-05 | F58: 1.7349896e-05 | G58: 1.6198068e-05 | H58: 1.504624e-05 | I58: 1.3894413e-05 | J58: 1.2742585e-05 | K58: 1.2922082e-05 | L58: 1.3095464e-05 | M58: 1.3360099e-05 | N58: 1.3526108e-05 | O58: 1.3650187e-05 | P58: 1.3739639e-05 | Q58: 1.3796351e-05 | R58: 1.3935824e-05 | S58: 1.4153294e-05 | T58: 1.4307851e-05 | U58: 1.4361701e-05 | V58: 1.4587847e-05 | W58: 1.4714272e-05 | X58: 1.4767564e-05 | Y58: 1.4995034e-05 | Z58: 1.5247742e-05 | AA58: 1.5386494e-05 | AB58: 1.556703e-05 | AC58: 1.5649888e-05 | AD58: 1.5655022e-05 | AE58: 1.5688497e-05 | AF58: 1.5683758e-05 | AG58: =_xlfn.FORECAST.ETS(AG53,$B$58:$AF$58,$B$53:$AF$53) -> 1.5681847e-05 | AH58: =_xlfn.FORECAST.ETS(AH53,$B$58:$AF$58,$B$53:$AF$53) -> 1.5680016e-05 | AI58: =_xlfn.FORECAST.ETS(AI53,$B$58:$AF$58,$B$53:$AF$53) -> 1.5678186e-05 | AJ58: =_xlfn.FORECAST.ETS(AJ53,$B$58:$AF$58,$B$53:$AF$53) -> 1.5676355e-05 | AK58: =_xlfn.FORECAST.ETS(AK53,$B$58:$AF$58,$B$53:$AF$53) -> 1.5674524e-05 | AL58: =_xlfn.FORECAST.ETS(AL53,$B$58:$AF$58,$B$53:$AF$53) -> 1.5672693e-05 | AM58: =_xlfn.FORECAST.ETS(AM53,$B$58:$AF$58,$B$53:$AF$53) -> 1.5670863e-05 | AN58: =_xlfn.FORECAST.ETS(AN53,$B$58:$AF$58,$B$53:$AF$53) -> 1.5669032e-05 | ... AZ58: =_xlfn.FORECAST.ETS(AZ53,$B$58:$AF$58,$B$53:$AF$53) -> 1.5647063e-05
A59: District Heating Sector | B59: 1.168118e-05 | C59: 1.4337337e-05 | D59: 2.201884e-05 | E59: 1.8279626e-05 | F59: 1.7129578e-05 | G59: 1.597953e-05 | H59: 1.4829482e-05 | I59: 1.3679434e-05 | J59: 1.2529387e-05 | K59: 1.2718015e-05 | L59: 1.291421e-05 | M59: 1.3112993e-05 | N59: 1.3292261e-05 | O59: 1.3385306e-05 | P59: 1.3522711e-05 | Q59: 1.3576444e-05 | R59: 1.3718558e-05 | S59: 1.3922841e-05 | T59: 1.40511e-05 | U59: 1.4099777e-05 | V59: 1.4333271e-05 | W59: 1.4442315e-05 | X59: 1.4505156e-05 | Y59: 1.4711251e-05 | Z59: 1.4951808e-05 | AA59: 1.5083351e-05 | AB59: 1.5300769e-05 | AC59: 1.5390797e-05 | AD59: 1.539076e-05 | AE59: 1.5433488e-05 | AF59: 1.5440184e-05 | AG59: =_xlfn.FORECAST.ETS(AG53,$B$59:$AF$59,$B$53:$AF$53) -> 1.5430569e-05 | AH59: =_xlfn.FORECAST.ETS(AH53,$B$59:$AF$59,$B$53:$AF$53) -> 1.5422915e-05 | AI59: =_xlfn.FORECAST.ETS(AI53,$B$59:$AF$59,$B$53:$AF$53) -> 1.5415261e-05 | AJ59: =_xlfn.FORECAST.ETS(AJ53,$B$59:$AF$59,$B$53:$AF$53) -> 1.5407607e-05 | AK59: =_xlfn.FORECAST.ETS(AK53,$B$59:$AF$59,$B$53:$AF$53) -> 1.5399953e-05 | AL59: =_xlfn.FORECAST.ETS(AL53,$B$59:$AF$59,$B$53:$AF$53) -> 1.5392299e-05 | AM59: =_xlfn.FORECAST.ETS(AM53,$B$59:$AF$59,$B$53:$AF$53) -> 1.5384645e-05 | AN59: =_xlfn.FORECAST.ETS(AN53,$B$59:$AF$59,$B$53:$AF$53) -> 1.5376991e-05 | ... AZ59: =_xlfn.FORECAST.ETS(AZ53,$B$59:$AF$59,$B$53:$AF$53) -> 1.5285145e-05
A60: LULUCF Sector | B60: 0 | C60: 0 | D60: 0 | E60: 0 | F60: 0 | G60: 0 | H60: 0 | I60: 0 | J60: 0 | K60: 0 | L60: 0 | M60: 0 | N60: 0 | O60: 0 | P60: 0 | Q60: 0 | R60: 0 | S60: 0 | T60: 0 | U60: 0 | V60: 0 | W60: 0 | X60: 0 | Y60: 0 | Z60: 0 | AA60: 0 | AB60: 0 | AC60: 0 | AD60: 0 | AE60: 0 | AF60: 0 | AG60: 0 | AH60: 0 | AI60: 0 | AJ60: 0 | AK60: 0 | AL60: 0 | AM60: 0 | AN60: 0 | AO60: 0 | AP60: 0 | AQ60: 0 | AR60: 0 | AS60: 0 | AT60: 0 | AU60: 0 | AV60: 0 | AW60: 0 | AX60: 0 | AY60: 0 | AZ60: 0
A61: Geoengineering Sector | B61: 1.1708485e-05 | C61: 1.4339363e-05 | D61: 2.2028825e-05 | E61: 1.8501723e-05 | F61: 1.7349896e-05 | G61: 1.6198068e-05 | H61: 1.504624e-05 | I61: 1.3894413e-05 | J61: 1.2742585e-05 | K61: 1.2922082e-05 | L61: 1.3095464e-05 | M61: 1.3360099e-05 | N61: 1.3526108e-05 | O61: 1.3650187e-05 | P61: 1.3739639e-05 | Q61: 1.3796351e-05 | R61: 1.3935824e-05 | S61: 1.4153294e-05 | T61: 1.4307851e-05 | U61: 1.4361701e-05 | V61: 1.4587847e-05 | W61: 1.4714272e-05 | X61: 1.4767564e-05 | Y61: 1.4995034e-05 | Z61: 1.5247742e-05 | AA61: 1.5386494e-05 | AB61: 1.556703e-05 | AC61: 1.5649888e-05 | AD61: 1.5655022e-05 | AE61: 1.5688497e-05 | AF61: 1.5683758e-05 | AG61: =_xlfn.FORECAST.ETS(AG53,$B$61:$AF$61,$B$53:$AF$53) -> 1.5681847e-05 | AH61: =_xlfn.FORECAST.ETS(AH53,$B$61:$AF$61,$B$53:$AF$53) -> 1.5680016e-05 | AI61: =_xlfn.FORECAST.ETS(AI53,$B$61:$AF$61,$B$53:$AF$53) -> 1.5678186e-05 | AJ61: =_xlfn.FORECAST.ETS(AJ53,$B$61:$AF$61,$B$53:$AF$53) -> 1.5676355e-05 | AK61: =_xlfn.FORECAST.ETS(AK53,$B$61:$AF$61,$B$53:$AF$53) -> 1.5674524e-05 | AL61: =_xlfn.FORECAST.ETS(AL53,$B$61:$AF$61,$B$53:$AF$53) -> 1.5672693e-05 | AM61: =_xlfn.FORECAST.ETS(AM53,$B$61:$AF$61,$B$53:$AF$53) -> 1.5670863e-05 | AN61: =_xlfn.FORECAST.ETS(AN53,$B$61:$AF$61,$B$53:$AF$53) -> 1.5669032e-05 | ... AZ61: =_xlfn.FORECAST.ETS(AZ53,$B$61:$AF$61,$B$53:$AF$53) -> 1.5647063e-05
A62: Biofuel Gasoline
A63: Year | B63: 2020 | C63: 2021 | D63: 2022 | E63: 2023 | F63: 2024 | G63: 2025 | H63: 2026 | I63: 2027 | J63: 2028 | K63: 2029 | L63: 2030 | M63: 2031 | N63: 2032 | O63: 2033 | P63: 2034 | Q63: 2035 | R63: 2036 | S63: 2037 | T63: 2038 | U63: 2039 | V63: 2040 | W63: 2041 | X63: 2042 | Y63: 2043 | Z63: 2044 | AA63: 2045 | AB63: 2046 | AC63: 2047 | AD63: 2048 | AE63: 2049 | AF63: 2050 | AG63: 2051 | AH63: 2052 | AI63: 2053 | AJ63: 2054 | AK63: 2055 | AL63: 2056 | AM63: 2057 | AN63: 2058 | AO63: 2059 | AP63: 2060 | AQ63: 2061 | AR63: 2062 | AS63: 2063 | AT63: 2064 | AU63: 2065 | AV63: 2066 | AW63: 2067 | AX63: 2068 | AY63: 2069 | AZ63: 2070
A64: Transportation Sector | B64: 1.2558726e-05 | C64: 1.5006498e-05 | D64: 1.5129905e-05 | E64: 1.5209111e-05 | F64: 1.5051184e-05 | G64: 1.4872987e-05 | H64: 1.5096538e-05 | I64: 1.5547915e-05 | J64: 1.5887296e-05 | K64: 1.6210223e-05 | L64: 1.7061356e-05 | M64: 1.7558506e-05 | N64: 1.7941594e-05 | O64: 1.8157524e-05 | P64: 1.8652222e-05 | Q64: 1.8724324e-05 | R64: 1.8814969e-05 | S64: 1.9020214e-05 | T64: 1.9372611e-05 | U64: 1.9416321e-05 | V64: 1.9653072e-05 | W64: 1.9878433e-05 | X64: 1.9922621e-05 | Y64: 2.0184501e-05 | Z64: 2.0465893e-05 | AA64: 2.0631456e-05 | AB64: 2.0869771e-05 | AC64: 2.1006863e-05 | AD64: 2.1016654e-05 | AE64: 2.1116624e-05 | AF64: 2.1194442e-05 | AG64: =_xlfn.FORECAST.ETS(AG63,$B$64:$AF$64,$B$63:$AF$63) -> 2.1316523e-05 | AH64: =_xlfn.FORECAST.ETS(AH63,$B$64:$AF$64,$B$63:$AF$63) -> 2.1438486e-05 | AI64: =_xlfn.FORECAST.ETS(AI63,$B$64:$AF$64,$B$63:$AF$63) -> 2.1560449e-05 | AJ64: =_xlfn.FORECAST.ETS(AJ63,$B$64:$AF$64,$B$63:$AF$63) -> 2.1682413e-05 | AK64: =_xlfn.FORECAST.ETS(AK63,$B$64:$AF$64,$B$63:$AF$63) -> 2.1804376e-05 | AL64: =_xlfn.FORECAST.ETS(AL63,$B$64:$AF$64,$B$63:$AF$63) -> 2.1926339e-05 | AM64: =_xlfn.FORECAST.ETS(AM63,$B$64:$AF$64,$B$63:$AF$63) -> 2.2048302e-05 | AN64: =_xlfn.FORECAST.ETS(AN63,$B$64:$AF$64,$B$63:$AF$63) -> 2.2170265e-05 | ... AZ64: =_xlfn.FORECAST.ETS(AZ63,$B$64:$AF$64,$B$63:$AF$63) -> 2.3633824e-05
A65: Electricity Sector | B65: 0 | C65: 0 | D65: 0 | E65: 0 | F65: 0 | G65: 0 | H65: 0 | I65: 0 | J65: 0 | K65: 0 | L65: 0 | M65: 0 | N65: 0 | O65: 0 | P65: 0 | Q65: 0 | R65: 0 | S65: 0 | T65: 0 | U65: 0 | V65: 0 | W65: 0 | X65: 0 | Y65: 0 | Z65: 0 | AA65: 0 | AB65: 0 | AC65: 0 | AD65: 0 | AE65: 0 | AF65: 0 | AG65: 0 | AH65: 0 | AI65: 0 | AJ65: 0 | AK65: 0 | AL65: 0 | AM65: 0 | AN65: 0 | AO65: 0 | AP65: 0 | AQ65: 0 | AR65: 0 | AS65: 0 | AT65: 0 | AU65: 0 | AV65: 0 | AW65: 0 | AX65: 0 | AY65: 0 | AZ65: 0
A66: Residential Buildings Sector | B66: 0 | C66: 0 | D66: 0 | E66: 0 | F66: 0 | G66: 0 | H66: 0 | I66: 0 | J66: 0 | K66: 0 | L66: 0 | M66: 0 | N66: 0 | O66: 0 | P66: 0 | Q66: 0 | R66: 0 | S66: 0 | T66: 0 | U66: 0 | V66: 0 | W66: 0 | X66: 0 | Y66: 0 | Z66: 0 | AA66: 0 | AB66: 0 | AC66: 0 | AD66: 0 | AE66: 0 | AF66: 0 | AG66: 0 | AH66: 0 | AI66: 0 | AJ66: 0 | AK66: 0 | AL66: 0 | AM66: 0 | AN66: 0 | AO66: 0 | AP66: 0 | AQ66: 0 | AR66: 0 | AS66: 0 | AT66: 0 | AU66: 0 | AV66: 0 | AW66: 0 | AX66: 0 | AY66: 0 | AZ66: 0
A67: Commercial Buildings Sector | B67: 0 | C67: 0 | D67: 0 | E67: 0 | F67: 0 | G67: 0 | H67: 0 | I67: 0 | J67: 0 | K67: 0 | L67: 0 | M67: 0 | N67: 0 | O67: 0 | P67: 0 | Q67: 0 | R67: 0 | S67: 0 | T67: 0 | U67: 0 | V67: 0 | W67: 0 | X67: 0 | Y67: 0 | Z67: 0 | AA67: 0 | AB67: 0 | AC67: 0 | AD67: 0 | AE67: 0 | AF67: 0 | AG67: 0 | AH67: 0 | AI67: 0 | AJ67: 0 | AK67: 0 | AL67: 0 | AM67: 0 | AN67: 0 | AO67: 0 | AP67: 0 | AQ67: 0 | AR67: 0 | AS67: 0 | AT67: 0 | AU67: 0 | AV67: 0 | AW67: 0 | AX67: 0 | AY67: 0 | AZ67: 0
A68: Industry Sector | B68: 0 | C68: 0 | D68: 0 | E68: 0 | F68: 0 | G68: 0 | H68: 0 | I68: 0 | J68: 0 | K68: 0 | L68: 0 | M68: 0 | N68: 0 | O68: 0 | P68: 0 | Q68: 0 | R68: 0 | S68: 0 | T68: 0 | U68: 0 | V68: 0 | W68: 0 | X68: 0 | Y68: 0 | Z68: 0 | AA68: 0 | AB68: 0 | AC68: 0 | AD68: 0 | AE68: 0 | AF68: 0 | AG68: 0 | AH68: 0 | AI68: 0 | AJ68: 0 | AK68: 0 | AL68: 0 | AM68: 0 | AN68: 0 | AO68: 0 | AP68: 0 | AQ68: 0 | AR68: 0 | AS68: 0 | AT68: 0 | AU68: 0 | AV68: 0 | AW68: 0 | AX68: 0 | AY68: 0 | AZ68: 0
A69: District Heating Sector | B69: 0 | C69: 0 | D69: 0 | E69: 0 | F69: 0 | G69: 0 | H69: 0 | I69: 0 | J69: 0 | K69: 0 | L69: 0 | M69: 0 | N69: 0 | O69: 0 | P69: 0 | Q69: 0 | R69: 0 | S69: 0 | T69: 0 | U69: 0 | V69: 0 | W69: 0 | X69: 0 | Y69: 0 | Z69: 0 | AA69: 0 | AB69: 0 | AC69: 0 | AD69: 0 | AE69: 0 | AF69: 0 | AG69: 0 | AH69: 0 | AI69: 0 | AJ69: 0 | AK69: 0 | AL69: 0 | AM69: 0 | AN69: 0 | AO69: 0 | AP69: 0 | AQ69: 0 | AR69: 0 | AS69: 0 | AT69: 0 | AU69: 0 | AV69: 0 | AW69: 0 | AX69: 0 | AY69: 0 | AZ69: 0
A70: LULUCF Sector | B70: 0 | C70: 0 | D70: 0 | E70: 0 | F70: 0 | G70: 0 | H70: 0 | I70: 0 | J70: 0 | K70: 0 | L70: 0 | M70: 0 | N70: 0 | O70: 0 | P70: 0 | Q70: 0 | R70: 0 | S70: 0 | T70: 0 | U70: 0 | V70: 0 | W70: 0 | X70: 0 | Y70: 0 | Z70: 0 | AA70: 0 | AB70: 0 | AC70: 0 | AD70: 0 | AE70: 0 | AF70: 0 | AG70: 0 | AH70: 0 | AI70: 0 | AJ70: 0 | AK70: 0 | AL70: 0 | AM70: 0 | AN70: 0 | AO70: 0 | AP70: 0 | AQ70: 0 | AR70: 0 | AS70: 0 | AT70: 0 | AU70: 0 | AV70: 0 | AW70: 0 | AX70: 0 | AY70: 0 | AZ70: 0
A71: Geoengineering Sector | B71: 0 | C71: 0 | D71: 0 | E71: 0 | F71: 0 | G71: 0 | H71: 0 | I71: 0 | J71: 0 | K71: 0 | L71: 0 | M71: 0 | N71: 0 | O71: 0 | P71: 0 | Q71: 0 | R71: 0 | S71: 0 | T71: 0 | U71: 0 | V71: 0 | W71: 0 | X71: 0 | Y71: 0 | Z71: 0 | AA71: 0 | AB71: 0 | AC71: 0 | AD71: 0 | AE71: 0 | AF71: 0 | AG71: 0 | AH71: 0 | AI71: 0 | AJ71: 0 | AK71: 0 | AL71: 0 | AM71: 0 | AN71: 0 | AO71: 0 | AP71: 0 | AQ71: 0 | AR71: 0 | AS71: 0 | AT71: 0 | AU71: 0 | AV71: 0 | AW71: 0 | AX71: 0 | AY71: 0 | AZ71: 0
A72: Biofuel Diesel
A73: Year | B73: 2020 | C73: 2021 | D73: 2022 | E73: 2023 | F73: 2024 | G73: 2025 | H73: 2026 | I73: 2027 | J73: 2028 | K73: 2029 | L73: 2030 | M73: 2031 | N73: 2032 | O73: 2033 | P73: 2034 | Q73: 2035 | R73: 2036 | S73: 2037 | T73: 2038 | U73: 2039 | V73: 2040 | W73: 2041 | X73: 2042 | Y73: 2043 | Z73: 2044 | AA73: 2045 | AB73: 2046 | AC73: 2047 | AD73: 2048 | AE73: 2049 | AF73: 2050 | AG73: 2051 | AH73: 2052 | AI73: 2053 | AJ73: 2054 | AK73: 2055 | AL73: 2056 | AM73: 2057 | AN73: 2058 | AO73: 2059 | AP73: 2060 | AQ73: 2061 | AR73: 2062 | AS73: 2063 | AT73: 2064 | AU73: 2065 | AV73: 2066 | AW73: 2067 | AX73: 2068 | AY73: 2069 | AZ73: 2070
A74: Transportation Sector | B74: 1.2380099e-05 | C74: 1.2337063e-05 | D74: 1.3174898e-05 | E74: 1.4731359e-05 | F74: 1.5347416e-05 | G74: 1.5826636e-05 | H74: 1.6238322e-05 | I74: 1.6757256e-05 | J74: 1.717985e-05 | K74: 1.7480586e-05 | L74: 1.8315367e-05 | M74: 1.8613107e-05 | N74: 1.8970277e-05 | O74: 1.9168768e-05 | P74: 1.9325044e-05 | Q74: 1.9408195e-05 | R74: 1.9472842e-05 | S74: 1.9769626e-05 | T74: 2.0005703e-05 | U74: 2.0007525e-05 | V74: 2.0433226e-05 | W74: 2.068223e-05 | X74: 2.0846538e-05 | Y74: 2.1106943e-05 | Z74: 2.1227992e-05 | AA74: 2.1277615e-05 | AB74: 2.159131e-05 | AC74: 2.1740855e-05 | AD74: 2.1803794e-05 | AE74: 2.1971007e-05 | AF74: 2.2014282e-05 | AG74: =_xlfn.FORECAST.ETS(AG73,$B$74:$AF$74,$B$73:$AF$73) -> 2.2194586e-05 | AH74: =_xlfn.FORECAST.ETS(AH73,$B$74:$AF$74,$B$73:$AF$73) -> 2.233175e-05 | AI74: =_xlfn.FORECAST.ETS(AI73,$B$74:$AF$74,$B$73:$AF$73) -> 2.2468913e-05 | AJ74: =_xlfn.FORECAST.ETS(AJ73,$B$74:$AF$74,$B$73:$AF$73) -> 2.2606076e-05 | AK74: =_xlfn.FORECAST.ETS(AK73,$B$74:$AF$74,$B$73:$AF$73) -> 2.274324e-05 | AL74: =_xlfn.FORECAST.ETS(AL73,$B$74:$AF$74,$B$73:$AF$73) -> 2.2880403e-05 | AM74: =_xlfn.FORECAST.ETS(AM73,$B$74:$AF$74,$B$73:$AF$73) -> 2.3017566e-05 | AN74: =_xlfn.FORECAST.ETS(AN73,$B$74:$AF$74,$B$73:$AF$73) -> 2.3154729e-05 | ... AZ74: =_xlfn.FORECAST.ETS(AZ73,$B$74:$AF$74,$B$73:$AF$73) -> 2.4800689e-05
A75: Electricity Sector | B75: 0 | C75: 0 | D75: 0 | E75: 0 | F75: 0 | G75: 0 | H75: 0 | I75: 0 | J75: 0 | K75: 0 | L75: 0 | M75: 0 | N75: 0 | O75: 0 | P75: 0 | Q75: 0 | R75: 0 | S75: 0 | T75: 0 | U75: 0 | V75: 0 | W75: 0 | X75: 0 | Y75: 0 | Z75: 0 | AA75: 0 | AB75: 0 | AC75: 0 | AD75: 0 | AE75: 0 | AF75: 0 | AG75: 0 | AH75: 0 | AI75: 0 | AJ75: 0 | AK75: 0 | AL75: 0 | AM75: 0 | AN75: 0 | AO75: 0 | AP75: 0 | AQ75: 0 | AR75: 0 | AS75: 0 | AT75: 0 | AU75: 0 | AV75: 0 | AW75: 0 | AX75: 0 | AY75: 0 | AZ75: 0
A76: Residential Buildings Sector | B76: 0 | C76: 0 | D76: 0 | E76: 0 | F76: 0 | G76: 0 | H76: 0 | I76: 0 | J76: 0 | K76: 0 | L76: 0 | M76: 0 | N76: 0 | O76: 0 | P76: 0 | Q76: 0 | R76: 0 | S76: 0 | T76: 0 | U76: 0 | V76: 0 | W76: 0 | X76: 0 | Y76: 0 | Z76: 0 | AA76: 0 | AB76: 0 | AC76: 0 | AD76: 0 | AE76: 0 | AF76: 0 | AG76: 0 | AH76: 0 | AI76: 0 | AJ76: 0 | AK76: 0 | AL76: 0 | AM76: 0 | AN76: 0 | AO76: 0 | AP76: 0 | AQ76: 0 | AR76: 0 | AS76: 0 | AT76: 0 | AU76: 0 | AV76: 0 | AW76: 0 | AX76: 0 | AY76: 0 | AZ76: 0
A77: Commercial Buildings Sector | B77: 0 | C77: 0 | D77: 0 | E77: 0 | F77: 0 | G77: 0 | H77: 0 | I77: 0 | J77: 0 | K77: 0 | L77: 0 | M77: 0 | N77: 0 | O77: 0 | P77: 0 | Q77: 0 | R77: 0 | S77: 0 | T77: 0 | U77: 0 | V77: 0 | W77: 0 | X77: 0 | Y77: 0 | Z77: 0 | AA77: 0 | AB77: 0 | AC77: 0 | AD77: 0 | AE77: 0 | AF77: 0 | AG77: 0 | AH77: 0 | AI77: 0 | AJ77: 0 | AK77: 0 | AL77: 0 | AM77: 0 | AN77: 0 | AO77: 0 | AP77: 0 | AQ77: 0 | AR77: 0 | AS77: 0 | AT77: 0 | AU77: 0 | AV77: 0 | AW77: 0 | AX77: 0 | AY77: 0 | AZ77: 0
A78: Industry Sector | B78: 0 | C78: 0 | D78: 0 | E78: 0 | F78: 0 | G78: 0 | H78: 0 | I78: 0 | J78: 0 | K78: 0 | L78: 0 | M78: 0 | N78: 0 | O78: 0 | P78: 0 | Q78: 0 | R78: 0 | S78: 0 | T78: 0 | U78: 0 | V78: 0 | W78: 0 | X78: 0 | Y78: 0 | Z78: 0 | AA78: 0 | AB78: 0 | AC78: 0 | AD78: 0 | AE78: 0 | AF78: 0 | AG78: 0 | AH78: 0 | AI78: 0 | AJ78: 0 | AK78: 0 | AL78: 0 | AM78: 0 | AN78: 0 | AO78: 0 | AP78: 0 | AQ78: 0 | AR78: 0 | AS78: 0 | AT78: 0 | AU78: 0 | AV78: 0 | AW78: 0 | AX78: 0 | AY78: 0 | AZ78: 0
A79: District Heating Sector | B79: 0 | C79: 0 | D79: 0 | E79: 0 | F79: 0 | G79: 0 | H79: 0 | I79: 0 | J79: 0 | K79: 0 | L79: 0 | M79: 0 | N79: 0 | O79: 0 | P79: 0 | Q79: 0 | R79: 0 | S79: 0 | T79: 0 | U79: 0 | V79: 0 | W79: 0 | X79: 0 | Y79: 0 | Z79: 0 | AA79: 0 | AB79: 0 | AC79: 0 | AD79: 0 | AE79: 0 | AF79: 0 | AG79: 0 | AH79: 0 | AI79: 0 | AJ79: 0 | AK79: 0 | AL79: 0 | AM79: 0 | AN79: 0 | AO79: 0 | AP79: 0 | AQ79: 0 | AR79: 0 | AS79: 0 | AT79: 0 | AU79: 0 | AV79: 0 | AW79: 0 | AX79: 0 | AY79: 0 | AZ79: 0
A80: LULUCF Sector | B80: 0 | C80: 0 | D80: 0 | E80: 0 | F80: 0 | G80: 0 | H80: 0 | I80: 0 | J80: 0 | K80: 0 | L80: 0 | M80: 0 | N80: 0 | O80: 0 | P80: 0 | Q80: 0 | R80: 0 | S80: 0 | T80: 0 | U80: 0 | V80: 0 | W80: 0 | X80: 0 | Y80: 0 | Z80: 0 | AA80: 0 | AB80: 0 | AC80: 0 | AD80: 0 | AE80: 0 | AF80: 0 | AG80: 0 | AH80: 0 | AI80: 0 | AJ80: 0 | AK80: 0 | AL80: 0 | AM80: 0 | AN80: 0 | AO80: 0 | AP80: 0 | AQ80: 0 | AR80: 0 | AS80: 0 | AT80: 0 | AU80: 0 | AV80: 0 | AW80: 0 | AX80: 0 | AY80: 0 | AZ80: 0
A81: Geoengineering Sector | B81: 0 | C81: 0 | D81: 0 | E81: 0 | F81: 0 | G81: 0 | H81: 0 | I81: 0 | J81: 0 | K81: 0 | L81: 0 | M81: 0 | N81: 0 | O81: 0 | P81: 0 | Q81: 0 | R81: 0 | S81: 0 | T81: 0 | U81: 0 | V81: 0 | W81: 0 | X81: 0 | Y81: 0 | Z81: 0 | AA81: 0 | AB81: 0 | AC81: 0 | AD81: 0 | AE81: 0 | AF81: 0 | AG81: 0 | AH81: 0 | AI81: 0 | AJ81: 0 | AK81: 0 | AL81: 0 | AM81: 0 | AN81: 0 | AO81: 0 | AP81: 0 | AQ81: 0 | AR81: 0 | AS81: 0 | AT81: 0 | AU81: 0 | AV81: 0 | AW81: 0 | AX81: 0 | AY81: 0 | AZ81: 0
A82: Jet Fuel
A83: Year | B83: 2020 | C83: 2021 | D83: 2022 | E83: 2023 | F83: 2024 | G83: 2025 | H83: 2026 | I83: 2027 | J83: 2028 | K83: 2029 | L83: 2030 | M83: 2031 | N83: 2032 | O83: 2033 | P83: 2034 | Q83: 2035 | R83: 2036 | S83: 2037 | T83: 2038 | U83: 2039 | V83: 2040 | W83: 2041 | X83: 2042 | Y83: 2043 | Z83: 2044 | AA83: 2045 | AB83: 2046 | AC83: 2047 | AD83: 2048 | AE83: 2049 | AF83: 2050 | AG83: 2051 | AH83: 2052 | AI83: 2053 | AJ83: 2054 | AK83: 2055 | AL83: 2056 | AM83: 2057 | AN83: 2058 | AO83: 2059 | AP83: 2060 | AQ83: 2061 | AR83: 2062 | AS83: 2063 | AT83: 2064 | AU83: 2065 | AV83: 2066 | AW83: 2067 | AX83: 2068 | AY83: 2069 | AZ83: 2070
A84: Transportation Sector | B84: 7.7566703e-06 | C84: 1.1563325e-05 | D84: 2.0850154e-05 | E84: 1.6712544e-05 | F84: 1.5961729e-05 | G84: 1.5210915e-05 | H84: 1.44601e-05 | I84: 1.3709285e-05 | J84: 1.2958471e-05 | K84: 1.311934e-05 | L84: 1.3104677e-05 | M84: 1.351269e-05 | N84: 1.3683819e-05 | O84: 1.3789924e-05 | P84: 1.3937848e-05 | Q84: 1.402847e-05 | R84: 1.4189464e-05 | S84: 1.4412171e-05 | T84: 1.4572836e-05 | U84: 1.4656807e-05 | V84: 1.4832437e-05 | W84: 1.495952e-05 | X84: 1.5002668e-05 | Y84: 1.5250786e-05 | Z84: 1.5517655e-05 | AA84: 1.5621484e-05 | AB84: 1.5802554e-05 | AC84: 1.5886319e-05 | AD84: 1.5870793e-05 | AE84: 1.5916647e-05 | AF84: 1.5879607e-05 | AG84: =_xlfn.FORECAST.ETS(AG83,$B$84:$AF$84,$B$83:$AF$83) -> 1.5968506e-05 | AH84: =_xlfn.FORECAST.ETS(AH83,$B$84:$AF$84,$B$83:$AF$83) -> 1.6045577e-05 | AI84: =_xlfn.FORECAST.ETS(AI83,$B$84:$AF$84,$B$83:$AF$83) -> 1.6122649e-05 | AJ84: =_xlfn.FORECAST.ETS(AJ83,$B$84:$AF$84,$B$83:$AF$83) -> 1.619972e-05 | AK84: =_xlfn.FORECAST.ETS(AK83,$B$84:$AF$84,$B$83:$AF$83) -> 1.6276792e-05 | AL84: =_xlfn.FORECAST.ETS(AL83,$B$84:$AF$84,$B$83:$AF$83) -> 1.6353863e-05 | AM84: =_xlfn.FORECAST.ETS(AM83,$B$84:$AF$84,$B$83:$AF$83) -> 1.6430934e-05 | AN84: =_xlfn.FORECAST.ETS(AN83,$B$84:$AF$84,$B$83:$AF$83) -> 1.6508006e-05 | ... AZ84: =_xlfn.FORECAST.ETS(AZ83,$B$84:$AF$84,$B$83:$AF$83) -> 1.7432863e-05
A85: Electricity Sector | B85: 0 | C85: 0 | D85: 0 | E85: 0 | F85: 0 | G85: 0 | H85: 0 | I85: 0 | J85: 0 | K85: 0 | L85: 0 | M85: 0 | N85: 0 | O85: 0 | P85: 0 | Q85: 0 | R85: 0 | S85: 0 | T85: 0 | U85: 0 | V85: 0 | W85: 0 | X85: 0 | Y85: 0 | Z85: 0 | AA85: 0 | AB85: 0 | AC85: 0 | AD85: 0 | AE85: 0 | AF85: 0 | AG85: 0 | AH85: 0 | AI85: 0 | AJ85: 0 | AK85: 0 | AL85: 0 | AM85: 0 | AN85: 0 | AO85: 0 | AP85: 0 | AQ85: 0 | AR85: 0 | AS85: 0 | AT85: 0 | AU85: 0 | AV85: 0 | AW85: 0 | AX85: 0 | AY85: 0 | AZ85: 0
A86: Residential Buildings Sector | B86: 1.4387415e-05 | C86: 1.7080751e-05 | D86: 2.9901056e-05 | E86: 2.5300227e-05 | F86: 2.4224032e-05 | G86: 2.3147837e-05 | H86: 2.2071642e-05 | I86: 2.0995447e-05 | J86: 1.9919252e-05 | K86: 2.0055848e-05 | L86: 2.0074233e-05 | M86: 2.03236e-05 | N86: 2.0442511e-05 | O86: 2.051799e-05 | P86: 2.0575591e-05 | Q86: 2.0639857e-05 | R86: 2.0779953e-05 | S86: 2.0977397e-05 | T86: 2.110336e-05 | U86: 2.1158751e-05 | V86: 2.1374782e-05 | W86: 2.147095e-05 | X86: 2.149552e-05 | Y86: 2.1696126e-05 | Z86: 2.1926301e-05 | AA86: 2.2028202e-05 | AB86: 2.2211013e-05 | AC86: 2.2247962e-05 | AD86: 2.2194762e-05 | AE86: 2.2199463e-05 | AF86: 2.217083e-05 | AG86: =_xlfn.FORECAST.ETS(AG83,$B$86:$AF$86,$B$83:$AF$83) -> 2.2206883e-05 | AH86: =_xlfn.FORECAST.ETS(AH83,$B$86:$AF$86,$B$83:$AF$83) -> 2.2236746e-05 | AI86: =_xlfn.FORECAST.ETS(AI83,$B$86:$AF$86,$B$83:$AF$83) -> 2.226661e-05 | AJ86: =_xlfn.FORECAST.ETS(AJ83,$B$86:$AF$86,$B$83:$AF$83) -> 2.2296473e-05 | AK86: =_xlfn.FORECAST.ETS(AK83,$B$86:$AF$86,$B$83:$AF$83) -> 2.2326337e-05 | AL86: =_xlfn.FORECAST.ETS(AL83,$B$86:$AF$86,$B$83:$AF$83) -> 2.2356201e-05 | AM86: =_xlfn.FORECAST.ETS(AM83,$B$86:$AF$86,$B$83:$AF$83) -> 2.2386064e-05 | AN86: =_xlfn.FORECAST.ETS(AN83,$B$86:$AF$86,$B$83:$AF$83) -> 2.2415928e-05 | ... AZ86: =_xlfn.FORECAST.ETS(AZ83,$B$86:$AF$86,$B$83:$AF$83) -> 2.2774291e-05
A87: Commercial Buildings Sector | B87: 1.4449585e-05 | C87: 1.714231e-05 | D87: 3.0013671e-05 | E87: 2.4048234e-05 | F87: 2.2375084e-05 | G87: 2.0701934e-05 | H87: 1.9028784e-05 | I87: 1.7355634e-05 | J87: 1.5682484e-05 | K87: 1.5806261e-05 | L87: 1.5816928e-05 | M87: 1.6310977e-05 | N87: 1.6427193e-05 | O87: 1.653843e-05 | P87: 1.6595982e-05 | Q87: 1.6671424e-05 | R87: 1.6813277e-05 | S87: 1.700816e-05 | T87: 1.713298e-05 | U87: 1.7188402e-05 | V87: 1.7384096e-05 | W87: 1.7482501e-05 | X87: 1.7507274e-05 | Y87: 1.7720021e-05 | Z87: 1.7960665e-05 | AA87: 1.8065213e-05 | AB87: 1.8232871e-05 | AC87: 1.8280619e-05 | AD87: 1.8240904e-05 | AE87: 1.823774e-05 | AF87: 1.8190353e-05 | AG87: =_xlfn.FORECAST.ETS(AG83,$B$87:$AF$87,$B$83:$AF$83) -> 1.8116426e-05 | AH87: =_xlfn.FORECAST.ETS(AH83,$B$87:$AF$87,$B$83:$AF$83) -> 1.8045572e-05 | AI87: =_xlfn.FORECAST.ETS(AI83,$B$87:$AF$87,$B$83:$AF$83) -> 1.7974719e-05 | AJ87: =_xlfn.FORECAST.ETS(AJ83,$B$87:$AF$87,$B$83:$AF$83) -> 1.7903865e-05 | AK87: =_xlfn.FORECAST.ETS(AK83,$B$87:$AF$87,$B$83:$AF$83) -> 1.7833012e-05 | AL87: =_xlfn.FORECAST.ETS(AL83,$B$87:$AF$87,$B$83:$AF$83) -> 1.7762158e-05 | AM87: =_xlfn.FORECAST.ETS(AM83,$B$87:$AF$87,$B$83:$AF$83) -> 1.7691305e-05 | AN87: =_xlfn.FORECAST.ETS(AN83,$B$87:$AF$87,$B$83:$AF$83) -> 1.7620451e-05 | ... AZ87: =_xlfn.FORECAST.ETS(AZ83,$B$87:$AF$87,$B$83:$AF$83) -> 1.6770209e-05
A88: Industry Sector | B88: 0 | C88: 0 | D88: 0 | E88: 0 | F88: 0 | G88: 0 | H88: 0 | I88: 0 | J88: 0 | K88: 0 | L88: 0 | M88: 0 | N88: 0 | O88: 0 | P88: 0 | Q88: 0 | R88: 0 | S88: 0 | T88: 0 | U88: 0 | V88: 0 | W88: 0 | X88: 0 | Y88: 0 | Z88: 0 | AA88: 0 | AB88: 0 | AC88: 0 | AD88: 0 | AE88: 0 | AF88: 0 | AG88: 0 | AH88: 0 | AI88: 0 | AJ88: 0 | AK88: 0 | AL88: 0 | AM88: 0 | AN88: 0 | AO88: 0 | AP88: 0 | AQ88: 0 | AR88: 0 | AS88: 0 | AT88: 0 | AU88: 0 | AV88: 0 | AW88: 0 | AX88: 0 | AY88: 0 | AZ88: 0
A89: District Heating Sector | B89: 0 | C89: 0 | D89: 0 | E89: 0 | F89: 0 | G89: 0 | H89: 0 | I89: 0 | J89: 0 | K89: 0 | L89: 0 | M89: 0 | N89: 0 | O89: 0 | P89: 0 | Q89: 0 | R89: 0 | S89: 0 | T89: 0 | U89: 0 | V89: 0 | W89: 0 | X89: 0 | Y89: 0 | Z89: 0 | AA89: 0 | AB89: 0 | AC89: 0 | AD89: 0 | AE89: 0 | AF89: 0 | AG89: 0 | AH89: 0 | AI89: 0 | AJ89: 0 | AK89: 0 | AL89: 0 | AM89: 0 | AN89: 0 | AO89: 0 | AP89: 0 | AQ89: 0 | AR89: 0 | AS89: 0 | AT89: 0 | AU89: 0 | AV89: 0 | AW89: 0 | AX89: 0 | AY89: 0 | AZ89: 0
A90: LULUCF Sector | B90: 0 | C90: 0 | D90: 0 | E90: 0 | F90: 0 | G90: 0 | H90: 0 | I90: 0 | J90: 0 | K90: 0 | L90: 0 | M90: 0 | N90: 0 | O90: 0 | P90: 0 | Q90: 0 | R90: 0 | S90: 0 | T90: 0 | U90: 0 | V90: 0 | W90: 0 | X90: 0 | Y90: 0 | Z90: 0 | AA90: 0 | AB90: 0 | AC90: 0 | AD90: 0 | AE90: 0 | AF90: 0 | AG90: 0 | AH90: 0 | AI90: 0 | AJ90: 0 | AK90: 0 | AL90: 0 | AM90: 0 | AN90: 0 | AO90: 0 | AP90: 0 | AQ90: 0 | AR90: 0 | AS90: 0 | AT90: 0 | AU90: 0 | AV90: 0 | AW90: 0 | AX90: 0 | AY90: 0 | AZ90: 0
A91: Geoengineering Sector | B91: 0 | C91: 0 | D91: 0 | E91: 0 | F91: 0 | G91: 0 | H91: 0 | I91: 0 | J91: 0 | K91: 0 | L91: 0 | M91: 0 | N91: 0 | O91: 0 | P91: 0 | Q91: 0 | R91: 0 | S91: 0 | T91: 0 | U91: 0 | V91: 0 | W91: 0 | X91: 0 | Y91: 0 | Z91: 0 | AA91: 0 | AB91: 0 | AC91: 0 | AD91: 0 | AE91: 0 | AF91: 0 | AG91: 0 | AH91: 0 | AI91: 0 | AJ91: 0 | AK91: 0 | AL91: 0 | AM91: 0 | AN91: 0 | AO91: 0 | AP91: 0 | AQ91: 0 | AR91: 0 | AS91: 0 | AT91: 0 | AU91: 0 | AV91: 0 | AW91: 0 | AX91: 0 | AY91: 0 | AZ91: 0
A92: Lignite
A93: Year | B93: 2020 | C93: 2021 | D93: 2022 | E93: 2023 | F93: 2024 | G93: 2025 | H93: 2026 | I93: 2027 | J93: 2028 | K93: 2029 | L93: 2030 | M93: 2031 | N93: 2032 | O93: 2033 | P93: 2034 | Q93: 2035 | R93: 2036 | S93: 2037 | T93: 2038 | U93: 2039 | V93: 2040 | W93: 2041 | X93: 2042 | Y93: 2043 | Z93: 2044 | AA93: 2045 | AB93: 2046 | AC93: 2047 | AD93: 2048 | AE93: 2049 | AF93: 2050 | AG93: 2051 | AH93: 2052 | AI93: 2053 | AJ93: 2054 | AK93: 2055 | AL93: 2056 | AM93: 2057 | AN93: 2058 | AO93: 2059 | AP93: 2060 | AQ93: 2061 | AR93: 2062 | AS93: 2063 | AT93: 2064 | AU93: 2065 | AV93: 2066 | AW93: 2067 | AX93: 2068 | AY93: 2069 | AZ93: 2070
A94: Transportation Sector | B94: 0 | C94: 0 | D94: 0 | E94: 0 | F94: 0 | G94: 0 | H94: 0 | I94: 0 | J94: 0 | K94: 0 | L94: 0 | M94: 0 | N94: 0 | O94: 0 | P94: 0 | Q94: 0 | R94: 0 | S94: 0 | T94: 0 | U94: 0 | V94: 0 | W94: 0 | X94: 0 | Y94: 0 | Z94: 0 | AA94: 0 | AB94: 0 | AC94: 0 | AD94: 0 | AE94: 0 | AF94: 0 | AG94: 0 | AH94: 0 | AI94: 0 | AJ94: 0 | AK94: 0 | AL94: 0 | AM94: 0 | AN94: 0 | AO94: 0 | AP94: 0 | AQ94: 0 | AR94: 0 | AS94: 0 | AT94: 0 | AU94: 0 | AV94: 0 | AW94: 0 | AX94: 0 | AY94: 0 | AZ94: 0
A95: Electricity Sector | B95: 1.4943637e-06 | C95: 1.4956465e-06 | D95: 1.4753732e-06 | E95: 1.4628846e-06 | F95: 1.462231e-06 | G95: 1.4262005e-06 | H95: 1.4026301e-06 | I95: 1.4015992e-06 | J95: 1.3941888e-06 | K95: 1.3994385e-06 | L95: 1.397344e-06 | M95: 1.3964389e-06 | N95: 1.3883204e-06 | O95: 1.38577e-06 | P95: 1.3807442e-06 | Q95: 1.3708278e-06 | R95: 1.3597555e-06 | S95: 1.3574407e-06 | T95: 1.3569507e-06 | U95: 1.3550263e-06 | V95: 1.3586475e-06 | W95: 1.3556217e-06 | X95: 1.3478391e-06 | Y95: 1.3396224e-06 | Z95: 1.3357787e-06 | AA95: 1.3335446e-06 | AB95: 1.3314872e-06 | AC95: 1.3274879e-06 | AD95: 1.3212298e-06 | AE95: 1.3221902e-06 | AF95: 1.32022e-06 | AG95: =_xlfn.FORECAST.ETS(AG93,$B$95:$AF$95,$B$93:$AF$93) -> 1.316344e-06 | AH95: =_xlfn.FORECAST.ETS(AH93,$B$95:$AF$95,$B$93:$AF$93) -> 1.3124722e-06 | AI95: =_xlfn.FORECAST.ETS(AI93,$B$95:$AF$95,$B$93:$AF$93) -> 1.3086005e-06 | AJ95: =_xlfn.FORECAST.ETS(AJ93,$B$95:$AF$95,$B$93:$AF$93) -> 1.3047287e-06 | AK95: =_xlfn.FORECAST.ETS(AK93,$B$95:$AF$95,$B$93:$AF$93) -> 1.300857e-06 | AL95: =_xlfn.FORECAST.ETS(AL93,$B$95:$AF$95,$B$93:$AF$93) -> 1.2969852e-06 | AM95: =_xlfn.FORECAST.ETS(AM93,$B$95:$AF$95,$B$93:$AF$93) -> 1.2931135e-06 | AN95: =_xlfn.FORECAST.ETS(AN93,$B$95:$AF$95,$B$93:$AF$93) -> 1.2892417e-06 | ... AZ95: =_xlfn.FORECAST.ETS(AZ93,$B$95:$AF$95,$B$93:$AF$93) -> 1.2427807e-06
A96: Residential Buildings Sector | B96: 0 | C96: 0 | D96: 0 | E96: 0 | F96: 0 | G96: 0 | H96: 0 | I96: 0 | J96: 0 | K96: 0 | L96: 0 | M96: 0 | N96: 0 | O96: 0 | P96: 0 | Q96: 0 | R96: 0 | S96: 0 | T96: 0 | U96: 0 | V96: 0 | W96: 0 | X96: 0 | Y96: 0 | Z96: 0 | AA96: 0 | AB96: 0 | AC96: 0 | AD96: 0 | AE96: 0 | AF96: 0 | AG96: 0 | AH96: 0 | AI96: 0 | AJ96: 0 | AK96: 0 | AL96: 0 | AM96: 0 | AN96: 0 | AO96: 0 | AP96: 0 | AQ96: 0 | AR96: 0 | AS96: 0 | AT96: 0 | AU96: 0 | AV96: 0 | AW96: 0 | AX96: 0 | AY96: 0 | AZ96: 0
A97: Commercial Buildings Sector | B97: 0 | C97: 0 | D97: 0 | E97: 0 | F97: 0 | G97: 0 | H97: 0 | I97: 0 | J97: 0 | K97: 0 | L97: 0 | M97: 0 | N97: 0 | O97: 0 | P97: 0 | Q97: 0 | R97: 0 | S97: 0 | T97: 0 | U97: 0 | V97: 0 | W97: 0 | X97: 0 | Y97: 0 | Z97: 0 | AA97: 0 | AB97: 0 | AC97: 0 | AD97: 0 | AE97: 0 | AF97: 0 | AG97: 0 | AH97: 0 | AI97: 0 | AJ97: 0 | AK97: 0 | AL97: 0 | AM97: 0 | AN97: 0 | AO97: 0 | AP97: 0 | AQ97: 0 | AR97: 0 | AS97: 0 | AT97: 0 | AU97: 0 | AV97: 0 | AW97: 0 | AX97: 0 | AY97: 0 | AZ97: 0
A98: Industry Sector | B98: 0 | C98: 0 | D98: 0 | E98: 0 | F98: 0 | G98: 0 | H98: 0 | I98: 0 | J98: 0 | K98: 0 | L98: 0 | M98: 0 | N98: 0 | O98: 0 | P98: 0 | Q98: 0 | R98: 0 | S98: 0 | T98: 0 | U98: 0 | V98: 0 | W98: 0 | X98: 0 | Y98: 0 | Z98: 0 | AA98: 0 | AB98: 0 | AC98: 0 | AD98: 0 | AE98: 0 | AF98: 0 | AG98: 0 | AH98: 0 | AI98: 0 | AJ98: 0 | AK98: 0 | AL98: 0 | AM98: 0 | AN98: 0 | AO98: 0 | AP98: 0 | AQ98: 0 | AR98: 0 | AS98: 0 | AT98: 0 | AU98: 0 | AV98: 0 | AW98: 0 | AX98: 0 | AY98: 0 | AZ98: 0
A99: District Heating Sector | B99: 0 | C99: 0 | D99: 0 | E99: 0 | F99: 0 | G99: 0 | H99: 0 | I99: 0 | J99: 0 | K99: 0 | L99: 0 | M99: 0 | N99: 0 | O99: 0 | P99: 0 | Q99: 0 | R99: 0 | S99: 0 | T99: 0 | U99: 0 | V99: 0 | W99: 0 | X99: 0 | Y99: 0 | Z99: 0 | AA99: 0 | AB99: 0 | AC99: 0 | AD99: 0 | AE99: 0 | AF99: 0 | AG99: 0 | AH99: 0 | AI99: 0 | AJ99: 0 | AK99: 0 | AL99: 0 | AM99: 0 | AN99: 0 | AO99: 0 | AP99: 0 | AQ99: 0 | AR99: 0 | AS99: 0 | AT99: 0 | AU99: 0 | AV99: 0 | AW99: 0 | AX99: 0 | AY99: 0 | AZ99: 0
A100: LULUCF Sector | B100: 0 | C100: 0 | D100: 0 | E100: 0 | F100: 0 | G100: 0 | H100: 0 | I100: 0 | J100: 0 | K100: 0 | L100: 0 | M100: 0 | N100: 0 | O100: 0 | P100: 0 | Q100: 0 | R100: 0 | S100: 0 | T100: 0 | U100: 0 | V100: 0 | W100: 0 | X100: 0 | Y100: 0 | Z100: 0 | AA100: 0 | AB100: 0 | AC100: 0 | AD100: 0 | AE100: 0 | AF100: 0 | AG100: 0 | AH100: 0 | AI100: 0 | AJ100: 0 | AK100: 0 | AL100: 0 | AM100: 0 | AN100: 0 | AO100: 0 | AP100: 0 | AQ100: 0 | AR100: 0 | AS100: 0 | AT100: 0 | AU100: 0 | AV100: 0 | AW100: 0 | AX100: 0 | AY100: 0 | AZ100: 0
...

Sheet Fuel Taxes
B1: 2020 | C1: 2021 | D1: 2022 | E1: 2023 | F1: 2024 | G1: 2025 | H1: 2026 | I1: 2027 | J1: 2028 | K1: 2029 | L1: 2030 | M1: 2031 | N1: 2032 | O1: 2033 | P1: 2034 | Q1: 2035 | R1: 2036 | S1: 2037 | T1: 2038 | U1: 2039 | V1: 2040 | W1: 2041 | X1: 2042 | Y1: 2043 | Z1: 2044 | AA1: 2045 | AB1: 2046 | AC1: 2047 | AD1: 2048 | AE1: 2049 | AF1: 2050 | AG1: 2051 | AH1: 2052 | AI1: 2053 | AJ1: 2054 | AK1: 2055 | AL1: 2056 | AM1: 2057 | AN1: 2058 | AO1: 2059 | AP1: 2060 | AQ1: 2061 | AR1: 2062 | AS1: 2063 | AT1: 2064 | AU1: 2065 | AV1: 2066 | AW1: 2067 | AX1: 2068 | AY1: 2069 | AZ1: 2070
A2: Hard Coal
A3: Year | B3: 2020 | C3: 2021 | D3: 2022 | E3: 2023 | F3: 2024 | G3: 2025 | H3: 2026 | I3: 2027 | J3: 2028 | K3: 2029 | L3: 2030 | M3: 2031 | N3: 2032 | O3: 2033 | P3: 2034 | Q3: 2035 | R3: 2036 | S3: 2037 | T3: 2038 | U3: 2039 | V3: 2040 | W3: 2041 | X3: 2042 | Y3: 2043 | Z3: 2044 | AA3: 2045 | AB3: 2046 | AC3: 2047 | AD3: 2048 | AE3: 2049 | AF3: 2050 | AG3: 2051 | AH3: 2052 | AI3: 2053 | AJ3: 2054 | AK3: 2055 | AL3: 2056 | AM3: 2057 | AN3: 2058 | AO3: 2059 | AP3: 2060 | AQ3: 2061 | AR3: 2062 | AS3: 2063 | AT3: 2064 | AU3: 2065 | AV3: 2066 | AW3: 2067 | AX3: 2068 | AY3: 2069 | AZ3: 2070
A4: Transportation Sector | B4: 0 | C4: 0 | D4: 0 | E4: 0 | F4: 0 | G4: 0 | H4: 0 | I4: 0 | J4: 0 | K4: 0 | L4: 0 | M4: 0 | N4: 0 | O4: 0 | P4: 0 | Q4: 0 | R4: 0 | S4: 0 | T4: 0 | U4: 0 | V4: 0 | W4: 0 | X4: 0 | Y4: 0 | Z4: 0 | AA4: 0 | AB4: 0 | AC4: 0 | AD4: 0 | AE4: 0 | AF4: 0 | AG4: 0 | AH4: 0 | AI4: 0 | AJ4: 0 | AK4: 0 | AL4: 0 | AM4: 0 | AN4: 0 | AO4: 0 | AP4: 0 | AQ4: 0 | AR4: 0 | AS4: 0 | AT4: 0 | AU4: 0 | AV4: 0 | AW4: 0 | AX4: 0 | AY4: 0 | AZ4: 0
A5: Electricity Sector | B5: 1.1886185e-07 | C5: 1.1896389e-07 | D5: 1.1735134e-07 | E5: 1.16358e-07 | F5: 1.1630602e-07 | G5: 1.1344014e-07 | H5: 1.1156535e-07 | I5: 1.1148335e-07 | J5: 1.1089393e-07 | K5: 1.1131149e-07 | L5: 1.111449e-07 | M5: 1.110729e-07 | N5: 1.1042715e-07 | O5: 1.102243e-07 | P5: 1.0982455e-07 | Q5: 1.0903579e-07 | R5: 1.081551e-07 | S5: 1.0797098e-07 | T5: 1.07932e-07 | U5: 1.0777894e-07 | V5: 1.0806697e-07 | W5: 1.078263e-07 | X5: 1.0720727e-07 | Y5: 1.0655371e-07 | Z5: 1.0624798e-07 | AA5: 1.0607028e-07 | AB5: 1.0590664e-07 | AC5: 1.0558853e-07 | AD5: 1.0509076e-07 | AE5: 1.0516715e-07 | AF5: 1.0501044e-07 | AG5: =_xlfn.FORECAST.ETS(AG3,$B$5:$AF$5,$B$3:$AF$3) -> 1.0470215e-07 | AH5: =_xlfn.FORECAST.ETS(AH3,$B$5:$AF$5,$B$3:$AF$3) -> 1.0439419e-07 | AI5: =_xlfn.FORECAST.ETS(AI3,$B$5:$AF$5,$B$3:$AF$3) -> 1.0408623e-07 | AJ5: =_xlfn.FORECAST.ETS(AJ3,$B$5:$AF$5,$B$3:$AF$3) -> 1.0377827e-07 | AK5: =_xlfn.FORECAST.ETS(AK3,$B$5:$AF$5,$B$3:$AF$3) -> 1.0347031e-07 | AL5: =_xlfn.FORECAST.ETS(AL3,$B$5:$AF$5,$B$3:$AF$3) -> 1.0316235e-07 | AM5: =_xlfn.FORECAST.ETS(AM3,$B$5:$AF$5,$B$3:$AF$3) -> 1.0285439e-07 | AN5: =_xlfn.FORECAST.ETS(AN3,$B$5:$AF$5,$B$3:$AF$3) -> 1.0254643e-07 | ... AZ5: =_xlfn.FORECAST.ETS(AZ3,$B$5:$AF$5,$B$3:$AF$3) -> 9.8850915e-08
A6: Residential Buildings Sector | B6: 0 | C6: 0 | D6: 0 | E6: 0 | F6: 0 | G6: 0 | H6: 0 | I6: 0 | J6: 0 | K6: 0 | L6: 0 | M6: 0 | N6: 0 | O6: 0 | P6: 0 | Q6: 0 | R6: 0 | S6: 0 | T6: 0 | U6: 0 | V6: 0 | W6: 0 | X6: 0 | Y6: 0 | Z6: 0 | AA6: 0 | AB6: 0 | AC6: 0 | AD6: 0 | AE6: 0 | AF6: 0 | AG6: 0 | AH6: 0 | AI6: 0 | AJ6: 0 | AK6: 0 | AL6: 0 | AM6: 0 | AN6: 0 | AO6: 0 | AP6: 0 | AQ6: 0 | AR6: 0 | AS6: 0 | AT6: 0 | AU6: 0 | AV6: 0 | AW6: 0 | AX6: 0 | AY6: 0 | AZ6: 0
A7: Commercial Buildings Sector | B7: 0 | C7: 0 | D7: 0 | E7: 0 | F7: 0 | G7: 0 | H7: 0 | I7: 0 | J7: 0 | K7: 0 | L7: 0 | M7: 0 | N7: 0 | O7: 0 | P7: 0 | Q7: 0 | R7: 0 | S7: 0 | T7: 0 | U7: 0 | V7: 0 | W7: 0 | X7: 0 | Y7: 0 | Z7: 0 | AA7: 0 | AB7: 0 | AC7: 0 | AD7: 0 | AE7: 0 | AF7: 0 | AG7: 0 | AH7: 0 | AI7: 0 | AJ7: 0 | AK7: 0 | AL7: 0 | AM7: 0 | AN7: 0 | AO7: 0 | AP7: 0 | AQ7: 0 | AR7: 0 | AS7: 0 | AT7: 0 | AU7: 0 | AV7: 0 | AW7: 0 | AX7: 0 | AY7: 0 | AZ7: 0
A8: Industry Sector | B8: 2.0654559e-07 | C8: 1.9087969e-07 | D8: 1.8045439e-07 | E8: 1.7616985e-07 | F8: 1.7096885e-07 | G8: 1.6800177e-07 | H8: 1.658882e-07 | I8: 1.6469492e-07 | J8: 1.6463215e-07 | K8: 1.6489424e-07 | L8: 1.6568959e-07 | M8: 1.6636407e-07 | N8: 1.6738053e-07 | O8: 1.6819459e-07 | P8: 1.6901255e-07 | Q8: 1.6973204e-07 | R8: 1.7048175e-07 | S8: 1.7138992e-07 | T8: 1.7234383e-07 | U8: 1.7306766e-07 | V8: 1.7387332e-07 | W8: 1.7479083e-07 | X8: 1.7541428e-07 | Y8: 1.7623054e-07 | Z8: 1.7715642e-07 | AA8: 1.7810719e-07 | AB8: 1.7909348e-07 | AC8: 1.7986401e-07 | AD8: 1.8037161e-07 | AE8: 1.8110172e-07 | AF8: 1.8210538e-07 | AG8: =_xlfn.FORECAST.ETS(AG3,$B$8:$AF$8,$B$3:$AF$3) -> 1.8303079e-07 | AH8: =_xlfn.FORECAST.ETS(AH3,$B$8:$AF$8,$B$3:$AF$3) -> 1.8395681e-07 | AI8: =_xlfn.FORECAST.ETS(AI3,$B$8:$AF$8,$B$3:$AF$3) -> 1.8488283e-07 | AJ8: =_xlfn.FORECAST.ETS(AJ3,$B$8:$AF$8,$B$3:$AF$3) -> 1.8580886e-07 | AK8: =_xlfn.FORECAST.ETS(AK3,$B$8:$AF$8,$B$3:$AF$3) -> 1.8673488e-07 | AL8: =_xlfn.FORECAST.ETS(AL3,$B$8:$AF$8,$B$3:$AF$3) -> 1.8766091e-07 | AM8: =_xlfn.FORECAST.ETS(AM3,$B$8:$AF$8,$B$3:$AF$3) -> 1.8858693e-07 | AN8: =_xlfn.FORECAST.ETS(AN3,$B$8:$AF$8,$B$3:$AF$3) -> 1.8951295e-07 | ... AZ8: =_xlfn.FORECAST.ETS(AZ3,$B$8:$AF$8,$B$3:$AF$3) -> 2.0062524e-07
A9: District Heating Sector | B9: 1.1886185e-07 | C9: 1.1896389e-07 | D9: 1.1735134e-07 | E9: 1.16358e-07 | F9: 1.1630602e-07 | G9: 1.1344014e-07 | H9: 1.1156535e-07 | I9: 1.1148335e-07 | J9: 1.1089393e-07 | K9: 1.1131149e-07 | L9: 1.111449e-07 | M9: 1.110729e-07 | N9: 1.1042715e-07 | O9: 1.102243e-07 | P9: 1.0982455e-07 | Q9: 1.0903579e-07 | R9: 1.081551e-07 | S9: 1.0797098e-07 | T9: 1.07932e-07 | U9: 1.0777894e-07 | V9: 1.0806697e-07 | W9: 1.078263e-07 | X9: 1.0720727e-07 | Y9: 1.0655371e-07 | Z9: 1.0624798e-07 | AA9: 1.0607028e-07 | AB9: 1.0590664e-07 | AC9: 1.0558853e-07 | AD9: 1.0509076e-07 | AE9: 1.0516715e-07 | AF9: 1.0501044e-07 | AG9: =_xlfn.FORECAST.ETS(AG3,$B$9:$AF$9,$B$3:$AF$3) -> 1.0470215e-07 | AH9: =_xlfn.FORECAST.ETS(AH3,$B$9:$AF$9,$B$3:$AF$3) -> 1.0439419e-07 | AI9: =_xlfn.FORECAST.ETS(AI3,$B$9:$AF$9,$B$3:$AF$3) -> 1.0408623e-07 | AJ9: =_xlfn.FORECAST.ETS(AJ3,$B$9:$AF$9,$B$3:$AF$3) -> 1.0377827e-07 | AK9: =_xlfn.FORECAST.ETS(AK3,$B$9:$AF$9,$B$3:$AF$3) -> 1.0347031e-07 | AL9: =_xlfn.FORECAST.ETS(AL3,$B$9:$AF$9,$B$3:$AF$3) -> 1.0316235e-07 | AM9: =_xlfn.FORECAST.ETS(AM3,$B$9:$AF$9,$B$3:$AF$3) -> 1.0285439e-07 | AN9: =_xlfn.FORECAST.ETS(AN3,$B$9:$AF$9,$B$3:$AF$3) -> 1.0254643e-07 | ... AZ9: =_xlfn.FORECAST.ETS(AZ3,$B$9:$AF$9,$B$3:$AF$3) -> 9.8850915e-08
A10: LULUCF Sector | B10: 0 | C10: 0 | D10: 0 | E10: 0 | F10: 0 | G10: 0 | H10: 0 | I10: 0 | J10: 0 | K10: 0 | L10: 0 | M10: 0 | N10: 0 | O10: 0 | P10: 0 | Q10: 0 | R10: 0 | S10: 0 | T10: 0 | U10: 0 | V10: 0 | W10: 0 | X10: 0 | Y10: 0 | Z10: 0 | AA10: 0 | AB10: 0 | AC10: 0 | AD10: 0 | AE10: 0 | AF10: 0 | AG10: 0 | AH10: 0 | AI10: 0 | AJ10: 0 | AK10: 0 | AL10: 0 | AM10: 0 | AN10: 0 | AO10: 0 | AP10: 0 | AQ10: 0 | AR10: 0 | AS10: 0 | AT10: 0 | AU10: 0 | AV10: 0 | AW10: 0 | AX10: 0 | AY10: 0 | AZ10: 0
A11: Geoengineering Sector | B11: 2.0654559e-07 | C11: 1.9087969e-07 | D11: 1.8045439e-07 | E11: 1.7616985e-07 | F11: 1.7096885e-07 | G11: 1.6800177e-07 | H11: 1.658882e-07 | I11: 1.6469492e-07 | J11: 1.6463215e-07 | K11: 1.6489424e-07 | L11: 1.6568959e-07 | M11: 1.6636407e-07 | N11: 1.6738053e-07 | O11: 1.6819459e-07 | P11: 1.6901255e-07 | Q11: 1.6973204e-07 | R11: 1.7048175e-07 | S11: 1.7138992e-07 | T11: 1.7234383e-07 | U11: 1.7306766e-07 | V11: 1.7387332e-07 | W11: 1.7479083e-07 | X11: 1.7541428e-07 | Y11: 1.7623054e-07 | Z11: 1.7715642e-07 | AA11: 1.7810719e-07 | AB11: 1.7909348e-07 | AC11: 1.7986401e-07 | AD11: 1.8037161e-07 | AE11: 1.8110172e-07 | AF11: 1.8210538e-07 | AG11: =_xlfn.FORECAST.ETS(AG3,$B$11:$AF$11,$B$3:$AF$3) -> 1.8303079e-07 | AH11: =_xlfn.FORECAST.ETS(AH3,$B$11:$AF$11,$B$3:$AF$3) -> 1.8395681e-07 | AI11: =_xlfn.FORECAST.ETS(AI3,$B$11:$AF$11,$B$3:$AF$3) -> 1.8488283e-07 | AJ11: =_xlfn.FORECAST.ETS(AJ3,$B$11:$AF$11,$B$3:$AF$3) -> 1.8580886e-07 | AK11: =_xlfn.FORECAST.ETS(AK3,$B$11:$AF$11,$B$3:$AF$3) -> 1.8673488e-07 | AL11: =_xlfn.FORECAST.ETS(AL3,$B$11:$AF$11,$B$3:$AF$3) -> 1.8766091e-07 | AM11: =_xlfn.FORECAST.ETS(AM3,$B$11:$AF$11,$B$3:$AF$3) -> 1.8858693e-07 | AN11: =_xlfn.FORECAST.ETS(AN3,$B$11:$AF$11,$B$3:$AF$3) -> 1.8951295e-07 | ... AZ11: =_xlfn.FORECAST.ETS(AZ3,$B$11:$AF$11,$B$3:$AF$3) -> 2.0062524e-07
A12: Natural Gas
A13: Year | B13: 2020 | C13: 2021 | D13: 2022 | E13: 2023 | F13: 2024 | G13: 2025 | H13: 2026 | I13: 2027 | J13: 2028 | K13: 2029 | L13: 2030 | M13: 2031 | N13: 2032 | O13: 2033 | P13: 2034 | Q13: 2035 | R13: 2036 | S13: 2037 | T13: 2038 | U13: 2039 | V13: 2040 | W13: 2041 | X13: 2042 | Y13: 2043 | Z13: 2044 | AA13: 2045 | AB13: 2046 | AC13: 2047 | AD13: 2048 | AE13: 2049 | AF13: 2050 | AG13: 2051 | AH13: 2052 | AI13: 2053 | AJ13: 2054 | AK13: 2055 | AL13: 2056 | AM13: 2057 | AN13: 2058 | AO13: 2059 | AP13: 2060 | AQ13: 2061 | AR13: 2062 | AS13: 2063 | AT13: 2064 | AU13: 2065 | AV13: 2066 | AW13: 2067 | AX13: 2068 | AY13: 2069 | AZ13: 2070
A14: Transportation Sector | B14: 7.850164e-07 | C14: 8.6118307e-07 | D14: 1.5907141e-06 | E14: 1.3698213e-06 | F14: 1.034879e-06 | G14: 9.6225779e-07 | H14: 9.2369829e-07 | I14: 8.8513879e-07 | J14: 8.4657929e-07 | K14: 8.0801979e-07 | L14: 7.6946029e-07 | M14: 7.5323387e-07 | N14: 7.4853201e-07 | O14: 7.4096738e-07 | P14: 7.3257426e-07 | Q14: 7.2456951e-07 | R14: 7.1712215e-07 | S14: 7.1001435e-07 | T14: 7.068344e-07 | U14: 7.0122546e-07 | V14: 6.9856977e-07 | W14: 6.9413557e-07 | X14: 6.9042157e-07 | Y14: 6.8664176e-07 | Z14: 6.8376439e-07 | AA14: 6.8195197e-07 | AB14: 6.8081728e-07 | AC14: 6.8072625e-07 | AD14: 6.8129498e-07 | AE14: 6.8330273e-07 | AF14: 6.8453116e-07 | AG14: =_xlfn.FORECAST.ETS(AG1,$D$14:$AF$14,$D$13:$AF$13) -> 6.6654316e-07 | AH14: =_xlfn.FORECAST.ETS(AH1,$D$14:$AF$14,$D$13:$AF$13) -> 6.4855515e-07 | AI14: =_xlfn.FORECAST.ETS(AI1,$D$14:$AF$14,$D$13:$AF$13) -> 6.3056715e-07 | AJ14: =_xlfn.FORECAST.ETS(AJ1,$D$14:$AF$14,$D$13:$AF$13) -> 6.1257915e-07 | AK14: =_xlfn.FORECAST.ETS(AK1,$D$14:$AF$14,$D$13:$AF$13) -> 5.9459114e-07 | AL14: =_xlfn.FORECAST.ETS(AL1,$D$14:$AF$14,$D$13:$AF$13) -> 5.7660314e-07 | AM14: =_xlfn.FORECAST.ETS(AM1,$D$14:$AF$14,$D$13:$AF$13) -> 5.5861514e-07 | AN14: =_xlfn.FORECAST.ETS(AN1,$D$14:$AF$14,$D$13:$AF$13) -> 5.4062713e-07 | ... AZ14: =_xlfn.FORECAST.ETS(AZ1,$D$14:$AF$14,$D$13:$AF$13) -> 3.2477109e-07
A15: Electricity Sector | B15: 1.4764358e-07 | C15: 2.7081529e-07 | D15: 5.002301e-07 | E15: 4.3076617e-07 | F15: 3.2543725e-07 | G15: 3.0260014e-07 | H15: 2.8563208e-07 | I15: 2.6866402e-07 | J15: 2.5169596e-07 | K15: 2.347279e-07 | L15: 2.1775984e-07 | M15: 2.176538e-07 | N15: 2.2093407e-07 | O15: 2.2500313e-07 | P15: 2.270227e-07 | Q15: 2.2703706e-07 | R15: 2.2717291e-07 | S15: 2.2595908e-07 | T15: 2.2770629e-07 | U15: 2.2760748e-07 | V15: 2.2753069e-07 | W15: 2.2693216e-07 | X15: 2.2607393e-07 | Y15: 2.251242e-07 | Z15: 2.2510544e-07 | AA15: 2.2554478e-07 | AB15: 2.2580055e-07 | AC15: 2.2698005e-07 | AD15: 2.2987751e-07 | AE15: 2.3289049e-07 | AF15: 2.3535447e-07 | AG15: =_xlfn.FORECAST.ETS(AG1,$B$15:$AF$15,$B$13:$AF$13) -> 2.3583686e-07 | AH15: =_xlfn.FORECAST.ETS(AH1,$B$15:$AF$15,$B$13:$AF$13) -> 2.3632366e-07 | AI15: =_xlfn.FORECAST.ETS(AI1,$B$15:$AF$15,$B$13:$AF$13) -> 2.3681046e-07 | AJ15: =_xlfn.FORECAST.ETS(AJ1,$B$15:$AF$15,$B$13:$AF$13) -> 2.3729726e-07 | AK15: =_xlfn.FORECAST.ETS(AK1,$B$15:$AF$15,$B$13:$AF$13) -> 2.3778406e-07 | AL15: =_xlfn.FORECAST.ETS(AL1,$B$15:$AF$15,$B$13:$AF$13) -> 2.3827086e-07 | AM15: =_xlfn.FORECAST.ETS(AM1,$B$15:$AF$15,$B$13:$AF$13) -> 2.3875766e-07 | AN15: =_xlfn.FORECAST.ETS(AN1,$B$15:$AF$15,$B$13:$AF$13) -> 2.3924446e-07 | ... AZ15: =_xlfn.FORECAST.ETS(AZ1,$B$15:$AF$15,$B$13:$AF$13) -> 2.4508606e-07
A16: Residential Buildings Sector | B16: 6.1178407e-07 | C16: 8.6118307e-07 | D16: 1.5907141e-06 | E16: 1.3698213e-06 | F16: 1.034879e-06 | G16: 9.6225779e-07 | H16: 9.0241186e-07 | I16: 8.4256592e-07 | J16: 7.8271999e-07 | K16: 7.2287405e-07 | L16: 6.6302812e-07 | M16: 6.6583394e-07 | N16: 6.7139825e-07 | O16: 6.7796724e-07 | P16: 6.8192494e-07 | Q16: 6.8403808e-07 | R16: 6.8498938e-07 | S16: 6.8661757e-07 | T16: 6.8847928e-07 | U16: 6.8972242e-07 | V16: 6.9013703e-07 | W16: 6.9163154e-07 | X16: 6.9213422e-07 | Y16: 6.9296264e-07 | Z16: 6.9326329e-07 | AA16: 6.9530603e-07 | AB16: 6.9642515e-07 | AC16: 6.9902546e-07 | AD16: 7.0179823e-07 | AE16: 7.0569899e-07 | AF16: 7.092845e-07 | AG16: =_xlfn.FORECAST.ETS(AG1,$B$16:$AF$16,$B$13:$AF$13) -> 7.0874137e-07 | AH16: =_xlfn.FORECAST.ETS(AH1,$B$16:$AF$16,$B$13:$AF$13) -> 7.0820742e-07 | AI16: =_xlfn.FORECAST.ETS(AI1,$B$16:$AF$16,$B$13:$AF$13) -> 7.0767346e-07 | AJ16: =_xlfn.FORECAST.ETS(AJ1,$B$16:$AF$16,$B$13:$AF$13) -> 7.071395e-07 | AK16: =_xlfn.FORECAST.ETS(AK1,$B$16:$AF$16,$B$13:$AF$13) -> 7.0660555e-07 | AL16: =_xlfn.FORECAST.ETS(AL1,$B$16:$AF$16,$B$13:$AF$13) -> 7.0607159e-07 | AM16: =_xlfn.FORECAST.ETS(AM1,$B$16:$AF$16,$B$13:$AF$13) -> 7.0553763e-07 | AN16: =_xlfn.FORECAST.ETS(AN1,$B$16:$AF$16,$B$13:$AF$13) -> 7.0500368e-07 | ... AZ16: =_xlfn.FORECAST.ETS(AZ1,$B$16:$AF$16,$B$13:$AF$13) -> 6.985962e-07
A17: Commercial Buildings Sector | B17: 4.3598623e-07 | C17: 6.3281082e-07 | D17: 1.1688816e-06 | E17: 1.0065661e-06 | F17: 7.604453e-07 | G17: 7.070821e-07 | H17: 6.6455042e-07 | I17: 6.2201873e-07 | J17: 5.7948705e-07 | K17: 5.3695536e-07 | L17: 4.9442368e-07 | M17: 4.9505467e-07 | N17: 4.9832504e-07 | O17: 5.0342968e-07 | P17: 5.0622079e-07 | Q17: 5.073629e-07 | R17: 5.0746207e-07 | S17: 5.0824736e-07 | T17: 5.0929259e-07 | U17: 5.098776e-07 | V17: 5.0975647e-07 | W17: 5.1071918e-07 | X17: 5.106676e-07 | Y17: 5.1108419e-07 | Z17: 5.1089653e-07 | AA17: 5.1245107e-07 | AB17: 5.1315377e-07 | AC17: 5.1526588e-07 | AD17: 5.1757537e-07 | AE17: 5.2090137e-07 | AF17: 5.2393172e-07 | AG17: =_xlfn.FORECAST.ETS(AG1,$B$17:$AF$17,$B$13:$AF$13) -> 5.2363576e-07 | AH17: =_xlfn.FORECAST.ETS(AH1,$B$17:$AF$17,$B$13:$AF$13) -> 5.2334719e-07 | AI17: =_xlfn.FORECAST.ETS(AI1,$B$17:$AF$17,$B$13:$AF$13) -> 5.2305861e-07 | AJ17: =_xlfn.FORECAST.ETS(AJ1,$B$17:$AF$17,$B$13:$AF$13) -> 5.2277004e-07 | AK17: =_xlfn.FORECAST.ETS(AK1,$B$17:$AF$17,$B$13:$AF$13) -> 5.2248147e-07 | AL17: =_xlfn.FORECAST.ETS(AL1,$B$17:$AF$17,$B$13:$AF$13) -> 5.221929e-07 | AM17: =_xlfn.FORECAST.ETS(AM1,$B$17:$AF$17,$B$13:$AF$13) -> 5.2190432e-07 | AN17: =_xlfn.FORECAST.ETS(AN1,$B$17:$AF$17,$B$13:$AF$13) -> 5.2161575e-07 | ... AZ17: =_xlfn.FORECAST.ETS(AZ1,$B$17:$AF$17,$B$13:$AF$13) -> 5.1815288e-07
A18: Industry Sector | B18: 1.8465104e-07 | C18: 3.216733e-07 | D18: 5.9417129e-07 | E18: 5.1166232e-07 | F18: 3.8655305e-07 | G18: 3.5942723e-07 | H18: 3.3818733e-07 | I18: 3.1694743e-07 | J18: 2.9570753e-07 | K18: 2.7446762e-07 | L18: 2.5322772e-07 | M18: 2.5374041e-07 | N18: 2.568732e-07 | O18: 2.6120829e-07 | P18: 2.6318587e-07 | Q18: 2.6383725e-07 | R18: 2.6386698e-07 | S18: 2.6320246e-07 | T18: 2.6428756e-07 | U18: 2.638627e-07 | V18: 2.6330507e-07 | W18: 2.6310154e-07 | X18: 2.6197596e-07 | Y18: 2.6095613e-07 | Z18: 2.6041829e-07 | AA18: 2.6085286e-07 | AB18: 2.6103196e-07 | AC18: 2.6236686e-07 | AD18: 2.6476786e-07 | AE18: 2.6798998e-07 | AF18: 2.7029144e-07 | AG18: =_xlfn.FORECAST.ETS(AG1,$B$18:$AF$18,$B$13:$AF$13) -> 2.7050459e-07 | AH18: =_xlfn.FORECAST.ETS(AH1,$B$18:$AF$18,$B$13:$AF$13) -> 2.7072237e-07 | AI18: =_xlfn.FORECAST.ETS(AI1,$B$18:$AF$18,$B$13:$AF$13) -> 2.7094016e-07 | AJ18: =_xlfn.FORECAST.ETS(AJ1,$B$18:$AF$18,$B$13:$AF$13) -> 2.7115795e-07 | AK18: =_xlfn.FORECAST.ETS(AK1,$B$18:$AF$18,$B$13:$AF$13) -> 2.7137573e-07 | AL18: =_xlfn.FORECAST.ETS(AL1,$B$18:$AF$18,$B$13:$AF$13) -> 2.7159352e-07 | AM18: =_xlfn.FORECAST.ETS(AM1,$B$18:$AF$18,$B$13:$AF$13) -> 2.7181131e-07 | AN18: =_xlfn.FORECAST.ETS(AN1,$B$18:$AF$18,$B$13:$AF$13) -> 2.720291e-07 | ... AZ18: =_xlfn.FORECAST.ETS(AZ1,$B$18:$AF$18,$B$13:$AF$13) -> 2.7464254e-07
A19: District Heating Sector | B19: 1.4764358e-07 | C19: 2.7081529e-07 | D19: 5.002301e-07 | E19: 4.3076617e-07 | F19: 3.2543725e-07 | G19: 3.0260014e-07 | H19: 2.8563208e-07 | I19: 2.6866402e-07 | J19: 2.5169596e-07 | K19: 2.347279e-07 | L19: 2.1775984e-07 | M19: 2.176538e-07 | N19: 2.2093407e-07 | O19: 2.2500313e-07 | P19: 2.270227e-07 | Q19: 2.2703706e-07 | R19: 2.2717291e-07 | S19: 2.2595908e-07 | T19: 2.2770629e-07 | U19: 2.2760748e-07 | V19: 2.2753069e-07 | W19: 2.2693216e-07 | X19: 2.2607393e-07 | Y19: 2.251242e-07 | Z19: 2.2510544e-07 | AA19: 2.2554478e-07 | AB19: 2.2580055e-07 | AC19: 2.2698005e-07 | AD19: 2.2987751e-07 | AE19: 2.3289049e-07 | AF19: 2.3535447e-07 | AG19: =_xlfn.FORECAST.ETS(AG1,$B$19:$AF$19,$B$13:$AF$13) -> 2.3583686e-07 | AH19: =_xlfn.FORECAST.ETS(AH1,$B$19:$AF$19,$B$13:$AF$13) -> 2.3632366e-07 | AI19: =_xlfn.FORECAST.ETS(AI1,$B$19:$AF$19,$B$13:$AF$13) -> 2.3681046e-07 | AJ19: =_xlfn.FORECAST.ETS(AJ1,$B$19:$AF$19,$B$13:$AF$13) -> 2.3729726e-07 | AK19: =_xlfn.FORECAST.ETS(AK1,$B$19:$AF$19,$B$13:$AF$13) -> 2.3778406e-07 | AL19: =_xlfn.FORECAST.ETS(AL1,$B$19:$AF$19,$B$13:$AF$13) -> 2.3827086e-07 | AM19: =_xlfn.FORECAST.ETS(AM1,$B$19:$AF$19,$B$13:$AF$13) -> 2.3875766e-07 | AN19: =_xlfn.FORECAST.ETS(AN1,$B$19:$AF$19,$B$13:$AF$13) -> 2.3924446e-07 | ... AZ19: =_xlfn.FORECAST.ETS(AZ1,$B$19:$AF$19,$B$13:$AF$13) -> 2.4508606e-07
A20: LULUCF Sector | B20: 0 | C20: 0 | D20: 0 | E20: 0 | F20: 0 | G20: 0 | H20: 0 | I20: 0 | J20: 0 | K20: 0 | L20: 0 | M20: 0 | N20: 0 | O20: 0 | P20: 0 | Q20: 0 | R20: 0 | S20: 0 | T20: 0 | U20: 0 | V20: 0 | W20: 0 | X20: 0 | Y20: 0 | Z20: 0 | AA20: 0 | AB20: 0 | AC20: 0 | AD20: 0 | AE20: 0 | AF20: 0 | AG20: 0 | AH20: 0 | AI20: 0 | AJ20: 0 | AK20: 0 | AL20: 0 | AM20: 0 | AN20: 0 | AO20: 0 | AP20: 0 | AQ20: 0 | AR20: 0 | AS20: 0 | AT20: 0 | AU20: 0 | AV20: 0 | AW20: 0 | AX20: 0 | AY20: 0 | AZ20: 0
A21: Geoengineering Sector | B21: 1.8465104e-07 | C21: 3.216733e-07 | D21: 5.9417129e-07 | E21: 5.1166232e-07 | F21: 3.8655305e-07 | G21: 3.5942723e-07 | H21: 3.3818733e-07 | I21: 3.1694743e-07 | J21: 2.9570753e-07 | K21: 2.7446762e-07 | L21: 2.5322772e-07 | M21: 2.5374041e-07 | N21: 2.568732e-07 | O21: 2.6120829e-07 | P21: 2.6318587e-07 | Q21: 2.6383725e-07 | R21: 2.6386698e-07 | S21: 2.6320246e-07 | T21: 2.6428756e-07 | U21: 2.638627e-07 | V21: 2.6330507e-07 | W21: 2.6310154e-07 | X21: 2.6197596e-07 | Y21: 2.6095613e-07 | Z21: 2.6041829e-07 | AA21: 2.6085286e-07 | AB21: 2.6103196e-07 | AC21: 2.6236686e-07 | AD21: 2.6476786e-07 | AE21: 2.6798998e-07 | AF21: 2.7029144e-07 | AG21: =_xlfn.FORECAST.ETS(AG1,$B$21:$AF$21,$B$13:$AF$13) -> 2.7050459e-07 | AH21: =_xlfn.FORECAST.ETS(AH1,$B$21:$AF$21,$B$13:$AF$13) -> 2.7072237e-07 | AI21: =_xlfn.FORECAST.ETS(AI1,$B$21:$AF$21,$B$13:$AF$13) -> 2.7094016e-07 | AJ21: =_xlfn.FORECAST.ETS(AJ1,$B$21:$AF$21,$B$13:$AF$13) -> 2.7115795e-07 | AK21: =_xlfn.FORECAST.ETS(AK1,$B$21:$AF$21,$B$13:$AF$13) -> 2.7137573e-07 | AL21: =_xlfn.FORECAST.ETS(AL1,$B$21:$AF$21,$B$13:$AF$13) -> 2.7159352e-07 | AM21: =_xlfn.FORECAST.ETS(AM1,$B$21:$AF$21,$B$13:$AF$13) -> 2.7181131e-07 | AN21: =_xlfn.FORECAST.ETS(AN1,$B$21:$AF$21,$B$13:$AF$13) -> 2.720291e-07 | ... AZ21: =_xlfn.FORECAST.ETS(AZ1,$B$21:$AF$21,$B$13:$AF$13) -> 2.7464254e-07
A22: Nuclear
A23: Year | B23: 2020 | C23: 2021 | D23: 2022 | E23: 2023 | F23: 2024 | G23: 2025 | H23: 2026 | I23: 2027 | J23: 2028 | K23: 2029 | L23: 2030 | M23: 2031 | N23: 2032 | O23: 2033 | P23: 2034 | Q23: 2035 | R23: 2036 | S23: 2037 | T23: 2038 | U23: 2039 | V23: 2040 | W23: 2041 | X23: 2042 | Y23: 2043 | Z23: 2044 | AA23: 2045 | AB23: 2046 | AC23: 2047 | AD23: 2048 | AE23: 2049 | AF23: 2050 | AG23: 2051 | AH23: 2052 | AI23: 2053 | AJ23: 2054 | AK23: 2055 | AL23: 2056 | AM23: 2057 | AN23: 2058 | AO23: 2059 | AP23: 2060 | AQ23: 2061 | AR23: 2062 | AS23: 2063 | AT23: 2064 | AU23: 2065 | AV23: 2066 | AW23: 2067 | AX23: 2068 | AY23: 2069 | AZ23: 2070
A24: Transportation Sector | B24: 0 | C24: 0 | D24: 0 | E24: 0 | F24: 0 | G24: 0 | H24: 0 | I24: 0 | J24: 0 | K24: 0 | L24: 0 | M24: 0 | N24: 0 | O24: 0 | P24: 0 | Q24: 0 | R24: 0 | S24: 0 | T24: 0 | U24: 0 | V24: 0 | W24: 0 | X24: 0 | Y24: 0 | Z24: 0 | AA24: 0 | AB24: 0 | AC24: 0 | AD24: 0 | AE24: 0 | AF24: 0 | AG24: 0 | AH24: 0 | AI24: 0 | AJ24: 0 | AK24: 0 | AL24: 0 | AM24: 0 | AN24: 0 | AO24: 0 | AP24: 0 | AQ24: 0 | AR24: 0 | AS24: 0 | AT24: 0 | AU24: 0 | AV24: 0 | AW24: 0 | AX24: 0 | AY24: 0 | AZ24: 0
A25: Electricity Sector | B25: 4.1389358e-08 | C25: 4.1291801e-08 | D25: 4.1352241e-08 | E25: 4.1473178e-08 | F25: 4.1533618e-08 | G25: 4.1654498e-08 | H25: 4.1714995e-08 | I25: 4.1835875e-08 | J25: 4.1896315e-08 | K25: 4.2017253e-08 | L25: 4.213819e-08 | M25: 4.219863e-08 | N25: 4.2319567e-08 | O25: 4.2440447e-08 | P25: 4.2500887e-08 | Q25: 4.2621824e-08 | R25: 4.2742762e-08 | S25: 4.2803202e-08 | T25: 4.2924082e-08 | U25: 4.3045019e-08 | V25: 4.3165956e-08 | W25: 4.3286836e-08 | X25: 4.3407774e-08 | Y25: 4.3528653e-08 | Z25: 4.3649591e-08 | AA25: 4.3770528e-08 | AB25: 4.3891408e-08 | AC25: 4.4012345e-08 | AD25: 4.4133225e-08 | AE25: 4.4254163e-08 | AF25: 4.4375042e-08 | AG25: =_xlfn.FORECAST.ETS(AG13,$B$25:$AF$25,$B$23:$AF$23) -> 4.4495983e-08 | AH25: =_xlfn.FORECAST.ETS(AH13,$B$25:$AF$25,$B$23:$AF$23) -> 4.4616914e-08 | AI25: =_xlfn.FORECAST.ETS(AI13,$B$25:$AF$25,$B$23:$AF$23) -> 4.4737845e-08 | AJ25: =_xlfn.FORECAST.ETS(AJ13,$B$25:$AF$25,$B$23:$AF$23) -> 4.4858776e-08 | AK25: =_xlfn.FORECAST.ETS(AK13,$B$25:$AF$25,$B$23:$AF$23) -> 4.4979707e-08 | AL25: =_xlfn.FORECAST.ETS(AL13,$B$25:$AF$25,$B$23:$AF$23) -> 4.5100638e-08 | AM25: =_xlfn.FORECAST.ETS(AM13,$B$25:$AF$25,$B$23:$AF$23) -> 4.5221569e-08 | AN25: =_xlfn.FORECAST.ETS(AN13,$B$25:$AF$25,$B$23:$AF$23) -> 4.53425e-08 | ... AZ25: =_xlfn.FORECAST.ETS(AZ13,$B$25:$AF$25,$B$23:$AF$23) -> 4.6793673e-08
A26: Residential Buildings Sector | B26: 0 | C26: 0 | D26: 0 | E26: 0 | F26: 0 | G26: 0 | H26: 0 | I26: 0 | J26: 0 | K26: 0 | L26: 0 | M26: 0 | N26: 0 | O26: 0 | P26: 0 | Q26: 0 | R26: 0 | S26: 0 | T26: 0 | U26: 0 | V26: 0 | W26: 0 | X26: 0 | Y26: 0 | Z26: 0 | AA26: 0 | AB26: 0 | AC26: 0 | AD26: 0 | AE26: 0 | AF26: 0 | AG26: 0 | AH26: 0 | AI26: 0 | AJ26: 0 | AK26: 0 | AL26: 0 | AM26: 0 | AN26: 0 | AO26: 0 | AP26: 0 | AQ26: 0 | AR26: 0 | AS26: 0 | AT26: 0 | AU26: 0 | AV26: 0 | AW26: 0 | AX26: 0 | AY26: 0 | AZ26: 0
A27: Commercial Buildings Sector | B27: 0 | C27: 0 | D27: 0 | E27: 0 | F27: 0 | G27: 0 | H27: 0 | I27: 0 | J27: 0 | K27: 0 | L27: 0 | M27: 0 | N27: 0 | O27: 0 | P27: 0 | Q27: 0 | R27: 0 | S27: 0 | T27: 0 | U27: 0 | V27: 0 | W27: 0 | X27: 0 | Y27: 0 | Z27: 0 | AA27: 0 | AB27: 0 | AC27: 0 | AD27: 0 | AE27: 0 | AF27: 0 | AG27: 0 | AH27: 0 | AI27: 0 | AJ27: 0 | AK27: 0 | AL27: 0 | AM27: 0 | AN27: 0 | AO27: 0 | AP27: 0 | AQ27: 0 | AR27: 0 | AS27: 0 | AT27: 0 | AU27: 0 | AV27: 0 | AW27: 0 | AX27: 0 | AY27: 0 | AZ27: 0
A28: Industry Sector | B28: 0 | C28: 0 | D28: 0 | E28: 0 | F28: 0 | G28: 0 | H28: 0 | I28: 0 | J28: 0 | K28: 0 | L28: 0 | M28: 0 | N28: 0 | O28: 0 | P28: 0 | Q28: 0 | R28: 0 | S28: 0 | T28: 0 | U28: 0 | V28: 0 | W28: 0 | X28: 0 | Y28: 0 | Z28: 0 | AA28: 0 | AB28: 0 | AC28: 0 | AD28: 0 | AE28: 0 | AF28: 0 | AG28: 0 | AH28: 0 | AI28: 0 | AJ28: 0 | AK28: 0 | AL28: 0 | AM28: 0 | AN28: 0 | AO28: 0 | AP28: 0 | AQ28: 0 | AR28: 0 | AS28: 0 | AT28: 0 | AU28: 0 | AV28: 0 | AW28: 0 | AX28: 0 | AY28: 0 | AZ28: 0
A29: District Heating Sector | B29: 0 | C29: 0 | D29: 0 | E29: 0 | F29: 0 | G29: 0 | H29: 0 | I29: 0 | J29: 0 | K29: 0 | L29: 0 | M29: 0 | N29: 0 | O29: 0 | P29: 0 | Q29: 0 | R29: 0 | S29: 0 | T29: 0 | U29: 0 | V29: 0 | W29: 0 | X29: 0 | Y29: 0 | Z29: 0 | AA29: 0 | AB29: 0 | AC29: 0 | AD29: 0 | AE29: 0 | AF29: 0 | AG29: 0 | AH29: 0 | AI29: 0 | AJ29: 0 | AK29: 0 | AL29: 0 | AM29: 0 | AN29: 0 | AO29: 0 | AP29: 0 | AQ29: 0 | AR29: 0 | AS29: 0 | AT29: 0 | AU29: 0 | AV29: 0 | AW29: 0 | AX29: 0 | AY29: 0 | AZ29: 0
A30: LULUCF Sector | B30: 0 | C30: 0 | D30: 0 | E30: 0 | F30: 0 | G30: 0 | H30: 0 | I30: 0 | J30: 0 | K30: 0 | L30: 0 | M30: 0 | N30: 0 | O30: 0 | P30: 0 | Q30: 0 | R30: 0 | S30: 0 | T30: 0 | U30: 0 | V30: 0 | W30: 0 | X30: 0 | Y30: 0 | Z30: 0 | AA30: 0 | AB30: 0 | AC30: 0 | AD30: 0 | AE30: 0 | AF30: 0 | AG30: 0 | AH30: 0 | AI30: 0 | AJ30: 0 | AK30: 0 | AL30: 0 | AM30: 0 | AN30: 0 | AO30: 0 | AP30: 0 | AQ30: 0 | AR30: 0 | AS30: 0 | AT30: 0 | AU30: 0 | AV30: 0 | AW30: 0 | AX30: 0 | AY30: 0 | AZ30: 0
A31: Geoengineering Sector | B31: 0 | C31: 0 | D31: 0 | E31: 0 | F31: 0 | G31: 0 | H31: 0 | I31: 0 | J31: 0 | K31: 0 | L31: 0 | M31: 0 | N31: 0 | O31: 0 | P31: 0 | Q31: 0 | R31: 0 | S31: 0 | T31: 0 | U31: 0 | V31: 0 | W31: 0 | X31: 0 | Y31: 0 | Z31: 0 | AA31: 0 | AB31: 0 | AC31: 0 | AD31: 0 | AE31: 0 | AF31: 0 | AG31: 0 | AH31: 0 | AI31: 0 | AJ31: 0 | AK31: 0 | AL31: 0 | AM31: 0 | AN31: 0 | AO31: 0 | AP31: 0 | AQ31: 0 | AR31: 0 | AS31: 0 | AT31: 0 | AU31: 0 | AV31: 0 | AW31: 0 | AX31: 0 | AY31: 0 | AZ31: 0
A32: Biomass
A33: Year | B33: 2020 | C33: 2021 | D33: 2022 | E33: 2023 | F33: 2024 | G33: 2025 | H33: 2026 | I33: 2027 | J33: 2028 | K33: 2029 | L33: 2030 | M33: 2031 | N33: 2032 | O33: 2033 | P33: 2034 | Q33: 2035 | R33: 2036 | S33: 2037 | T33: 2038 | U33: 2039 | V33: 2040 | W33: 2041 | X33: 2042 | Y33: 2043 | Z33: 2044 | AA33: 2045 | AB33: 2046 | AC33: 2047 | AD33: 2048 | AE33: 2049 | AF33: 2050 | AG33: 2051 | AH33: 2052 | AI33: 2053 | AJ33: 2054 | AK33: 2055 | AL33: 2056 | AM33: 2057 | AN33: 2058 | AO33: 2059 | AP33: 2060 | AQ33: 2061 | AR33: 2062 | AS33: 2063 | AT33: 2064 | AU33: 2065 | AV33: 2066 | AW33: 2067 | AX33: 2068 | AY33: 2069 | AZ33: 2070
A34: Transportation Sector | B34: 0 | C34: 0 | D34: 0 | E34: 0 | F34: 0 | G34: 0 | H34: 0 | I34: 0 | J34: 0 | K34: 0 | L34: 0 | M34: 0 | N34: 0 | O34: 0 | P34: 0 | Q34: 0 | R34: 0 | S34: 0 | T34: 0 | U34: 0 | V34: 0 | W34: 0 | X34: 0 | Y34: 0 | Z34: 0 | AA34: 0 | AB34: 0 | AC34: 0 | AD34: 0 | AE34: 0 | AF34: 0 | AG34: 0 | AH34: 0 | AI34: 0 | AJ34: 0 | AK34: 0 | AL34: 0 | AM34: 0 | AN34: 0 | AO34: 0 | AP34: 0 | AQ34: 0 | AR34: 0 | AS34: 0 | AT34: 0 | AU34: 0 | AV34: 0 | AW34: 0 | AX34: 0 | AY34: 0 | AZ34: 0
A35: Electricity Sector | B35: 1.3797744e-07 | C35: 1.3797744e-07 | D35: 1.3797744e-07 | E35: 1.3797744e-07 | F35: 1.3797744e-07 | G35: 1.3797744e-07 | H35: 1.3797744e-07 | I35: 1.3797744e-07 | J35: 1.3797744e-07 | K35: 1.3797744e-07 | L35: 1.3797744e-07 | M35: 1.3797744e-07 | N35: 1.3797744e-07 | O35: 1.3797744e-07 | P35: 1.3797744e-07 | Q35: 1.3797744e-07 | R35: 1.3797744e-07 | S35: 1.3797744e-07 | T35: 1.3797744e-07 | U35: 1.3797744e-07 | V35: 1.3797744e-07 | W35: 1.3797744e-07 | X35: 1.3797744e-07 | Y35: 1.3797744e-07 | Z35: 1.3797744e-07 | AA35: 1.3797744e-07 | AB35: 1.3797744e-07 | AC35: 1.3797744e-07 | AD35: 1.3797744e-07 | AE35: 1.3797744e-07 | AF35: 1.3797744e-07 | AG35: 1.3797744e-07 | AH35: 1.3797744e-07 | AI35: 1.3797744e-07 | AJ35: 1.3797744e-07 | AK35: 1.3797744e-07 | AL35: 1.3797744e-07 | AM35: 1.3797744e-07 | AN35: 1.3797744e-07 | AO35: 1.3797744e-07 | AP35: 1.3797744e-07 | AQ35: 1.3797744e-07 | AR35: 1.3797744e-07 | AS35: 1.3797744e-07 | AT35: 1.3797744e-07 | AU35: 1.3797744e-07 | AV35: 1.3797744e-07 | AW35: 1.3797744e-07 | AX35: 1.3797744e-07 | AY35: 1.3797744e-07 | AZ35: 1.3797744e-07
A36: Residential Buildings Sector | B36: 5.500452e-07 | C36: 5.500452e-07 | D36: 5.500452e-07 | E36: 5.500452e-07 | F36: 5.500452e-07 | G36: 5.500452e-07 | H36: 5.500452e-07 | I36: 5.500452e-07 | J36: 5.500452e-07 | K36: 5.500452e-07 | L36: 5.500452e-07 | M36: 5.500452e-07 | N36: 5.500452e-07 | O36: 5.500452e-07 | P36: 5.500452e-07 | Q36: 5.500452e-07 | R36: 5.500452e-07 | S36: 5.500452e-07 | T36: 5.500452e-07 | U36: 5.500452e-07 | V36: 5.500452e-07 | W36: 5.500452e-07 | X36: 5.500452e-07 | Y36: 5.500452e-07 | Z36: 5.500452e-07 | AA36: 5.500452e-07 | AB36: 5.500452e-07 | AC36: 5.500452e-07 | AD36: 5.500452e-07 | AE36: 5.500452e-07 | AF36: 5.500452e-07 | AG36: 5.500452e-07 | AH36: 5.500452e-07 | AI36: 5.500452e-07 | AJ36: 5.500452e-07 | AK36: 5.500452e-07 | AL36: 5.500452e-07 | AM36: 5.500452e-07 | AN36: 5.500452e-07 | AO36: 5.500452e-07 | AP36: 5.500452e-07 | AQ36: 5.500452e-07 | AR36: 5.500452e-07 | AS36: 5.500452e-07 | AT36: 5.500452e-07 | AU36: 5.500452e-07 | AV36: 5.500452e-07 | AW36: 5.500452e-07 | AX36: 5.500452e-07 | AY36: 5.500452e-07 | AZ36: 5.500452e-07
A37: Commercial Buildings Sector | B37: 2.5544472e-07 | C37: 2.5544472e-07 | D37: 2.5544472e-07 | E37: 2.5544472e-07 | F37: 2.5544472e-07 | G37: 2.5544472e-07 | H37: 2.5544472e-07 | I37: 2.5544472e-07 | J37: 2.5544472e-07 | K37: 2.5544472e-07 | L37: 2.5544472e-07 | M37: 2.5544472e-07 | N37: 2.5544472e-07 | O37: 2.5544472e-07 | P37: 2.5544472e-07 | Q37: 2.5544472e-07 | R37: 2.5544472e-07 | S37: 2.5544472e-07 | T37: 2.5544472e-07 | U37: 2.5544472e-07 | V37: 2.5544472e-07 | W37: 2.5544472e-07 | X37: 2.5544472e-07 | Y37: 2.5544472e-07 | Z37: 2.5544472e-07 | AA37: 2.5544472e-07 | AB37: 2.5544472e-07 | AC37: 2.5544472e-07 | AD37: 2.5544472e-07 | AE37: 2.5544472e-07 | AF37: 2.5544472e-07 | AG37: 2.5544472e-07 | AH37: 2.5544472e-07 | AI37: 2.5544472e-07 | AJ37: 2.5544472e-07 | AK37: 2.5544472e-07 | AL37: 2.5544472e-07 | AM37: 2.5544472e-07 | AN37: 2.5544472e-07 | AO37: 2.5544472e-07 | AP37: 2.5544472e-07 | AQ37: 2.5544472e-07 | AR37: 2.5544472e-07 | AS37: 2.5544472e-07 | AT37: 2.5544472e-07 | AU37: 2.5544472e-07 | AV37: 2.5544472e-07 | AW37: 2.5544472e-07 | AX37: 2.5544472e-07 | AY37: 2.5544472e-07 | AZ37: 2.5544472e-07
